Workbook

Sheet INC HS Data
A1: Name | B1: Site | C1: Name | D1: Tenure at Date of Injury | E1: Employment Type | F1: Nature of Injury | G1: Claim | H1: Claim Status
A2: DOUGLAS, KARIN | B2: 2032 | C2: Traralgon | D2: 2 | E2: PART TIME | F2: Residual soft tissue disorders due to trauma or unknown mechanisms
A3: MITCHELL, ANGELA | B3: 1005 | C3: Elizabeth | D3: 0 | E3: PART TIME | F3: Residual soft tissue disorders due to trauma or unknown mechanisms
A4: KNIGHT, REBEKAH | B4: 4045 | C4: Ulverstone | D4: 17 | E4: FULL TIME | F4: Residual soft tissue disorders due to trauma or unknown mechanisms
A5: PRIDMORE-JOHNSTON, REBECCA | B5: 4043 | C5: Launceston | D5: 2 | E5: PART TIME | F5: Contusion, bruising and superficial crushing
A6: ANDREWS, SIOBHAN | B6: 4044 | C6: Devonport | D6: 0 | E6: CASUAL | F6: Laceration or open wound not involving traumatic amputation
A7: DIMAKAKOS, MELISSA | B7: 2023 | C7: Epping | D7: 20 | E7: PART TIME | F7: Residual soft tissue disorders due to trauma or unknown mechanisms
A8: KOKKINOS, ANGELA | B8: 2020 | C8: Forest Hill | D8: 2 | E8: CASUAL | F8: Laceration or open wound not involving traumatic amputation | G8: Claim | H8: Accepted Claim
A9: CSIKOS, JAMISON | B9: 2028 | C9: Cranbourne Park | D9: 2 | E9: PART TIME | F9: Residual soft tissue disorders due to trauma or unknown mechanisms
A10: SANDHU, KULDEEP KAUR | B10: 9095 | C10: Chermside | D10: 1 | E10: PART TIME | F10: Residual soft tissue disorders due to trauma or unknown mechanisms | G10: Claim | H10: Accepted Claim
A11: THOMAS, LAUREN | B11: 1005 | C11: Elizabeth | D11: 0 | E11: CASUAL | F11: Foreign body on external eye, in ear or nose or in respiratory, digestive or reproductive tract
A12: DANILEUSKI, THOMAS | B12: 9095 | C12: Chermside | D12: 6 | E12: PART TIME | F12: Residual soft tissue disorders due to trauma or unknown mechanisms | G12: Claim | H12: Accepted Claim
A13: HENDY, KATE | B13: 1011 | C13: Marion | D13: 24 | E13: PART TIME | F13: Residual soft tissue disorders due to trauma or unknown mechanisms
A14: DOWSETT, TAMERA | B14: 6071 | C14: Tweed Heads | D14: 1 | E14: FULL TIME | F14: Residual soft tissue disorders due to trauma or unknown mechanisms
A15: ALLEN, SUSAN | B15: 1006 | C15: West Lakes | D15: 13 | E15: PART TIME | F15: Residual soft tissue disorders due to trauma or unknown mechanisms | G15: Claim | H15: Accepted Claim (MEO)
A16: KARYN, FALCO | B16: 9098 | C16: Carindale | D16: 0 | E16: FULL TIME | F16: Residual soft tissue disorders due to trauma or unknown mechanisms
A17: LAWSON, NIKKITA | B17: 4043 | C17: Launceston | D17: 7 | E17: PART TIME | F17: Laceration or open wound not involving traumatic amputation
A18: MCMULLEN, ALYSE | B18: 2042 | C18: Carnegie (Hs Home) | D18: 2 | E18: FULL TIME | F18: Laceration or open wound not involving traumatic amputation
A19: HUNTER, SARAH | B19: 1011 | C19: Marion | D19: 8 | E19: FULL TIME | F19: Residual soft tissue disorders due to trauma or unknown mechanisms
A20: NUTTALL, BELINDA | B20: 2021 | C20: Geelong | D20: 6 | E20: FULL TIME | F20: Residual soft tissue disorders due to trauma or unknown mechanisms
A21: MAVER, GEORGIE | B21: 2023 | C21: Epping | D21: 2 | E21: FULL TIME | F21: Residual soft tissue disorders due to trauma or unknown mechanisms
A22: ZIGOURAS, LOREDANA | B22: 2025 | C22: Southland | D22: 3 | E22: CASUAL | F22: Residual soft tissue disorders due to trauma or unknown mechanisms
A23: ARNOLD, MAKENZIE | B23: 4045 | C23: Ulverstone | D23: 1 | E23: CASUAL | F23: Other mental diseases, not elsewhere classified
A24: BYNION, FAY | B24: 2025 | C24: Southland | D24: 1 | E24: FULL TIME | F24: Residual soft tissue disorders due to trauma or unknown mechanisms
A25: ADDAMS, SAMANTHA | B25: 2019 | C25: Ballarat | D25: 0 | E25: PART TIME | F25: Reaction to stressors - other, multiple or not specified | G25: Claim | H25: Pending Claim
A26: GANGI, ALESSIA | B26: 2024 | C26: Highpoint | D26: 0 | E26: CASUAL
A27: SMITH, KIEREN | B27: 1011 | C27: Marion | D27: 10 | E27: PART TIME | F27: Laceration or open wound not involving traumatic amputation
A28: MEAD, SUSANNE | B28: 2029 | C28: Waurn Ponds (Hs Home) | D28: 0 | E28: PART TIME | F28: Laceration or open wound not involving traumatic amputation
A29: MORRISS, ASHLEY | B29: 6068 | C29: Wagga Wagga | D29: 0 | E29: CASUAL | F29: Laceration or open wound not involving traumatic amputation
A30: DE GENNARO, MADELINE | B30: 1011 | C30: Marion | D30: 2 | E30: CASUAL | F30: Laceration or open wound not involving traumatic amputation
A31: MCGURGAN, KAYLA | B31: 2026 | C31: Shepparton | D31: 1 | E31: CASUAL | F31: Residual soft tissue disorders due to trauma or unknown mechanisms
A32: ADAMS, CHRISTINE | B32: 2029 | C32: Waurn Ponds (Hs Home) | D32: 1 | E32: PART TIME | F32: Laceration or open wound not involving traumatic amputation
A33: BOURNE, MAREE | B33: 6068 | C33: Wagga Wagga | D33: 4 | E33: PART TIME | F33: Residual soft tissue disorders due to trauma or unknown mechanisms
A34: PENFOLD, ALANA | B34: 1005 | C34: Elizabeth | D34: 3 | E34: CASUAL | F34: Laceration or open wound not involving traumatic amputation
A35: RUSH, GEORGINA | B35: 4045 | C35: Ulverstone | D35: 2 | E35: PART TIME | F35: Reaction to stressors - other, multiple or not specified
A36: FORBES, LILLY MAY | B36: 6071 | C36: Tweed Heads | D36: 1 | E36: PART TIME | F36: Residual soft tissue disorders due to trauma or unknown mechanisms
A37: MCNAMARA, NEASHER | B37: 9095 | C37: Chermside | D37: 4 | E37: FULL TIME | F37: Residual soft tissue disorders due to trauma or unknown mechanisms | G37: Claim | H37: Accepted Claim
A38: MARINO, ANGELA | B38: 1010 | C38: Whyalla | D38: 2 | E38: PART TIME | F38: Laceration or open wound not involving traumatic amputation
A39: QUEEN, DECLAN | B39: 4042 | C39: Cambridge | D39: 1 | E39: PART TIME | F39: Residual soft tissue disorders due to trauma or unknown mechanisms
A40: HANSEN, LACHLAN | B40: 9097 | C40: Hervey Bay | D40: 0 | E40: PART TIME | F40: Foreign body on external eye, in ear or nose or in respiratory, digestive or reproductive tract
A41: NICOLAISEN, CHRISTINA | B41: 2022 | C41: Knox City | D41: 15 | E41: FULL TIME | F41: Laceration or open wound not involving traumatic amputation
A42: VELLACOTT, ELIZA | B42: 9088 | C42: West Burleigh (Mega Home) | D42: 1 | E42: CASUAL | F42: Residual soft tissue disorders due to trauma or unknown mechanisms | G42: Claim | H42: Accepted Claim
A43: SMITH, KIEREN | B43: 1011 | C43: Marion | D43: 10 | E43: PART TIME | F43: Short term shock from exposure to disturbing circumstances
A44: TROTTER, MEGAN | B44: 9088 | C44: West Burleigh (Mega Home) | D44: 0 | E44: PART TIME | F44: Residual soft tissue disorders due to trauma or unknown mechanisms
A45: ROSSI, MARIA | B45: 1011 | C45: Marion | D45: 29 | E45: PART TIME | F45: Residual soft tissue disorders due to trauma or unknown mechanisms | G45: Claim | H45: Accepted Claim
A46: WELLS, AMANDA | B46: 1013 | C46: Gepps Cross (Hs Home) | D46: 26 | E46: FULL TIME | F46: Residual soft tissue disorders due to trauma or unknown mechanisms
A47: MCGREGOR, COOPER | B47: 2025 | C47: Southland | D47: 1 | E47: PART TIME | F47: Residual soft tissue disorders due to trauma or unknown mechanisms
A48: TODD, ERIC | B48: 5060 | C48: Bathurst | D48: 0 | E48: PART TIME | F48: Residual soft tissue disorders due to trauma or unknown mechanisms
A49: SHARAN, NATASHA | B49: 9087 | C49: Loganholme | D49: 1 | E49: PART TIME | F49: Laceration or open wound not involving traumatic amputation
A50: MIRABELLA, EMILY | B50: 2019 | C50: Ballarat | D50: 6 | E50: PART TIME | F50: Residual soft tissue disorders due to trauma or unknown mechanisms
A51: EIFFE, TRACEY | B51: 1011 | C51: Marion | D51: 2 | E51: PART TIME | F51: Residual soft tissue disorders due to trauma or unknown mechanisms
A52: HARTIGAN, CORY | B52: 2039 | C52: Fountain Gate | D52: 3 | E52: FULL TIME | F52: Laceration or open wound not involving traumatic amputation
A53: EIFFE, TRACEY | B53: 1011 | C53: Marion | D53: 2 | E53: PART TIME | F53: Laceration or open wound not involving traumatic amputation
A54: NAJEM, MARLENE | B54: 5089 | C54: Rockdale | D54: 0 | E54: PART TIME | F54: Residual soft tissue disorders due to trauma or unknown mechanisms
A55: BOLITHO, CHARLOTTE | B55: 2019 | C55: Ballarat | D55: 1 | E55: PART TIME | F55: Contusion, bruising and superficial crushing
A56: REID, SIMONE | B56: 4043 | C56: Launceston | D56: 0 | E56: CASUAL | F56: Residual soft tissue disorders due to trauma or unknown mechanisms
A57: CULGAN, JODIE | B57: 6071 | C57: Tweed Heads | D57: 1 | E57: FULL TIME | F57: Contusion, bruising and superficial crushing
A58: WEEDON, HELEN | B58: 2031 | C58: Sunbury | D58: 1 | E58: PART TIME | F58: Residual soft tissue disorders due to trauma or unknown mechanisms | G58: Claim | H58: Accepted Claim
A59: HUANG, QIN | B59: 2033 | C59: Eastland | D59: 4 | E59: PART TIME | F59: Unspecified injuries
A60: INCE, HOLLY | B60: 1011 | C60: Marion | D60: 1 | E60: CASUAL | F60: Reaction to stressors - other, multiple or not specified
A61: JOHNSON, JANE | B61: 1011 | C61: Marion | D61: 2 | E61: CASUAL | F61: Laceration or open wound not involving traumatic amputation
A62: MADDOCK, HANNAH | B62: 9095 | C62: Chermside | D62: 3 | E62: PART TIME | F62: Contusion, bruising and superficial crushing
A63: RICHARDS, JULIE | B63: 1008 | C63: Tea Tree Plaza | D63: 1 | E63: PART TIME | F63: Multiple injuries
A64: BAILEY, MANDY | B64: 1011 | C64: Marion | D64: 6 | E64: PART TIME | F64: Contusion, bruising and superficial crushing
A65: RANSOME, VANESSA | B65: 2033 | C65: Eastland | D65: 1 | E65: CASUAL | F65: Diseases of muscle, tendon and related tissue
A66: DEAN, KAREN | B66: 2030 | C66: Warrnambool | D66: 1 | E66: PART TIME | F66: Contusion, bruising and superficial crushing
A67: PARKIN, WESLEY | B67: 2042 | C67: Carnegie (Hs Home) | D67: 1 | E67: CASUAL | F67: Contusion, bruising and superficial crushing
A68: TULLY, ARCHER | B68: 4042 | C68: Cambridge | D68: 0 | E68: CASUAL | F68: Laceration or open wound not involving traumatic amputation
A69: WILCZEK, CHLOE | B69: 1011 | C69: Marion | D69: 6 | E69: PART TIME | F69: Laceration or open wound not involving traumatic amputation
A70: KIM, LINDA | B70: 2028 | C70: Cranbourne Park | D70: 11 | E70: FULL TIME | F70: Residual soft tissue disorders due to trauma or unknown mechanisms
... A73: EDWARDS, DANIEL | B73: 9095 | C73: Chermside | D73: 15 | E73: FULL TIME | F73: Residual soft tissue disorders due to trauma or unknown mechanisms
A74: NOWLAND, AMELIA | B74: 9095 | C74: Chermside | D74: 12 | E74: PART TIME | F74: Residual soft tissue disorders due to trauma or unknown mechanisms | G74: Claim | H74: Accepted Claim (MEO)
A75: MCGRATH, INGRID | B75: 5053 | C75: Shellharbour (Hs Home) | D75: 8 | E75: PART TIME | F75: Residual soft tissue disorders due to trauma or unknown mechanisms
A76: PRINCE, SHEENA | B76: 6076 | C76: Moruya | D76: 0 | E76: PART TIME | F76: Residual soft tissue disorders due to trauma or unknown mechanisms
A77: EUSTACE, DARELLE | B77: 9086 | C77: Mt Gravatt | D77: 1 | E77: PART TIME | F77: Laceration or open wound not involving traumatic amputation
A78: SMITH, KIEREN | B78: 1011 | C78: Marion | D78: 10 | E78: PART TIME | F78: Laceration or open wound not involving traumatic amputation
A79: FROST, ANGELA | B79: 1011 | C79: Marion | D79: 9 | E79: PART TIME | F79: Residual soft tissue disorders due to trauma or unknown mechanisms
A80: JEFFERY, JOSEPH | B80: 2026 | C80: Shepparton | D80: 5 | E80: FULL TIME | F80: Short term shock from exposure to disturbing circumstances
A81: SHARAN, NATASHA | B81: 9087 | C81: Loganholme | D81: 1 | E81: PART TIME | F81: Laceration or open wound not involving traumatic amputation
A82: BYNION, FAY | B82: 2025 | C82: Southland | D82: 1 | E82: FULL TIME | F82: Residual soft tissue disorders due to trauma or unknown mechanisms | G82: Claim | H82: Declined Claim
A83: RALPH, RACHEL | B83: 6078 | C83: Ulladulla | D83: 4 | E83: PART TIME | F83: Residual soft tissue disorders due to trauma or unknown mechanisms
A84: ADDAMS, SAMANTHA | B84: 2019 | C84: Ballarat | D84: 0 | E84: PART TIME | F84: Residual soft tissue disorders due to trauma or unknown mechanisms
A85: JAMES, CAROLYN | B85: 1012 | C85: Colonnades | D85: 0 | E85: CASUAL | F85: Residual soft tissue disorders due to trauma or unknown mechanisms
A86: AKOK, BENJAMIN | B86: 2017 | C86: Woodgrove | D86: 1 | E86: PART TIME | F86: Short term shock from exposure to disturbing circumstances
A87: KEY, DEBORAH | B87: 5060 | C87: Bathurst | D87: 0 | E87: PART TIME | F87: Residual soft tissue disorders due to trauma or unknown mechanisms
A88: MENGOD, VANESSA | B88: 1008 | C88: Tea Tree Plaza | D88: 29 | E88: FULL TIME | F88: Residual soft tissue disorders due to trauma or unknown mechanisms
A89: IRVINE, MARGARET | B89: 6071 | C89: Tweed Heads | D89: 1 | E89: PART TIME | F89: Residual soft tissue disorders due to trauma or unknown mechanisms
A90: HUNTER, SARAH | B90: 1011 | C90: Marion | D90: 8 | E90: FULL TIME | F90: Contusion, bruising and superficial crushing
A91: FROST, ANGELA | B91: 1011 | C91: Marion | D91: 9 | E91: PART TIME | F91: Residual soft tissue disorders due to trauma or unknown mechanisms
A92: MIOCIC, ANA | B92: 1013 | C92: Gepps Cross (Hs Home) | D92: 1 | E92: CASUAL | F92: Residual soft tissue disorders due to trauma or unknown mechanisms
A93: SMITH, KIEREN | B93: 1011 | C93: Marion | D93: 10 | E93: PART TIME | F93: Residual soft tissue disorders due to trauma or unknown mechanisms
A94: OSLAY, SHERRIDAN | B94: 2022 | C94: Knox City | D94: 1 | E94: PART TIME | F94: Residual soft tissue disorders due to trauma or unknown mechanisms | G94: Claim | H94: Accepted Claim
A95: WOODS, TYLER | B95: 2059 | C95: Bairnsdale | D95: 0 | E95: CASUAL | F95: Trauma to joints and ligaments
A96: AYERS, JENNIFER | B96: 6071 | C96: Tweed Heads | D96: 1 | E96: CASUAL | F96: Residual soft tissue disorders due to trauma or unknown mechanisms | G96: Claim | H96: Accepted Claim (MEO)
A97: YOUSSOUF, ZEYNEB | B97: 2024 | C97: Highpoint | D97: 0 | E97: CASUAL | F97: Residual soft tissue disorders due to trauma or unknown mechanisms
A98: HENDY, KATE | B98: 1011 | C98: Marion | D98: 24 | E98: PART TIME | F98: Trauma to muscles and tendons
A99: MANILA, AILAMA | B99: 2025 | C99: Southland | D99: 8 | E99: FULL TIME | F99: Residual soft tissue disorders due to trauma or unknown mechanisms
A100: MCMAHON, JUDY | B100: 2026 | C100: Shepparton | D100: 17 | E100: PART TIME | F100: Residual soft tissue disorders due to trauma or unknown mechanisms
A101: CULGAN, JODIE | B101: 6071 | C101: Tweed Heads | D101: 1 | E101: FULL TIME | F101: Residual soft tissue disorders due to trauma or unknown mechanisms
A102: NICHOLLS, TAHLYA | B102: 9097 | C102: Hervey Bay | D102: 0 | E102: FULL TIME | F102: Residual soft tissue disorders due to trauma or unknown mechanisms
...

Sheet HS Graphs
E18: Figure 1 | F18: Total Incidents within 19-month period | S18: Figure 3 | T18: Total Incidents and Claims within 19-month period
E36: Figure 2 | F36: Total Claims within 19-month period | S36: Figure 4 | T36: Total Incidents and Claims within 19-month period by Age Groups
E54: Figure 4 | F54: Total Incidents and Claims within 19-month period by Tenure Groups | S54: Figure 5 | T54: Total Incidents and Claims between 1-5 Years Tenure from Date of Injury
M73: Figure 6 | N73: Total Incidents and Claims within 19-month period (NSW Only)

Sheet Group Graph

Sheet Pie Charts
A3: Incidents | B3: 270 | P3: Team Member Incidents | Q3: 300
A4: Claims | B4: 57 | P4: Non-Work Related | Q4: 27
F16: Figure 1 | G16: Incidents and Claims within 18-month period | U16: Figure 3 | V16: Non-Work Related incidents
A18: Accepted Claim | B18: 36 | P18: Non-Work Related | Q18: 23
A19: Pending Claim | B19: 13 | P19: Pending Claims | Q19: 1
A20: Accepted Claim (MEO) | B20: 5 | P20: Accepted Claims | Q20: 2
A21: Invalid Claim | B21: 2 | P21: Declined Claims | Q21: 1
A22: Declined Claim | B22: 1
F33: Figure 2 | G33: Claim Status within 18-month period | U33: Figure 4 | V33: Claim Status within Non-Work Related

Sheet Pivot
H1: Claim | I1: Claim | K1: Claim | L1: Claim | O1: Claim | P1: Claim
A2: HS Incidents Per Age Group and Region | D2: HS Incidents Per Tenure Group | H2: HS Claims Per Age Group and Region | K2: HS Claim Per Tenure Group | O2: Incident Correlation NWR_TMJ
A3: Row Labels | B3: Count of Grouping Level 2 | D3: Row Labels | E3: Count of Grouping Level 2 | H3: Row Labels | I3: Count of Age Bracket | K3: Row Labels | L3: Count of Grouping Level 2 | O3: Count of Incidents Correlation NWR_TMJ | P3: Column Labels
A4: Harris Scarfe - NSW/ACT | B4: 34 | D4: Under 1 Year | E4: 62 | H4: Harris Scarfe - NSW/ACT | I4: 4 | K4: Under 1 Year | L4: 8 | O4: Row Labels | P4: 20-24 Years | Q4: 25-34 Years | R4: 35-44 Years | S4: 45-54 Years | T4: More Than 55 Years | U4: Grand Total
A5: Less Than 20 Years | B5: 1 | D5: 1-5 Years | E5: 165 | H5: 20-24 Years | I5: 1 | K5: 1-5 Years | L5: 28 | O5: Accepted Claim | S5: 1 | T5: 1 | U5: 2
A6: 20-24 Years | B6: 5 | D6: 6-10 Years | E6: 47 | H6: 25-34 Years | I6: 1 | K6: 6-10 Years | L6: 9 | O6: Declined Claim | Q6: 1 | U6: 1
A7: 25-34 Years | B7: 8 | D7: 11-15 Years | E7: 17 | H7: 35-44 Years | I7: 1 | K7: 11-15 Years | L7: 8 | O7: Pending Claim | R7: 1 | U7: 1
A8: 35-44 Years | B8: 2 | D8: 16-20 Years | E8: 17 | H8: 45-54 Years | I8: 1 | K8: 16-20 Years | L8: 3 | O8: Grand Total | Q8: 1 | R8: 1 | S8: 1 | T8: 1 | U8: 4
A9: 45-54 Years | B9: 8 | D9: 21-25 Years | E9: 7 | H9: Harris Scarfe - QLD | I9: 17 | K9: 26-30 Years | L9: 1
A10: More Than 55 Years | B10: 10 | D10: 26-30 Years | E10: 7 | H10: 20-24 Years | I10: 4 | K10: Grand Total | L10: 57
A11: Harris Scarfe - QLD | B11: 74 | D11: More Than 30 Years | E11: 5 | H11: 25-34 Years | I11: 5
A12: Less Than 20 Years | B12: 6 | D12: Grand Total | E12: 327 | H12: 35-44 Years | I12: 2
A13: 20-24 Years | B13: 8 | H13: 45-54 Years | I13: 3
A14: 25-34 Years | B14: 22 | H14: More Than 55 Years | I14: 3
A15: 35-44 Years | B15: 8 | D15: Tenure Bracket at Date of Injury | E15: 1-5 Years | H15: Harris Scarfe - SA/TAS | I15: 12
A16: 45-54 Years | B16: 17 | D16: HS Incidents between 1-5 years Tenure | H16: 20-24 Years | I16: 2
A17: More Than 55 Years | B17: 13 | D17: Row Labels | E17: Count of Grouping Level 2 | H17: 25-34 Years | I17: 2
A18: Harris Scarfe - SA/TAS | B18: 103 | D18: 1 | E18: 72 | H18: 35-44 Years | I18: 2
A19: Less Than 20 Years | B19: 9 | D19: 2 | E19: 38 | H19: 45-54 Years | I19: 2
A20: 20-24 Years | B20: 15 | D20: 3 | E20: 23 | H20: More Than 55 Years | I20: 4
A21: 25-34 Years | B21: 16 | D21: 4 | E21: 20 | H21: Harris Scarfe - VIC | I21: 13
A22: 35-44 Years | B22: 14 | D22: 5 | E22: 12 | H22: 20-24 Years | I22: 3
A23: 45-54 Years | B23: 18 | D23: Grand Total | E23: 165 | H23: 25-34 Years | I23: 2
A24: More Than 55 Years | B24: 31 | H24: 35-44 Years | I24: 2
A25: Harris Scarfe - VIC | B25: 64 | H25: 45-54 Years | I25: 1
A26: Less Than 20 Years | B26: 4 | H26: More Than 55 Years | I26: 5
A27: 20-24 Years | B27: 14 | H27: Harris Scarfe - VIC & NSW | I27: 11
A28: 25-34 Years | B28: 9 | H28: 25-34 Years | I28: 1
A29: 35-44 Years | B29: 8 | H29: 35-44 Years | I29: 4
A30: 45-54 Years | B30: 15 | H30: 45-54 Years | I30: 1
A31: More Than 55 Years | B31: 14 | H31: More Than 55 Years | I31: 5
A32: Harris Scarfe - VIC & NSW | B32: 52 | H32: Grand Total | I32: 57
A33: Less Than 20 Years | B33: 1
A34: 20-24 Years | B34: 7 | H34: Tenure Bracket at Date of Injury | I34: 1-5 Years
A35: 25-34 Years | B35: 8 | H35: Claim | I35: Claim
A36: 35-44 Years | B36: 12 | H36: HS Claims between 1-5 years Tenure
A37: 45-54 Years | B37: 8 | H37: Row Labels | I37: Count of Claim
A38: More Than 55 Years | B38: 16 | H38: 1 | I38: 12
A39: Grand Total | B39: 327 | H39: 2 | I39: 8
H40: 3 | I40: 3
H41: 4 | I41: 3
H42: 5 | I42: 2
H43: Grand Total | I43: 28

Sheet HS FEED
A1: Harris Scarfe | B1: FY24 | S1: FY25
A2: Incidents | B2: ="JUL, "&B1 -> JUL, FY24 | C2: ="AUG, "&B1 -> AUG, FY24 | D2: ="SEP, "&B1 -> SEP, FY24 | E2: ="Q1, "&B1 -> Q1, FY24 | F2: ="OCT, "&B1 -> OCT, FY24 | G2: ="NOV, "&B1 -> NOV, FY24 | H2: ="DEC, "&B1 -> DEC, FY24 | I2: ="Q2, "&B1 -> Q2, FY24 | J2: ="JAN, "&B1 -> JAN, FY24 | K2: ="FEB, "&B1 -> FEB, FY24 | L2: ="MAR, "&B1 -> MAR, FY24 | M2: ="Q3, "&B1 -> Q3, FY24 | N2: ="APR, "&B1 -> APR, FY24 | O2: ="MAY, "&B1 -> MAY, FY24 | P2: ="JUN, "&B1 -> JUN, FY24 | Q2: ="Q4, "&B1 -> Q4, FY24 | R2: ="Full Year, "&B1 -> Full Year, FY24 | S2: ="JUL, "&S1 -> JUL, FY25 | T2: ="AUG, "&S1 -> AUG, FY25 | U2: ="SEP, "&S1 -> SEP, FY25 | V2: ="Q1, "&S1 -> Q1, FY25 | W2: ="OCT, "&S1 -> OCT, FY25 | X2: ="NOV, "&S1 -> NOV, FY25 | Y2: ="DEC, "&S1 -> DEC, FY25 | Z2: ="Q2, "&S1 -> Q2, FY25 | AA2: ="JAN, "&S1 -> JAN, FY25 | AB2: ="FEB, "&S1 -> FEB, FY25 | AC2: ="MAR, "&S1 -> MAR, FY25 | AD2: ="Q3, "&S1 -> Q3, FY25 | AE2: ="APR, "&S1 -> APR, FY25 | AF2: ="MAY, "&S1 -> MAY, FY25 | AG2: ="JUN, "&S1 -> JUN, FY25 | AH2: ="Q4, "&S1 -> Q4, FY25 | AI2: ="Full Year, "&S1 -> Full Year, FY25
A3: Incidents | B3: =COUNTIFS('18-Month HS Incidents'!$AO:$AO,'HS FEED'!B$2) -> 0 | C3: =COUNTIFS('18-Month HS Incidents'!$AO:$AO,'HS FEED'!C$2) -> 0 | D3: =COUNTIFS('18-Month HS Incidents'!$AO:$AO,'HS FEED'!D$2) -> 0 | E3: =SUBTOTAL(9,B3:D3) -> 0 | F3: =COUNTIFS('18-Month HS Incidents'!$AO:$AO,'HS FEED'!F$2) -> 13 | G3: =COUNTIFS('18-Month HS Incidents'!$AO:$AO,'HS FEED'!G$2) -> 19 | H3: =COUNTIFS('18-Month HS Incidents'!$AO:$AO,'HS FEED'!H$2) -> 27 | I3: =SUBTOTAL(9,F3:H3) -> 59 | J3: =COUNTIFS('18-Month HS Incidents'!$AO:$AO,'HS FEED'!J$2) -> 17 | K3: =COUNTIFS('18-Month HS Incidents'!$AO:$AO,'HS FEED'!K$2) -> 20 | L3: =COUNTIFS('18-Month HS Incidents'!$AO:$AO,'HS FEED'!L$2) -> 17 | M3: =SUBTOTAL(9,J3:L3) -> 54 | N3: =COUNTIFS('18-Month HS Incidents'!$AO:$AO,'HS FEED'!N$2) -> 12 | O3: =COUNTIFS('18-Month HS Incidents'!$AO:$AO,'HS FEED'!O$2) -> 30 | P3: =COUNTIFS('18-Month HS Incidents'!$AO:$AO,'HS FEED'!P$2) -> 18 | Q3: =SUBTOTAL(9,N3:P3) -> 60 | R3: =SUBTOTAL(9,B3:Q3) -> 173 | S3: =COUNTIFS('18-Month HS Incidents'!$AO:$AO,'HS FEED'!S$2) -> 16 | T3: =COUNTIFS('18-Month HS Incidents'!$AO:$AO,'HS FEED'!T$2) -> 24 | U3: =COUNTIFS('18-Month HS Incidents'!$AO:$AO,'HS FEED'!U$2) -> 17 | V3: =SUBTOTAL(9,S3:U3) -> 57 | W3: =COUNTIFS('18-Month HS Incidents'!$AO:$AO,'HS FEED'!W$2) -> 16 | X3: =COUNTIFS('18-Month HS Incidents'!$AO:$AO,'HS FEED'!X$2) -> 18 | Y3: =COUNTIFS('18-Month HS Incidents'!$AO:$AO,'HS FEED'!Y$2) -> 17 | Z3: =SUBTOTAL(9,W3:Y3) -> 51 | AA3: =COUNTIFS('18-Month HS Incidents'!$AO:$AO,'HS FEED'!AA$2) -> 8 | AB3: =COUNTIFS('18-Month HS Incidents'!$AO:$AO,'HS FEED'!AB$2) -> 9 | AC3: =COUNTIFS('18-Month HS Incidents'!$AO:$AO,'HS FEED'!AC$2) -> 19 | AD3: =SUBTOTAL(9,AA3:AC3) -> 36 | AE3: =COUNTIFS('18-Month HS Incidents'!$AO:$AO,'HS FEED'!AE$2) -> 10 | AF3: =COUNTIFS('18-Month HS Incidents'!$AO:$AO,'HS FEED'!AF$2) -> 0 | AG3: =COUNTIFS('18-Month HS Incidents'!$AO:$AO,'HS FEED'!AG$2) -> 0 | AH3: =SUBTOTAL(9,AE3:AG3) -> 10 | AI3: =SUBTOTAL(9,S3:AH3) -> 154
A4: YTD Incident | B4: =SUBTOTAL(9,$B3:B3) -> 0 | C4: =SUBTOTAL(9,$B3:C3) -> 0 | D4: =SUBTOTAL(9,$B3:D3) -> 0 | E4: =SUBTOTAL(9,$B3:E3) -> 0 | F4: =SUBTOTAL(9,$B3:F3) -> 13 | G4: =SUBTOTAL(9,$B3:G3) -> 32 | H4: =SUBTOTAL(9,$B3:H3) -> 59 | I4: =SUBTOTAL(9,$B3:I3) -> 59 | ... R4: =SUBTOTAL(9,$B3:R3) -> 173 | S4: =SUBTOTAL(9,$S3:S3) -> 16 | T4: =SUBTOTAL(9,$S3:T3) -> 40 | U4: =SUBTOTAL(9,$S3:U3) -> 57 | V4: =SUBTOTAL(9,$S3:V3) -> 57 | W4: =SUBTOTAL(9,$S3:W3) -> 73 | X4: =SUBTOTAL(9,$S3:X3) -> 91 | Y4: =SUBTOTAL(9,$S3:Y3) -> 108 | Z4: =SUBTOTAL(9,$S3:Z3) -> 108 | ... AI4: =SUBTOTAL(9,$S3:AI3) -> 154
A6: Claims
A7: Claim | B7: =COUNTIFS('18-Month HS Incidents'!$AO:$AO,'HS FEED'!B$2,'18-Month HS Incidents'!$AR:$AR,"Claim") -> 0 | C7: =COUNTIFS('18-Month HS Incidents'!$AO:$AO,'HS FEED'!C$2,'18-Month HS Incidents'!$AR:$AR,"Claim") -> 0 | D7: =COUNTIFS('18-Month HS Incidents'!$AO:$AO,'HS FEED'!D$2,'18-Month HS Incidents'!$AR:$AR,"Claim") -> 0 | E7: =SUBTOTAL(9,B7:D7) -> 0 | F7: =COUNTIFS('18-Month HS Incidents'!$AO:$AO,'HS FEED'!F$2,'18-Month HS Incidents'!$AR:$AR,"Claim") -> 3 | G7: =COUNTIFS('18-Month HS Incidents'!$AO:$AO,'HS FEED'!G$2,'18-Month HS Incidents'!$AR:$AR,"Claim") -> 2 | H7: =COUNTIFS('18-Month HS Incidents'!$AO:$AO,'HS FEED'!H$2,'18-Month HS Incidents'!$AR:$AR,"Claim") -> 4 | I7: =SUBTOTAL(9,F7:H7) -> 9 | J7: =COUNTIFS('18-Month HS Incidents'!$AO:$AO,'HS FEED'!J$2,'18-Month HS Incidents'!$AR:$AR,"Claim") -> 1 | K7: =COUNTIFS('18-Month HS Incidents'!$AO:$AO,'HS FEED'!K$2,'18-Month HS Incidents'!$AR:$AR,"Claim") -> 3 | L7: =COUNTIFS('18-Month HS Incidents'!$AO:$AO,'HS FEED'!L$2,'18-Month HS Incidents'!$AR:$AR,"Claim") -> 2 | M7: =SUBTOTAL(9,J7:L7) -> 6 | N7: =COUNTIFS('18-Month HS Incidents'!$AO:$AO,'HS FEED'!N$2,'18-Month HS Incidents'!$AR:$AR,"Claim") -> 1 | O7: =COUNTIFS('18-Month HS Incidents'!$AO:$AO,'HS FEED'!O$2,'18-Month HS Incidents'!$AR:$AR,"Claim") -> 6 | P7: =COUNTIFS('18-Month HS Incidents'!$AO:$AO,'HS FEED'!P$2,'18-Month HS Incidents'!$AR:$AR,"Claim") -> 4 | Q7: =SUBTOTAL(9,N7:P7) -> 11 | R7: =SUBTOTAL(9,B7:Q7) -> 26 | S7: =COUNTIFS('18-Month HS Incidents'!$AO:$AO,'HS FEED'!S$2,'18-Month HS Incidents'!$AR:$AR,"Claim") -> 3 | T7: =COUNTIFS('18-Month HS Incidents'!$AO:$AO,'HS FEED'!T$2,'18-Month HS Incidents'!$AR:$AR,"Claim") -> 6 | U7: =COUNTIFS('18-Month HS Incidents'!$AO:$AO,'HS FEED'!U$2,'18-Month HS Incidents'!$AR:$AR,"Claim") -> 3 | V7: =SUBTOTAL(9,S7:U7) -> 12 | W7: =COUNTIFS('18-Month HS Incidents'!$AO:$AO,'HS FEED'!W$2,'18-Month HS Incidents'!$AR:$AR,"Claim") -> 3 | X7: =COUNTIFS('18-Month HS Incidents'!$AO:$AO,'HS FEED'!X$2,'18-Month HS Incidents'!$AR:$AR,"Claim") -> 5 | Y7: =COUNTIFS('18-Month HS Incidents'!$AO:$AO,'HS FEED'!Y$2,'18-Month HS Incidents'!$AR:$AR,"Claim") -> 3 | Z7: =SUBTOTAL(9,W7:Y7) -> 11 | AA7: =COUNTIFS('18-Month HS Incidents'!$AO:$AO,'HS FEED'!AA$2,'18-Month HS Incidents'!$AR:$AR,"Claim") -> 1 | AB7: =COUNTIFS('18-Month HS Incidents'!$AO:$AO,'HS FEED'!AB$2,'18-Month HS Incidents'!$AR:$AR,"Claim") -> 2 | AC7: =COUNTIFS('18-Month HS Incidents'!$AO:$AO,'HS FEED'!AC$2,'18-Month HS Incidents'!$AR:$AR,"Claim") -> 3 | AD7: =SUBTOTAL(9,AA7:AC7) -> 6 | AE7: =COUNTIFS('18-Month HS Incidents'!$AO:$AO,'HS FEED'!AE$2,'18-Month HS Incidents'!$AR:$AR,"Claim") -> 2 | AF7: =COUNTIFS('18-Month HS Incidents'!$AO:$AO,'HS FEED'!AF$2,'18-Month HS Incidents'!$AR:$AR,"Claim") -> 0 | AG7: =COUNTIFS('18-Month HS Incidents'!$AO:$AO,'HS FEED'!AG$2,'18-Month HS Incidents'!$AR:$AR,"Claim") -> 0 | AH7: =SUBTOTAL(9,AE7:AG7) -> 2 | AI7: =SUBTOTAL(9,S7:AH7) -> 31
A8: YTD Claim | B8: =SUBTOTAL(9,$B7:B7) -> 0 | C8: =SUBTOTAL(9,$B7:C7) -> 0 | D8: =SUBTOTAL(9,$B7:D7) -> 0 | E8: =SUBTOTAL(9,$B7:E7) -> 0 | F8: =SUBTOTAL(9,$B7:F7) -> 3 | G8: =SUBTOTAL(9,$B7:G7) -> 5 | H8: =SUBTOTAL(9,$B7:H7) -> 9 | I8: =SUBTOTAL(9,$B7:I7) -> 9 | ... R8: =SUBTOTAL(9,$B7:R7) -> 26 | S8: =SUBTOTAL(9,$S7:S7) -> 3 | T8: =SUBTOTAL(9,$S7:T7) -> 9 | U8: =SUBTOTAL(9,$S7:U7) -> 12 | V8: =SUBTOTAL(9,$S7:V7) -> 12 | W8: =SUBTOTAL(9,$S7:W7) -> 15 | X8: =SUBTOTAL(9,$S7:X7) -> 20 | Y8: =SUBTOTAL(9,$S7:Y7) -> 23 | Z8: =SUBTOTAL(9,$S7:Z7) -> 23 | ... AI8: =SUBTOTAL(9,$S7:AI7) -> 31
A11: NSW | AK11: Less Than 20 Years | AL11: 20-24 Years | AM11: 25-34 Years | AN11: 35-44 Years | AO11: 45-54 Years | AP11: More Than 55 Years
A12: Incidents | B12: =COUNTIFS('18-Month HS Incidents'!$AO:$AO,'HS FEED'!B$2,'18-Month HS Incidents'!$AW:$AW,'HS FEED'!$A$11) -> 0 | C12: =COUNTIFS('18-Month HS Incidents'!$AO:$AO,'HS FEED'!C$2,'18-Month HS Incidents'!$AW:$AW,'HS FEED'!$A$11) -> 0 | D12: =COUNTIFS('18-Month HS Incidents'!$AO:$AO,'HS FEED'!D$2,'18-Month HS Incidents'!$AW:$AW,'HS FEED'!$A$11) -> 0 | E12: =SUBTOTAL(9,B12:D12) -> 0 | F12: =COUNTIFS('18-Month HS Incidents'!$AO:$AO,'HS FEED'!F$2,'18-Month HS Incidents'!$AW:$AW,'HS FEED'!$A$11) -> 1 | G12: =COUNTIFS('18-Month HS Incidents'!$AO:$AO,'HS FEED'!G$2,'18-Month HS Incidents'!$AW:$AW,'HS FEED'!$A$11) -> 2 | H12: =COUNTIFS('18-Month HS Incidents'!$AO:$AO,'HS FEED'!H$2,'18-Month HS Incidents'!$AW:$AW,'HS FEED'!$A$11) -> 4 | I12: =SUBTOTAL(9,F12:H12) -> 7 | J12: =COUNTIFS('18-Month HS Incidents'!$AO:$AO,'HS FEED'!J$2,'18-Month HS Incidents'!$AW:$AW,'HS FEED'!$A$11) -> 2 | K12: =COUNTIFS('18-Month HS Incidents'!$AO:$AO,'HS FEED'!K$2,'18-Month HS Incidents'!$AW:$AW,'HS FEED'!$A$11) -> 4 | L12: =COUNTIFS('18-Month HS Incidents'!$AO:$AO,'HS FEED'!L$2,'18-Month HS Incidents'!$AW:$AW,'HS FEED'!$A$11) -> 5 | M12: =SUBTOTAL(9,J12:L12) -> 11 | N12: =COUNTIFS('18-Month HS Incidents'!$AO:$AO,'HS FEED'!N$2,'18-Month HS Incidents'!$AW:$AW,'HS FEED'!$A$11) -> 1 | O12: =COUNTIFS('18-Month HS Incidents'!$AO:$AO,'HS FEED'!O$2,'18-Month HS Incidents'!$AW:$AW,'HS FEED'!$A$11) -> 4 | P12: =COUNTIFS('18-Month HS Incidents'!$AO:$AO,'HS FEED'!P$2,'18-Month HS Incidents'!$AW:$AW,'HS FEED'!$A$11) -> 0 | Q12: =SUBTOTAL(9,N12:P12) -> 5 | R12: =SUBTOTAL(9,B12:Q12) -> 23 | S12: =COUNTIFS('18-Month HS Incidents'!$AO:$AO,'HS FEED'!S$2,'18-Month HS Incidents'!$AW:$AW,'HS FEED'!$A$11) -> 2 | T12: =COUNTIFS('18-Month HS Incidents'!$AO:$AO,'HS FEED'!T$2,'18-Month HS Incidents'!$AW:$AW,'HS FEED'!$A$11) -> 2 | U12: =COUNTIFS('18-Month HS Incidents'!$AO:$AO,'HS FEED'!U$2,'18-Month HS Incidents'!$AW:$AW,'HS FEED'!$A$11) -> 4 | V12: =SUBTOTAL(9,S12:U12) -> 8 | W12: =COUNTIFS('18-Month HS Incidents'!$AO:$AO,'HS FEED'!W$2,'18-Month HS Incidents'!$AW:$AW,'HS FEED'!$A$11) -> 3 | X12: =COUNTIFS('18-Month HS Incidents'!$AO:$AO,'HS FEED'!X$2,'18-Month HS Incidents'!$AW:$AW,'HS FEED'!$A$11) -> 3 | Y12: =COUNTIFS('18-Month HS Incidents'!$AO:$AO,'HS FEED'!Y$2,'18-Month HS Incidents'!$AW:$AW,'HS FEED'!$A$11) -> 2 | Z12: =SUBTOTAL(9,W12:Y12) -> 8 | AA12: =COUNTIFS('18-Month HS Incidents'!$AO:$AO,'HS FEED'!AA$2,'18-Month HS Incidents'!$AW:$AW,'HS FEED'!$A$11) -> 0 | AB12: =COUNTIFS('18-Month HS Incidents'!$AO:$AO,'HS FEED'!AB$2,'18-Month HS Incidents'!$AW:$AW,'HS FEED'!$A$11) -> 2 | AC12: =COUNTIFS('18-Month HS Incidents'!$AO:$AO,'HS FEED'!AC$2,'18-Month HS Incidents'!$AW:$AW,'HS FEED'!$A$11) -> 0 | AD12: =SUBTOTAL(9,AA12:AC12) -> 2 | AE12: =COUNTIFS('18-Month HS Incidents'!$AO:$AO,'HS FEED'!AE$2,'18-Month HS Incidents'!$AW:$AW,'HS FEED'!$A$11) -> 2 | AF12: =COUNTIFS('18-Month HS Incidents'!$AO:$AO,'HS FEED'!AF$2,'18-Month HS Incidents'!$AW:$AW,'HS FEED'!$A$11) -> 0 | AG12: =COUNTIFS('18-Month HS Incidents'!$AO:$AO,'HS FEED'!AG$2,'18-Month HS Incidents'!$AW:$AW,'HS FEED'!$A$11) -> 0 | AH12: =SUBTOTAL(9,AE12:AG12) -> 2 | AI12: =SUBTOTAL(9,S12:AH12) -> 20 | AJ12: Incidents | AK12: 21 | AL12: 49 | AM12: 63 | AN12: 44 | AO12: 66 | AP12: 84
A13: Claims | B13: =COUNTIFS('18-Month HS Incidents'!$AO:$AO,'HS FEED'!B$2,'18-Month HS Incidents'!$AR:$AR,"Claim",'18-Month HS Incidents'!$AW:$AW,'HS FEED'!$A$11) -> 0 | C13: =COUNTIFS('18-Month HS Incidents'!$AO:$AO,'HS FEED'!C$2,'18-Month HS Incidents'!$AR:$AR,"Claim",'18-Month HS Incidents'!$AW:$AW,'HS FEED'!$A$11) -> 0 | D13: =COUNTIFS('18-Month HS Incidents'!$AO:$AO,'HS FEED'!D$2,'18-Month HS Incidents'!$AR:$AR,"Claim",'18-Month HS Incidents'!$AW:$AW,'HS FEED'!$A$11) -> 0 | E13: =SUBTOTAL(9,B13:D13) -> 0 | F13: =COUNTIFS('18-Month HS Incidents'!$AO:$AO,'HS FEED'!F$2,'18-Month HS Incidents'!$AR:$AR,"Claim",'18-Month HS Incidents'!$AW:$AW,'HS FEED'!$A$11) -> 0 | G13: =COUNTIFS('18-Month HS Incidents'!$AO:$AO,'HS FEED'!G$2,'18-Month HS Incidents'!$AR:$AR,"Claim",'18-Month HS Incidents'!$AW:$AW,'HS FEED'!$A$11) -> 0 | H13: =COUNTIFS('18-Month HS Incidents'!$AO:$AO,'HS FEED'!H$2,'18-Month HS Incidents'!$AR:$AR,"Claim",'18-Month HS Incidents'!$AW:$AW,'HS FEED'!$A$11) -> 0 | I13: =SUBTOTAL(9,F13:H13) -> 0 | J13: =COUNTIFS('18-Month HS Incidents'!$AO:$AO,'HS FEED'!J$2,'18-Month HS Incidents'!$AR:$AR,"Claim",'18-Month HS Incidents'!$AW:$AW,'HS FEED'!$A$11) -> 0 | K13: =COUNTIFS('18-Month HS Incidents'!$AO:$AO,'HS FEED'!K$2,'18-Month HS Incidents'!$AR:$AR,"Claim",'18-Month HS Incidents'!$AW:$AW,'HS FEED'!$A$11) -> 1 | L13: =COUNTIFS('18-Month HS Incidents'!$AO:$AO,'HS FEED'!L$2,'18-Month HS Incidents'!$AR:$AR,"Claim",'18-Month HS Incidents'!$AW:$AW,'HS FEED'!$A$11) -> 0 | M13: =SUBTOTAL(9,J13:L13) -> 1 | N13: =COUNTIFS('18-Month HS Incidents'!$AO:$AO,'HS FEED'!N$2,'18-Month HS Incidents'!$AR:$AR,"Claim",'18-Month HS Incidents'!$AW:$AW,'HS FEED'!$A$11) -> 0 | O13: =COUNTIFS('18-Month HS Incidents'!$AO:$AO,'HS FEED'!O$2,'18-Month HS Incidents'!$AR:$AR,"Claim",'18-Month HS Incidents'!$AW:$AW,'HS FEED'!$A$11) -> 0 | P13: =COUNTIFS('18-Month HS Incidents'!$AO:$AO,'HS FEED'!P$2,'18-Month HS Incidents'!$AR:$AR,"Claim",'18-Month HS Incidents'!$AW:$AW,'HS FEED'!$A$11) -> 0 | Q13: =SUBTOTAL(9,N13:P13) -> 0 | R13: =SUBTOTAL(9,B13:Q13) -> 1 | S13: =COUNTIFS('18-Month HS Incidents'!$AO:$AO,'HS FEED'!S$2,'18-Month HS Incidents'!$AR:$AR,"Claim",'18-Month HS Incidents'!$AW:$AW,'HS FEED'!$A$11) -> 1 | T13: =COUNTIFS('18-Month HS Incidents'!$AO:$AO,'HS FEED'!T$2,'18-Month HS Incidents'!$AR:$AR,"Claim",'18-Month HS Incidents'!$AW:$AW,'HS FEED'!$A$11) -> 0 | U13: =COUNTIFS('18-Month HS Incidents'!$AO:$AO,'HS FEED'!U$2,'18-Month HS Incidents'!$AR:$AR,"Claim",'18-Month HS Incidents'!$AW:$AW,'HS FEED'!$A$11) -> 1 | V13: =SUBTOTAL(9,S13:U13) -> 2 | W13: =COUNTIFS('18-Month HS Incidents'!$AO:$AO,'HS FEED'!W$2,'18-Month HS Incidents'!$AR:$AR,"Claim",'18-Month HS Incidents'!$AW:$AW,'HS FEED'!$A$11) -> 1 | X13: =COUNTIFS('18-Month HS Incidents'!$AO:$AO,'HS FEED'!X$2,'18-Month HS Incidents'!$AR:$AR,"Claim",'18-Month HS Incidents'!$AW:$AW,'HS FEED'!$A$11) -> 1 | Y13: =COUNTIFS('18-Month HS Incidents'!$AO:$AO,'HS FEED'!Y$2,'18-Month HS Incidents'!$AR:$AR,"Claim",'18-Month HS Incidents'!$AW:$AW,'HS FEED'!$A$11) -> 0 | Z13: =SUBTOTAL(9,W13:Y13) -> 2 | AA13: =COUNTIFS('18-Month HS Incidents'!$AO:$AO,'HS FEED'!AA$2,'18-Month HS Incidents'!$AR:$AR,"Claim",'18-Month HS Incidents'!$AW:$AW,'HS FEED'!$A$11) -> 0 | AB13: =COUNTIFS('18-Month HS Incidents'!$AO:$AO,'HS FEED'!AB$2,'18-Month HS Incidents'!$AR:$AR,"Claim",'18-Month HS Incidents'!$AW:$AW,'HS FEED'!$A$11) -> 0 | AC13: =COUNTIFS('18-Month HS Incidents'!$AO:$AO,'HS FEED'!AC$2,'18-Month HS Incidents'!$AR:$AR,"Claim",'18-Month HS Incidents'!$AW:$AW,'HS FEED'!$A$11) -> 0 | AD13: =SUBTOTAL(9,AA13:AC13) -> 0 | AE13: =COUNTIFS('18-Month HS Incidents'!$AO:$AO,'HS FEED'!AE$2,'18-Month HS Incidents'!$AR:$AR,"Claim",'18-Month HS Incidents'!$AW:$AW,'HS FEED'!$A$11) -> 1 | AF13: =COUNTIFS('18-Month HS Incidents'!$AO:$AO,'HS FEED'!AF$2,'18-Month HS Incidents'!$AR:$AR,"Claim",'18-Month HS Incidents'!$AW:$AW,'HS FEED'!$A$11) -> 0 | AG13: =COUNTIFS('18-Month HS Incidents'!$AO:$AO,'HS FEED'!AG$2,'18-Month HS Incidents'!$AR:$AR,"Claim",'18-Month HS Incidents'!$AW:$AW,'HS FEED'!$A$11) -> 0 | AH13: =SUBTOTAL(9,AE13:AG13) -> 1 | AI13: =SUBTOTAL(9,S13:AH13) -> 5 | AJ13: Claims | AK13: 0 | AL13: 10 | AM13: 11 | AN13: 11 | AO13: 8 | AP13: 17
AK18: Under 1 Year | AL18: 1-5 Years | AM18: 6-10 Years | AN18: 11-15 Years | AO18: 16-20 Years | AP18: 21-25 Years | AQ18: 26-30 Years | AR18: More Than 30 Years
AJ19: Incidents | AK19: 62 | AL19: 165 | AM19: 47 | AN19: 17 | AO19: 17 | AP19: 7 | AQ19: 7 | AR19: 5
AJ20: Claims | AK20: 8 | AL20: 28 | AM20: 9 | AN20: 8 | AO20: 3 | AP20: 0 | AQ20: 1 | AR20: 0
AK23: 1 Year | AL23: 2 Years | AM23: 3 Years | AN23: 4 Years | AO23: 5 Years
AJ24: Incidents | AK24: 72 | AL24: 38 | AM24: 23 | AN24: 20 | AO24: 12
AJ25: Claims | AK25: 12 | AL25: 8 | AM25: 3 | AN25: 3 | AO25: 2

Sheet Group FEED
A1: Group | B1: FY24 | S1: FY25
A2: Incidents | B2: ="JUL, "&B1 -> JUL, FY24 | C2: ="AUG, "&B1 -> AUG, FY24 | D2: ="SEP, "&B1 -> SEP, FY24 | E2: ="Q1, "&B1 -> Q1, FY24 | F2: ="OCT, "&B1 -> OCT, FY24 | G2: ="NOV, "&B1 -> NOV, FY24 | H2: ="DEC, "&B1 -> DEC, FY24 | I2: ="Q2, "&B1 -> Q2, FY24 | J2: ="JAN, "&B1 -> JAN, FY24 | K2: ="FEB, "&B1 -> FEB, FY24 | L2: ="MAR, "&B1 -> MAR, FY24 | M2: ="Q3, "&B1 -> Q3, FY24 | N2: ="APR, "&B1 -> APR, FY24 | O2: ="MAY, "&B1 -> MAY, FY24 | P2: ="JUN, "&B1 -> JUN, FY24 | Q2: ="Q4, "&B1 -> Q4, FY24 | R2: ="Full Year, "&B1 -> Full Year, FY24 | S2: ="JUL, "&S1 -> JUL, FY25 | T2: ="AUG, "&S1 -> AUG, FY25 | U2: ="SEP, "&S1 -> SEP, FY25 | V2: ="Q1, "&S1 -> Q1, FY25 | W2: ="OCT, "&S1 -> OCT, FY25 | X2: ="NOV, "&S1 -> NOV, FY25 | Y2: ="DEC, "&S1 -> DEC, FY25 | Z2: ="Q2, "&S1 -> Q2, FY25 | AA2: ="JAN, "&S1 -> JAN, FY25 | AB2: ="FEB, "&S1 -> FEB, FY25 | AC2: ="MAR, "&S1 -> MAR, FY25 | AD2: ="Q3, "&S1 -> Q3, FY25 | AE2: ="APR, "&S1 -> APR, FY25 | AF2: ="MAY, "&S1 -> MAY, FY25 | AG2: ="JUN, "&S1 -> JUN, FY25 | AH2: ="Q4, "&S1 -> Q4, FY25 | AI2: ="Full Year, "&S1 -> Full Year, FY25
A3: Incidents | B3: =COUNTIF('INC DATA DUMP - FY23+'!$AA:$AA,'Group FEED'!B$2) -> 75 | C3: =COUNTIF('INC DATA DUMP - FY23+'!$AA:$AA,'Group FEED'!C$2) -> 107 | D3: =COUNTIF('INC DATA DUMP - FY23+'!$AA:$AA,'Group FEED'!D$2) -> 79 | E3: =SUBTOTAL(9,B3:D3) -> 261 | F3: =COUNTIF('INC DATA DUMP - FY23+'!$AA:$AA,'Group FEED'!F$2) -> 89 | G3: =COUNTIF('INC DATA DUMP - FY23+'!$AA:$AA,'Group FEED'!G$2) -> 107 | H3: =COUNTIF('INC DATA DUMP - FY23+'!$AA:$AA,'Group FEED'!H$2) -> 109 | I3: =SUBTOTAL(9,F3:H3) -> 305 | J3: =COUNTIF('INC DATA DUMP - FY23+'!$AA:$AA,'Group FEED'!J$2) -> 80 | K3: =COUNTIF('INC DATA DUMP - FY23+'!$AA:$AA,'Group FEED'!K$2) -> 93 | L3: =COUNTIF('INC DATA DUMP - FY23+'!$AA:$AA,'Group FEED'!L$2) -> 94 | M3: =SUBTOTAL(9,J3:L3) -> 267 | N3: =COUNTIF('INC DATA DUMP - FY23+'!$AA:$AA,'Group FEED'!N$2) -> 72 | O3: =COUNTIF('INC DATA DUMP - FY23+'!$AA:$AA,'Group FEED'!O$2) -> 114 | P3: =COUNTIF('INC DATA DUMP - FY23+'!$AA:$AA,'Group FEED'!P$2) -> 85 | Q3: =SUBTOTAL(9,N3:P3) -> 271 | R3: =SUBTOTAL(9,B3:Q3) -> 1104 | S3: =COUNTIF('INC DATA DUMP - FY23+'!$AA:$AA,'Group FEED'!S$2) -> 73 | T3: =COUNTIF('INC DATA DUMP - FY23+'!$AA:$AA,'Group FEED'!T$2) -> 103 | U3: =COUNTIF('INC DATA DUMP - FY23+'!$AA:$AA,'Group FEED'!U$2) -> 66 | V3: =SUBTOTAL(9,S3:U3) -> 242 | W3: =COUNTIF('INC DATA DUMP - FY23+'!$AA:$AA,'Group FEED'!W$2) -> 83 | X3: =COUNTIF('INC DATA DUMP - FY23+'!$AA:$AA,'Group FEED'!X$2) -> 101 | Y3: =COUNTIF('INC DATA DUMP - FY23+'!$AA:$AA,'Group FEED'!Y$2) -> 81 | Z3: =SUBTOTAL(9,W3:Y3) -> 265 | AA3: =COUNTIF('INC DATA DUMP - FY23+'!$AA:$AA,'Group FEED'!AA$2) -> 66 | AB3: =COUNTIF('INC DATA DUMP - FY23+'!$AA:$AA,'Group FEED'!AB$2) -> 85 | AC3: =COUNTIF('INC DATA DUMP - FY23+'!$AA:$AA,'Group FEED'!AC$2) -> 81 | AD3: =SUBTOTAL(9,AA3:AC3) -> 232 | AE3: =COUNTIF('INC DATA DUMP - FY23+'!$AA:$AA,'Group FEED'!AE$2) -> 65 | AF3: =COUNTIF('INC DATA DUMP - FY23+'!$AA:$AA,'Group FEED'!AF$2) -> 95 | AG3: =COUNTIF('INC DATA DUMP - FY23+'!$AA:$AA,'Group FEED'!AG$2) -> 0 | AH3: =SUBTOTAL(9,AE3:AG3) -> 160 | AI3: =SUBTOTAL(9,S3:AH3) -> 899
A4: YTD Incidents | B4: =SUBTOTAL(9,$B3:B3) -> 75 | C4: =SUBTOTAL(9,$B3:C3) -> 182 | D4: =SUBTOTAL(9,$B3:D3) -> 261 | E4: =SUBTOTAL(9,$B3:E3) -> 261 | F4: =SUBTOTAL(9,$B3:F3) -> 350 | G4: =SUBTOTAL(9,$B3:G3) -> 457 | H4: =SUBTOTAL(9,$B3:H3) -> 566 | I4: =SUBTOTAL(9,$B3:I3) -> 566 | ... R4: =SUBTOTAL(9,$B3:R3) -> 1104 | S4: =SUBTOTAL(9,$S3:S3) -> 73 | T4: =SUBTOTAL(9,$S3:T3) -> 176 | U4: =SUBTOTAL(9,$S3:U3) -> 242 | V4: =SUBTOTAL(9,$S3:V3) -> 242 | W4: =SUBTOTAL(9,$S3:W3) -> 325 | X4: =SUBTOTAL(9,$S3:X3) -> 426 | Y4: =SUBTOTAL(9,$S3:Y3) -> 507 | Z4: =SUBTOTAL(9,$S3:Z3) -> 507 | ... AI4: =SUBTOTAL(9,$S3:AI3) -> 899
A6: Claims
A7: Claims | B7: =COUNTIFS('INC DATA DUMP - FY23+'!$AD:$AD,"Claim",'INC DATA DUMP - FY23+'!$AA:$AA,'Group FEED'!B$2) -> 7 | C7: =COUNTIFS('INC DATA DUMP - FY23+'!$AD:$AD,"Claim",'INC DATA DUMP - FY23+'!$AA:$AA,'Group FEED'!C$2) -> 18 | D7: =COUNTIFS('INC DATA DUMP - FY23+'!$AD:$AD,"Claim",'INC DATA DUMP - FY23+'!$AA:$AA,'Group FEED'!D$2) -> 11 | E7: =SUBTOTAL(9,B7:D7) -> 36 | F7: =COUNTIFS('INC DATA DUMP - FY23+'!$AD:$AD,"Claim",'INC DATA DUMP - FY23+'!$AA:$AA,'Group FEED'!F$2) -> 12 | G7: =COUNTIFS('INC DATA DUMP - FY23+'!$AD:$AD,"Claim",'INC DATA DUMP - FY23+'!$AA:$AA,'Group FEED'!G$2) -> 14 | H7: =COUNTIFS('INC DATA DUMP - FY23+'!$AD:$AD,"Claim",'INC DATA DUMP - FY23+'!$AA:$AA,'Group FEED'!H$2) -> 9 | I7: =SUBTOTAL(9,F7:H7) -> 35 | J7: =COUNTIFS('INC DATA DUMP - FY23+'!$AD:$AD,"Claim",'INC DATA DUMP - FY23+'!$AA:$AA,'Group FEED'!J$2) -> 11 | K7: =COUNTIFS('INC DATA DUMP - FY23+'!$AD:$AD,"Claim",'INC DATA DUMP - FY23+'!$AA:$AA,'Group FEED'!K$2) -> 11 | L7: =COUNTIFS('INC DATA DUMP - FY23+'!$AD:$AD,"Claim",'INC DATA DUMP - FY23+'!$AA:$AA,'Group FEED'!L$2) -> 15 | M7: =SUBTOTAL(9,J7:L7) -> 37 | N7: =COUNTIFS('INC DATA DUMP - FY23+'!$AD:$AD,"Claim",'INC DATA DUMP - FY23+'!$AA:$AA,'Group FEED'!N$2) -> 7 | O7: =COUNTIFS('INC DATA DUMP - FY23+'!$AD:$AD,"Claim",'INC DATA DUMP - FY23+'!$AA:$AA,'Group FEED'!O$2) -> 19 | P7: =COUNTIFS('INC DATA DUMP - FY23+'!$AD:$AD,"Claim",'INC DATA DUMP - FY23+'!$AA:$AA,'Group FEED'!P$2) -> 16 | Q7: =SUBTOTAL(9,N7:P7) -> 42 | R7: =SUBTOTAL(9,B7:Q7) -> 150 | S7: =COUNTIFS('INC DATA DUMP - FY23+'!$AD:$AD,"Claim",'INC DATA DUMP - FY23+'!$AA:$AA,'Group FEED'!S$2) -> 14 | T7: =COUNTIFS('INC DATA DUMP - FY23+'!$AD:$AD,"Claim",'INC DATA DUMP - FY23+'!$AA:$AA,'Group FEED'!T$2) -> 29 | U7: =COUNTIFS('INC DATA DUMP - FY23+'!$AD:$AD,"Claim",'INC DATA DUMP - FY23+'!$AA:$AA,'Group FEED'!U$2) -> 16 | V7: =SUBTOTAL(9,S7:U7) -> 59 | W7: =COUNTIFS('INC DATA DUMP - FY23+'!$AD:$AD,"Claim",'INC DATA DUMP - FY23+'!$AA:$AA,'Group FEED'!W$2) -> 19 | X7: =COUNTIFS('INC DATA DUMP - FY23+'!$AD:$AD,"Claim",'INC DATA DUMP - FY23+'!$AA:$AA,'Group FEED'!X$2) -> 22 | Y7: =COUNTIFS('INC DATA DUMP - FY23+'!$AD:$AD,"Claim",'INC DATA DUMP - FY23+'!$AA:$AA,'Group FEED'!Y$2) -> 10 | Z7: =SUBTOTAL(9,W7:Y7) -> 51 | AA7: =COUNTIFS('INC DATA DUMP - FY23+'!$AD:$AD,"Claim",'INC DATA DUMP - FY23+'!$AA:$AA,'Group FEED'!AA$2) -> 13 | AB7: =COUNTIFS('INC DATA DUMP - FY23+'!$AD:$AD,"Claim",'INC DATA DUMP - FY23+'!$AA:$AA,'Group FEED'!AB$2) -> 13 | AC7: =COUNTIFS('INC DATA DUMP - FY23+'!$AD:$AD,"Claim",'INC DATA DUMP - FY23+'!$AA:$AA,'Group FEED'!AC$2) -> 11 | AD7: =SUBTOTAL(9,AA7:AC7) -> 37 | AE7: =COUNTIFS('INC DATA DUMP - FY23+'!$AD:$AD,"Claim",'INC DATA DUMP - FY23+'!$AA:$AA,'Group FEED'!AE$2) -> 12 | AF7: =COUNTIFS('INC DATA DUMP - FY23+'!$AD:$AD,"Claim",'INC DATA DUMP - FY23+'!$AA:$AA,'Group FEED'!AF$2) -> 8 | AG7: =COUNTIFS('INC DATA DUMP - FY23+'!$AD:$AD,"Claim",'INC DATA DUMP - FY23+'!$AA:$AA,'Group FEED'!AG$2) -> 0 | AH7: =SUBTOTAL(9,AE7:AG7) -> 20 | AI7: =SUBTOTAL(9,S7:AH7) -> 167
A8: YTD Claims | B8: =SUBTOTAL(9,$B7:B7) -> 7 | C8: =SUBTOTAL(9,$B7:C7) -> 25 | D8: =SUBTOTAL(9,$B7:D7) -> 36 | E8: =SUBTOTAL(9,$B7:E7) -> 36 | F8: =SUBTOTAL(9,$B7:F7) -> 48 | G8: =SUBTOTAL(9,$B7:G7) -> 62 | H8: =SUBTOTAL(9,$B7:H7) -> 71 | I8: =SUBTOTAL(9,$B7:I7) -> 71 | ... R8: =SUBTOTAL(9,$B7:R7) -> 150 | S8: =SUBTOTAL(9,$S7:S7) -> 14 | T8: =SUBTOTAL(9,$S7:T7) -> 43 | U8: =SUBTOTAL(9,$S7:U7) -> 59 | V8: =SUBTOTAL(9,$S7:V7) -> 59 | W8: =SUBTOTAL(9,$S7:W7) -> 78 | X8: =SUBTOTAL(9,$S7:X7) -> 100 | Y8: =SUBTOTAL(9,$S7:Y7) -> 110 | Z8: =SUBTOTAL(9,$S7:Z7) -> 110 | ... AI8: =SUBTOTAL(9,$S7:AI7) -> 167

Sheet INC DATA DUMP - FY23+
A1: SolvInjury ID | B1: Claim Number | C1: Mental Injury | D1: Employee ID | E1: Name | F1: Date of Injury | G1: Time of Injury | H1: Policy | I1: Site | J1: Name | K1: Injury Description | L1: Incident Description | M1: Injury Type | N1: Liability Status | O1: Current Capacity | P1: Open/Closed | Q1: Days Lost | R1: Worksafe Notified | S1: Injury Outcome | T1: Nature of Injury | U1: Bodily Location | V1: Mechanism | W1: Sub Mechanism | X1: Agency | Y1: Equipment | Z1: Closure Rate | AA1: Fiscal Month | AB1: Fiscal Quarter | AC1: Outcome Code | AD1: Claim | AE1: Claim Status | AF1: MOI | AG1: Agency | AH1: Company on Policy | AI1: State | AJ1: Class 3 | AK1: Company | AL1: Region | AM1: Grouping Level 1 | AN1: Grouping Level 2
A2: SRG-INJ-3692 | C2: No | D2: AU239233 | E2: EDWARDS, JODY | F2: 45809 | G2: 0.45486111 | H2: Spotlight NSW | I2: S030 | J2: Birkenhead Point | K2: top of head | L2: Jody was putting back outdoor blinds when the top bar, which had not been properly installed, dislodged and fell on her head. She hadnâ€™t noticed it had hit the bar while lifting the blind. This has been an ongoing issue. A customer heard the bar fall and checked Jodyâ€™s head for any cuts or bleeding. | M2: Injury | O2: No Assessment | P2: Open | Q2: 0 | R2: FALSE | S2: First Aid Injury | T2: Contusion, bruising and superficial crushing | U2: Head - unspecified locations | V2: Being Hit By Moving Objects | W2: Being hit by falling objects | X2: Human agencies | Y2: R-Bar | Z2: 0 | AA2: MAY, FY25 | AB2: Q4, FY25 | AC2: FAIs | AF2: Being Hit By Moving Objects | AG2: Human agencies | AH2: Spotlight | AI2: NSW | AJ2: Store | AK2: Spotlight AU | AL2: NSW Central | AM2: Spotlight AU | AN2: Spotlight AU - NSW Central
A3: SRG-INJ-3695 | C3: No | D3: AU334785 | E3: GORDON, TAMMEE LEE | F3: 45809 | G3: 0.42361111 | H3: Anaconda NSW | I3: A061 | J3: Marsden Park | K3: Left foot, big toe | L3: Tamme was serving customer with the ammunition boxes large maxxtrax recovery boards to slip off the shelf onto her toe Tammee, she visited doctor they dressed the wound on left toe and suggested an X-Ray | M3: Injury | O3: No Assessment | P3: Open | Q3: 0 | R3: FALSE | S3: Lost Time Injury | T3: Laceration or open wound not involving traumatic amputation | U3: Foot and toes | V3: Being Hit By Moving Objects | W3: Being hit by falling objects | X3: Human agencies | Y3: Boxes | Z3: 0 | AA3: MAY, FY25 | AB3: Q4, FY25 | AC3: LTIs | AF3: Being Hit By Moving Objects | AG3: Human agencies | AH3: Anaconda | AI3: NSW | AJ3: Store | AK3: Anaconda | AL3: NSW North | AM3: Anaconda | AN3: Anaconda - NSW North
A4: SRG-INJ-3696 | C4: No | D4: AU338012 | E4: DE CHAZAL, VENETIA | F4: 45808 | G4: 0.49097222 | H4: Spotlight QLD | I4: S080 | J4: Maroochydore | K4: Knee | L4: Ven tripped on a bar that was protruding from a M2M display and fell, landing on her knee. Ven came off the floor and we applied an ide pack to the injury. She sat for 15 minutes then returned to the floor. | M4: Injury | O4: No Assessment | P4: Open | Q4: 0 | R4: FALSE | S4: First Aid Injury | T4: Trauma to muscles and tendons | U4: Knee | V4: Being Hit By Moving Objects | W4: Being hit by falling objects | X4: Human agencies | Z4: 0 | AA4: MAY, FY25 | AB4: Q4, FY25 | AC4: FAIs | AF4: Being Hit By Moving Objects | AG4: Human agencies | AH4: Spotlight | AI4: QLD | AJ4: Store | AK4: Spotlight AU | AL4: QLD Central / TAS | AM4: Spotlight AU | AN4: Spotlight AU - QLD Central / TAS
A5: SRG-INJ-3687 | C5: No | D5: AU300442 | E5: SMART, ROSALIND | F5: 45807 | G5: 0.5625 | H5: Spotlight QLD | I5: S079 | J5: West Burleigh | K5: left knee with already sustained injury | L5: A substance impaired person in store, talking to himself constantly the whole time in store decided when team member was approaching to walk past to put his foot out in front of her. Team member did a big sidestep to avoid going near the guy and tripping over his foot, passing between 2 dump bins. | M5: Injury | O5: No Assessment | P5: Open | Q5: 0 | R5: FALSE | S5: Not Applicable | T5: Trauma to muscles and tendons | U5: Knee | V5: Falls, Trips and Slips of a Person | W5: Falls on the same level | X5: Human agencies | Z5: 0 | AA5: MAY, FY25 | AB5: Q4, FY25 | AC5: Incident | AF5: Falls, Trips and Slips of a Person | AG5: Human agencies | AH5: Spotlight | AI5: QLD | AJ5: Store | AK5: Spotlight AU | AL5: NSW North / QLD South | AM5: Spotlight AU | AN5: Spotlight AU - NSW North / QLD South
A6: SRG-INJ-3689 | C6: No | D6: AU214010 | E6: CHARLTON, VICKIE | F6: 45807 | G6: 0.61458333 | H6: Spotlight TAS | I6: S060 | J6: Hobart - Glenorchy | K6: right thumb and wrist, bit of numbness and aching | L6: Vickie was picking up a box of ready made curtains from the bottom of the pallet and the box of ready mades slipped back onto her hand. | M6: Injury | O6: No Assessment | P6: Open | Q6: 0 | R6: FALSE | S6: Not Applicable | T6: Trauma to muscles and tendons | U6: Hand, finger and thumb | V6: Body Stressing | W6: Muscular stress while lifting, carrying, or putting down objects | X6: Human agencies | Y6: Boxes | Z6: 0 | AA6: MAY, FY25 | AB6: Q4, FY25 | AC6: Incident | AF6: Body Stressing | AG6: Human agencies | AH6: Spotlight | AI6: TAS | AJ6: Store | AK6: Spotlight AU | AL6: QLD Central / TAS | AM6: Spotlight AU | AN6: Spotlight AU - QLD Central / TAS
A7: SRG-INJ-3694 | C7: No | D7: AU307953 | E7: TYLER-WHITEMAN, KYRA | F7: 45807 | G7: 0.64166667 | H7: Anaconda WA | I7: A090 | J7: Mandurah | K7: sprain to right ankle | L7: Kyra was standing on a 3 step ladder, forgot she was above ground level and stepped straight onto the floor. Sprain to right ankle | M7: Injury | O7: No Assessment | P7: Open | Q7: 0 | R7: FALSE | S7: Not Applicable | T7: Trauma to muscles and tendons | U7: Ankle | V7: Falls, Trips and Slips of a Person | W7: Falls from a height | X7: Human agencies | Y7: Ladder | Z7: 0 | AA7: MAY, FY25 | AB7: Q4, FY25 | AC7: Incident | AF7: Falls, Trips and Slips of a Person | AG7: Human agencies | AH7: Anaconda | AI7: WA | AJ7: Store | AK7: Anaconda | AL7: WA | AM7: Anaconda | AN7: Anaconda - WA
A8: SRG-INJ-3685 | C8: No | D8: AU316673 | E8: WELLSTEAD, BENJAMIN | F8: 45806 | G8: 0.59375 | H8: Spotlight WA | I8: S084 | J8: Bunbury | K8: Mid back. Strain and pain. | L8: While serving a customer I picked up a 160x230cm KOO Ombre Charcoal rug and returned the product to the bin. As I picked it up a felt a pull and sharp pain in my mid back. I reported the incident immediately to DTL Paul Rodgers. Rested and stretched in the office for 10 minutes and return to work. | M8: Injury | O8: No Assessment | P8: Open | Q8: 0 | R8: FALSE | S8: Not Applicable | T8: Trauma to muscles and tendons | U8: Back-Upper and lower | V8: Body Stressing | W8: Muscular stress while lifting, carrying, or putting down objects | X8: Human agencies | Z8: 0 | AA8: MAY, FY25 | AB8: Q4, FY25 | AC8: Incident | AF8: Body Stressing | AG8: Human agencies | AH8: Spotlight | AI8: WA | AJ8: Store | AK8: Spotlight AU | AL8: WA | AM8: Spotlight AU | AN8: Spotlight AU - WA
A9: SRG-INJ-3682 | C9: No | D9: AU233860 | E9: MCKEE, SAM | F9: 45806 | G9: 0.60347222 | H9: Anaconda ACT | I9: A027 | J9: Fyshwick | K9: crush/laceration right thumb | L9: throwing fixtures into skip bin, fixture slipped and thumb became jammed between fixture and skip bin | M9: Injury | O9: No Assessment | P9: Open | Q9: 0 | R9: FALSE | S9: First Aid Injury | T9: Laceration or open wound not involving traumatic amputation | U9: Hand, finger and thumb | V9: Being Hit By Moving Objects | W9: Being trapped between stationary and moving objects | X9: Human agencies | Z9: 0 | AA9: MAY, FY25 | AB9: Q4, FY25 | AC9: FAIs | AF9: Being Hit By Moving Objects | AG9: Human agencies | AH9: Anaconda | AI9: ACT | AJ9: Store | AK9: Anaconda | AL9: SA / ACT | AM9: Anaconda | AN9: Anaconda - SA / ACT
A10: SRG-INJ-3686 | C10: No | D10: AU338492 | E10: BESTER, ADDISON | F10: 45806 | G10: 0.78125 | H10: Spotlight TAS | I10: S102 | J10: Burnie | K10: Fingers being cut | L10: Adi was pulling flannelette sheets out of a pallet and onto the tables during nightfill and received a couple of papercuts on her fingers while handling the sheets from the card wrap-around on the sheets. | M10: Injury | O10: No Assessment | P10: Closed | Q10: 0 | R10: FALSE | S10: First Aid Injury | T10: Laceration or open wound not involving traumatic amputation | U10: Hand, finger and thumb | V10: Hitting Objects With a Part of the Body | W10: Hitting stationary objects | X10: Human agencies | Z10: 0 | AA10: MAY, FY25 | AB10: Q4, FY25 | AC10: FAIs | AF10: Hitting Objects With a Part of the Body | AG10: Human agencies | AH10: Spotlight | AI10: TAS | AJ10: Store | AK10: Spotlight AU | AL10: QLD Central / TAS | AM10: Spotlight AU | AN10: Spotlight AU - QLD Central / TAS
A11: SRG-INJ-3677 | C11: No | D11: AU310973 | E11: MCCULLOCH, CHASE | F11: 45806 | G11: 0.47569444 | H11: Spotlight QLD | I11: S161 | J11: Carindale | K11: upper left eyebrow, upper left cheek and left side of nose was hit by falling stock | L11: pulling the roll cage through the fire corridoor, roll cage got stuck in a hole and tiped. stock fell off. hit my upper left cheek left eyebrow and left side of my nose. the floors had been logged due to the unsafe nature of the floor and multiple holes in the concrete that the cages get stuck in. | M11: Injury | O11: No Assessment | P11: Open | Q11: 0 | R11: FALSE | S11: First Aid Injury | T11: Contusion, bruising and superficial crushing | U11: Face, not elsewhere classified | V11: Being Hit By Moving Objects | W11: Being hit by falling objects | X11: Human agencies | Y11: Roll Cages | Z11: 0 | AA11: MAY, FY25 | AB11: Q4, FY25 | AC11: FAIs | AF11: Being Hit By Moving Objects | AG11: Human agencies | AH11: Spotlight | AI11: QLD | AJ11: Store | AK11: Spotlight AU | AL11: QLD Central / TAS | AM11: Spotlight AU | AN11: Spotlight AU - QLD Central / TAS
A12: SRG-INJ-3688 | C12: No | D12: AU337223 | E12: ELLA, CHELSEA | F12: 45806 | G12: 0.63263889 | H12: Spotlight QLD | I12: S168 | J12: Windsor | K12: right hand | L12: Chelsea was up a ladder putting a cast Iron casserole dish on the shelf which was heavier then most baking items and hit her right hand on the ladder which has caused redness and swelling, tightness of the hand in opening and closing fist. | M12: Injury | O12: No Assessment | P12: Open | Q12: 0 | R12: FALSE | S12: Not Applicable | T12: Trauma to muscles and tendons | U12: Hand, finger and thumb | V12: Body Stressing | W12: Muscular stress while lifting, carrying, or putting down objects | X12: Human agencies | Z12: 0 | AA12: MAY, FY25 | AB12: Q4, FY25 | AC12: Incident | AF12: Body Stressing | AG12: Human agencies | AH12: Spotlight | AI12: QLD | AJ12: Store | AK12: Spotlight AU | AL12: QLD North | AM12: Spotlight AU | AN12: Spotlight AU - QLD North
A13: SRG-INJ-3684 | C13: No | D13: AU204295 | E13: SCHILLING, SHERIDAN | F13: 45806 | G13: 0.62361111 | H13: Spotlight SA | I13: S117 | J13: Noarlunga | K13: right temporal lobe | L13: Removing a roller blind from the bay when another blind fell and hit her on right temporal area | M13: Injury | O13: No Assessment | P13: Open | Q13: 0 | R13: FALSE | S13: Not Applicable | T13: Laceration or open wound not involving traumatic amputation | U13: Head - unspecified locations | V13: Being Hit By Moving Objects | W13: Being hit by falling objects | X13: Human agencies | Z13: 0 | AA13: MAY, FY25 | AB13: Q4, FY25 | AC13: Incident | AF13: Being Hit By Moving Objects | AG13: Human agencies | AH13: Spotlight | AI13: SA | AJ13: Store | AK13: Spotlight AU | AL13: SA/NT | AM13: Spotlight AU | AN13: Spotlight AU - SA/NT
A14: SRG-INJ-3675 | C14: No | D14: AU310802 | E14: SOONDRA, AMANDA | F14: 45805 | G14: 0.42083333 | H14: Spotlight SA | I14: S044 | J14: Munno Para | K14: sore hip | L14: Amanda has said when working in greenery her back started to hurt believes it may have been when working Manu cast iron stock but noticed no pain until evening progress back sore around 6:30pm | M14: Injury | O14: No Assessment | P14: Open | Q14: 0 | R14: FALSE | S14: Not Applicable | T14: Trauma to muscles and tendons | U14: Hip | V14: Body Stressing | W14: Muscular stress while lifting, carrying, or putting down objects | X14: Human agencies | Z14: 0 | AA14: MAY, FY25 | AB14: Q4, FY25 | AC14: Incident | AF14: Body Stressing | AG14: Human agencies | AH14: Spotlight | AI14: SA | AJ14: Store | AK14: Spotlight AU | AL14: SA/NT | AM14: Spotlight AU | AN14: Spotlight AU - SA/NT
A15: SRG-INJ-3681 | C15: No | D15: AU337204 | E15: HURLEY, ASTON | F15: 45805 | G15: 0.51388889 | H15: Spotlight VIC | I15: S049 | J15: Horsham | K15: Right Hand | L15: team member walked around corner and his right hand ( top of hand behind the index ) collided with the edge of a cove. the edge did not have a plastic cover insert for protection and was a little sharp however it was blunt force that has cause an abrasion to the skin ( 1 cm width ) as well as immediate swelling and bruising on entire hand. TM dropped to the ground in pain, did not land on the hand. was holding the hand with his left hand and was curdled on the ground. TM proceeded out back and informed Adam DTL and was treated with an ice pack with a tea towel. Pain over night, Panadol for treatment. grip cause pain and stretching. Pain has stayed stagnate and abrasion and swelling have remained the same. Today using avoidance of using to cure pain. does not believe will see a doctor but believes may be fractured. optimistic it will get better on its own. | M15: Injury | O15: No Assessment | P15: Open | Q15: 0 | R15: FALSE | S15: First Aid Injury | T15: Laceration or open wound not involving traumatic amputation | U15: Hand, finger and thumb | V15: Hitting Objects With a Part of the Body | W15: Rubbing and chafing | X15: Human agencies | Z15: 0 | AA15: MAY, FY25 | AB15: Q4, FY25 | AC15: FAIs | AF15: Hitting Objects With a Part of the Body | AG15: Human agencies | AH15: Spotlight | AI15: VIC | AJ15: Store | AK15: Spotlight AU | AL15: VIC West | AM15: Spotlight AU | AN15: Spotlight AU - VIC West
A16: SRG-INJ-3678 | C16: Yes | D16: AU317008 | E16: HARMER, BREANNAH | F16: 45805 | G16: 0.4375 | H16: Anaconda SA | I16: A075 | J16: Munno Para | K16: Bullying | L16: team member threw back her keys and said you can cover my shifts for this and week. texted the regional manager saying she was having the rest of the week off sick due to bullying in the work place and wants to go on stress leave. | M16: Injury | O16: No Assessment | P16: Open | Q16: 0 | R16: FALSE | S16: Lost Time Injury | T16: Mental diseases unspecified | U16: Psychological system | V16: Mental Stress | W16: Work related harassment and/or workplace bullying | X16: Human agencies | Z16: 0 | AA16: MAY, FY25 | AB16: Q4, FY25 | AC16: LTIs | AF16: Mental Stress | AG16: Human agencies | AH16: Anaconda | AI16: SA | AJ16: Store | AK16: Anaconda | AL16: SA / ACT | AM16: Anaconda | AN16: Anaconda - SA / ACT
A17: SRG-INJ-3670 | C17: No | D17: AU339367 | E17: BARTELT, SUZANNE | F17: 45804 | G17: 0.59166667 | H17: Spotlight QLD | I17: S205 | J17: Airlie Beach | K17: Left shoulder | L17: Suzanne Bartelt was unloading a pallet of stock in the sew center, and during the process of lifting multiple fabric rolls at the same time felt a pain the left shoulder. | M17: Injury | O17: No Assessment | P17: Closed | Q17: 0 | R17: FALSE | S17: Not Applicable | T17: Trauma to muscles and tendons | U17: Shoulder | V17: Body Stressing | W17: Muscular stress with no objects being handled | X17: Human agencies | Z17: 0 | AA17: MAY, FY25 | AB17: Q4, FY25 | AC17: Incident | AF17: Body Stressing | AG17: Human agencies | AH17: Spotlight | AI17: QLD | AJ17: Store | AK17: Spotlight AU | AL17: QLD North | AM17: Spotlight AU | AN17: Spotlight AU - QLD North
A18: SRG-INJ-3674 | C18: No | D18: AU237793 | E18: GIBLETT, SAMONE | F18: 45804 | G18: 0.45277778 | H18: Spotlight VIC | I18: S015 | J18: Bairnsdale | K18: both shoulders are sore/ strained and a sore left knee | L18: Had to move the anti fatigue mats behind POS3 to be able to get the wave in to geta print down for a customer. Ella was operating the Wave and was getting a print down but was waiting for Samone to grab another to put it back up. Samone tripped over the 3 mats, piled behind counter as she gave a print to Ella. | M18: Injury | O18: No Assessment | P18: Closed | Q18: 0 | R18: FALSE | S18: Not Applicable | T18: Trauma to muscles and tendons | U18: Upper limb - multiple locations | V18: Falls, Trips and Slips of a Person | W18: Falls on the same level | X18: Human agencies | Z18: 0 | AA18: MAY, FY25 | AB18: Q4, FY25 | AC18: Incident | AF18: Falls, Trips and Slips of a Person | AG18: Human agencies | AH18: Spotlight | AI18: VIC | AJ18: Store | AK18: Spotlight AU | AL18: VIC East | AM18: Spotlight AU | AN18: Spotlight AU - VIC East
A19: SRG-INJ-3676 | C19: No | D19: AU218050 | E19: PHILPOTT, LINDY-ANN | F19: 45804 | G19: 0.75902778 | H19: Spotlight TAS | I19: S102 | J19: Burnie | K19: top of head | L19: she accidentally knocked an A4 frame, which fell and hit Lindy on the head. Sophie provided an ice pack and confirmed Lindy was onfirmed Lindy was okay to continue her shift. Lindy later reported the incident to Henry, and we are completing the repor | M19: Injury | O19: No Assessment | P19: Open | Q19: 0 | R19: FALSE | S19: First Aid Injury | T19: Contusion, bruising and superficial crushing | U19: Head - unspecified locations | V19: Being Hit By Moving Objects | W19: Being hit by falling objects | X19: Human agencies | Z19: 0 | AA19: MAY, FY25 | AB19: Q4, FY25 | AC19: FAIs | AF19: Being Hit By Moving Objects | AG19: Human agencies | AH19: Spotlight | AI19: TAS | AJ19: Store | AK19: Spotlight AU | AL19: QLD Central / TAS | AM19: Spotlight AU | AN19: Spotlight AU - QLD Central / TAS
A20: SRG-INJ-3667 | C20: No | D20: AU298862 | E20: SEKULIC, AMY | F20: 45803 | G20: 0.48263889 | H20: Spotlight NSW | I20: S045 | J20: Lidcombe | K20: Left Knee on impact with Floor as well as right hand and right foot | L20: Team member was picking items in despatch for eComm when loose stock fell from a shelf as she pulled down a box. As she turned to pick up the box, she slipped on a piece of broken plastic and fell, injuring her hand, knee, and foot. | M20: Injury | O20: Unfit | P20: Open | Q20: 5 | R20: FALSE | S20: Lost Time Injury | T20: Contusion, bruising and superficial crushing | U20: Upper limb - multiple locations | V20: Hitting Objects With a Part of the Body | W20: Hitting stationary objects | X20: Human agencies | Z20: 0 | AA20: MAY, FY25 | AB20: Q4, FY25 | AC20: LTIs | AF20: Hitting Objects With a Part of the Body | AG20: Human agencies | AH20: Spotlight | AI20: NSW | AJ20: Store | AK20: Spotlight AU | AL20: NSW South / ACT | AM20: Spotlight AU | AN20: Spotlight AU - NSW South / ACT
A21: SRG-INJ-3666 | C21: No | D21: HS297107 | E21: DANOS, NICOLE | F21: 45803 | G21: 0.34027778 | H21: Harris Scarfe TAS | I21: 4043 | J21: Launceston | K21: Nicky landed on her left shoulder, which it tender | L21: Nicky was picking ecom when cleaners were mopping floor without wet floor signage. Nicky slipped and fell. | M21: Injury | O21: Fit | P21: Open | Q21: 0 | R21: FALSE | S21: Not Applicable | T21: Trauma to muscles and tendons | U21: Shoulder | V21: Falls, Trips and Slips of a Person | W21: Falls on the same level | X21: Human agencies | Z21: 0 | AA21: MAY, FY25 | AB21: Q4, FY25 | AC21: Incident | AF21: Falls, Trips and Slips of a Person | AG21: Human agencies | AH21: Harris Scarfe | AI21: TAS | AJ21: Store | AK21: Harris Scarfe | AL21: SA/TAS | AM21: Harris Scarfe | AN21: Harris Scarfe - SA/TAS
A22: SRG-INJ-3669 | C22: No | D22: HS251836 | E22: CARVER, JOSEPHINE | F22: 45803 | G22: 0.39583333 | H22: Harris Scarfe TAS | I22: 4044 | J22: Devonport | K22: Left side of face cheekbone | L22: Josephine Carver Moving bars from fixtures in shelving flicked up and hit me in the face. | M22: Injury | O22: No Assessment | P22: Closed | Q22: 0 | R22: FALSE | S22: Not Applicable | T22: Contusion, bruising and superficial crushing | U22: Face, not elsewhere classified | V22: Hitting Objects With a Part of the Body | W22: Hitting stationary objects | X22: Human agencies | Z22: 0 | AA22: MAY, FY25 | AB22: Q4, FY25 | AC22: Incident | AF22: Hitting Objects With a Part of the Body | AG22: Human agencies | AH22: Harris Scarfe | AI22: TAS | AJ22: Store | AK22: Harris Scarfe | AL22: SA/TAS | AM22: Harris Scarfe | AN22: Harris Scarfe - SA/TAS
A23: SRG-INJ-3664 | C23: No | D23: HS325818 | E23: PIPER, LILIJANA | F23: 45802 | G23: 0.60763889 | H23: Harris Scarfe TAS | I23: 4044 | J23: Devonport | K23: Left knuckle | L23: When moving stock I scraped my knuckle on shelf bracket. | M23: Injury | O23: No Assessment | P23: Closed | Q23: 0 | R23: FALSE | S23: Not Applicable | T23: Contusion, bruising and superficial crushing | U23: Hand, finger and thumb | V23: Hitting Objects With a Part of the Body | W23: Rubbing and chafing | X23: Human agencies | Z23: 0 | AA23: MAY, FY25 | AB23: Q4, FY25 | AC23: Incident | AF23: Hitting Objects With a Part of the Body | AG23: Human agencies | AH23: Harris Scarfe | AI23: TAS | AJ23: Store | AK23: Harris Scarfe | AL23: SA/TAS | AM23: Harris Scarfe | AN23: Harris Scarfe - SA/TAS
A24: SRG-INJ-3671 | C24: No | D24: AU238405 | E24: CARR, LOREN | F24: 45801 | G24: 0.60416667 | H24: Anaconda VIC | I24: A039 | J24: Highett | K24: Back, right hand side/lower back pain and numbness | L24: Moving display tents around on the tent floor and clearing bulkstacks. Towards the end of the day I could feel my back become quiet sore. By the next morning it felt like muscular pain which has now moved to numbness in the back and sore with movement. | M24: Injury | O24: No Assessment | P24: Open | Q24: 0 | R24: FALSE | S24: Not Applicable | T24: Trauma to muscles and tendons | U24: Back-Upper and lower | V24: Body Stressing | W24: Muscular stress while lifting, carrying, or putting down objects | X24: Human agencies | Z24: 0 | AA24: MAY, FY25 | AB24: Q4, FY25 | AC24: Incident | AF24: Body Stressing | AG24: Human agencies | AH24: Anaconda | AI24: VIC | AJ24: Store | AK24: Anaconda | AL24: VIC North / East | AM24: Anaconda | AN24: Anaconda - VIC North / East
A25: SRG-INJ-3668 | C25: No | D25: AU338493 | E25: GILL, LAMIA | F25: 45801 | G25: 0.625 | H25: Spotlight WA | I25: S115 | J25: Albany | K25: Left little finger nail ripped off. | L25: Team member was reaching in to an eco base to adjust some stock and caught her fingernail on the mesh sides. This then ripped off her little fingernail entirely and she needed to go the hospital to get the remainder of the nail removed. | M25: Injury | O25: No Assessment | P25: Open | Q25: 0 | R25: FALSE | S25: Lost Time Injury | T25: Laceration or open wound not involving traumatic amputation | U25: Hand, finger and thumb | V25: Hitting Objects With a Part of the Body | W25: Hitting stationary objects | X25: Human agencies | Z25: 0 | AA25: MAY, FY25 | AB25: Q4, FY25 | AC25: LTIs | AF25: Hitting Objects With a Part of the Body | AG25: Human agencies | AH25: Spotlight | AI25: WA | AJ25: Store | AK25: Spotlight AU | AL25: WA | AM25: Spotlight AU | AN25: Spotlight AU - WA
A26: SRG-INJ-3661 | C26: No | D26: AU339712 | E26: THOMAS, RILEY | F26: 45800 | G26: 0.5 | H26: Anaconda QLD | I26: A038 | J26: Toowoomba | K26: Right middle side of back | L26: Riley (Sid) was lifting a kids fluid rapid 50cm bike onto 2nd storage shelf in our back storage room (waist height as) and as he lifted the bike box he got a sharp pain in the muscular side of his back. Sid reported it immediately to myself (Ash). I assessed the 2nd shelf and product. Sid refused ICE or medical treatment & said "it happens sometimes" (prior injury) and said he will be all good and wanted to continue his shift. Sid was placed solely on customer service for the remainder of his shift. Manual Handling / product lifting Training will be re-touched on next shift. Sid did say at the commencement of his shift that it was feeling better. Follow up by leaders will be followed over coming days to ensure he is still ok and no medical treatment is needed. | M26: Injury | O26: No Assessment | P26: Closed | Q26: 0 | R26: FALSE | S26: Not Applicable | T26: Trauma to muscles and tendons | U26: Back-Upper and lower | V26: Body Stressing | W26: Muscular stress while lifting, carrying, or putting down objects | X26: Human agencies | Z26: 0 | AA26: MAY, FY25 | AB26: Q4, FY25 | AC26: Incident | AF26: Body Stressing | AG26: Human agencies | AH26: Anaconda | AI26: QLD | AJ26: Store | AK26: Anaconda | AL26: QLD NW / NT | AM26: Anaconda | AN26: Anaconda - QLD NW / NT
A27: SRG-INJ-3660 | C27: No | D27: HS281818 | E27: ZOUNIS, CHRISTINE | F27: 45800 | G27: 0.41666667 | H27: Harris Scarfe SA | I27: 1011 | J27: Marion | K27: cut to the left top of hand | L27: I was unpacking boxes in the dock and heard Christine squeal in pain. I came around the corner to see Christine holding her hand. She had sliced the top of her hand with the safety knife. We put tissues on it straight away to stop the bleeding. Once the bleeding had resolved we cleaned with an alcohol wipe and then applied a bandage to the area as a bandaid was not quite big enough. I asked Christine if she wanted to go to the doctors or the hospital and she advised that she did not and a bandage would be sufficient. The bandage is big enough to stop her bending her hand too much to allow it time to heal and not reopen. Upon inspecting the knife we have found that the black plastic part of the blade section of the knife had worn away and had exposed the blade through the black plastic. Please see attached photos. We have taped up the blade and disposed of it and given Christine a new safety knife to use. | M27: Injury | O27: No Assessment | P27: Open | Q27: 0 | R27: FALSE | S27: First Aid Injury | T27: Laceration or open wound not involving traumatic amputation | U27: Hand, finger and thumb | V27: Hitting Objects With a Part of the Body | W27: Hitting stationary objects | X27: Human agencies | Z27: 0 | AA27: MAY, FY25 | AB27: Q4, FY25 | AC27: FAIs | AF27: Hitting Objects With a Part of the Body | AG27: Human agencies | AH27: Harris Scarfe | AI27: SA | AJ27: Store | AK27: Harris Scarfe | AL27: SA/TAS | AM27: Harris Scarfe | AN27: Harris Scarfe - SA/TAS
A28: SRG-INJ-3663 | C28: No | D28: AU239433 | E28: POHATU, NASSEY HURIHIA | F28: 45800 | G28: 0.64513889 | H28: Spotlight QLD | I28: S039 | J28: Ashmore | K28: Sharp pain under right knee cap. felt only when weight is applied. | L28: Went into this area to tidy it up and put stock onto front bays and then remove stock to put in another area. Bent down to put Plastic storage container stock onto shelf. Then stood up straight, felt extreme pain in my knee under knee cap. felt like a tear and it stung. Pain subsided a little bit in 10-15min i was able to put a little bit of pressure on it and i used a trolley for assistance to get back to the office. | M28: Injury | O28: No Assessment | P28: Closed | Q28: 0 | R28: FALSE | S28: Not Applicable | T28: Trauma to muscles and tendons | U28: Knee | V28: Body Stressing | W28: Muscular stress while lifting, carrying, or putting down objects | X28: Human agencies | Z28: 0 | AA28: MAY, FY25 | AB28: Q4, FY25 | AC28: Incident | AF28: Body Stressing | AG28: Human agencies | AH28: Spotlight | AI28: QLD | AJ28: Store | AK28: Spotlight AU | AL28: NSW North / QLD South | AM28: Spotlight AU | AN28: Spotlight AU - NSW North / QLD South
A29: SRG-INJ-3662 | C29: No | D29: AU324403 | E29: LEWIS, SHAREE | F29: 45800 | G29: 0.67638889 | H29: Spotlight SA | I29: S025 | J29: Trinity Gardens | K29: lower left side has a cut/graze. painful | L29: Sharee was looking for a Click and Collect and 1x 90cm blind that was hung up fell down and scraped her back. Sharee came to the dress department to let me know what had happened, I asked if she wanted to leave or to sit down she declined. Sharee then showed me her back and i saw a cut/graze from the fallen blind. | M29: Injury | O29: No Assessment | P29: Closed | Q29: 0 | R29: FALSE | S29: Not Applicable | T29: Laceration or open wound not involving traumatic amputation | U29: Back-Upper and lower | V29: Being Hit By Moving Objects | W29: Being hit by falling objects | X29: Human agencies | Z29: 0 | AA29: MAY, FY25 | AB29: Q4, FY25 | AC29: Incident | AF29: Being Hit By Moving Objects | AG29: Human agencies | AH29: Spotlight | AI29: SA | AJ29: Store | AK29: Spotlight AU | AL29: SA/NT | AM29: Spotlight AU | AN29: Spotlight AU - SA/NT
A30: SRG-INJ-3657 | C30: No | D30: HS323716 | E30: BYNION, FAY | F30: 45799 | G30: 0.31597222 | H30: Harris Scarfe VIC | I30: 2042 | J30: Carnegie (Hs Home) | K30: Lower back pain at tailbone. | L30: Fay was relaying dinner sets to fit out new stock which she had just unboxed from a pallet. While lifting one of the dinner sets her lower back (tailbone) had a sudden spike in pain and seized up. She immediately stopped what she was doing and took paracetamol & ibuprofen, before delegating any lifting tasks to another team member. | M30: Injury | O30: No Assessment | P30: Open | Q30: 0 | R30: FALSE | S30: First Aid Injury | T30: Trauma to muscles and tendons | U30: Back-Upper and lower | V30: Body Stressing | W30: Muscular stress while lifting, carrying, or putting down objects | X30: Human agencies | Z30: 0 | AA30: MAY, FY25 | AB30: Q4, FY25 | AC30: FAIs | AF30: Body Stressing | AG30: Human agencies | AH30: Harris Scarfe | AI30: VIC | AJ30: Store | AK30: Harris Scarfe | AL30: VIC | AM30: Harris Scarfe | AN30: Harris Scarfe - VIC
A31: SRG-INJ-3679 | C31: No | D31: AU339459 | E31: HIGGINS, LEANNE | F31: 45799 | G31: 0.45833333 | H31: Spotlight QLD | I31: S205 | J31: Airlie Beach | K31: Left glute muscle | L31: Lifting heavy boxes unloading pallets, sore glute muscle from lifting the weight of stock | M31: Injury | O31: No Assessment | P31: Open | Q31: 0 | R31: FALSE | S31: Not Applicable | T31: Trauma to muscles and tendons | U31: Lower leg | V31: Body Stressing | W31: Muscular stress while lifting, carrying, or putting down objects | X31: Human agencies | Y31: Boxes | Z31: 0 | AA31: MAY, FY25 | AB31: Q4, FY25 | AC31: Incident | AF31: Body Stressing | AG31: Human agencies | AH31: Spotlight | AI31: QLD | AJ31: Store | AK31: Spotlight AU | AL31: QLD North | AM31: Spotlight AU | AN31: Spotlight AU - QLD North
A32: SRG-INJ-3680 | C32: No | D32: HS296667 | E32: COATES, MARISA | F32: 45799 | G32: 0.78125 | H32: Harris Scarfe VIC | I32: 2048 | J32: Tarneit | K32: pinky finger | L32: White pushing stock out, Marissa sustained injury on her left pinky finger from a broken dinner plate. First aid was applied. | M32: Injury | O32: No Assessment | P32: Open | Q32: 0 | R32: FALSE | S32: First Aid Injury | T32: Laceration or open wound not involving traumatic amputation | U32: Hand, finger and thumb | V32: Hitting Objects With a Part of the Body | W32: Hitting stationary objects | X32: Human agencies | Z32: 0 | AA32: MAY, FY25 | AB32: Q4, FY25 | AC32: FAIs | AF32: Hitting Objects With a Part of the Body | AG32: Human agencies | AH32: Harris Scarfe | AI32: VIC | AJ32: Store | AK32: Harris Scarfe | AL32: VIC & NSW | AM32: Harris Scarfe | AN32: Harris Scarfe - VIC & NSW
A33: SRG-INJ-3649 | C33: No | D33: AU339201 | E33: HENDERSON, KATHERINE | F33: 45798 | G33: 0.46805556 | H33: Spotlight QLD | I33: S205 | J33: Airlie Beach | K33: Right Knee | L33: TM already had a knee that was causing her concern and was wearing a knee support. In walking at a fast pace whilst carrying fabric she overextended her knee backwards and felt a pulling feeling in the back of the knee. DTL advised the VM of the incident and asked if she could do lighter duties that did not include walking at a fast pace. | M33: Injury | O33: No Assessment | P33: Open | Q33: 0 | R33: FALSE | S33: Not Applicable | T33: Trauma to muscles and tendons | U33: Knee | V33: Body Stressing | W33: Muscular stress while lifting, carrying, or putting down objects | X33: Human agencies | Z33: 0 | AA33: MAY, FY25 | AB33: Q4, FY25 | AC33: Incident | AF33: Body Stressing | AG33: Human agencies | AH33: Spotlight | AI33: QLD | AJ33: Store | AK33: Spotlight AU | AL33: QLD North | AM33: Spotlight AU | AN33: Spotlight AU - QLD North
A34: SRG-INJ-3651 | C34: No | D34: AU334407 | E34: VUDRAG, ALISIA | F34: 45798 | G34: 0.45833333 | H34: Anaconda QLD | I34: A037 | J34: Cairns | K34: Cut to left hand wrist | L34: Lisa was filling firepit stock, heavy flatpak firepit. As Lisa was removing the firepit flatpak a customer pushed her cage and spoke to her which resulted in the side catch of the cage tearing Lisa's skin on her left hand wrist. Cutting it open. | M34: Injury | O34: No Assessment | P34: Closed | Q34: 0 | R34: FALSE | S34: First Aid Injury | T34: Laceration or open wound not involving traumatic amputation | U34: Hand, finger and thumb | V34: Being Hit By Moving Objects | W34: Being trapped between stationary and moving objects | X34: Human agencies | Z34: 0 | AA34: MAY, FY25 | AB34: Q4, FY25 | AC34: FAIs | AF34: Being Hit By Moving Objects | AG34: Human agencies | AH34: Anaconda | AI34: QLD | AJ34: Store | AK34: Anaconda | AL34: BRISBANE / FNQ Cluster | AM34: Anaconda | AN34: Anaconda - BRISBANE / FNQ Cluster
A35: SRG-INJ-3653 | B35: 8015117 | C35: No | D35: AU327050 | E35: BALL, KELLY | F35: 45798 | G35: 0.52083333 | H35: Anaconda NSW | I35: A068 | J35: Coffs Harbour | K35: right toe | L35: went to lift a bike of the pallet of stock as it was unstable and the bike fell and land on the right big toe | M35: Claim | N35: Accepted Claim | O35: Restricted Hours | P35: Open | Q35: 7 | R35: FALSE | S35: Medical Treatment Injury | T35: Trauma to muscles and tendons | U35: Foot and toes | V35: Being Hit By Moving Objects | W35: Being hit by falling objects | X35: Human agencies | Z35: Open | AA35: MAY, FY25 | AB35: Q4, FY25 | AC35: MTIs | AD35: Claim | AE35: Accepted Claim | AF35: Being Hit By Moving Objects | AG35: Human agencies | AH35: Anaconda | AI35: NSW | AJ35: Store | AK35: Anaconda | AL35: BRISBANE / FNQ Cluster | AM35: Anaconda | AN35: Anaconda - BRISBANE / FNQ Cluster
A36: SRG-INJ-3658 | C36: No | D36: AU336412 | E36: BARWICK, SAMARA | F36: 45798 | G36: 0.57222222 | H36: Anaconda NSW | I36: A029 | J36: Bennetts Green | K36: Right index finger - closest to hand | L36: Samara put her hand on the door when exiting to stop it slamming closed. Her right index finger was caught between the door and door frame.. Her finger bruised and became swollen, we applied ice to the area. | M36: Injury | O36: No Assessment | P36: Closed | Q36: 0 | R36: FALSE | S36: First Aid Injury | T36: Contusion, bruising and superficial crushing | U36: Hand, finger and thumb | V36: Being Hit By Moving Objects | W36: Being trapped between stationary and moving objects | X36: Human agencies | Z36: 0 | AA36: MAY, FY25 | AB36: Q4, FY25 | AC36: FAIs | AF36: Being Hit By Moving Objects | AG36: Human agencies | AH36: Anaconda | AI36: NSW | AJ36: Store | AK36: Anaconda | AL36: NSW North | AM36: Anaconda | AN36: Anaconda - NSW North
A37: SRG-INJ-3655 | C37: No | D37: AU323733 | E37: COCKS, BRYCE | F37: 45798 | G37: 0.63888889 | H37: Spotlight WA | I37: S052 | J37: Innaloo | K37: Side of right hand | L37: Started his shift with the store manager Lidia having a discussion about the number of pallets he needs to work. Was feeling frustrated from the start, then with the added pressure of having mixed pallets to work and then a difficult box of picture frames, which he could not get open. Was overwhelmed with frustration and slammed his fist into the box. Nothing in the box was broken although he caused some injury to his right hand. He came to me (Lisa Cocks, his mum & Furnishings DTL) for first aid and to advise what happened. A large hematoma came up on knuckle of his pinky finger which has been constantly iced and rested. Unfortunately he is unable to complete his shift and will be going home. | M37: Injury | O37: No Assessment | P37: Open | Q37: 0 | R37: FALSE | S37: Lost Time Injury | T37: Laceration or open wound not involving traumatic amputation | U37: Hand, finger and thumb | V37: Hitting Objects With a Part of the Body | W37: Hitting stationary objects | X37: Human agencies | Z37: 0 | AA37: MAY, FY25 | AB37: Q4, FY25 | AC37: LTIs | AF37: Hitting Objects With a Part of the Body | AG37: Human agencies | AH37: Spotlight | AI37: WA | AJ37: Store | AK37: Spotlight AU | AL37: WA | AM37: Spotlight AU | AN37: Spotlight AU - WA
A38: SRG-INJ-3656 | C38: No | D38: AU320820 | E38: PEDURU ARACHCHIGE, MODITHA RANAHANSA | F38: 45798 | G38: 0.625 | H38: Spotlight VIC | I38: S900 | J38: Spotlight Pty Ltd | K38: Right calf | L38: Moditha was stacking pallet for S120 when Charles came next to him. Charles was using an electric pallet jack which hit Moditha's picking pallet. The corner of the pallet hit Moditha's left leg (calf) and he had to sit down at the spot as he was feeling a terrible pain. | M38: Injury | O38: No Assessment | P38: Closed | Q38: 0 | R38: FALSE | S38: Not Applicable | T38: Contusion, bruising and superficial crushing | U38: Lower leg | V38: Being Hit By Moving Objects | W38: Being hit by falling objects | X38: Human agencies | Z38: 0 | AA38: MAY, FY25 | AB38: Q4, FY25 | AC38: Incident | AF38: Being Hit By Moving Objects | AG38: Human agencies | AH38: Spotlight | AI38: VIC | AJ38: SG | AK38: Spotlight SG | AL38: Spot SG | AM38: Support Group AU | AN38: Support Group AU
A39: SRG-INJ-3673 | C39: No | D39: AU334482 | E39: GUEST, JOSHUA | F39: 45798 | G39: 0.10416667 | H39: Spotlight VIC | I39: S145 | J39: Roxburgh Park | K39: lower back lumbar | L39: team member was lifting a euro bin by himself and strained his back | M39: Injury | O39: No Assessment | P39: Open | Q39: 0 | R39: FALSE | S39: Medical Treatment Injury | T39: Trauma to muscles and tendons | U39: Back-Upper and lower | V39: Body Stressing | W39: Muscular stress while lifting, carrying, or putting down objects | X39: Human agencies | Z39: 0 | AA39: MAY, FY25 | AB39: Q4, FY25 | AC39: MTIs | AF39: Body Stressing | AG39: Human agencies | AH39: Spotlight | AI39: VIC | AJ39: Store | AK39: Spotlight AU | AL39: VIC West | AM39: Spotlight AU | AN39: Spotlight AU - VIC West
A40: SRG-INJ-3654 | C40: No | D40: AU207912 | E40: LYON, SANDRA | F40: 45798 | G40: 0.52083333 | H40: Spotlight NSW | I40: S081 | J40: Tuggerah | K40: Right pointer finger | L40: Team member was lining the Australia Post crate with cardboard to protect packages due to wet weather as she lent forward no the cage caught her finger | M40: Injury | O40: No Assessment | P40: Open | Q40: 0 | R40: FALSE | S40: Not Applicable | T40: Contusion, bruising and superficial crushing | U40: Hand, finger and thumb | V40: Being Hit By Moving Objects | W40: Being trapped between stationary and moving objects | X40: Human agencies | Z40: 0 | AA40: MAY, FY25 | AB40: Q4, FY25 | AC40: Incident | AF40: Being Hit By Moving Objects | AG40: Human agencies | AH40: Spotlight | AI40: NSW | AJ40: Store | AK40: Spotlight AU | AL40: NSW Central | AM40: Spotlight AU | AN40: Spotlight AU - NSW Central
A41: SRG-INJ-3647 | C41: No | D41: AU336298 | E41: ALLEN, JAIME | F41: 45797 | G41: 0.4375 | H41: Spotlight NSW | I41: S081 | J41: Tuggerah | K41: forehesd | L41: Staff member bent down to put something on a low shelf and knocked head on shelf | M41: Injury | O41: No Assessment | P41: Closed | Q41: 0 | R41: FALSE | S41: Not Applicable | T41: Contusion, bruising and superficial crushing | U41: Head - unspecified locations | V41: Hitting Objects With a Part of the Body | W41: Hitting stationary objects | X41: Human agencies | Z41: 0 | AA41: MAY, FY25 | AB41: Q4, FY25 | AC41: Incident | AF41: Hitting Objects With a Part of the Body | AG41: Human agencies | AH41: Spotlight | AI41: NSW | AJ41: Store | AK41: Spotlight AU | AL41: NSW Central | AM41: Spotlight AU | AN41: Spotlight AU - NSW Central
A42: SRG-INJ-3652 | C42: No | D42: AU329441 | E42: FENWICK, TAHNAYA | F42: 45797 | G42: 0.64236111 | H42: Spotlight NSW | I42: S123 | J42: Wagga Wagga | K42: left pinky toe | L42: Tahnaya was straightening up photo frames when one fell from eye level and landed on her left pinky toe | M42: Injury | O42: No Assessment | P42: Closed | Q42: 0 | R42: FALSE | S42: Not Applicable | T42: Contusion, bruising and superficial crushing | U42: Hand, finger and thumb | V42: Being Hit By Moving Objects | W42: Being hit by falling objects | X42: Human agencies | Z42: 0 | AA42: MAY, FY25 | AB42: Q4, FY25 | AC42: Incident | AF42: Being Hit By Moving Objects | AG42: Human agencies | AH42: Spotlight | AI42: NSW | AJ42: Store | AK42: Spotlight AU | AL42: NSW South / ACT | AM42: Spotlight AU | AN42: Spotlight AU - NSW South / ACT
A43: SRG-INJ-3648 | C43: No | D43: AU319449 | E43: ALLISON, RYAN | F43: 45797 | G43: 0.47916667 | H43: Spotlight VIC | I43: S110 | J43: Frankston | K43: Bump on the head, a bit of a headache | L43: Customer lifted up the track to have a look at it and tilted it to the side and it hit Ryan on the top of his head | M43: Injury | O43: No Assessment | P43: Closed | Q43: 0 | R43: FALSE | S43: Not Applicable | T43: Contusion, bruising and superficial crushing | U43: Head - unspecified locations | V43: Being Hit By Moving Objects | W43: Being hit by falling objects | X43: Human agencies | Z43: 0 | AA43: MAY, FY25 | AB43: Q4, FY25 | AC43: Incident | AF43: Being Hit By Moving Objects | AG43: Human agencies | AH43: Spotlight | AI43: VIC | AJ43: Store | AK43: Spotlight AU | AL43: VIC East | AM43: Spotlight AU | AN43: Spotlight AU - VIC East
A44: SRG-INJ-3650 | C44: No | D44: AU339115 | E44: MUNRO, PAUL | F44: 45797 | G44: 0.48402778 | H44: Spotlight SA | I44: S106 | J44: Mount Barker | K44: Left hand | L44: Paul was trying to charge the walkie stacker and the charger didn't turn on so he waited and nothing happened, he then disconnected it and tried again and nothing happened so he flicked off the power point and then went to push the power cord to see if it was loose and got electrocuted. | M44: Claim | N44: Pending Claim | O44: Restricted Duties | P44: Open | Q44: 0 | R44: FALSE | S44: Lost Time Injury | T44: Electrocution, shock from electric current | U44: Hand, finger and thumb | V44: Heat, Electricity and Other Environmental Factors | W44: Contact with electricity | X44: Office and electronic equipment | Z44: Open | AA44: MAY, FY25 | AB44: Q4, FY25 | AC44: LTIs | AD44: Claim | AE44: Pending Claim | AF44: Heat, Electricity and Other Environmental Factors | AG44: Office and electronic equipment | AH44: Spotlight | AI44: SA | AJ44: Store | AK44: Spotlight AU | AL44: SA/NT | AM44: Spotlight AU | AN44: Spotlight AU - SA/NT
A45: SRG-INJ-3665 | C45: No | D45: AU234663 | E45: CHISHOLM, JENNIFER | F45: 45796 | G45: 0.70833333 | H45: Spotlight SA | I45: S124 | J45: Albert Park | K45: Soreness to lower back. | L45: Was no specific incident. Gradually became sore through the night. Jennifer hasn't mentioned it to me at all, until after calling in sick today (Thursday 22/05/2025). Message stated that Jennifer is "unwell and hurt her back". I have explained to Jennifer that she will need to go to get a doctors certificate of clearance to come back to work, and that i would supply the forms we need filled out. | M45: Injury | O45: No Assessment | P45: Open | Q45: 0 | R45: FALSE | S45: Not Applicable | T45: Trauma to muscles and tendons | U45: Back-Upper and lower | V45: Body Stressing | W45: Muscular stress while lifting, carrying, or putting down objects | X45: Human agencies | Z45: 0 | AA45: MAY, FY25 | AB45: Q4, FY25 | AC45: Incident | AF45: Body Stressing | AG45: Human agencies | AH45: Spotlight | AI45: SA | AJ45: Store | AK45: Spotlight AU | AL45: SA/NT | AM45: Spotlight AU | AN45: Spotlight AU - SA/NT
A46: SRG-INJ-3646 | C46: No | D46: AU318000 | E46: REGLE, NATALIE | F46: 45796 | G46: 0.58333333 | H46: Spotlight NSW | I46: S125 | J46: Wetherill Park | K46: Top of head and left side of face | L46: Natalie was picking stock for an Ecom order and climbing back down the step ladder when 4 canvaes fell off the shelf and hit her on the top of her head and the left side of her face | M46: Injury | O46: No Assessment | P46: Closed | Q46: 0 | R46: FALSE | S46: First Aid Injury | T46: Contusion, bruising and superficial crushing | U46: Face, not elsewhere classified | V46: Being Hit By Moving Objects | W46: Being hit by falling objects | X46: Human agencies | Y46: Ladder | Z46: 0 | AA46: MAY, FY25 | AB46: Q4, FY25 | AC46: FAIs | AF46: Being Hit By Moving Objects | AG46: Human agencies | AH46: Spotlight | AI46: NSW | AJ46: Store | AK46: Spotlight AU | AL46: NSW South / ACT | AM46: Spotlight AU | AN46: Spotlight AU - NSW South / ACT
A47: SRG-INJ-3645 | C47: No | D47: AU317789 | E47: SOMERVILLE, BRENNA | F47: 45795 | G47: 0.65972222 | H47: Spotlight QLD | I47: S047 | J47: Rockhampton | K47: drink bottle thrown at her back | L47: Some kids came in and stole some hair ties and drink out of the fridge. Team member asked if they were going to pay for the drink and the young boy started mouthing off at her, squirting her with the drink as well as over products and the floor. The team member stepped back from them and walked away and the kid through the drink bottle at her. | M47: Injury | O47: No Assessment | P47: Closed | Q47: 0 | R47: FALSE | S47: Not Applicable | T47: Contusion, bruising and superficial crushing | U47: Back-Upper and lower | V47: Being Hit By Moving Objects | W47: Being assaulted by a person or persons | X47: Human agencies | Z47: 0 | AA47: MAY, FY25 | AB47: Q4, FY25 | AC47: Incident | AF47: Being Hit By Moving Objects | AG47: Human agencies | AH47: Spotlight | AI47: QLD | AJ47: Store | AK47: Spotlight AU | AL47: QLD North | AM47: Spotlight AU | AN47: Spotlight AU - QLD North
A48: SRG-INJ-3644 | C48: No | D48: AU327002 | E48: BRADBURN, SAMANTHA | F48: 45795 | G48: 0.52013889 | H48: Spotlight WA | I48: S107 | J48: Geraldton | K48: left knee,sore back,neck and arms | L48: Sam was putting away fabric from the furnishings counter . looking at the security cameras there was 4 rolls laying on the floor. Sam finished marking back a roll of furnishings fabric then proceeded to take it back to the shelf,not looking sam then tripped over fabric that was laying on the floor. Sam fell forward landing face down .Sam then found her head piece then called out To Liam ( DTL ) that she was on the floor .Liam then came to see Sam as she was getting up off the floor,Liam then got her a chair to sit on .Sam had pain in her left knee and it swelled up straight away .Liam then got a staff member to get a ice pack. Liam then called myself (store Manager) as i was not rostered on .I then came down to the store to see if Sam was ok . Sam was complaining that she had a very sore knee,her back and neck were sore also and her arms. Sams daughter was rung to come and get her as she was going to try and walk out of the store to go to hospital,i asked Sam to try and stand up to see if she could walk,she was in alot of pain so i insisted that we get an ambulance to pick her up . Throughout this time we kept an ice pack on her knee and just monitored her,Ambulance then arrived got her on the bed and up to the hospital she went. | M48: Claim | N48: Pending Claim | O48: Unfit | P48: Open | Q48: 9 | R48: FALSE | S48: Lost Time Injury | T48: Trauma to muscles and tendons | U48: Lower limb - multiple locations | V48: Falls, Trips and Slips of a Person | W48: Falls on the same level | X48: Human agencies | Z48: Open | AA48: MAY, FY25 | AB48: Q4, FY25 | AC48: LTIs | AD48: Claim | AE48: Pending Claim | AF48: Falls, Trips and Slips of a Person | AG48: Human agencies | AH48: Spotlight | AI48: WA | AJ48: Store | AK48: Spotlight AU | AL48: WA | AM48: Spotlight AU | AN48: Spotlight AU - WA
A49: SRG-INJ-3643 | C49: No | D49: AU330389 | E49: HARKINS, SAMUEL | F49: 45794 | G49: 0.54166667 | H49: Anaconda NSW | I49: A061 | J49: Marsden Park | K49: Right Foot, big toe | L49: While assisting with a Click & Collect Rooftop Tent order, a customer attempted to help by pulling the item, causing it to slide off the trolley and land on Samuelâ€™s right foot, which also hit the trolley. Initially, the pain was mild, similar to stubbing a toe, but it has worsened in24hr | M49: Injury | O49: No Assessment | P49: Closed | Q49: 0 | R49: FALSE | S49: Not Applicable | T49: Contusion, bruising and superficial crushing | U49: Foot and toes | V49: Hitting Objects With a Part of the Body | W49: Hitting stationary objects | X49: Human agencies | Z49: 0 | AA49: MAY, FY25 | AB49: Q4, FY25 | AC49: Incident | AF49: Hitting Objects With a Part of the Body | AG49: Human agencies | AH49: Anaconda | AI49: NSW | AJ49: Store | AK49: Anaconda | AL49: NSW North | AM49: Anaconda | AN49: Anaconda - NSW North
A50: SRG-INJ-3642 | C50: No | D50: AU237620 | E50: FICHERA, ANGELA | F50: 45794 | G50: 0.66666667 | H50: Spotlight NSW | I50: S030 | J50: Birkenhead Point | K50: Left side ribs, right pinky finger | L50: Angela fell off the yellow step stool, onto a trolley. The trolley slipped away and the customer helped her up. | M50: Injury | O50: No Assessment | P50: Closed | Q50: 0 | R50: FALSE | S50: Not Applicable | T50: Contusion, bruising and superficial crushing | U50: Hand, finger and thumb | V50: Falls, Trips and Slips of a Person | W50: Stepping, kneeling or sitting on objects | X50: Human agencies | Z50: 0 | AA50: MAY, FY25 | AB50: Q4, FY25 | AC50: Incident | AF50: Falls, Trips and Slips of a Person | AG50: Human agencies | AH50: Spotlight | AI50: NSW | AJ50: Store | AK50: Spotlight AU | AL50: NSW Central | AM50: Spotlight AU | AN50: Spotlight AU - NSW Central
A51: SRG-INJ-3640 | C51: No | D51: AU237054 | E51: MORSON, KELLY | F51: 45793 | G51: 0.64305556 | H51: Spotlight NSW | I51: S019 | J51: Penrith | K51: left hand | L51: A team member was removing a large sign above valance and asked to pass it down to me whilst passing it down the team member dropped the sign and it feel from a height onto my left hand | M51: Injury | O51: No Assessment | P51: Closed | Q51: 0 | R51: FALSE | S51: First Aid Injury | T51: Contusion, bruising and superficial crushing | U51: Hand, finger and thumb | V51: Being Hit By Moving Objects | W51: Being hit by falling objects | X51: Human agencies | Z51: 0 | AA51: MAY, FY25 | AB51: Q4, FY25 | AC51: FAIs | AF51: Being Hit By Moving Objects | AG51: Human agencies | AH51: Spotlight | AI51: NSW | AJ51: Store | AK51: Spotlight AU | AL51: NSW South / ACT | AM51: Spotlight AU | AN51: Spotlight AU - NSW South / ACT
A52: SRG-INJ-3639 | C52: No | D52: AU339160 | E52: DAVEY, OLIVER | F52: 45793 | G52: 0.45833333 | H52: Anaconda VIC | I52: A020 | J52: Preston | K52: spasm from right calf to lower back, pulsing pain in area. limping from calf injury | L52: Ollie was helping put the beams into the dexion to keep stock secure, one beam was stuck, squatted to push it up using his shoulder to try release it, when pushing - calf on right leg had tensed/spasmed and shot pain to lower back. Flagged to team shortly after, pain still hitting lower back and still pulsing pain in calf muscle. Limping due to pain. Stopped all duties of work, sitting to rest for time being. | M52: Claim | N52: Pending Claim | O52: Restricted Hours | P52: Open | Q52: 6 | R52: FALSE | S52: Lost Time Injury | T52: Trauma to muscles and tendons | U52: Back-Upper and lower | V52: Body Stressing | W52: Muscular stress while lifting, carrying, or putting down objects | X52: Human agencies | Z52: Open | AA52: MAY, FY25 | AB52: Q4, FY25 | AC52: LTIs | AD52: Claim | AE52: Pending Claim | AF52: Body Stressing | AG52: Human agencies | AH52: Anaconda | AI52: VIC | AJ52: Store | AK52: Anaconda | AL52: VIC West / TAS | AM52: Anaconda | AN52: Anaconda - VIC West / TAS
A53: SRG-INJ-3637 | C53: No | D53: HS322742 | E53: KOLIO, FALEALAGO | F53: 45793 | G53: 0.38541667 | H53: Harris Scarfe VIC | I53: 2900 | J53: Harris Scarfe Pty Ltd Head Office | K53: Right arm elbow | L53: While collecting the floor mats to be thrown out, the team member hit the right elbow on the top of the bin. The team member then kept cleaning and informed his supervisor at 9:30am before first break. After the break the team member informed the supervisor that he wanted to keep cleaning and leave after the job was completed. At 11:00am the supervisor noticed that they were using a broom with 1 hand. Supervisor has then said to team member we will go fill out the incident report so the team member can go home. | M53: Injury | O53: No Assessment | P53: Closed | Q53: 0 | R53: FALSE | S53: First Aid Injury | T53: Trauma to muscles and tendons | U53: Elbow | V53: Hitting Objects With a Part of the Body | W53: Hitting stationary objects | X53: Human agencies | Z53: 0 | AA53: MAY, FY25 | AB53: Q4, FY25 | AC53: FAIs | AF53: Hitting Objects With a Part of the Body | AG53: Human agencies | AH53: Harris Scarfe | AI53: VIC | AJ53: SG | AK53: Harris Scarfe SG | AL53: HS SG | AM53: Support Group AU | AN53: Support Group AU
A54: SRG-INJ-3635 | C54: No | D54: HS333309 | E54: JESSEN, JANE | F54: 45792 | G54: 0.57986111 | H54: Harris Scarfe QLD | I54: 9086 | J54: Mt Gravatt | K54: right ring finger | L54: shelf collapsed as assistant store manager was stacking bowls onto shelf, large amount of stock proceeded to fall to the floor and shatter and manager was cut in the process. no serious injury to manager just minor cuts, blood was present on the floor during clean up. | M54: Injury | O54: No Assessment | P54: Closed | Q54: 0 | R54: FALSE | S54: First Aid Injury | T54: Laceration or open wound not involving traumatic amputation | U54: Hand, finger and thumb | V54: Being Hit By Moving Objects | W54: Being hit by falling objects | X54: Human agencies | Z54: 0 | AA54: MAY, FY25 | AB54: Q4, FY25 | AC54: FAIs | AF54: Being Hit By Moving Objects | AG54: Human agencies | AH54: Harris Scarfe | AI54: QLD | AJ54: Store | AK54: Harris Scarfe | AL54: QLD | AM54: Harris Scarfe | AN54: Harris Scarfe - QLD
A55: SRG-INJ-3634 | C55: No | D55: AU311355 | E55: PETERSON, SANDRA | F55: 45792 | G55: 0.39930556 | H55: Anaconda NSW | I55: A029 | J55: Bennetts Green | K55: sternum | L55: Sandy was sliding a Queen titan Swag on the floor to take down the front of the store when it caught something on the floor and got stuck. When it got stuck it pushed against Sandy into her sternum. She reported being winded, pain in her chest where the box struck her. | M55: Injury | O55: No Assessment | P55: Closed | Q55: 0 | R55: FALSE | S55: Not Applicable | T55: Contusion, bruising and superficial crushing | U55: Chest (thorax) | V55: Body Stressing | W55: Muscular stress while lifting, carrying, or putting down objects | X55: Human agencies | Z55: 0 | AA55: MAY, FY25 | AB55: Q4, FY25 | AC55: Incident | AF55: Body Stressing | AG55: Human agencies | AH55: Anaconda | AI55: NSW | AJ55: Store | AK55: Anaconda | AL55: NSW North | AM55: Anaconda | AN55: Anaconda - NSW North
A56: SRG-INJ-3641 | C56: No | D56: AU334404 | E56: HALL, DYLAN | F56: 45791 | G56: 0.41805556 | H56: Anaconda SA | I56: A008 | J56: Mile End | K56: Finger | L56: Holding something for another team member while de-spooling and something got jammed and braid wrapped around finger and cut it. | M56: Injury | O56: No Assessment | P56: Closed | Q56: 0 | R56: FALSE | S56: First Aid Injury | T56: Laceration or open wound not involving traumatic amputation | U56: Hand, finger and thumb | V56: Being Hit By Moving Objects | W56: Being trapped between stationary and moving objects | X56: Human agencies | Z56: 0 | AA56: MAY, FY25 | AB56: Q4, FY25 | AC56: FAIs | AF56: Being Hit By Moving Objects | AG56: Human agencies | AH56: Anaconda | AI56: SA | AJ56: Store | AK56: Anaconda | AL56: SA / ACT | AM56: Anaconda | AN56: Anaconda - SA / ACT
A57: SRG-INJ-3630 | C57: No | D57: HS331215 | E57: HOWARD, STEPHANIE | F57: 45791 | G57: 0.57638889 | H57: Harris Scarfe TAS | I57: 4044 | J57: Devonport | K57: rolled ankle | L57: Was coming down the stairs empty handed, missed the bottom step and rolled ankle. Had manager come have a look and sat down to rest ankle before trying to put weight on foot. Was able to walk with some pain. | M57: Injury | O57: No Assessment | P57: Closed | Q57: 0 | R57: FALSE | S57: Not Applicable | T57: Trauma to muscles and tendons | U57: Ankle | V57: Falls, Trips and Slips of a Person | W57: Falls on the same level | X57: Human agencies | Z57: 0 | AA57: MAY, FY25 | AB57: Q4, FY25 | AC57: Incident | AF57: Falls, Trips and Slips of a Person | AG57: Human agencies | AH57: Harris Scarfe | AI57: TAS | AJ57: Store | AK57: Harris Scarfe | AL57: SA/TAS | AM57: Harris Scarfe | AN57: Harris Scarfe - SA/TAS
A58: SRG-INJ-3631 | C58: No | D58: HS297493 | E58: KIFF, JACOB | F58: 45791 | G58: 0.64930556 | H58: Harris Scarfe NSW | I58: 6078 | J58: Ulladulla | K58: cut/ laeration from sharp metal | L58: Customer injured themselves (cut) on a dish rack in the kitchen accessories department. Jacob kiff was removing the items from the selling floor as a hierarchy control, and also cut himself on the razor sharp metal | M58: Injury | O58: No Assessment | P58: Closed | Q58: 0 | R58: FALSE | S58: Not Applicable | T58: Laceration or open wound not involving traumatic amputation | U58: Hand, finger and thumb | V58: Hitting Objects With a Part of the Body | W58: Hitting stationary objects | X58: Human agencies | Z58: 0 | AA58: MAY, FY25 | AB58: Q4, FY25 | AC58: Incident | AF58: Hitting Objects With a Part of the Body | AG58: Human agencies | AH58: Harris Scarfe | AI58: NSW | AJ58: Store | AK58: Harris Scarfe | AL58: NSW/ACT | AM58: Harris Scarfe | AN58: Harris Scarfe - NSW/ACT
A59: SRG-INJ-3636 | C59: No | D59: AU221905 | E59: MOORE-GALLAGHER, MICHAEL | F59: 45791 | G59: 0.68819444 | H59: Spotlight QLD | I59: S116 | J59: Ipswich | K59: Top of head | L59: Michael was adding more clearance rugs to the fixture . He lifted a rug from the back and knocked the RB bar causing it to fall and hit the top front of his head. | M59: Injury | O59: No Assessment | P59: Closed | Q59: 0 | R59: FALSE | S59: Not Applicable | T59: Contusion, bruising and superficial crushing | U59: Head - unspecified locations | V59: Being Hit By Moving Objects | W59: Being hit by falling objects | X59: Human agencies | Z59: 0 | AA59: MAY, FY25 | AB59: Q4, FY25 | AC59: Incident | AF59: Being Hit By Moving Objects | AG59: Human agencies | AH59: Spotlight | AI59: QLD | AJ59: Store | AK59: Spotlight AU | AL59: QLD Central / TAS | AM59: Spotlight AU | AN59: Spotlight AU - QLD Central / TAS
A60: SRG-INJ-3672 | C60: No | D60: AU334482 | E60: GUEST, JOSHUA | F60: 45791 | G60: 0.66666667 | H60: Spotlight VIC | I60: S145 | J60: Roxburgh Park | K60: potential sprain on left wrist | L60: Lifting fabric roll and heard a pop | M60: Injury | O60: No Assessment | P60: Open | Q60: 0 | R60: FALSE | S60: Medical Treatment Injury | T60: Trauma to muscles and tendons | U60: Wrist | V60: Body Stressing | W60: Muscular stress while lifting, carrying, or putting down objects | X60: Human agencies | Z60: 0 | AA60: MAY, FY25 | AB60: Q4, FY25 | AC60: MTIs | AF60: Body Stressing | AG60: Human agencies | AH60: Spotlight | AI60: VIC | AJ60: Store | AK60: Spotlight AU | AL60: VIC West | AM60: Spotlight AU | AN60: Spotlight AU - VIC West
A61: SRG-INJ-3633 | C61: No | D61: AU310388 | E61: RUSSELL, LARA | F61: 45790 | G61: 0.52777778 | H61: Spotlight VIC | I61: S013 | J61: Ballarat | K61: Right Ankle | L61: Was pushing trolley through dispatch doors and another team member was behind me who - to get through the doors - had to push the trolley with a little force but I was a bit too close and she slammed her trolley into my ankle. | M61: Injury | O61: No Assessment | P61: Closed | Q61: 0 | R61: FALSE | S61: Not Applicable | T61: Trauma to muscles and tendons | U61: Ankle | V61: Being Hit By Moving Objects | W61: Being hit by a person accidentally | X61: Human agencies | Z61: 0 | AA61: MAY, FY25 | AB61: Q4, FY25 | AC61: Incident | AF61: Being Hit By Moving Objects | AG61: Human agencies | AH61: Spotlight | AI61: VIC | AJ61: Store | AK61: Spotlight AU | AL61: VIC West | AM61: Spotlight AU | AN61: Spotlight AU - VIC West
A62: SRG-INJ-3632 | C62: No | D62: AU338911 | E62: BUSHBY, CAITLIN | F62: 45790 | G62: 0.77083333 | H62: Spotlight SA | I62: S106 | J62: Mount Barker | K62: RIGHT PALM OF HAND | L62: DURING A TEAM MEMBER LIFTING A BOX THERE WAS A PIECE OF GLASS THAT HAD BEEN LODGED IN THE BOXED ON ONE OF THE CORNERS WHICH HAD BECOME LODGED IN THE TEAM MEMBERS PALM. | M62: Injury | O62: No Assessment | P62: Closed | Q62: 0 | R62: FALSE | S62: First Aid Injury | T62: Laceration or open wound not involving traumatic amputation | U62: Hand, finger and thumb | V62: Hitting Objects With a Part of the Body | W62: Hitting stationary objects | X62: Human agencies | Z62: 0 | AA62: MAY, FY25 | AB62: Q4, FY25 | AC62: FAIs | AF62: Hitting Objects With a Part of the Body | AG62: Human agencies | AH62: Spotlight | AI62: SA | AJ62: Store | AK62: Spotlight AU | AL62: SA/NT | AM62: Spotlight AU | AN62: Spotlight AU - SA/NT
A63: SRG-INJ-3628 | C63: No | D63: HS700382 | E63: KOVACS, THOMAS | F63: 45790 | G63: 0.34513889 | H63: Harris Scarfe NSW | I63: 6078 | J63: Ulladulla | K63: sting | L63: Tom was placing empty boxes into the skip bin when he felt a sharp pain in his left outer pinky finger â€” he had been stung by a bee. He flicked the bee off and used a splinter probe from the first aid kit to remove the stinger. His left pinky and hand have localized swelling and pain but he is other | M63: Injury | O63: No Assessment | P63: Closed | Q63: 0 | R63: FALSE | S63: Not Applicable | T63: Contusion, bruising and superficial crushing | U63: Hand, finger and thumb | V63: Chemicals and Other Substances | W63: Insect and spider bites and stings | X63: Human agencies | Z63: 0 | AA63: MAY, FY25 | AB63: Q4, FY25 | AC63: Incident | AF63: Chemicals and Other Substances | AG63: Human agencies | AH63: Harris Scarfe | AI63: NSW | AJ63: Store | AK63: Harris Scarfe | AL63: NSW/ACT | AM63: Harris Scarfe | AN63: Harris Scarfe - NSW/ACT
A64: SRG-INJ-3626 | C64: No | D64: HS295516 | E64: NUTTALL, BELINDA | F64: 45789 | G64: 0.47916667 | H64: Harris Scarfe VIC | I64: 2029 | J64: Waurn Ponds (Hs Home) | K64: base of right thumb | L64: I was walking through the back dock to find a cage for a team member. There was some empty crushed down boxes on the floor. I tripped and fell down. Put my hands down to stop myself. Hit my hand and elbow (right) and my left hand to a lesser extent.on the concrete floor.. The base of my right thumb is sore. I iced it straight away.. I also have a little niggle on the base of my left thumb | M64: Injury | O64: No Assessment | P64: Closed | Q64: 0 | R64: FALSE | S64: First Aid Injury | T64: Contusion, bruising and superficial crushing | U64: Hand, finger and thumb | V64: Falls, Trips and Slips of a Person | W64: Falls on the same level | X64: Human agencies | Z64: 0 | AA64: MAY, FY25 | AB64: Q4, FY25 | AC64: FAIs | AF64: Falls, Trips and Slips of a Person | AG64: Human agencies | AH64: Harris Scarfe | AI64: VIC | AJ64: Store | AK64: Harris Scarfe | AL64: VIC & NSW | AM64: Harris Scarfe | AN64: Harris Scarfe - VIC & NSW
A65: SRG-INJ-3625 | C65: No | D65: AU216035 | E65: BALDWIN, MELISSA | F65: 45789 | G65: 0.45277778 | H65: Spotlight VIC | I65: S113 | J65: South Morang | K65: Right forearm bruising and scrapes, | L65: table tone bar got caught on another roll and came off when pulling it out, caught the team member on her arm as it fell. | M65: Injury | O65: No Assessment | P65: Closed | Q65: 0 | R65: FALSE | S65: First Aid Injury | T65: Contusion, bruising and superficial crushing | U65: Forearm | V65: Being Hit By Moving Objects | W65: Being hit by falling objects | X65: Human agencies | Z65: 0 | AA65: MAY, FY25 | AB65: Q4, FY25 | AC65: FAIs | AF65: Being Hit By Moving Objects | AG65: Human agencies | AH65: Spotlight | AI65: VIC | AJ65: Store | AK65: Spotlight AU | AL65: VIC West | AM65: Spotlight AU | AN65: Spotlight AU - VIC West
A66: SRG-INJ-3638 | C66: No | D66: HS327986 | E66: D'ALOIA, AMY | F66: 45788 | G66: 0.53472222 | H66: Harris Scarfe SA | I66: 1008 | J66: Tea Tree Plaza | K66: right wrist | L66: Amy was refilling/ moving cast iron and dinner sets on Sunday and at the end of day noticed her right wrist was sore. she strapped it wed and thurs and went to the dr thursday. | M66: Injury | O66: No Assessment | P66: Open | Q66: 0 | R66: FALSE | S66: Not Applicable | T66: Trauma to muscles and tendons | U66: Wrist | V66: Body Stressing | W66: Muscular stress while lifting, carrying, or putting down objects | X66: Human agencies | Z66: 0 | AA66: MAY, FY25 | AB66: Q4, FY25 | AC66: Incident | AF66: Body Stressing | AG66: Human agencies | AH66: Harris Scarfe | AI66: SA | AJ66: Store | AK66: Harris Scarfe | AL66: SA/TAS | AM66: Harris Scarfe | AN66: Harris Scarfe - SA/TAS
A67: SRG-INJ-3624 | C67: No | D67: AU321758 | E67: CUSKELLY, MIKAYLA | F67: 45787 | G67: 0.49305556 | H67: Spotlight VIC | I67: S026 | J67: Bendigo | K67: cut to finger | L67: Cut to finger on a staple | M67: Injury | O67: No Assessment | P67: Closed | Q67: 0 | R67: FALSE | S67: Not Applicable | T67: Laceration or open wound not involving traumatic amputation | U67: Hand, finger and thumb | V67: Being Hit By Moving Objects | W67: Being trapped between stationary and moving objects | X67: Human agencies | Z67: 0 | AA67: MAY, FY25 | AB67: Q4, FY25 | AC67: Incident | AF67: Being Hit By Moving Objects | AG67: Human agencies | AH67: Spotlight | AI67: VIC | AJ67: Store | AK67: Spotlight AU | AL67: VIC West | AM67: Spotlight AU | AN67: Spotlight AU - VIC West
A68: SRG-INJ-3683 | C68: No | D68: AU238601 | E68: SULLIVAN, MARY | F68: 45787 | G68: 0.47916667 | H68: Spotlight VIC | I68: S002 | J68: Box Hill | K68: strain in shoulder causing her to not be able to lift her arm properly | L68: was carrying a large heavy curtains, which put a lot of strain on her shoulder | M68: Injury | O68: No Assessment | P68: Open | Q68: 0 | R68: FALSE | S68: Not Applicable | T68: Trauma to muscles and tendons | U68: Shoulder | V68: Body Stressing | W68: Muscular stress while lifting, carrying, or putting down objects | X68: Human agencies | Z68: 0 | AA68: MAY, FY25 | AB68: Q4, FY25 | AC68: Incident | AF68: Body Stressing | AG68: Human agencies | AH68: Spotlight | AI68: VIC | AJ68: Store | AK68: Spotlight AU | AL68: VIC East | AM68: Spotlight AU | AN68: Spotlight AU - VIC East
A69: SRG-INJ-3621 | C69: No | D69: AU313474 | E69: SLOMAN-SMITH, DANNIELLE | F69: 45786 | G69: 0.45833333 | H69: Spotlight SA | I69: S074 | J69: Clovercrest | K69: Left side middle of back, now radiating out | L69: Staff member was picking up a large bolt of wadding for a customer and felt a pop in her back. She took some pain killers after wards and continued to work for a period of time but is suffering pain in her back and finding it difficult to breathe. | M69: Injury | O69: No Assessment | P69: Closed | Q69: 0 | R69: FALSE | S69: Not Applicable | T69: Trauma to muscles and tendons | U69: Back-Upper and lower | V69: Body Stressing | W69: Muscular stress while lifting, carrying, or putting down objects | X69: Human agencies | Z69: 0 | AA69: MAY, FY25 | AB69: Q4, FY25 | AC69: Incident | AF69: Body Stressing | AG69: Human agencies | AH69: Spotlight | AI69: SA | AJ69: Store | AK69: Spotlight AU | AL69: SA/NT | AM69: Spotlight AU | AN69: Spotlight AU - SA/NT
A70: SRG-INJ-3627 | C70: No | D70: AU235749 | E70: ADVANI, MALINI | F70: 45786 | G70: 0.66666667 | H70: Spotlight VIC | I70: S098 | J70: Burnside | K70: right shoulder and arm heavily strained | L70: lifted heavy sewing machines from the steel cages onto the shelves. | M70: Injury | O70: No Assessment | P70: Closed | Q70: 0 | R70: FALSE | S70: Not Applicable | T70: Trauma to muscles and tendons | U70: Shoulder | V70: Body Stressing | W70: Muscular stress while lifting, carrying, or putting down objects | X70: Human agencies | Z70: 0 | AA70: MAY, FY25 | AB70: Q4, FY25 | AC70: Incident | AF70: Body Stressing | AG70: Human agencies | AH70: Spotlight | AI70: VIC | AJ70: Store | AK70: Spotlight AU | AL70: VIC West | AM70: Spotlight AU | AN70: Spotlight AU - VIC West
A71: SRG-INJ-3622 | C71: No | D71: AU317307 | E71: HEWITT, HARRY | F71: 45786 | G71: 0.60416667 | H71: Anaconda TAS | I71: A080 | J71: Glenorchy | K71: middle back strain | L71: Team member was working a pallet of stock and went to grab mirrors from the middle and when they lifted the mirror they felt a sudden pain in their back. | M71: Injury | O71: No Assessment | P71: Closed | Q71: 0 | R71: FALSE | S71: Not Applicable | T71: Trauma to muscles and tendons | U71: Back-Upper and lower | V71: Body Stressing | W71: Muscular stress while lifting, carrying, or putting down objects | X71: Human agencies | Z71: 0 | AA71: MAY, FY25 | AB71: Q4, FY25 | AC71: Incident | AF71: Body Stressing | AG71: Human agencies | AH71: Anaconda | AI71: TAS | AJ71: Store | AK71: Anaconda | AL71: VIC West / TAS | AM71: Anaconda | AN71: Anaconda - VIC West / TAS
A72: SRG-INJ-3620 | C72: No | D72: AU200056 | E72: KOKOLIS, ELLEANOR | F72: 45785 | G72: 0.54166667 | H72: Anaconda QLD | I72: A049 | J72: Tingalpa | K72: Right pinky finger | L72: "When covering [another team member | M72: Injury | O72: No Assessment | P72: Closed | Q72: 0 | R72: FALSE | S72: Not Applicable | T72: Laceration or open wound not involving traumatic amputation | U72: Hand, finger and thumb | V72: Being Hit By Moving Objects | W72: Being hit by falling objects | X72: Human agencies | Z72: 0 | AA72: MAY, FY25 | AB72: Q4, FY25 | AC72: Incident | AF72: Being Hit By Moving Objects | AG72: Human agencies | AH72: Anaconda | AI72: QLD | AJ72: Store | AK72: Anaconda | AL72: QLD Central | AM72: Anaconda | AN72: Anaconda - QLD Central
A73: SRG-INJ-3619 | C73: No | D73: AU336253 | E73: KERR, AMANDA | F73: 45785 | G73: 0.60416667 | H73: Spotlight VIC | I73: S026 | J73: Bendigo | K73: Cut and bump on Forhead | L73: Arbee Bar came out of shelf whilst stocking shelf and nocked forhead | M73: Injury | O73: No Assessment | P73: Closed | Q73: 0 | R73: FALSE | S73: First Aid Injury | T73: Laceration or open wound not involving traumatic amputation | U73: Face, not elsewhere classified | V73: Being Hit By Moving Objects | W73: Being hit by falling objects | X73: Human agencies | Z73: 0 | AA73: MAY, FY25 | AB73: Q4, FY25 | AC73: FAIs | AF73: Being Hit By Moving Objects | AG73: Human agencies | AH73: Spotlight | AI73: VIC | AJ73: Store | AK73: Spotlight AU | AL73: VIC West | AM73: Spotlight AU | AN73: Spotlight AU - VIC West
A74: SRG-INJ-3615 | C74: No | D74: AU322418 | E74: CLARKSON, JODIE | F74: 45785 | G74: 0.48333333 | H74: Spotlight VIC | I74: S014 | J74: Bayswater | K74: sore lower back | L74: LIFTING CAPRICE 270 DUAL ROLLER BLIND OUT OF BAY FOR CUSTOMER | M74: Injury | O74: No Assessment | P74: Closed | Q74: 0 | R74: FALSE | S74: Not Applicable | T74: Trauma to muscles and tendons | U74: Back-Upper and lower | V74: Body Stressing | W74: Muscular stress while lifting, carrying, or putting down objects | X74: Human agencies | Z74: 0 | AA74: MAY, FY25 | AB74: Q4, FY25 | AC74: Incident | AF74: Body Stressing | AG74: Human agencies | AH74: Spotlight | AI74: VIC | AJ74: Store | AK74: Spotlight AU | AL74: VIC East | AM74: Spotlight AU | AN74: Spotlight AU - VIC East
A75: SRG-INJ-3618 | C75: No | D75: AU200062 | E75: MARINO, ROSANNA | F75: 45785 | G75: 0.63541667 | H75: Spotlight VIC | I75: S008 | J75: Essendon | K75: both kness are hurt when she fell | L75: At 3.15 Rossana was working stock in Furnishing and started walking didnt see blinds and fell over the blinds onto her knees on the floor, | M75: Injury | O75: No Assessment | P75: Closed | Q75: 0 | R75: FALSE | S75: First Aid Injury | T75: Trauma to muscles and tendons | U75: Knee | V75: Falls, Trips and Slips of a Person | W75: Falls on the same level | X75: Human agencies | Z75: 0 | AA75: MAY, FY25 | AB75: Q4, FY25 | AC75: FAIs | AF75: Falls, Trips and Slips of a Person | AG75: Human agencies | AH75: Spotlight | AI75: VIC | AJ75: Store | AK75: Spotlight AU | AL75: VIC West | AM75: Spotlight AU | AN75: Spotlight AU - VIC West
A76: SRG-INJ-3616 | C76: No | D76: AU322860 | E76: BROWN, EVE | F76: 45785 | G76: 0.45486111 | H76: Spotlight ACT | I76: S153 | J76: Gungahlin | K76: twisted ankle | L76: twisted ankle | M76: Injury | O76: No Assessment | P76: Closed | Q76: 0 | R76: FALSE | S76: Not Applicable | T76: Trauma to muscles and tendons | U76: Ankle | V76: Body Stressing | W76: Muscular stress with no objects being handled | X76: Human agencies | Z76: 0 | AA76: MAY, FY25 | AB76: Q4, FY25 | AC76: Incident | AF76: Body Stressing | AG76: Human agencies | AH76: Spotlight | AI76: ACT | AJ76: Store | AK76: Spotlight AU | AL76: NSW South / ACT | AM76: Spotlight AU | AN76: Spotlight AU - NSW South / ACT
A77: SRG-INJ-3610 | C77: No | D77: AU290163 | E77: MCMILLAN, SUSAN | F77: 45784 | G77: 0.40694444 | H77: Spotlight NSW | I77: S100 | J77: Nowra | K77: Twisted ankle and knee as she fell and hit knee and elbow on ground when she fell | L77: Team member was packaging an online order and tripped on an empty roll of pallet wrap. The team member the tried to stop her fall by grabbing a close by pallet, however was unable to stop her fall and fell to the ground. | M77: Injury | O77: No Assessment | P77: Closed | Q77: 0 | R77: FALSE | S77: First Aid Injury | T77: Contusion, bruising and superficial crushing | U77: Knee | V77: Falls, Trips and Slips of a Person | W77: Falls on the same level | X77: Human agencies | Z77: 0 | AA77: MAY, FY25 | AB77: Q4, FY25 | AC77: FAIs | AF77: Falls, Trips and Slips of a Person | AG77: Human agencies | AH77: Spotlight | AI77: NSW | AJ77: Store | AK77: Spotlight AU | AL77: NSW South / ACT | AM77: Spotlight AU | AN77: Spotlight AU - NSW South / ACT
A78: SRG-INJ-3611 | C78: No | D78: AU318305 | E78: SMITH, CARROLLYN | F78: 45784 | G78: 0.47916667 | H78: Spotlight QLD | I78: S035 | J78: Everton Park | K78: felt twinge in lower left of back | L78: Carry was unpacking a pallet and she has lent over and stretched to far and has felt a twinge in her back | M78: Injury | O78: No Assessment | P78: Closed | Q78: 0 | R78: FALSE | S78: Not Applicable | T78: Trauma to muscles and tendons | U78: Back-Upper and lower | V78: Body Stressing | W78: Muscular stress while lifting, carrying, or putting down objects | X78: Human agencies | Z78: 0 | AA78: MAY, FY25 | AB78: Q4, FY25 | AC78: Incident | AF78: Body Stressing | AG78: Human agencies | AH78: Spotlight | AI78: QLD | AJ78: Store | AK78: Spotlight AU | AL78: QLD North | AM78: Spotlight AU | AN78: Spotlight AU - QLD North
A79: SRG-INJ-3623 | C79: No | D79: AU336253 | E79: KERR, AMANDA | F79: 45783 | G79: 0.4375 | H79: Spotlight VIC | I79: S026 | J79: Bendigo | K79: nock to ankle | L79: Nock to ankle whilst moving scoop of stock | M79: Injury | O79: No Assessment | P79: Closed | Q79: 0 | R79: FALSE | S79: Not Applicable | T79: Laceration or open wound not involving traumatic amputation | U79: Ankle | V79: Being Hit By Moving Objects | W79: Being hit by moving objects | X79: Human agencies | Z79: 0 | AA79: MAY, FY25 | AB79: Q4, FY25 | AC79: Incident | AF79: Being Hit By Moving Objects | AG79: Human agencies | AH79: Spotlight | AI79: VIC | AJ79: Store | AK79: Spotlight AU | AL79: VIC West | AM79: Spotlight AU | AN79: Spotlight AU - VIC West
A80: SRG-INJ-3612 | C80: No | D80: AU302777 | E80: DAVIES-REID, MICHELLE | F80: 45783 | G80: 0.625 | H80: Spotlight WA | I80: S115 | J80: Albany | K80: Left bicep | L80: Team member was unpacking lifting a box out of a pallet at waist height and felt pain in her left bicep, almost like a pulled muscle. Area was iced and team member took their own Nurofen for the pain but is still in pain today and has booked a doctor's appointment to get the injury looked at. | M80: Claim | N80: Pending Claim | O80: Restricted Duties | P80: Open | Q80: 0 | R80: FALSE | S80: Medical Treatment Injury | T80: Trauma to muscles and tendons | U80: Hand, finger and thumb | V80: Body Stressing | W80: Repetitive movement, low muscle loading | X80: Human agencies | Z80: Open | AA80: MAY, FY25 | AB80: Q4, FY25 | AC80: MTIs | AD80: Claim | AE80: Pending Claim | AF80: Body Stressing | AG80: Human agencies | AH80: Spotlight | AI80: WA | AJ80: Store | AK80: Spotlight AU | AL80: WA | AM80: Spotlight AU | AN80: Spotlight AU - WA
A81: SRG-INJ-3609 | C81: No | D81: AU336386 | E81: SANT, HENRY | F81: 45782 | G81: 0.38888889 | H81: Spotlight NSW | I81: S054 | J81: Bathurst | K81: Left hand pointer finger | L81: TM whilst filling the stapler got a staple lodged in his left pointer finger | M81: Injury | O81: No Assessment | P81: Closed | Q81: 0 | R81: FALSE | S81: First Aid Injury | T81: Contusion, bruising and superficial crushing | U81: Hand, finger and thumb | V81: Hitting Objects With a Part of the Body | W81: Hitting stationary objects | X81: Human agencies | Z81: 0 | AA81: MAY, FY25 | AB81: Q4, FY25 | AC81: FAIs | AF81: Hitting Objects With a Part of the Body | AG81: Human agencies | AH81: Spotlight | AI81: NSW | AJ81: Store | AK81: Spotlight AU | AL81: NSW Central | AM81: Spotlight AU | AN81: Spotlight AU - NSW Central
A82: SRG-INJ-3617 | C82: No | D82: AU239233 | E82: EDWARDS, JODY | F82: 45782 | G82: 0.6875 | H82: Spotlight NSW | I82: S030 | J82: Birkenhead Point | K82: Upper Back | L82: Muscle discomfort after reaching and lifting m2m stock | M82: Injury | O82: No Assessment | P82: Closed | Q82: 0 | R82: FALSE | S82: Not Applicable | T82: Trauma to muscles and tendons | U82: Back-Upper and lower | V82: Body Stressing | W82: Muscular stress while lifting, carrying, or putting down objects | X82: Human agencies | Z82: 0 | AA82: MAY, FY25 | AB82: Q4, FY25 | AC82: Incident | AF82: Body Stressing | AG82: Human agencies | AH82: Spotlight | AI82: NSW | AJ82: Store | AK82: Spotlight AU | AL82: NSW Central | AM82: Spotlight AU | AN82: Spotlight AU - NSW Central
A83: SRG-INJ-3608 | C83: No | D83: AU232530 | E83: SONG, MINSOPAAL | F83: 45781 | G83: 0.46666667 | H83: Spotlight VIC | I83: S005 | J83: Sandown | K83: Right Foot | L83: I went to go and pick up an order that was a large carton full of mason jars, not labeled as being heavy and not labelled as being fragile. the top was secured with tape only but the bottom was not. it was only folded in and weaved to be closed. There were 10 packs of 8 mason jars that spilled out from under neath and smashed into my right foot as i picked it up to move because it was put in a location that wouldn't have been noticed by despatched to be shipped. | M83: Injury | O83: No Assessment | P83: Closed | Q83: 0 | R83: FALSE | S83: First Aid Injury | T83: Contusion, bruising and superficial crushing | U83: Foot and toes | V83: Being Hit By Moving Objects | W83: Being hit by falling objects | X83: Human agencies | Z83: 0 | AA83: MAY, FY25 | AB83: Q4, FY25 | AC83: FAIs | AF83: Being Hit By Moving Objects | AG83: Human agencies | AH83: Spotlight | AI83: VIC | AJ83: Store | AK83: Spotlight AU | AL83: VIC East | AM83: Spotlight AU | AN83: Spotlight AU - VIC East
A84: SRG-INJ-3613 | C84: No | D84: AU200168 | E84: MACDONALD, JAKE | F84: 45781 | G84: 0.43055556 | H84: Anaconda NSW | I84: A062 | J84: Campbelltown | K84: Store headset (radio) shocked/zapped team members right ear when receiving communication (sound). | L84: Team member was receiving comunication through radio and felt the headset shock him on right ear. | M84: Injury | O84: No Assessment | P84: Closed | Q84: 0 | R84: FALSE | S84: Not Applicable | T84: Audio shock, audio shriek | U84: Ear | V84: Sound and Pressure | W84: Other variations in pressure | X84: Human agencies | Z84: 0 | AA84: MAY, FY25 | AB84: Q4, FY25 | AC84: Incident | AF84: Sound and Pressure | AG84: Human agencies | AH84: Anaconda | AI84: NSW | AJ84: Store | AK84: Anaconda | AL84: NSW South | AM84: Anaconda | AN84: Anaconda - NSW South
A85: SRG-INJ-3614 | C85: No | D85: AU317985 | E85: HILLYER, JAIMEE | F85: 45781 | G85: 0.49583333 | H85: Anaconda NSW | I85: A062 | J85: Campbelltown | K85: Injury consists of bruising and grazing to few areas inclduing left arm below elbow, right arm above elbow/blow shoulder, left leg above ankle and left inner leg above/behind knee. (see images) | L85: Team member moved a basket to access shelves more easily. After picking up a basket of hooks from the shelf, they stepped back and tripped over the earlier-moved basket, resulting in a fall. Injuries were assessed on the ground, with photos taken of grazes and early bruising. | M85: Injury | O85: No Assessment | P85: Closed | Q85: 0 | R85: FALSE | S85: Not Applicable | T85: Contusion, bruising and superficial crushing | U85: Back-Upper and lower | V85: Falls, Trips and Slips of a Person | W85: Falls on the same level | X85: Human agencies | Z85: 0 | AA85: MAY, FY25 | AB85: Q4, FY25 | AC85: Incident | AF85: Falls, Trips and Slips of a Person | AG85: Human agencies | AH85: Anaconda | AI85: NSW | AJ85: Store | AK85: Anaconda | AL85: NSW South | AM85: Anaconda | AN85: Anaconda - NSW South
A86: SRG-INJ-3607 | B86: S24KV242206 | C86: No | D86: AU327446 | E86: THORNTON, JOANNE | F86: 45780 | G86: 0.49583333 | H86: Spotlight QLD | I86: S094 | J86: Cairns | K86: shoulder muscle pull | L86: team member was putting fabric away on shelf and felt a pain in muscle. | M86: Claim | N86: Accepted Claim | O86: Unfit | P86: Open | Q86: 23 | R86: FALSE | S86: Lost Time Injury | T86: Trauma to muscles and tendons | U86: Shoulder | V86: Body Stressing | W86: Muscular stress while lifting, carrying, or putting down objects | X86: Human agencies | Z86: Open | AA86: MAY, FY25 | AB86: Q4, FY25 | AC86: LTIs | AD86: Claim | AE86: Accepted Claim | AF86: Body Stressing | AG86: Human agencies | AH86: Spotlight | AI86: QLD | AJ86: Store | AK86: Spotlight AU | AL86: QLD North | AM86: Spotlight AU | AN86: Spotlight AU - QLD North
A87: SRG-INJ-3606 | B87: S24KR242308 | C87: No | D87: AU327703 | E87: MILES, ELIZABETH | F87: 45779 | G87: 0.61805556 | H87: Spotlight QLD | I87: S139 | J87: Hervey Bay | K87: Lower right back/hip | L87: Liz was tidying stock through aisles and leant down to pick up an item from the bottom shelf, she felt a pull in her lower back and could barely stand. Liz then called for help and was assisted to the staff room where she sat down. Liz was monitored to see if the pain would ease. Still no better after 15-20, the ambulance was then called. | M87: Claim | N87: Accepted Claim | O87: Unfit | P87: Open | Q87: 21 | R87: FALSE | S87: Medical Treatment Injury | T87: Diseases of muscle, tendon and related tissue | U87: Back-Upper and lower | V87: Body Stressing | W87: Muscular stress while handling objects other than lifting, carrying or putting down | X87: Human agencies | Z87: Open | AA87: MAY, FY25 | AB87: Q4, FY25 | AC87: MTIs | AD87: Claim | AE87: Accepted Claim | AF87: Body Stressing | AG87: Human agencies | AH87: Spotlight | AI87: QLD | AJ87: Store | AK87: Spotlight AU | AL87: QLD Central / TAS | AM87: Spotlight AU | AN87: Spotlight AU - QLD Central / TAS
A88: SRG-INJ-3604 | C88: No | D88: AU338408 | E88: SCHUTZ, RILEY | F88: 45779 | G88: 0.43055556 | H88: Anaconda QLD | I88: A038 | J88: Toowoomba | K88: Right Eye | L88: Riley had finished working a cage of kayak backrests, and took his cage out to the bins to empty rubbish. As Riley was loading rubbish into the industrial bins in despatch, a small fragment of rock got in his right eye, thinking it blew up with the wind outside. Ash (Team Leader) was near by at the time and Riley reported it on the spot. Riley went to the bathroom to try & get it out but was unsuccessful. I (Ash) grabbed eye wash from the first aid box and told him to flush his eye out. Riley did that and the small fragment of rock came out. Riley's eye was red & blurry following. Riley had a 10 minute break following. His eye was improving and was happy to resume normal duties. | M88: Injury | O88: No Assessment | P88: Closed | Q88: 0 | R88: FALSE | S88: First Aid Injury | T88: Contusion, bruising and superficial crushing | U88: Eye | V88: Being Hit By Moving Objects | W88: Being hit by falling objects | X88: Human agencies | Z88: 0 | AA88: MAY, FY25 | AB88: Q4, FY25 | AC88: FAIs | AF88: Being Hit By Moving Objects | AG88: Human agencies | AH88: Anaconda | AI88: QLD | AJ88: Store | AK88: Anaconda | AL88: QLD NW / NT | AM88: Anaconda | AN88: Anaconda - QLD NW / NT
A89: SRG-INJ-3605 | C89: No | D89: HS326116 | E89: CONNELLY, RYAN | F89: 45779 | G89: 0.4625 | H89: Harris Scarfe TAS | I89: 4044 | J89: Devonport | K89: Wood splinter into left eye | L89: Ryan was stacking a pallet when a piece of wood splintered off and hit his left eye. He tried to rinse it out, and was then sent to Specsavers, where they confirmed there was no damage to the eye. he is well no time loss no md treatmen required back | M89: Injury | O89: No Assessment | P89: Closed | Q89: 0 | R89: FALSE | S89: Not Applicable | T89: Contusion, bruising and superficial crushing | U89: Eye | V89: Being Hit By Moving Objects | W89: Being hit by falling objects | X89: Human agencies | Z89: 0 | AA89: MAY, FY25 | AB89: Q4, FY25 | AC89: Incident | AF89: Being Hit By Moving Objects | AG89: Human agencies | AH89: Harris Scarfe | AI89: TAS | AJ89: Store | AK89: Harris Scarfe | AL89: SA/TAS | AM89: Harris Scarfe | AN89: Harris Scarfe - SA/TAS
A90: SRG-INJ-3602 | C90: No | D90: HS327110 | E90: GANGEMI, OLIVIA | F90: 45778 | G90: 0.50625 | H90: Harris Scarfe VIC | I90: 2045 | J90: Frankston | K90: right fingers index and middle | L90: Olivia Gangemi was washing her dishes and was using the hot water tap, she got distracted while doing this and she lent in and two of her right fingers got burnt, olivia spoke to management, we applied cold water, ice pack, and we used burnaid/antiseptic cream to help aid with the pain and recovery, | M90: Injury | O90: No Assessment | P90: Closed | Q90: 0 | R90: FALSE | S90: First Aid Injury | T90: Hot burn | U90: Hand, finger and thumb | V90: Heat, Electricity and Other Environmental Factors | W90: Contact with hot objects | X90: Human agencies | Z90: 0 | AA90: MAY, FY25 | AB90: Q4, FY25 | AC90: FAIs | AF90: Heat, Electricity and Other Environmental Factors | AG90: Human agencies | AH90: Harris Scarfe | AI90: VIC | AJ90: Store | AK90: Harris Scarfe | AL90: VIC | AM90: Harris Scarfe | AN90: Harris Scarfe - VIC
A91: SRG-INJ-3601 | C91: No | D91: AU329307 | E91: HAYNES, INGRID | F91: 45778 | G91: 0.50277778 | H91: Spotlight NSW | I91: S174 | J91: Alexandria | K91: Left ring finger | L91: Removing RB bar and smashed my finger with the end of it | M91: Injury | O91: No Assessment | P91: Closed | Q91: 0 | R91: FALSE | S91: Not Applicable | T91: Contusion, bruising and superficial crushing | U91: Hand, finger and thumb | V91: Hitting Objects With a Part of the Body | W91: Hitting stationary objects | X91: Human agencies | Z91: 0 | AA91: MAY, FY25 | AB91: Q4, FY25 | AC91: Incident | AF91: Hitting Objects With a Part of the Body | AG91: Human agencies | AH91: Spotlight | AI91: NSW | AJ91: Store | AK91: Spotlight AU | AL91: NSW Central | AM91: Spotlight AU | AN91: Spotlight AU - NSW Central
A92: SRG-INJ-3603 | C92: No | D92: AU334745 | E92: MCELHINNEY, DEBBIE | F92: 45777 | G92: 0.72916667 | H92: Spotlight NSW | I92: S042 | J92: Queanbeyan | K92: Right wrist | L92: Team member experienced arm pain after a full day of heavy lifting. The pain worsened the next day (1/5/25) but she continued working with moderate lifting. She reported increased pain and inflammation today (2/5/25), so Iâ€™ve sent her home to rest and recover. | M92: Injury | O92: No Assessment | P92: Closed | Q92: 0 | R92: FALSE | S92: Not Applicable | T92: Trauma to muscles and tendons | U92: Hand, finger and thumb | V92: Body Stressing | W92: Muscular stress while handling objects other than lifting, carrying or putting down | X92: Human agencies | Z92: 0 | AA92: MAY, FY25 | AB92: Q4, FY25 | AC92: Incident | AF92: Body Stressing | AG92: Human agencies | AH92: Spotlight | AI92: NSW | AJ92: Store | AK92: Spotlight AU | AL92: NSW South / ACT | AM92: Spotlight AU | AN92: Spotlight AU - NSW South / ACT
A93: SRG-INJ-3599 | C93: No | D93: AU204764 | E93: ANDERSON, KELLY | F93: 45776 | G93: 0.70833333 | H93: Spotlight QLD | I93: S111 | J93: Morayfield | K93: Right Eye | L93: Unpacking stock got some fibre in eye | M93: Injury | O93: No Assessment | P93: Closed | Q93: 0 | R93: FALSE | S93: First Aid Injury | T93: Contusion, bruising and superficial crushing | U93: Eye | V93: Chemicals and Other Substances | W93: Single contact with chemical or substance | X93: Human agencies | Z93: 0 | AA93: MAY, FY25 | AB93: Q4, FY25 | AC93: FAIs | AF93: Chemicals and Other Substances | AG93: Human agencies | AH93: Spotlight | AI93: QLD | AJ93: Store | AK93: Spotlight AU | AL93: QLD Central / TAS | AM93: Spotlight AU | AN93: Spotlight AU - QLD Central / TAS
A94: SRG-INJ-3597 | C94: No | D94: AU318266 | E94: DAWKINS, NATASHA | F94: 45776 | G94: 0.45833333 | H94: Anaconda VIC | I94: A013 | J94: Frankston | K94: Twisting of the arm causing pain and stifness in the right Bicep | L94: Team member was trying to move (Push) a rollie rack full of apparel. The rack didnt move and the team member gave another pull and the rack tipped over. In the process the team members arm was pulled awekwardly as the rail fell. Now has a sore right bicep. | M94: Injury | O94: No Assessment | P94: Closed | Q94: 0 | R94: FALSE | S94: Lost Time Injury | T94: Contusion, bruising and superficial crushing | U94: Upper arm | V94: Being Hit By Moving Objects | W94: Being hit by falling objects | X94: Human agencies | Z94: 0 | AA94: MAY, FY25 | AB94: Q4, FY25 | AC94: LTIs | AF94: Being Hit By Moving Objects | AG94: Human agencies | AH94: Anaconda | AI94: VIC | AJ94: Store | AK94: Anaconda | AL94: VIC North / East | AM94: Anaconda | AN94: Anaconda - VIC North / East
A95: SRG-INJ-3600 | C95: No | D95: HS297188 | E95: PULLING, ALEXANDER | F95: 45775 | G95: 0.52083333 | H95: Harris Scarfe VIC | I95: 2039 | J95: Fountain Gate | K95: head/neck | L95: i reached into plastics bin to retrieve shoe boxes (that werent supposed to be there). Then the lid fell on my head as i was trying to retrieve boxes. I was dazed for a bit, then grabbed boxes and shut the lid. Then I walked back into the dock with sore head. Didnt think much of it but my sleepings affected. | M95: Injury | O95: No Assessment | P95: Closed | Q95: 0 | R95: FALSE | S95: Not Applicable | T95: Contusion, bruising and superficial crushing | U95: Head and Neck | V95: Being Hit By Moving Objects | W95: Being hit by falling objects | X95: Human agencies | Z95: 0 | AA95: MAY, FY25 | AB95: Q4, FY25 | AC95: Incident | AF95: Being Hit By Moving Objects | AG95: Human agencies | AH95: Harris Scarfe | AI95: VIC | AJ95: Store | AK95: Harris Scarfe | AL95: VIC | AM95: Harris Scarfe | AN95: Harris Scarfe - VIC
A96: SRG-INJ-3595 | B96: G7511369 | C96: No | D96: HS331188 | E96: EYRE, KELLY | F96: 45775 | G96: 0.52083333 | H96: Harris Scarfe TAS | I96: 4045 | J96: Ulverstone | K96: right knee | L96: while helping a customer and recovering jeans, i knelt down on the floor with my right knee and felt something pop inside my knee | M96: Claim | N96: Pending Claim | O96: Restricted Duties | P96: Open | Q96: 2 | R96: FALSE | S96: Lost Time Injury | T96: Trauma to muscles and tendons | U96: Knee | V96: Body Stressing | W96: Muscular stress with no objects being handled | X96: Human agencies | Z96: Open | AA96: MAY, FY25 | AB96: Q4, FY25 | AC96: LTIs | AD96: Claim | AE96: Pending Claim | AF96: Body Stressing | AG96: Human agencies | AH96: Harris Scarfe | AI96: TAS | AJ96: Store | AK96: Harris Scarfe | AL96: SA/TAS | AM96: Harris Scarfe | AN96: Harris Scarfe - SA/TAS
A97: SRG-INJ-3593 | C97: No | D97: HS337411 | E97: KENDALL, CHARLOTTE | F97: 45774 | G97: 0.50555556 | H97: Harris Scarfe QLD | I97: 9095 | J97: Chermside | K97: Rolled left ankle | L97: Charlotte was putting stock back and when she bent over she lost balance and rolled her ankle. | M97: Injury | O97: Restricted Duties | P97: Closed | Q97: 0 | R97: FALSE | S97: Medical Treatment Injury | T97: Trauma to muscles and tendons | U97: Ankle | V97: Falls, Trips and Slips of a Person | W97: Falls on the same level | X97: Human agencies | Z97: 0 | AA97: APR, FY25 | AB97: Q4, FY25 | AC97: MTIs | AF97: Falls, Trips and Slips of a Person | AG97: Human agencies | AH97: Harris Scarfe | AI97: QLD | AJ97: Store | AK97: Harris Scarfe | AL97: QLD | AM97: Harris Scarfe | AN97: Harris Scarfe - QLD
A98: SRG-INJ-3592 | C98: No | D98: HS322470 | E98: SMITH, EMILY | F98: 45773 | G98: 0.33333333 | H98: Harris Scarfe TAS | I98: 4042 | J98: Cambridge | K98: Right Hip | L98: Emily reported and injury/incident on 04.01.2025 INC11004. Without any Medical follow up required at the time. Report only. Since the start of April Emily has had pain come back in the same spot in her hip from this injury. At the time of pain coming back it was only in her hip when walking but a few days later Emily is experiencing a shooting pain in her right shin and into her foot. This has progressively gotten worse and at times a struggle for her to walk with out discomfort. Emily is now also from walking to compensate the pain in her hip is having some swelling/pain in her right knee. After rest she seems to be ok of a morning, after a few hours of working/walking it becomes painful and therefore affecting the way she walks. Emily was unable to attend work on 26/4 due to this. | M98: Claim | N98: Pending Claim | O98: Unfit | P98: Open | Q98: 19 | R98: FALSE | S98: Not Applicable | T98: Trauma to muscles and tendons | U98: Hip | V98: Vehicle Incidents and Other | W98: Unspecified mechanisms of incident | X98: Human agencies | Z98: Open | AA98: APR, FY25 | AB98: Q4, FY25 | AC98: Incident | AD98: Claim | AE98: Pending Claim | AF98: Vehicle Incidents and Other | AG98: Human agencies | AH98: Harris Scarfe | AI98: TAS | AJ98: Store | AK98: Harris Scarfe | AL98: SA/TAS | AM98: Harris Scarfe | AN98: Harris Scarfe - SA/TAS
A99: SRG-INJ-3596 | C99: No | D99: AU335836 | E99: HUNTER, BONNIE | F99: 45773 | G99: 0.59027778 | H99: Spotlight TAS | I99: S011 | J99: Launceston | K99: Cut to left pinkie finger | L99: Bonnie Hunter was trimming the ribbon and the weight of the bouquet fell off the counter. Bonnie went to catch the weight and had scissors in her hand and the scissors cut her left pinkie finger | M99: Injury | O99: No Assessment | P99: Closed | Q99: 0 | R99: FALSE | S99: First Aid Injury | T99: Laceration or open wound not involving traumatic amputation | U99: Hand, finger and thumb | V99: Hitting Objects With a Part of the Body | W99: Hitting stationary objects | X99: Human agencies | Y99: Scissors | Z99: 0 | AA99: APR, FY25 | AB99: Q4, FY25 | AC99: FAIs | AF99: Hitting Objects With a Part of the Body | AG99: Human agencies | AH99: Spotlight | AI99: TAS | AJ99: Store | AK99: Spotlight AU | AL99: QLD Central / TAS | AM99: Spotlight AU | AN99: Spotlight AU - QLD Central / TAS
A100: SRG-INJ-3594 | C100: No | D100: AU298980 | E100: PHILIPPI, MADISON | F100: 45771 | G100: 0.81458333 | H100: Spotlight QLD | I100: S139 | J100: Hervey Bay | K100: Left upper arm | L100: Holly was removing curtains for M2M when 2 boxes of stock fell down hitting Madison on left arm above elbow. | M100: Injury | O100: No Assessment | P100: Closed | Q100: 0 | R100: FALSE | S100: Not Applicable | T100: Trauma to muscles and tendons | U100: Upper arm | V100: Being Hit By Moving Objects | W100: Being hit by falling objects | X100: Human agencies | Y100: Boxes | Z100: 0 | AA100: APR, FY25 | AB100: Q4, FY25 | AC100: Incident | AF100: Being Hit By Moving Objects | AG100: Human agencies | AH100: Spotlight | AI100: QLD | AJ100: Store | AK100: Spotlight AU | AL100: QLD Central / TAS | AM100: Spotlight AU | AN100: Spotlight AU - QLD Central / TAS
...

Sheet 18-Month HS Incidents
A1: SolvInjury ID | B1: Done Safe ID | C1: Claim Number | D1: Mental Injury | E1: Employee ID | F1: Name | G1: Date of Birth | H1: Date of Injury | I1: Time of Injury | J1: Policy | K1: Site | L1: Name | M1: Injury Description | N1: Incident Description | O1: Injury Type | P1: Liability Status | Q1: Current Capacity | R1: Open/Closed | S1: Days Lost | T1: Worksafe Notified | U1: Injury Outcome | V1: Nature of Injury | W1: Bodily Location | X1: Mechanism | Y1: Sub Mechanism | Z1: Agency | AA1: Equipment | AB1: Closure Rate | AC1: NWR | AD1: Psycho Social | AE1: Incidents Correlation NWR_TMJ | AF1: Hire Date | AG1: Term Date | AH1: Tenure at Date of Injury | AI1: Tenure with the Company | AJ1: Tenure Bracket at Date of Injury | AK1: Employment type | AL1: Base hours | AM1: Age | AN1: Age Bracket | AO1: Fiscal Month | AP1: Fiscal Quarter | AQ1: Outcome Code | AR1: Claim | AS1: Claim Status | AT1: MOI | AU1: Agency | AV1: Company on Policy | AW1: State | AX1: Class 3 | AY1: Company | AZ1: Region | BA1: Grouping Level 1 | BB1: Grouping Level 2
A2: SRG-INJ-1844 | B2: INC3730 | D2: No | E2: 297458 | F2: DOUGLAS, KARIN | G2: 20892 | H2: 45195 | I2: 0.4375 | J2: Harris Scarfe VIC | K2: 2032 | L2: Traralgon | M2: Head sore | N2: Team member lifted dinnersets off shelf which caused shelf to lift up and hit Karin in the head | O2: Injury | Q2: No Assessment | R2: Closed | S2: 0 | T2: FALSE | U2: Not Applicable | V2: Residual soft tissue disorders due to trauma or unknown mechanisms | W2: Head - unspecified locations | X2: Being Hit By Moving Objects | Y2: Being hit by moving objects | Z2: Other materials and objects | AB2: 0 | AC2: #N/A | AD2: #N/A | AF2: 44329 | AG2: 45363 | AH2: =DATEDIF(AF2,H2,"Y") -> 2 | AI2: =IF(AG2=0,DATEDIF(AF2,TODAY(),"Y"),DATEDIF(AF2,AG2,"Y")) -> 2 | AJ2: =IF(AH2=0,"Under 1 Year",IF(AND(AH2>=1,AH2<=5),"1-5 Years",IF(AND(AH2>=6,AH2<=10),"6-10 Years",IF(AND(AH2>=11,AH2<=15),"11-15 Years",IF(AND(AH2>=16,AH2<=20),"16-20 Years",IF(AND(AH2>=21,AH2<=25),"21-25 Years",IF(AND(AH2>=26,AH2<=30),"26-30 Years","More Than 30 Years"))))))) -> 1-5 Years | AK2: PART TIME | AL2: 21.5 | AM2: 68 | AN2: =IF(AM2<20,"Less Than 20 Years",IF(AND(AM2>=20,AM2<=24),"20-24 Years",IF(AND(AM2>=25,AM2<=34),"25-34 Years",IF(AND(AM2>=35,AM2<=44),"35-44 Years",IF(AND(AM2>=45,AM2<=54),"45-54 Years","More Than 55 Years"))))) -> More Than 55 Years | AO2: OCT, FY24 | AP2: Q2, FY24 | AQ2: Incident | AT2: Being Hit By Moving Objects | AU2: Other materials and objects | AV2: Harris Scarfe | AW2: VIC | AX2: Store | AY2: Harris Scarfe | AZ2: VIC | BA2: Harris Scarfe | BB2: Harris Scarfe - VIC
A3: SRG-INJ-1849 | B3: INC3757 | D3: No | E3: 327134 | F3: MITCHELL, ANGELA | G3: 22258 | H3: 45196 | I3: 0.39236111 | J3: Harris Scarfe SA | K3: 1005 | L3: Elizabeth | M3: Hit head on corner of wall. Has a little bump but not feeling dizzy or sick. | N3: Angela was bending down to put stock away and bumped her head on the corner of the wall when she got up. Angela left early but not related to this. She was not feeling well in the morning. | O3: Injury | Q3: No Assessment | R3: Closed | S3: 0 | T3: FALSE | U3: First Aid Injury | V3: Residual soft tissue disorders due to trauma or unknown mechanisms | W3: Head - unspecified locations | X3: Hitting Objects With a Part of the Body | Y3: Hitting stationary objects | Z3: Human agencies | AB3: 0 | AC3: #N/A | AD3: #N/A | AF3: 44900 | AH3: =DATEDIF(AF3,H3,"Y") -> 0 | AI3: =IF(AG3=0,DATEDIF(AF3,TODAY(),"Y"),DATEDIF(AF3,AG3,"Y")) -> 3 | AJ3: =IF(AH3=0,"Under 1 Year",IF(AND(AH3>=1,AH3<=5),"1-5 Years",IF(AND(AH3>=6,AH3<=10),"6-10 Years",IF(AND(AH3>=11,AH3<=15),"11-15 Years",IF(AND(AH3>=16,AH3<=20),"16-20 Years",IF(AND(AH3>=21,AH3<=25),"21-25 Years",IF(AND(AH3>=26,AH3<=30),"26-30 Years","More Than 30 Years"))))))) -> Under 1 Year | AK3: PART TIME | AL3: 35 | AM3: 64 | AN3: =IF(AM3<20,"Less Than 20 Years",IF(AND(AM3>=20,AM3<=24),"20-24 Years",IF(AND(AM3>=25,AM3<=34),"25-34 Years",IF(AND(AM3>=35,AM3<=44),"35-44 Years",IF(AND(AM3>=45,AM3<=54),"45-54 Years","More Than 55 Years"))))) -> More Than 55 Years | AO3: OCT, FY24 | AP3: Q2, FY24 | AQ3: FAIs | AT3: Hitting Objects With a Part of the Body | AU3: Human agencies | AV3: Harris Scarfe | AW3: SA | AX3: Store | AY3: Harris Scarfe | AZ3: SA/TAS | BA3: Harris Scarfe | BB3: Harris Scarfe - SA/TAS
A4: SRG-INJ-1857 | B4: INC3797 | D4: No | E4: 288086 | F4: KNIGHT, REBEKAH | G4: 28881 | H4: 45200 | I4: 0.52013889 | J4: Harris Scarfe TAS | K4: 4045 | L4: Ulverstone | M4: Strained back | N4: I tried to help a customer to lift and move the Harris Scarfe sign that had blown off of the building and broken the front door. I have pulled a muscle in my lower back right side. | O4: Injury | Q4: No Assessment | R4: Closed | S4: 0 | T4: FALSE | U4: Not Applicable | V4: Residual soft tissue disorders due to trauma or unknown mechanisms | W4: Lower limb - multiple locations | X4: Body Stressing | Y4: Muscular stress while lifting, carrying, or putting down objects | Z4: Other materials and objects | AB4: 0 | AC4: #N/A | AD4: #N/A | AF4: 38789 | AH4: =DATEDIF(AF4,H4,"Y") -> 17 | AI4: =IF(AG4=0,DATEDIF(AF4,TODAY(),"Y"),DATEDIF(AF4,AG4,"Y")) -> 20 | AJ4: =IF(AH4=0,"Under 1 Year",IF(AND(AH4>=1,AH4<=5),"1-5 Years",IF(AND(AH4>=6,AH4<=10),"6-10 Years",IF(AND(AH4>=11,AH4<=15),"11-15 Years",IF(AND(AH4>=16,AH4<=20),"16-20 Years",IF(AND(AH4>=21,AH4<=25),"21-25 Years",IF(AND(AH4>=26,AH4<=30),"26-30 Years","More Than 30 Years"))))))) -> 16-20 Years | AK4: SALARIED | AL4: 38 | AM4: 46 | AN4: =IF(AM4<20,"Less Than 20 Years",IF(AND(AM4>=20,AM4<=24),"20-24 Years",IF(AND(AM4>=25,AM4<=34),"25-34 Years",IF(AND(AM4>=35,AM4<=44),"35-44 Years",IF(AND(AM4>=45,AM4<=54),"45-54 Years","More Than 55 Years"))))) -> 45-54 Years | AO4: OCT, FY24 | AP4: Q2, FY24 | AQ4: Incident | AT4: Body Stressing | AU4: Other materials and objects | AV4: Harris Scarfe | AW4: TAS | AX4: Store | AY4: Harris Scarfe | AZ4: SA/TAS | BA4: Harris Scarfe | BB4: Harris Scarfe - SA/TAS
A5: SRG-INJ-1858 | B5: INC3815 | D5: No | E5: 297563 | F5: PRIDMORE-JOHNSTON, REBECCA | G5: 35423 | H5: 45202 | I5: 0.47916667 | J5: Harris Scarfe TAS | K5: 4043 | L5: Launceston | M5: right ankle | N5: Rebecca Pridmore was empty rubbish when she scratched her right ankle on stock cage | O5: Injury | Q5: No Assessment | R5: Closed | S5: 0 | T5: FALSE | U5: Not Applicable | V5: Contusion, bruising and superficial crushing | W5: Ankle | X5: Hitting Objects With a Part of the Body | Y5: Hitting stationary objects | Z5: Other materials and objects | AB5: 0 | AC5: #N/A | AD5: #N/A | AF5: 44424 | AH5: =DATEDIF(AF5,H5,"Y") -> 2 | AI5: =IF(AG5=0,DATEDIF(AF5,TODAY(),"Y"),DATEDIF(AF5,AG5,"Y")) -> 5 | AJ5: =IF(AH5=0,"Under 1 Year",IF(AND(AH5>=1,AH5<=5),"1-5 Years",IF(AND(AH5>=6,AH5<=10),"6-10 Years",IF(AND(AH5>=11,AH5<=15),"11-15 Years",IF(AND(AH5>=16,AH5<=20),"16-20 Years",IF(AND(AH5>=21,AH5<=25),"21-25 Years",IF(AND(AH5>=26,AH5<=30),"26-30 Years","More Than 30 Years"))))))) -> 1-5 Years | AK5: PART TIME | AL5: 31 | AM5: 28 | AN5: =IF(AM5<20,"Less Than 20 Years",IF(AND(AM5>=20,AM5<=24),"20-24 Years",IF(AND(AM5>=25,AM5<=34),"25-34 Years",IF(AND(AM5>=35,AM5<=44),"35-44 Years",IF(AND(AM5>=45,AM5<=54),"45-54 Years","More Than 55 Years"))))) -> 25-34 Years | AO5: OCT, FY24 | AP5: Q2, FY24 | AQ5: Incident | AT5: Hitting Objects With a Part of the Body | AU5: Other materials and objects | AV5: Harris Scarfe | AW5: TAS | AX5: Store | AY5: Harris Scarfe | AZ5: SA/TAS | BA5: Harris Scarfe | BB5: Harris Scarfe - SA/TAS
A6: SRG-INJ-1859 | B6: INC3816 | D6: No | E6: 325752 | F6: ANDREWS, SIOBHAN | G6: 37082 | H6: 45202 | I6: 0.51388889 | J6: Harris Scarfe TAS | K6: 4044 | L6: Devonport | M6: The right thumb, over the knuckle. | N6: I was rearranging stock on the shelving units when my thumb got cut along the knuckle. The shelving unit had a sharp nook and had cut my thumb. Then I cleaned the wound with an alcohol wipe, and wrapped the injury with an adhesive strip (band-aid). | O6: Injury | Q6: No Assessment | R6: Closed | S6: 0 | T6: FALSE | U6: First Aid Injury | V6: Laceration or open wound not involving traumatic amputation | W6: Hand, finger and thumb | X6: Hitting Objects With a Part of the Body | Y6: Hitting stationary objects | Z6: Human agencies | AB6: 0 | AC6: #N/A | AD6: #N/A | AF6: 44858 | AG6: 45330 | AH6: =DATEDIF(AF6,H6,"Y") -> 0 | AI6: =IF(AG6=0,DATEDIF(AF6,TODAY(),"Y"),DATEDIF(AF6,AG6,"Y")) -> 1 | AJ6: =IF(AH6=0,"Under 1 Year",IF(AND(AH6>=1,AH6<=5),"1-5 Years",IF(AND(AH6>=6,AH6<=10),"6-10 Years",IF(AND(AH6>=11,AH6<=15),"11-15 Years",IF(AND(AH6>=16,AH6<=20),"16-20 Years",IF(AND(AH6>=21,AH6<=25),"21-25 Years",IF(AND(AH6>=26,AH6<=30),"26-30 Years","More Than 30 Years"))))))) -> Under 1 Year | AK6: CASUAL | AL6: 0.01 | AM6: 23 | AN6: =IF(AM6<20,"Less Than 20 Years",IF(AND(AM6>=20,AM6<=24),"20-24 Years",IF(AND(AM6>=25,AM6<=34),"25-34 Years",IF(AND(AM6>=35,AM6<=44),"35-44 Years",IF(AND(AM6>=45,AM6<=54),"45-54 Years","More Than 55 Years"))))) -> 20-24 Years | AO6: OCT, FY24 | AP6: Q2, FY24 | AQ6: FAIs | AT6: Hitting Objects With a Part of the Body | AU6: Human agencies | AV6: Harris Scarfe | AW6: TAS | AX6: Store | AY6: Harris Scarfe | AZ6: SA/TAS | BA6: Harris Scarfe | BB6: Harris Scarfe - SA/TAS
A7: SRG-INJ-1879 | B7: INC3892 | D7: No | E7: 286152 | F7: DIMAKAKOS, MELISSA | G7: 27488 | H7: 45203 | I7: 0.47013889 | J7: Harris Scarfe VIC | K7: 2023 | L7: Epping | M7: moving heavy loose dinnerware/ dinnersets | N7: on Tuesday Melisa had to take everything off the gondola including lose dinnerware/dinner sets and on Wednesday after moving the new gondola she had to put all the stock back on . she said she had to try to rush to get the job done as it was through trading hours and right close to entry door and there could be a hazard there. | O7: Injury | Q7: No Assessment | R7: Closed | S7: 0 | T7: FALSE | U7: Not Applicable | V7: Residual soft tissue disorders due to trauma or unknown mechanisms | W7: Shoulder | X7: Body Stressing | Y7: Muscular stress while lifting, carrying, or putting down objects | Z7: Other materials and objects | AB7: 0 | AC7: #N/A | AD7: #N/A | AF7: 37754 | AH7: =DATEDIF(AF7,H7,"Y") -> 20 | AI7: =IF(AG7=0,DATEDIF(AF7,TODAY(),"Y"),DATEDIF(AF7,AG7,"Y")) -> 23 | AJ7: =IF(AH7=0,"Under 1 Year",IF(AND(AH7>=1,AH7<=5),"1-5 Years",IF(AND(AH7>=6,AH7<=10),"6-10 Years",IF(AND(AH7>=11,AH7<=15),"11-15 Years",IF(AND(AH7>=16,AH7<=20),"16-20 Years",IF(AND(AH7>=21,AH7<=25),"21-25 Years",IF(AND(AH7>=26,AH7<=30),"26-30 Years","More Than 30 Years"))))))) -> 16-20 Years | AK7: PART TIME | AL7: 34.75 | AM7: 50 | AN7: =IF(AM7<20,"Less Than 20 Years",IF(AND(AM7>=20,AM7<=24),"20-24 Years",IF(AND(AM7>=25,AM7<=34),"25-34 Years",IF(AND(AM7>=35,AM7<=44),"35-44 Years",IF(AND(AM7>=45,AM7<=54),"45-54 Years","More Than 55 Years"))))) -> 45-54 Years | AO7: OCT, FY24 | AP7: Q2, FY24 | AQ7: Incident | AT7: Body Stressing | AU7: Other materials and objects | AV7: Harris Scarfe | AW7: VIC | AX7: Store | AY7: Harris Scarfe | AZ7: VIC & NSW | BA7: Harris Scarfe | BB7: Harris Scarfe - VIC & NSW
A8: SRG-INJ-1872 | B8: INC3861 | C8: 12230032770 | D8: No | E8: 297478 | F8: KOKKINOS, ANGELA | G8: 25458 | H8: 45205 | I8: 0.57291667 | J8: Harris Scarfe VIC | K8: 2020 | L8: Forest Hill | M8: Laceration over the dorsum of the right hand/ Laceration ulnar aspect of the right ring finger | N8: Angela was trying to see on high shelf of white wall, she was holding two cups while looking for more she steps backward and didn't notice a step stool in the aisle and fell onto the orange step stool and sideward onto floor. the two loose cups she was holding fell onto the ground and broke on tiles and Angela fell onto the loose broken pieces cutting her right hand on top, and right ring finger. | O8: Claim | P8: Accepted Claim | Q8: Restricted Duties | R8: Open | S8: 64 | T8: FALSE | U8: Lost Time Injury | V8: Laceration or open wound not involving traumatic amputation | W8: Hand, finger and thumb | X8: Falls, Trips and Slips of a Person | Y8: Falls from a height | Z8: Other materials and objects | AB8: Open | AC8: Non Work Related Injury | AD8: #N/A | AE8: Linked | AF8: 44340 | AG8: 45583 | AH8: =DATEDIF(AF8,H8,"Y") -> 2 | AI8: =IF(AG8=0,DATEDIF(AF8,TODAY(),"Y"),DATEDIF(AF8,AG8,"Y")) -> 3 | AJ8: =IF(AH8=0,"Under 1 Year",IF(AND(AH8>=1,AH8<=5),"1-5 Years",IF(AND(AH8>=6,AH8<=10),"6-10 Years",IF(AND(AH8>=11,AH8<=15),"11-15 Years",IF(AND(AH8>=16,AH8<=20),"16-20 Years",IF(AND(AH8>=21,AH8<=25),"21-25 Years",IF(AND(AH8>=26,AH8<=30),"26-30 Years","More Than 30 Years"))))))) -> 1-5 Years | AK8: CASUAL | AL8: 0.01 | AM8: 55 | AN8: =IF(AM8<20,"Less Than 20 Years",IF(AND(AM8>=20,AM8<=24),"20-24 Years",IF(AND(AM8>=25,AM8<=34),"25-34 Years",IF(AND(AM8>=35,AM8<=44),"35-44 Years",IF(AND(AM8>=45,AM8<=54),"45-54 Years","More Than 55 Years"))))) -> More Than 55 Years | AO8: OCT, FY24 | AP8: Q2, FY24 | AQ8: LTIs | AR8: Claim | AS8: Accepted Claim | AT8: Falls, Trips and Slips of a Person | AU8: Other materials and objects | AV8: Harris Scarfe | AW8: VIC | AX8: Store | AY8: Harris Scarfe | AZ8: VIC | BA8: Harris Scarfe | BB8: Harris Scarfe - VIC
A9: SRG-INJ-1908 | B9: INC3975 | D9: No | E9: 297080 | F9: CSIKOS, JAMISON | G9: 37732 | H9: 45212 | I9: 0.34027778 | J9: Harris Scarfe VIC | K9: 2028 | L9: Cranbourne Park | M9: left cheeks | N9: Box was up high and fall onto team members face. | O9: Injury | Q9: No Assessment | R9: Closed | S9: 0 | T9: FALSE | U9: Not Applicable | V9: Residual soft tissue disorders due to trauma or unknown mechanisms | W9: Face, not elsewhere classified | X9: Being Hit By Moving Objects | Y9: Being hit by falling objects | Z9: Other materials and objects | AA9: Boxes | AB9: 0 | AC9: #N/A | AD9: #N/A | AF9: 44118 | AG9: 45729 | AH9: =DATEDIF(AF9,H9,"Y") -> 2 | AI9: =IF(AG9=0,DATEDIF(AF9,TODAY(),"Y"),DATEDIF(AF9,AG9,"Y")) -> 4 | AJ9: =IF(AH9=0,"Under 1 Year",IF(AND(AH9>=1,AH9<=5),"1-5 Years",IF(AND(AH9>=6,AH9<=10),"6-10 Years",IF(AND(AH9>=11,AH9<=15),"11-15 Years",IF(AND(AH9>=16,AH9<=20),"16-20 Years",IF(AND(AH9>=21,AH9<=25),"21-25 Years",IF(AND(AH9>=26,AH9<=30),"26-30 Years","More Than 30 Years"))))))) -> 1-5 Years | AK9: PART TIME | AL9: 36 | AM9: 22 | AN9: =IF(AM9<20,"Less Than 20 Years",IF(AND(AM9>=20,AM9<=24),"20-24 Years",IF(AND(AM9>=25,AM9<=34),"25-34 Years",IF(AND(AM9>=35,AM9<=44),"35-44 Years",IF(AND(AM9>=45,AM9<=54),"45-54 Years","More Than 55 Years"))))) -> 20-24 Years | AO9: OCT, FY24 | AP9: Q2, FY24 | AQ9: Incident | AT9: Being Hit By Moving Objects | AU9: Other materials and objects | AV9: Harris Scarfe | AW9: VIC | AX9: Store | AY9: Harris Scarfe | AZ9: VIC | BA9: Harris Scarfe | BB9: Harris Scarfe - VIC
A10: SRG-INJ-1907 | B10: INC3972 | C10: S23RG061184 | D10: No | E10: 324107 | F10: SANDHU, KULDEEP KAUR | G10: 29964 | H10: 45212 | I10: 0.6875 | J10: Harris Scarfe QLD | K10: 9095 | L10: Chermside | M10: Pain in right hand localised to the thumb and fingers | N10: We have had an excess of beach towels come in to our Store which all needed to be folded as per the VM merchandising guidelines. Kuldeep's right hand has localised pain around the right thumb and finger area. | O10: Claim | P10: Accepted Claim | Q10: Fit | R10: Closed | S10: 11 | T10: FALSE | U10: Lost Time Injury | V10: Residual soft tissue disorders due to trauma or unknown mechanisms | W10: Hand, finger and thumb | X10: Body Stressing | Y10: Muscular stress while handling objects other than lifting, carrying or putting down | Z10: Human agencies | AB10: Closed | AC10: #N/A | AD10: #N/A | AF10: 44788 | AH10: =DATEDIF(AF10,H10,"Y") -> 1 | AI10: =IF(AG10=0,DATEDIF(AF10,TODAY(),"Y"),DATEDIF(AF10,AG10,"Y")) -> 4 | AJ10: =IF(AH10=0,"Under 1 Year",IF(AND(AH10>=1,AH10<=5),"1-5 Years",IF(AND(AH10>=6,AH10<=10),"6-10 Years",IF(AND(AH10>=11,AH10<=15),"11-15 Years",IF(AND(AH10>=16,AH10<=20),"16-20 Years",IF(AND(AH10>=21,AH10<=25),"21-25 Years",IF(AND(AH10>=26,AH10<=30),"26-30 Years","More Than 30 Years"))))))) -> 1-5 Years | AK10: PART TIME | AL10: 34.5 | AM10: 43 | AN10: =IF(AM10<20,"Less Than 20 Years",IF(AND(AM10>=20,AM10<=24),"20-24 Years",IF(AND(AM10>=25,AM10<=34),"25-34 Years",IF(AND(AM10>=35,AM10<=44),"35-44 Years",IF(AND(AM10>=45,AM10<=54),"45-54 Years","More Than 55 Years"))))) -> 35-44 Years | AO10: OCT, FY24 | AP10: Q2, FY24 | AQ10: LTIs | AR10: Claim | AS10: Accepted Claim | AT10: Body Stressing | AU10: Human agencies | AV10: Harris Scarfe | AW10: QLD | AX10: Store | AY10: Harris Scarfe | AZ10: QLD | BA10: Harris Scarfe | BB10: Harris Scarfe - QLD
A11: SRG-INJ-1899 | B11: INC3950 | D11: No | E11: 325800 | F11: THOMAS, LAUREN | G11: 38750 | H11: 45213 | I11: 0.59722222 | J11: Harris Scarfe SA | K11: 1005 | L11: Elizabeth | M11: Right eye stining | N11: Lauren was using hand sanitizer when the dispenser sprayed out into her eye. She rinsed her eye with water several times until it felt better. The sanitiser was placed away with a do not use sign on it | O11: Injury | Q11: No Assessment | R11: Closed | S11: 0 | T11: FALSE | U11: Not Applicable | V11: Foreign body on external eye, in ear or nose or in respiratory, digestive or reproductive tract | W11: Eye | X11: Chemicals and Other Substances | Y11: Single contact with chemical or substance | Z11: Other substances | AB11: 0 | AC11: #N/A | AD11: #N/A | AF11: 44858 | AH11: =DATEDIF(AF11,H11,"Y") -> 0 | AI11: =IF(AG11=0,DATEDIF(AF11,TODAY(),"Y"),DATEDIF(AF11,AG11,"Y")) -> 3 | AJ11: =IF(AH11=0,"Under 1 Year",IF(AND(AH11>=1,AH11<=5),"1-5 Years",IF(AND(AH11>=6,AH11<=10),"6-10 Years",IF(AND(AH11>=11,AH11<=15),"11-15 Years",IF(AND(AH11>=16,AH11<=20),"16-20 Years",IF(AND(AH11>=21,AH11<=25),"21-25 Years",IF(AND(AH11>=26,AH11<=30),"26-30 Years","More Than 30 Years"))))))) -> Under 1 Year | AK11: CASUAL | AL11: 0.01 | AM11: 19 | AN11: =IF(AM11<20,"Less Than 20 Years",IF(AND(AM11>=20,AM11<=24),"20-24 Years",IF(AND(AM11>=25,AM11<=34),"25-34 Years",IF(AND(AM11>=35,AM11<=44),"35-44 Years",IF(AND(AM11>=45,AM11<=54),"45-54 Years","More Than 55 Years"))))) -> Less Than 20 Years | AO11: OCT, FY24 | AP11: Q2, FY24 | AQ11: Incident | AT11: Chemicals and Other Substances | AU11: Other substances | AV11: Harris Scarfe | AW11: SA | AX11: Store | AY11: Harris Scarfe | AZ11: SA/TAS | BA11: Harris Scarfe | BB11: Harris Scarfe - SA/TAS
A12: SRG-INJ-1901 | B12: INC3960 | C12: S23AH062694 | D12: No | E12: 295133 | F12: DANILEUSKI, THOMAS | G12: 33215 | H12: 45214 | I12: 0.72569444 | J12: Harris Scarfe QLD | K12: 9095 | L12: Chermside | M12: Thomas hit the front of his face on the ground breaking his glasses and cutting his eyebrow and grazing his cheek. | N12: Thomas and myself were saying goodbye to each other when his right knee gave way and causing him to fall and hit his head face on breaking his glasses and cutting his eyebrow. he hit his right elbow as he came down as well. | O12: Claim | P12: Accepted Claim | Q12: Fit | R12: Closed | S12: 29 | T12: FALSE | U12: Lost Time Injury | V12: Residual soft tissue disorders due to trauma or unknown mechanisms | W12: Face, not elsewhere classified | X12: Falls, Trips and Slips of a Person | Y12: Falls from a height | Z12: Human agencies | AB12: Closed | AC12: Non Work Related Injury | AD12: #N/A | AF12: 42702 | AG12: 45592 | AH12: =DATEDIF(AF12,H12,"Y") -> 6 | AI12: =IF(AG12=0,DATEDIF(AF12,TODAY(),"Y"),DATEDIF(AF12,AG12,"Y")) -> 7 | AJ12: =IF(AH12=0,"Under 1 Year",IF(AND(AH12>=1,AH12<=5),"1-5 Years",IF(AND(AH12>=6,AH12<=10),"6-10 Years",IF(AND(AH12>=11,AH12<=15),"11-15 Years",IF(AND(AH12>=16,AH12<=20),"16-20 Years",IF(AND(AH12>=21,AH12<=25),"21-25 Years",IF(AND(AH12>=26,AH12<=30),"26-30 Years","More Than 30 Years"))))))) -> 6-10 Years | AK12: PART TIME | AL12: 35.25 | AM12: 34 | AN12: =IF(AM12<20,"Less Than 20 Years",IF(AND(AM12>=20,AM12<=24),"20-24 Years",IF(AND(AM12>=25,AM12<=34),"25-34 Years",IF(AND(AM12>=35,AM12<=44),"35-44 Years",IF(AND(AM12>=45,AM12<=54),"45-54 Years","More Than 55 Years"))))) -> 25-34 Years | AO12: OCT, FY24 | AP12: Q2, FY24 | AQ12: LTIs | AR12: Claim | AS12: Accepted Claim | AT12: Falls, Trips and Slips of a Person | AU12: Human agencies | AV12: Harris Scarfe | AW12: QLD | AX12: Store | AY12: Harris Scarfe | AZ12: QLD | BA12: Harris Scarfe | BB12: Harris Scarfe - QLD
A13: SRG-INJ-1917 | B13: INC3994 | D13: No | E13: 283771 | F13: HENDY, KATE | G13: 30526 | H13: 45217 | I13: 0.53819444 | J13: Harris Scarfe SA | K13: 1011 | L13: Marion | M13: Left shoulder | N13: Kate reported that she was experiencing some pain in her left shoulder as she was unpacking US Polo shirts out of their individual packets whilst at the registers. | O13: Injury | Q13: No Assessment | R13: Closed | S13: 0 | T13: FALSE | U13: Not Applicable | V13: Residual soft tissue disorders due to trauma or unknown mechanisms | W13: Shoulder | X13: Body Stressing | Y13: Muscular stress while lifting, carrying, or putting down objects | Z13: Other materials and objects | AB13: 0 | AC13: #N/A | AD13: #N/A | AF13: 36374 | AH13: =DATEDIF(AF13,H13,"Y") -> 24 | AI13: =IF(AG13=0,DATEDIF(AF13,TODAY(),"Y"),DATEDIF(AF13,AG13,"Y")) -> 27 | AJ13: =IF(AH13=0,"Under 1 Year",IF(AND(AH13>=1,AH13<=5),"1-5 Years",IF(AND(AH13>=6,AH13<=10),"6-10 Years",IF(AND(AH13>=11,AH13<=15),"11-15 Years",IF(AND(AH13>=16,AH13<=20),"16-20 Years",IF(AND(AH13>=21,AH13<=25),"21-25 Years",IF(AND(AH13>=26,AH13<=30),"26-30 Years","More Than 30 Years"))))))) -> 21-25 Years | AK13: PART TIME | AL13: 20.63 | AM13: 41 | AN13: =IF(AM13<20,"Less Than 20 Years",IF(AND(AM13>=20,AM13<=24),"20-24 Years",IF(AND(AM13>=25,AM13<=34),"25-34 Years",IF(AND(AM13>=35,AM13<=44),"35-44 Years",IF(AND(AM13>=45,AM13<=54),"45-54 Years","More Than 55 Years"))))) -> 35-44 Years | AO13: OCT, FY24 | AP13: Q2, FY24 | AQ13: Incident | AT13: Body Stressing | AU13: Other materials and objects | AV13: Harris Scarfe | AW13: SA | AX13: Store | AY13: Harris Scarfe | AZ13: SA/TAS | BA13: Harris Scarfe | BB13: Harris Scarfe - SA/TAS
A14: SRG-INJ-1930 | B14: INC4043 | D14: No | E14: 324204 | F14: DOWSETT, TAMERA | G14: 28895 | H14: 45221 | I14: 0.55069444 | J14: Harris Scarfe NSW | K14: 6071 | L14: Tweed Heads | M14: foot | N14: Tam was in napery and a shelf feel on her foot. | O14: Injury | Q14: No Assessment | R14: Closed | S14: 0 | T14: FALSE | U14: Not Applicable | V14: Residual soft tissue disorders due to trauma or unknown mechanisms | W14: Foot and toes | X14: Being Hit By Moving Objects | Y14: Being hit by falling objects | Z14: Other materials and objects | AB14: 0 | AC14: #N/A | AD14: #N/A | AF14: 44809 | AH14: =DATEDIF(AF14,H14,"Y") -> 1 | AI14: =IF(AG14=0,DATEDIF(AF14,TODAY(),"Y"),DATEDIF(AF14,AG14,"Y")) -> 4 | AJ14: =IF(AH14=0,"Under 1 Year",IF(AND(AH14>=1,AH14<=5),"1-5 Years",IF(AND(AH14>=6,AH14<=10),"6-10 Years",IF(AND(AH14>=11,AH14<=15),"11-15 Years",IF(AND(AH14>=16,AH14<=20),"16-20 Years",IF(AND(AH14>=21,AH14<=25),"21-25 Years",IF(AND(AH14>=26,AH14<=30),"26-30 Years","More Than 30 Years"))))))) -> 1-5 Years | AK14: SALARIED | AL14: 38 | AM14: 46 | AN14: =IF(AM14<20,"Less Than 20 Years",IF(AND(AM14>=20,AM14<=24),"20-24 Years",IF(AND(AM14>=25,AM14<=34),"25-34 Years",IF(AND(AM14>=35,AM14<=44),"35-44 Years",IF(AND(AM14>=45,AM14<=54),"45-54 Years","More Than 55 Years"))))) -> 45-54 Years | AO14: OCT, FY24 | AP14: Q2, FY24 | AQ14: Incident | AT14: Being Hit By Moving Objects | AU14: Other materials and objects | AV14: Harris Scarfe | AW14: NSW | AX14: Store | AY14: Harris Scarfe | AZ14: QLD | BA14: Harris Scarfe | BB14: Harris Scarfe - QLD
A15: SRG-INJ-2541 | B15: INC6416 | C15: 58519959/00 | D15: No | E15: 291457 | F15: ALLEN, SUSAN | G15: 20926 | H15: 45229 | I15: 0.56527778 | J15: Harris Scarfe SA | K15: 1006 | L15: West Lakes | M15: "was there an incident at work?" and stated, "well, you know, lifting things at work." | N15: Sue cannot define if there was actually an incident that occurred. Her statement was '"well, you know, lifting things at work." Sue did see a doctor and Physio. At the time, Sue took personal leave to see a doctor then a physio. Doctors cert and Work capacity forms were given to Teresa (manager). Often staff just place things on the desk without communicating, and they get missed. | O15: Claim | P15: Accepted Claim (MEO) | Q15: Permanently Restricted | R15: Closed | S15: 0 | T15: FALSE | U15: Medical Treatment Injury | V15: Residual soft tissue disorders due to trauma or unknown mechanisms | W15: Back-Upper and lower | X15: Body Stressing | Y15: Muscular stress with no objects being handled | Z15: Human agencies | AB15: Closed | AC15: #N/A | AD15: #N/A | AF15: 40445 | AH15: =DATEDIF(AF15,H15,"Y") -> 13 | AI15: =IF(AG15=0,DATEDIF(AF15,TODAY(),"Y"),DATEDIF(AF15,AG15,"Y")) -> 15 | AJ15: =IF(AH15=0,"Under 1 Year",IF(AND(AH15>=1,AH15<=5),"1-5 Years",IF(AND(AH15>=6,AH15<=10),"6-10 Years",IF(AND(AH15>=11,AH15<=15),"11-15 Years",IF(AND(AH15>=16,AH15<=20),"16-20 Years",IF(AND(AH15>=21,AH15<=25),"21-25 Years",IF(AND(AH15>=26,AH15<=30),"26-30 Years","More Than 30 Years"))))))) -> 11-15 Years | AK15: PART TIME | AL15: 13.5 | AM15: 68 | AN15: =IF(AM15<20,"Less Than 20 Years",IF(AND(AM15>=20,AM15<=24),"20-24 Years",IF(AND(AM15>=25,AM15<=34),"25-34 Years",IF(AND(AM15>=35,AM15<=44),"35-44 Years",IF(AND(AM15>=45,AM15<=54),"45-54 Years","More Than 55 Years"))))) -> More Than 55 Years | AO15: NOV, FY24 | AP15: Q2, FY24 | AQ15: MTIs | AR15: Claim | AS15: Accepted Claim (MEO) | AT15: Body Stressing | AU15: Human agencies | AV15: Harris Scarfe | AW15: SA | AX15: Store | AY15: Harris Scarfe | AZ15: SA/TAS | BA15: Harris Scarfe | BB15: Harris Scarfe - SA/TAS
A16: SRG-INJ-1963 | B16: INC4177 | D16: No | E16: 331290 | F16: KARYN, FALCO | G16: 29302 | H16: 45230 | I16: 0.5625 | J16: Harris Scarfe QLD | K16: 9098 | L16: Carindale | M16: lower right side of back | N16: lifted dinner set and threw out lower back (reoccurring injury) | O16: Injury | Q16: No Assessment | R16: Closed | S16: 0 | T16: FALSE | U16: Not Applicable | V16: Residual soft tissue disorders due to trauma or unknown mechanisms | W16: Back-Upper and lower | X16: Body Stressing | Y16: Muscular stress while lifting, carrying, or putting down objects | Z16: Human agencies | AB16: 0 | AC16: #N/A | AD16: #N/A | AF16: 45222 | AH16: =DATEDIF(AF16,H16,"Y") -> 0 | AI16: =IF(AG16=0,DATEDIF(AF16,TODAY(),"Y"),DATEDIF(AF16,AG16,"Y")) -> 2 | AJ16: =IF(AH16=0,"Under 1 Year",IF(AND(AH16>=1,AH16<=5),"1-5 Years",IF(AND(AH16>=6,AH16<=10),"6-10 Years",IF(AND(AH16>=11,AH16<=15),"11-15 Years",IF(AND(AH16>=16,AH16<=20),"16-20 Years",IF(AND(AH16>=21,AH16<=25),"21-25 Years",IF(AND(AH16>=26,AH16<=30),"26-30 Years","More Than 30 Years"))))))) -> Under 1 Year | AK16: SALARIED | AL16: 38 | AM16: 45 | AN16: =IF(AM16<20,"Less Than 20 Years",IF(AND(AM16>=20,AM16<=24),"20-24 Years",IF(AND(AM16>=25,AM16<=34),"25-34 Years",IF(AND(AM16>=35,AM16<=44),"35-44 Years",IF(AND(AM16>=45,AM16<=54),"45-54 Years","More Than 55 Years"))))) -> 45-54 Years | AO16: NOV, FY24 | AP16: Q2, FY24 | AQ16: Incident | AT16: Body Stressing | AU16: Human agencies | AV16: Harris Scarfe | AW16: QLD | AX16: Store | AY16: Harris Scarfe | AZ16: QLD | BA16: Harris Scarfe | BB16: Harris Scarfe - QLD
A17: SRG-INJ-1974 | B17: INC4233 | D17: No | E17: 294740 | F17: LAWSON, NIKKITA | G17: 36872 | H17: 45233 | I17: 0.68055556 | J17: Harris Scarfe TAS | K17: 4043 | L17: Launceston | M17: Under Left eye | N17: Checking for stock in the basement where there was fixture left on the floor. Accidentally stepped on it, its the fallen forward and hit me under the left eye leaving a small cut. Small cut cleaned with alcohol wipe and icepack applied. | O17: Injury | Q17: No Assessment | R17: Closed | S17: 0 | T17: FALSE | U17: First Aid Injury | V17: Laceration or open wound not involving traumatic amputation | W17: Eye | X17: Being Hit By Moving Objects | Y17: Being hit by falling objects | Z17: Other materials and objects | AB17: 0 | AC17: #N/A | AD17: #N/A | AF17: 42464 | AH17: =DATEDIF(AF17,H17,"Y") -> 7 | AI17: =IF(AG17=0,DATEDIF(AF17,TODAY(),"Y"),DATEDIF(AF17,AG17,"Y")) -> 10 | AJ17: =IF(AH17=0,"Under 1 Year",IF(AND(AH17>=1,AH17<=5),"1-5 Years",IF(AND(AH17>=6,AH17<=10),"6-10 Years",IF(AND(AH17>=11,AH17<=15),"11-15 Years",IF(AND(AH17>=16,AH17<=20),"16-20 Years",IF(AND(AH17>=21,AH17<=25),"21-25 Years",IF(AND(AH17>=26,AH17<=30),"26-30 Years","More Than 30 Years"))))))) -> 6-10 Years | AK17: PART TIME | AL17: 28 | AM17: 24 | AN17: =IF(AM17<20,"Less Than 20 Years",IF(AND(AM17>=20,AM17<=24),"20-24 Years",IF(AND(AM17>=25,AM17<=34),"25-34 Years",IF(AND(AM17>=35,AM17<=44),"35-44 Years",IF(AND(AM17>=45,AM17<=54),"45-54 Years","More Than 55 Years"))))) -> 20-24 Years | AO17: NOV, FY24 | AP17: Q2, FY24 | AQ17: FAIs | AT17: Being Hit By Moving Objects | AU17: Other materials and objects | AV17: Harris Scarfe | AW17: TAS | AX17: Store | AY17: Harris Scarfe | AZ17: SA/TAS | BA17: Harris Scarfe | BB17: Harris Scarfe - SA/TAS
A18: SRG-INJ-1980 | B18: INC4250 | D18: No | E18: 297591 | F18: MCMULLEN, ALYSE | G18: 35128 | H18: 45235 | I18: 0.52777778 | J18: Harris Scarfe VIC | K18: 2042 | L18: Carnegie (Hs Home) | M18: Cut to lateral knuckle of left index finger | N18: Alyse McMullen (ASM - Carnegie) was working in the Home Deco department near the front of the Carnegie HS Store. She found a diffuser that didn't have a display on show so she took it to the Register area to unbox the product to place it on show. The diffuser had a plug firmly wedged in it's opening which Alyse attempted to remove. She attempted to remove the lid of the diffuser using her Safety Cutter but slipped and cut her left hand (near the lateral knuckle of her index finger). She went to the bathroom to wash the wound and then returned to the store. She went to the office to lay down as she was feeling light-headed with shock. A Team Member (Callan Nicholson) applied a First Aid dressing and too k her to the Medical Centre in Carnegie Central. They were unable to assist, so Callen transported her to her own doctor in Cheltenham. He advised that she had escaped serious damage, but that the wound required 2 stitches and that after a couple of days away from work (which she was rostered to have off) she would need to return on limited duties. She was able to drive herself home. | O18: Injury | Q18: Fit | R18: Closed | S18: 0 | T18: FALSE | U18: Medical Treatment Injury | V18: Laceration or open wound not involving traumatic amputation | W18: Hand, finger and thumb | X18: Hitting Objects With a Part of the Body | Y18: Hitting stationary objects | Z18: Human agencies | AB18: 0 | AC18: #N/A | AD18: #N/A | AF18: 44431 | AH18: =DATEDIF(AF18,H18,"Y") -> 2 | AI18: =IF(AG18=0,DATEDIF(AF18,TODAY(),"Y"),DATEDIF(AF18,AG18,"Y")) -> 5 | AJ18: =IF(AH18=0,"Under 1 Year",IF(AND(AH18>=1,AH18<=5),"1-5 Years",IF(AND(AH18>=6,AH18<=10),"6-10 Years",IF(AND(AH18>=11,AH18<=15),"11-15 Years",IF(AND(AH18>=16,AH18<=20),"16-20 Years",IF(AND(AH18>=21,AH18<=25),"21-25 Years",IF(AND(AH18>=26,AH18<=30),"26-30 Years","More Than 30 Years"))))))) -> 1-5 Years | AK18: SALARIED | AL18: 38 | AM18: 29 | AN18: =IF(AM18<20,"Less Than 20 Years",IF(AND(AM18>=20,AM18<=24),"20-24 Years",IF(AND(AM18>=25,AM18<=34),"25-34 Years",IF(AND(AM18>=35,AM18<=44),"35-44 Years",IF(AND(AM18>=45,AM18<=54),"45-54 Years","More Than 55 Years"))))) -> 25-34 Years | AO18: NOV, FY24 | AP18: Q2, FY24 | AQ18: MTIs | AT18: Hitting Objects With a Part of the Body | AU18: Human agencies | AV18: Harris Scarfe | AW18: VIC | AX18: Store | AY18: Harris Scarfe | AZ18: VIC | BA18: Harris Scarfe | BB18: Harris Scarfe - VIC
A19: SRG-INJ-1983 | B19: INC4270 | D19: No | E19: 406820 | F19: HUNTER, SARAH | G19: 25843 | H19: 45236 | I19: 0.6875 | J19: Harris Scarfe SA | K19: 1011 | L19: Marion | M19: Strain to my right hand at the base of my finger between the middle and ring finger. | N19: When I got home last night I had some soreness in my right hand in between the middle and ring fingers. I had been re merchandising the women's apparel pad and executing markdowns in the area during the day and may have strained the area. I applied heat to the area but am still having some pain today. | O19: Injury | Q19: No Assessment | R19: Closed | S19: 0 | T19: FALSE | U19: First Aid Injury | V19: Residual soft tissue disorders due to trauma or unknown mechanisms | W19: Hand, finger and thumb | X19: Body Stressing | Y19: Muscular stress while lifting, carrying, or putting down objects | Z19: Human agencies | AB19: 0 | AC19: #N/A | AD19: #N/A | AF19: 42142 | AH19: =DATEDIF(AF19,H19,"Y") -> 8 | AI19: =IF(AG19=0,DATEDIF(AF19,TODAY(),"Y"),DATEDIF(AF19,AG19,"Y")) -> 11 | AJ19: =IF(AH19=0,"Under 1 Year",IF(AND(AH19>=1,AH19<=5),"1-5 Years",IF(AND(AH19>=6,AH19<=10),"6-10 Years",IF(AND(AH19>=11,AH19<=15),"11-15 Years",IF(AND(AH19>=16,AH19<=20),"16-20 Years",IF(AND(AH19>=21,AH19<=25),"21-25 Years",IF(AND(AH19>=26,AH19<=30),"26-30 Years","More Than 30 Years"))))))) -> 6-10 Years | AK19: SALARIED | AL19: 38 | AM19: 54 | AN19: =IF(AM19<20,"Less Than 20 Years",IF(AND(AM19>=20,AM19<=24),"20-24 Years",IF(AND(AM19>=25,AM19<=34),"25-34 Years",IF(AND(AM19>=35,AM19<=44),"35-44 Years",IF(AND(AM19>=45,AM19<=54),"45-54 Years","More Than 55 Years"))))) -> 45-54 Years | AO19: NOV, FY24 | AP19: Q2, FY24 | AQ19: FAIs | AT19: Body Stressing | AU19: Human agencies | AV19: Harris Scarfe | AW19: SA | AX19: Store | AY19: Harris Scarfe | AZ19: SA/TAS | BA19: Harris Scarfe | BB19: Harris Scarfe - SA/TAS
A20: SRG-INJ-1993 | B20: INC4296 | D20: No | E20: 295516 | F20: NUTTALL, BELINDA | G20: 25993 | H20: 45240 | I20: 0.6875 | J20: Harris Scarfe VIC | K20: 2021 | L20: Geelong | M20: Left calf muscle popped | N20: I was condensing stock to make room, using a safety step. I stepped on the safety step to reach the top shelf. Finished what I was doing and stepped down off the safety step onto the floor. My calf muscle popped and was too painful to walk on | O20: Injury | Q20: No Assessment | R20: Closed | S20: 0 | T20: FALSE | U20: Medical Treatment Injury | V20: Residual soft tissue disorders due to trauma or unknown mechanisms | W20: Lower leg | X20: Body Stressing | Y20: Muscular stress with no objects being handled | Z20: Human agencies | AB20: 0 | AC20: #N/A | AD20: #N/A | AF20: 42961 | AH20: =DATEDIF(AF20,H20,"Y") -> 6 | AI20: =IF(AG20=0,DATEDIF(AF20,TODAY(),"Y"),DATEDIF(AF20,AG20,"Y")) -> 9 | AJ20: =IF(AH20=0,"Under 1 Year",IF(AND(AH20>=1,AH20<=5),"1-5 Years",IF(AND(AH20>=6,AH20<=10),"6-10 Years",IF(AND(AH20>=11,AH20<=15),"11-15 Years",IF(AND(AH20>=16,AH20<=20),"16-20 Years",IF(AND(AH20>=21,AH20<=25),"21-25 Years",IF(AND(AH20>=26,AH20<=30),"26-30 Years","More Than 30 Years"))))))) -> 6-10 Years | AK20: SALARIED | AL20: 38 | AM20: 54 | AN20: =IF(AM20<20,"Less Than 20 Years",IF(AND(AM20>=20,AM20<=24),"20-24 Years",IF(AND(AM20>=25,AM20<=34),"25-34 Years",IF(AND(AM20>=35,AM20<=44),"35-44 Years",IF(AND(AM20>=45,AM20<=54),"45-54 Years","More Than 55 Years"))))) -> 45-54 Years | AO20: NOV, FY24 | AP20: Q2, FY24 | AQ20: MTIs | AT20: Body Stressing | AU20: Human agencies | AV20: Harris Scarfe | AW20: VIC | AX20: Store | AY20: Harris Scarfe | AZ20: VIC & NSW | BA20: Harris Scarfe | BB20: Harris Scarfe - VIC & NSW
A21: SRG-INJ-1995 | B21: INC4298 | D21: No | E21: 297588 | F21: MAVER, GEORGIE | G21: 37620 | H21: 45241 | I21: 0.58333333 | J21: Harris Scarfe VIC | K21: 2023 | L21: Epping | M21: lower back and wrist is hurting | N21: while carrying an arm full of clothes to move to another rack, Georgie tripped over a safety step stool which she did not see | O21: Injury | Q21: No Assessment | R21: Closed | S21: 0 | T21: FALSE | U21: Not Applicable | V21: Residual soft tissue disorders due to trauma or unknown mechanisms | W21: Upper and lower limbs | X21: Falls, Trips and Slips of a Person | Y21: Falls on the same level | Z21: Other materials and objects | AB21: 0 | AC21: #N/A | AD21: #N/A | AF21: 44435 | AH21: =DATEDIF(AF21,H21,"Y") -> 2 | AI21: =IF(AG21=0,DATEDIF(AF21,TODAY(),"Y"),DATEDIF(AF21,AG21,"Y")) -> 5 | AJ21: =IF(AH21=0,"Under 1 Year",IF(AND(AH21>=1,AH21<=5),"1-5 Years",IF(AND(AH21>=6,AH21<=10),"6-10 Years",IF(AND(AH21>=11,AH21<=15),"11-15 Years",IF(AND(AH21>=16,AH21<=20),"16-20 Years",IF(AND(AH21>=21,AH21<=25),"21-25 Years",IF(AND(AH21>=26,AH21<=30),"26-30 Years","More Than 30 Years"))))))) -> 1-5 Years | AK21: SALARIED | AL21: 38 | AM21: 22 | AN21: =IF(AM21<20,"Less Than 20 Years",IF(AND(AM21>=20,AM21<=24),"20-24 Years",IF(AND(AM21>=25,AM21<=34),"25-34 Years",IF(AND(AM21>=35,AM21<=44),"35-44 Years",IF(AND(AM21>=45,AM21<=54),"45-54 Years","More Than 55 Years"))))) -> 20-24 Years | AO21: NOV, FY24 | AP21: Q2, FY24 | AQ21: Incident | AT21: Falls, Trips and Slips of a Person | AU21: Other materials and objects | AV21: Harris Scarfe | AW21: VIC | AX21: Store | AY21: Harris Scarfe | AZ21: VIC & NSW | BA21: Harris Scarfe | BB21: Harris Scarfe - VIC & NSW
A22: SRG-INJ-1998 | B22: INC4319 | D22: No | E22: 407120 | F22: ZIGOURAS, LOREDANA | G22: 23357 | H22: 45241 | I22: 0.70486111 | J22: Harris Scarfe VIC | K22: 2025 | L22: Southland | M22: Soreness, brusing and tender left knee | N22: Wheeling out rails of Apparel clearance from our P2 space as I came around the corner the rail tipped completely over and I went over are the top of it, causing my left knee to be hurt and bruising on the inside of my right and left knees. | O22: Injury | Q22: No Assessment | R22: Closed | S22: 0 | T22: FALSE | U22: Not Applicable | V22: Residual soft tissue disorders due to trauma or unknown mechanisms | W22: Knee | X22: Falls, Trips and Slips of a Person | Y22: Falls on the same level | Z22: Other materials and objects | AB22: 0 | AC22: Non Work Related Injury | AD22: #N/A | AF22: 44032 | AH22: =DATEDIF(AF22,H22,"Y") -> 3 | AI22: =IF(AG22=0,DATEDIF(AF22,TODAY(),"Y"),DATEDIF(AF22,AG22,"Y")) -> 6 | AJ22: =IF(AH22=0,"Under 1 Year",IF(AND(AH22>=1,AH22<=5),"1-5 Years",IF(AND(AH22>=6,AH22<=10),"6-10 Years",IF(AND(AH22>=11,AH22<=15),"11-15 Years",IF(AND(AH22>=16,AH22<=20),"16-20 Years",IF(AND(AH22>=21,AH22<=25),"21-25 Years",IF(AND(AH22>=26,AH22<=30),"26-30 Years","More Than 30 Years"))))))) -> 1-5 Years | AK22: CASUAL | AL22: 0.01 | AM22: 61 | AN22: =IF(AM22<20,"Less Than 20 Years",IF(AND(AM22>=20,AM22<=24),"20-24 Years",IF(AND(AM22>=25,AM22<=34),"25-34 Years",IF(AND(AM22>=35,AM22<=44),"35-44 Years",IF(AND(AM22>=45,AM22<=54),"45-54 Years","More Than 55 Years"))))) -> More Than 55 Years | AO22: NOV, FY24 | AP22: Q2, FY24 | AQ22: Incident | AT22: Falls, Trips and Slips of a Person | AU22: Other materials and objects | AV22: Harris Scarfe | AW22: VIC | AX22: Store | AY22: Harris Scarfe | AZ22: VIC | BA22: Harris Scarfe | BB22: Harris Scarfe - VIC
A23: SRG-INJ-1994 | B23: INC4297 | D23: No | E23: 325769 | F23: ARNOLD, MAKENZIE | G23: 38933 | H23: 45241 | I23: 0.54861111 | J23: Harris Scarfe TAS | K23: 4045 | L23: Ulverstone | M23: Aggressive Customer | N23: Aggressive customer | O23: Injury | Q23: No Assessment | R23: Closed | S23: 0 | T23: FALSE | U23: Not Applicable | V23: Other mental diseases, not elsewhere classified | W23: Head - unspecified locations | X23: Mental Stress | Y23: Exposure to a traumatic event | Z23: Human agencies | AB23: 0 | AC23: #N/A | AD23: #N/A | AF23: 44858 | AH23: =DATEDIF(AF23,H23,"Y") -> 1 | AI23: =IF(AG23=0,DATEDIF(AF23,TODAY(),"Y"),DATEDIF(AF23,AG23,"Y")) -> 3 | AJ23: =IF(AH23=0,"Under 1 Year",IF(AND(AH23>=1,AH23<=5),"1-5 Years",IF(AND(AH23>=6,AH23<=10),"6-10 Years",IF(AND(AH23>=11,AH23<=15),"11-15 Years",IF(AND(AH23>=16,AH23<=20),"16-20 Years",IF(AND(AH23>=21,AH23<=25),"21-25 Years",IF(AND(AH23>=26,AH23<=30),"26-30 Years","More Than 30 Years"))))))) -> 1-5 Years | AK23: CASUAL | AL23: 0.01 | AM23: 18 | AN23: =IF(AM23<20,"Less Than 20 Years",IF(AND(AM23>=20,AM23<=24),"20-24 Years",IF(AND(AM23>=25,AM23<=34),"25-34 Years",IF(AND(AM23>=35,AM23<=44),"35-44 Years",IF(AND(AM23>=45,AM23<=54),"45-54 Years","More Than 55 Years"))))) -> Less Than 20 Years | AO23: NOV, FY24 | AP23: Q2, FY24 | AQ23: Incident | AT23: Mental Stress | AU23: Human agencies | AV23: Harris Scarfe | AW23: TAS | AX23: Store | AY23: Harris Scarfe | AZ23: SA/TAS | BA23: Harris Scarfe | BB23: Harris Scarfe - SA/TAS
A24: SRG-INJ-1999 | B24: INC4320 | D24: No | E24: 323716 | F24: BYNION, FAY | G24: 33608 | H24: 45243 | I24: 0.69444444 | J24: Harris Scarfe VIC | K24: 2025 | L24: Southland | M24: Soreness, brusing and tender left foot | N24: Fay was working and filling stock when the lid fell out of a box and landed directly on the top foot bone, causing pain and soreness | O24: Injury | Q24: No Assessment | R24: Closed | S24: 0 | T24: FALSE | U24: Not Applicable | V24: Residual soft tissue disorders due to trauma or unknown mechanisms | W24: Foot and toes | X24: Being Hit By Moving Objects | Y24: Being hit by falling objects | Z24: Other materials and objects | AB24: 0 | AC24: Non Work Related Injury | AD24: #N/A | AF24: 44767 | AH24: =DATEDIF(AF24,H24,"Y") -> 1 | AI24: =IF(AG24=0,DATEDIF(AF24,TODAY(),"Y"),DATEDIF(AF24,AG24,"Y")) -> 4 | AJ24: =IF(AH24=0,"Under 1 Year",IF(AND(AH24>=1,AH24<=5),"1-5 Years",IF(AND(AH24>=6,AH24<=10),"6-10 Years",IF(AND(AH24>=11,AH24<=15),"11-15 Years",IF(AND(AH24>=16,AH24<=20),"16-20 Years",IF(AND(AH24>=21,AH24<=25),"21-25 Years",IF(AND(AH24>=26,AH24<=30),"26-30 Years","More Than 30 Years"))))))) -> 1-5 Years | AK24: SALARIED | AL24: 38 | AM24: 33 | AN24: =IF(AM24<20,"Less Than 20 Years",IF(AND(AM24>=20,AM24<=24),"20-24 Years",IF(AND(AM24>=25,AM24<=34),"25-34 Years",IF(AND(AM24>=35,AM24<=44),"35-44 Years",IF(AND(AM24>=45,AM24<=54),"45-54 Years","More Than 55 Years"))))) -> 25-34 Years | AO24: NOV, FY24 | AP24: Q2, FY24 | AQ24: Incident | AT24: Being Hit By Moving Objects | AU24: Other materials and objects | AV24: Harris Scarfe | AW24: VIC | AX24: Store | AY24: Harris Scarfe | AZ24: VIC | BA24: Harris Scarfe | BB24: Harris Scarfe - VIC
A25: SRG-INJ-3486 | B25: INC12058 | C25: 12240077534 | D25: Yes | E25: 329940 | F25: ADDAMS, SAMANTHA | G25: 31789 | H25: 45244 | I25: 0.5 | J25: Harris Scarfe VIC | K25: 2019 | L25: Ballarat | M25: Psychosocial injury | N25: Experiencing ongoing bullying and harassment at her workplace, particularly from her Store Manager. Team Member details several incidents where they felt mistreated and singled out by SM over a period of time, especially since returning to work after a medical procedure. | O25: Claim | P25: Pending Claim | Q25: Unfit | R25: Open | S25: 40 | T25: FALSE | U25: Medical Treatment Injury | V25: Reaction to stressors - other, multiple or not specified | W25: Psychological system | X25: Mental Stress | Y25: Work related harassment and/or workplace bullying | Z25: Human agencies | AB25: Open | AC25: #N/A | AD25: Psychosocial | AF25: 45131 | AG25: 45746 | AH25: =DATEDIF(AF25,H25,"Y") -> 0 | AI25: =IF(AG25=0,DATEDIF(AF25,TODAY(),"Y"),DATEDIF(AF25,AG25,"Y")) -> 1 | AJ25: =IF(AH25=0,"Under 1 Year",IF(AND(AH25>=1,AH25<=5),"1-5 Years",IF(AND(AH25>=6,AH25<=10),"6-10 Years",IF(AND(AH25>=11,AH25<=15),"11-15 Years",IF(AND(AH25>=16,AH25<=20),"16-20 Years",IF(AND(AH25>=21,AH25<=25),"21-25 Years",IF(AND(AH25>=26,AH25<=30),"26-30 Years","More Than 30 Years"))))))) -> Under 1 Year | AK25: PART TIME | AL25: 22.5 | AM25: 38 | AN25: =IF(AM25<20,"Less Than 20 Years",IF(AND(AM25>=20,AM25<=24),"20-24 Years",IF(AND(AM25>=25,AM25<=34),"25-34 Years",IF(AND(AM25>=35,AM25<=44),"35-44 Years",IF(AND(AM25>=45,AM25<=54),"45-54 Years","More Than 55 Years"))))) -> 35-44 Years | AO25: NOV, FY24 | AP25: Q2, FY24 | AQ25: MTIs | AR25: Claim | AS25: Pending Claim | AT25: Mental Stress | AU25: Human agencies | AV25: Harris Scarfe | AW25: VIC | AX25: Store | AY25: Harris Scarfe | AZ25: VIC & NSW | BA25: Harris Scarfe | BB25: Harris Scarfe - VIC & NSW
A26: SRG-INJ-2010 | B26: INC4368 | D26: No | E26: 326552 | F26: GANGI, ALESSIA | G26: 38131 | H26: 45246 | I26: 0.81944444 | J26: Harris Scarfe VIC | K26: 2024 | L26: Highpoint | M26: Both legs | N26: Thursday 16th of Nov @7:40pm Alessia tripped over mannequin stand near fitting rooms, fellinto it hurtinh both legs. She felt a bit sore after mannequin was moved to centre of stand to make it more obvious. No camera in the area. | O26: Injury | Q26: No Assessment | R26: Closed | S26: 0 | T26: FALSE | U26: Not Applicable | AB26: 0 | AC26: #N/A | AD26: #N/A | AF26: 44886 | AH26: =DATEDIF(AF26,H26,"Y") -> 0 | AI26: =IF(AG26=0,DATEDIF(AF26,TODAY(),"Y"),DATEDIF(AF26,AG26,"Y")) -> 3 | AJ26: =IF(AH26=0,"Under 1 Year",IF(AND(AH26>=1,AH26<=5),"1-5 Years",IF(AND(AH26>=6,AH26<=10),"6-10 Years",IF(AND(AH26>=11,AH26<=15),"11-15 Years",IF(AND(AH26>=16,AH26<=20),"16-20 Years",IF(AND(AH26>=21,AH26<=25),"21-25 Years",IF(AND(AH26>=26,AH26<=30),"26-30 Years","More Than 30 Years"))))))) -> Under 1 Year | AK26: CASUAL | AL26: 0.01 | AM26: 20 | AN26: =IF(AM26<20,"Less Than 20 Years",IF(AND(AM26>=20,AM26<=24),"20-24 Years",IF(AND(AM26>=25,AM26<=34),"25-34 Years",IF(AND(AM26>=35,AM26<=44),"35-44 Years",IF(AND(AM26>=45,AM26<=54),"45-54 Years","More Than 55 Years"))))) -> 20-24 Years | AO26: NOV, FY24 | AP26: Q2, FY24 | AQ26: Incident | AT26: 0 | AU26: 0 | AV26: Harris Scarfe | AW26: VIC | AX26: Store | AY26: Harris Scarfe | AZ26: VIC & NSW | BA26: Harris Scarfe | BB26: Harris Scarfe - VIC & NSW
A27: SRG-INJ-2034 | B27: INC4436 | D27: No | E27: 293338 | F27: SMITH, KIEREN | G27: 34250 | H27: 45247 | I27: 0.625 | J27: Harris Scarfe SA | K27: 1011 | L27: Marion | M27: Laceration on right hand near pinky to mid way through palm. | N27: While taking out the plastics Kieren cut his right hand on a sharp bit of plastic shelving that has broken off. | O27: Injury | Q27: No Assessment | R27: Closed | S27: 0 | T27: FALSE | U27: First Aid Injury | V27: Laceration or open wound not involving traumatic amputation | W27: Hand, finger and thumb | X27: Hitting Objects With a Part of the Body | Y27: Hitting stationary objects | Z27: Human agencies | AB27: 0 | AC27: #N/A | AD27: #N/A | AF27: 41470 | AG27: 45443 | AH27: =DATEDIF(AF27,H27,"Y") -> 10 | AI27: =IF(AG27=0,DATEDIF(AF27,TODAY(),"Y"),DATEDIF(AF27,AG27,"Y")) -> 10 | AJ27: =IF(AH27=0,"Under 1 Year",IF(AND(AH27>=1,AH27<=5),"1-5 Years",IF(AND(AH27>=6,AH27<=10),"6-10 Years",IF(AND(AH27>=11,AH27<=15),"11-15 Years",IF(AND(AH27>=16,AH27<=20),"16-20 Years",IF(AND(AH27>=21,AH27<=25),"21-25 Years",IF(AND(AH27>=26,AH27<=30),"26-30 Years","More Than 30 Years"))))))) -> 6-10 Years | AK27: PART TIME | AL27: 30 | AM27: 31 | AN27: =IF(AM27<20,"Less Than 20 Years",IF(AND(AM27>=20,AM27<=24),"20-24 Years",IF(AND(AM27>=25,AM27<=34),"25-34 Years",IF(AND(AM27>=35,AM27<=44),"35-44 Years",IF(AND(AM27>=45,AM27<=54),"45-54 Years","More Than 55 Years"))))) -> 25-34 Years | AO27: NOV, FY24 | AP27: Q2, FY24 | AQ27: FAIs | AT27: Hitting Objects With a Part of the Body | AU27: Human agencies | AV27: Harris Scarfe | AW27: SA | AX27: Store | AY27: Harris Scarfe | AZ27: SA/TAS | BA27: Harris Scarfe | BB27: Harris Scarfe - SA/TAS
A28: SRG-INJ-2011 | B28: INC4369 | D28: No | E28: 328036 | F28: MEAD, SUSANNE | G28: 25871 | H28: 45247 | I28: 0.57638889 | J28: Harris Scarfe VIC | K28: 2029 | L28: Waurn Ponds (Hs Home) | M28: grazed arm armd grazed wrist | N28: fall from small ladder in back store room while retrieving stock for customer. | O28: Injury | Q28: No Assessment | R28: Closed | S28: 0 | T28: FALSE | U28: First Aid Injury | V28: Laceration or open wound not involving traumatic amputation | W28: Wrist | X28: Falls, Trips and Slips of a Person | Y28: Falls on the same level | Z28: Human agencies | AB28: 0 | AC28: #N/A | AD28: #N/A | AF28: 44977 | AH28: =DATEDIF(AF28,H28,"Y") -> 0 | AI28: =IF(AG28=0,DATEDIF(AF28,TODAY(),"Y"),DATEDIF(AF28,AG28,"Y")) -> 3 | AJ28: =IF(AH28=0,"Under 1 Year",IF(AND(AH28>=1,AH28<=5),"1-5 Years",IF(AND(AH28>=6,AH28<=10),"6-10 Years",IF(AND(AH28>=11,AH28<=15),"11-15 Years",IF(AND(AH28>=16,AH28<=20),"16-20 Years",IF(AND(AH28>=21,AH28<=25),"21-25 Years",IF(AND(AH28>=26,AH28<=30),"26-30 Years","More Than 30 Years"))))))) -> Under 1 Year | AK28: PART TIME | AL28: 14.25 | AM28: 54 | AN28: =IF(AM28<20,"Less Than 20 Years",IF(AND(AM28>=20,AM28<=24),"20-24 Years",IF(AND(AM28>=25,AM28<=34),"25-34 Years",IF(AND(AM28>=35,AM28<=44),"35-44 Years",IF(AND(AM28>=45,AM28<=54),"45-54 Years","More Than 55 Years"))))) -> 45-54 Years | AO28: NOV, FY24 | AP28: Q2, FY24 | AQ28: FAIs | AT28: Falls, Trips and Slips of a Person | AU28: Human agencies | AV28: Harris Scarfe | AW28: VIC | AX28: Store | AY28: Harris Scarfe | AZ28: VIC & NSW | BA28: Harris Scarfe | BB28: Harris Scarfe - VIC & NSW
A29: SRG-INJ-2015 | B29: INC4378 | D29: No | E29: 331399 | F29: MORRISS, ASHLEY | G29: 38268 | H29: 45248 | I29: 0.48194444 | J29: Harris Scarfe NSW | K29: 6068 | L29: Wagga Wagga | M29: LEFT FOOT - STEPPED ON SECURITY PIN | N29: Ashley stepped on pin that goes into a hammer tag. Went through the sole of shoe into her foot | O29: Injury | Q29: No Assessment | R29: Closed | S29: 0 | T29: FALSE | U29: First Aid Injury | V29: Laceration or open wound not involving traumatic amputation | W29: Foot and toes | X29: Hitting Objects With a Part of the Body | Y29: Hitting stationary objects | Z29: Human agencies | AB29: 0 | AC29: #N/A | AD29: Psychosocial | AF29: 45208 | AH29: =DATEDIF(AF29,H29,"Y") -> 0 | AI29: =IF(AG29=0,DATEDIF(AF29,TODAY(),"Y"),DATEDIF(AF29,AG29,"Y")) -> 2 | AJ29: =IF(AH29=0,"Under 1 Year",IF(AND(AH29>=1,AH29<=5),"1-5 Years",IF(AND(AH29>=6,AH29<=10),"6-10 Years",IF(AND(AH29>=11,AH29<=15),"11-15 Years",IF(AND(AH29>=16,AH29<=20),"16-20 Years",IF(AND(AH29>=21,AH29<=25),"21-25 Years",IF(AND(AH29>=26,AH29<=30),"26-30 Years","More Than 30 Years"))))))) -> Under 1 Year | AK29: CASUAL | AL29: 0.01 | AM29: 20 | AN29: =IF(AM29<20,"Less Than 20 Years",IF(AND(AM29>=20,AM29<=24),"20-24 Years",IF(AND(AM29>=25,AM29<=34),"25-34 Years",IF(AND(AM29>=35,AM29<=44),"35-44 Years",IF(AND(AM29>=45,AM29<=54),"45-54 Years","More Than 55 Years"))))) -> 20-24 Years | AO29: NOV, FY24 | AP29: Q2, FY24 | AQ29: FAIs | AT29: Hitting Objects With a Part of the Body | AU29: Human agencies | AV29: Harris Scarfe | AW29: NSW | AX29: Store | AY29: Harris Scarfe | AZ29: NSW/ACT | BA29: Harris Scarfe | BB29: Harris Scarfe - NSW/ACT
A30: SRG-INJ-2021 | B30: INC4401 | D30: No | E30: 318178 | F30: DE GENNARO, MADELINE | G30: 37575 | H30: 45251 | I30: 0.40277778 | J30: Harris Scarfe SA | K30: 1011 | L30: Marion | M30: Laceration between index and middle knuckle | N30: Madeline noticed a cut on her hand between her index and middle knuckles on her right hand. When I asked Madeline how she injured herself she was unsure and could not recall how it occurred. | O30: Injury | Q30: No Assessment | R30: Closed | S30: 0 | T30: FALSE | U30: First Aid Injury | V30: Laceration or open wound not involving traumatic amputation | W30: Hand, finger and thumb | X30: Body Stressing | Y30: Muscular stress with no objects being handled | Z30: Human agencies | AB30: 0 | AC30: #N/A | AD30: #N/A | AF30: 44501 | AH30: =DATEDIF(AF30,H30,"Y") -> 2 | AI30: =IF(AG30=0,DATEDIF(AF30,TODAY(),"Y"),DATEDIF(AF30,AG30,"Y")) -> 4 | AJ30: =IF(AH30=0,"Under 1 Year",IF(AND(AH30>=1,AH30<=5),"1-5 Years",IF(AND(AH30>=6,AH30<=10),"6-10 Years",IF(AND(AH30>=11,AH30<=15),"11-15 Years",IF(AND(AH30>=16,AH30<=20),"16-20 Years",IF(AND(AH30>=21,AH30<=25),"21-25 Years",IF(AND(AH30>=26,AH30<=30),"26-30 Years","More Than 30 Years"))))))) -> 1-5 Years | AK30: CASUAL | AL30: 0.01 | AM30: 22 | AN30: =IF(AM30<20,"Less Than 20 Years",IF(AND(AM30>=20,AM30<=24),"20-24 Years",IF(AND(AM30>=25,AM30<=34),"25-34 Years",IF(AND(AM30>=35,AM30<=44),"35-44 Years",IF(AND(AM30>=45,AM30<=54),"45-54 Years","More Than 55 Years"))))) -> 20-24 Years | AO30: NOV, FY24 | AP30: Q2, FY24 | AQ30: FAIs | AT30: Body Stressing | AU30: Human agencies | AV30: Harris Scarfe | AW30: SA | AX30: Store | AY30: Harris Scarfe | AZ30: SA/TAS | BA30: Harris Scarfe | BB30: Harris Scarfe - SA/TAS
A31: SRG-INJ-2026 | B31: INC4415 | D31: No | E31: 321428 | F31: MCGURGAN, KAYLA | G31: 33252 | H31: 45251 | I31: 0.50069444 | J31: Harris Scarfe VIC | K31: 2026 | L31: Shepparton | M31: lower back | N31: Kayla was walking towards the linen house wall to put stock on the shelf, the floor has a hole rotting away from old termites. As Kayla stepped forward she lost her balance and braced her other foot down and jolted her back. | O31: Injury | Q31: No Assessment | R31: Closed | S31: 0 | T31: FALSE | U31: Not Applicable | V31: Residual soft tissue disorders due to trauma or unknown mechanisms | W31: Back-Upper and lower | X31: Falls, Trips and Slips of a Person | Y31: Stepping, kneeling or sitting on objects | Z31: Other materials and objects | AB31: 0 | AC31: #N/A | AD31: #N/A | AF31: 44641 | AH31: =DATEDIF(AF31,H31,"Y") -> 1 | AI31: =IF(AG31=0,DATEDIF(AF31,TODAY(),"Y"),DATEDIF(AF31,AG31,"Y")) -> 4 | AJ31: =IF(AH31=0,"Under 1 Year",IF(AND(AH31>=1,AH31<=5),"1-5 Years",IF(AND(AH31>=6,AH31<=10),"6-10 Years",IF(AND(AH31>=11,AH31<=15),"11-15 Years",IF(AND(AH31>=16,AH31<=20),"16-20 Years",IF(AND(AH31>=21,AH31<=25),"21-25 Years",IF(AND(AH31>=26,AH31<=30),"26-30 Years","More Than 30 Years"))))))) -> 1-5 Years | AK31: CASUAL | AL31: 0.01 | AM31: 34 | AN31: =IF(AM31<20,"Less Than 20 Years",IF(AND(AM31>=20,AM31<=24),"20-24 Years",IF(AND(AM31>=25,AM31<=34),"25-34 Years",IF(AND(AM31>=35,AM31<=44),"35-44 Years",IF(AND(AM31>=45,AM31<=54),"45-54 Years","More Than 55 Years"))))) -> 25-34 Years | AO31: NOV, FY24 | AP31: Q2, FY24 | AQ31: Incident | AT31: Falls, Trips and Slips of a Person | AU31: Other materials and objects | AV31: Harris Scarfe | AW31: VIC | AX31: Store | AY31: Harris Scarfe | AZ31: VIC & NSW | BA31: Harris Scarfe | BB31: Harris Scarfe - VIC & NSW
A32: SRG-INJ-2027 | B32: INC4417 | D32: No | E32: 321779 | F32: ADAMS, CHRISTINE | G32: 23166 | H32: 45251 | I32: 0.73055556 | J32: Harris Scarfe VIC | K32: 2029 | L32: Waurn Ponds (Hs Home) | M32: Bottom lip and cut on the inside and bruised on the outside | N32: Team member was returning stock to shelves when team member slipped and knocked lip on shelf bar causing it to bleed and bruise | O32: Injury | Q32: No Assessment | R32: Closed | S32: 0 | T32: FALSE | U32: Not Applicable | V32: Laceration or open wound not involving traumatic amputation | W32: Mouth | X32: Falls, Trips and Slips of a Person | Y32: Falls on the same level | Z32: Human agencies | AB32: 0 | AC32: #N/A | AD32: #N/A | AF32: 44655 | AH32: =DATEDIF(AF32,H32,"Y") -> 1 | AI32: =IF(AG32=0,DATEDIF(AF32,TODAY(),"Y"),DATEDIF(AF32,AG32,"Y")) -> 4 | AJ32: =IF(AH32=0,"Under 1 Year",IF(AND(AH32>=1,AH32<=5),"1-5 Years",IF(AND(AH32>=6,AH32<=10),"6-10 Years",IF(AND(AH32>=11,AH32<=15),"11-15 Years",IF(AND(AH32>=16,AH32<=20),"16-20 Years",IF(AND(AH32>=21,AH32<=25),"21-25 Years",IF(AND(AH32>=26,AH32<=30),"26-30 Years","More Than 30 Years"))))))) -> 1-5 Years | AK32: PART TIME | AL32: 21.25 | AM32: 61 | AN32: =IF(AM32<20,"Less Than 20 Years",IF(AND(AM32>=20,AM32<=24),"20-24 Years",IF(AND(AM32>=25,AM32<=34),"25-34 Years",IF(AND(AM32>=35,AM32<=44),"35-44 Years",IF(AND(AM32>=45,AM32<=54),"45-54 Years","More Than 55 Years"))))) -> More Than 55 Years | AO32: NOV, FY24 | AP32: Q2, FY24 | AQ32: Incident | AT32: Falls, Trips and Slips of a Person | AU32: Human agencies | AV32: Harris Scarfe | AW32: VIC | AX32: Store | AY32: Harris Scarfe | AZ32: VIC & NSW | BA32: Harris Scarfe | BB32: Harris Scarfe - VIC & NSW
A33: SRG-INJ-2051 | B33: INC4479 | D33: No | E33: 296514 | F33: BOURNE, MAREE | G33: 20644 | H33: 45254 | I33: 0.35416667 | J33: Harris Scarfe NSW | K33: 6068 | L33: Wagga Wagga | M33: left side of forehead above eyebrow | N33: Maree was on 3 step ladder putting bulky mattress topper up on the top shelf - lost footing and banged left hand side of forehead. Maree was unfazed by incident and continued putting excess stock in reserve shelf. | O33: Injury | Q33: No Assessment | R33: Closed | S33: 0 | T33: FALSE | U33: Not Applicable | V33: Residual soft tissue disorders due to trauma or unknown mechanisms | W33: Face, not elsewhere classified | X33: Being Hit By Moving Objects | Y33: Being hit by falling objects | Z33: Other materials and objects | AB33: 0 | AC33: #N/A | AD33: Psychosocial | AF33: 43563 | AH33: =DATEDIF(AF33,H33,"Y") -> 4 | AI33: =IF(AG33=0,DATEDIF(AF33,TODAY(),"Y"),DATEDIF(AF33,AG33,"Y")) -> 7 | AJ33: =IF(AH33=0,"Under 1 Year",IF(AND(AH33>=1,AH33<=5),"1-5 Years",IF(AND(AH33>=6,AH33<=10),"6-10 Years",IF(AND(AH33>=11,AH33<=15),"11-15 Years",IF(AND(AH33>=16,AH33<=20),"16-20 Years",IF(AND(AH33>=21,AH33<=25),"21-25 Years",IF(AND(AH33>=26,AH33<=30),"26-30 Years","More Than 30 Years"))))))) -> 1-5 Years | AK33: PART TIME | AL33: 16 | AM33: 68 | AN33: =IF(AM33<20,"Less Than 20 Years",IF(AND(AM33>=20,AM33<=24),"20-24 Years",IF(AND(AM33>=25,AM33<=34),"25-34 Years",IF(AND(AM33>=35,AM33<=44),"35-44 Years",IF(AND(AM33>=45,AM33<=54),"45-54 Years","More Than 55 Years"))))) -> More Than 55 Years | AO33: NOV, FY24 | AP33: Q2, FY24 | AQ33: Incident | AT33: Being Hit By Moving Objects | AU33: Other materials and objects | AV33: Harris Scarfe | AW33: NSW | AX33: Store | AY33: Harris Scarfe | AZ33: NSW/ACT | BA33: Harris Scarfe | BB33: Harris Scarfe - NSW/ACT
A34: SRG-INJ-2046 | B34: INC4472 | D34: No | E34: 296943 | F34: PENFOLD, ALANA | G34: 33653 | H34: 45257 | I34: 0.46875 | J34: Harris Scarfe SA | K34: 1005 | L34: Elizabeth | M34: rh Little finger | N34: Alana was closing a postal cage and the latch sprang back catching her RH baby finger causing laceration and bleeding | O34: Injury | Q34: No Assessment | R34: Closed | S34: 0 | T34: FALSE | U34: First Aid Injury | V34: Laceration or open wound not involving traumatic amputation | W34: Hand, finger and thumb | X34: Hitting Objects With a Part of the Body | Y34: Hitting stationary objects | Z34: Human agencies | AB34: 0 | AC34: #N/A | AD34: #N/A | AF34: 44032 | AH34: =DATEDIF(AF34,H34,"Y") -> 3 | AI34: =IF(AG34=0,DATEDIF(AF34,TODAY(),"Y"),DATEDIF(AF34,AG34,"Y")) -> 6 | AJ34: =IF(AH34=0,"Under 1 Year",IF(AND(AH34>=1,AH34<=5),"1-5 Years",IF(AND(AH34>=6,AH34<=10),"6-10 Years",IF(AND(AH34>=11,AH34<=15),"11-15 Years",IF(AND(AH34>=16,AH34<=20),"16-20 Years",IF(AND(AH34>=21,AH34<=25),"21-25 Years",IF(AND(AH34>=26,AH34<=30),"26-30 Years","More Than 30 Years"))))))) -> 1-5 Years | AK34: CASUAL | AL34: 0.01 | AM34: 33 | AN34: =IF(AM34<20,"Less Than 20 Years",IF(AND(AM34>=20,AM34<=24),"20-24 Years",IF(AND(AM34>=25,AM34<=34),"25-34 Years",IF(AND(AM34>=35,AM34<=44),"35-44 Years",IF(AND(AM34>=45,AM34<=54),"45-54 Years","More Than 55 Years"))))) -> 25-34 Years | AO34: DEC, FY24 | AP34: Q2, FY24 | AQ34: FAIs | AT34: Hitting Objects With a Part of the Body | AU34: Human agencies | AV34: Harris Scarfe | AW34: SA | AX34: Store | AY34: Harris Scarfe | AZ34: SA/TAS | BA34: Harris Scarfe | BB34: Harris Scarfe - SA/TAS
A35: SRG-INJ-2055 | B35: INC4489 | D35: No | E35: 297536 | F35: RUSH, GEORGINA | G35: 25172 | H35: 45258 | I35: 0.61388889 | J35: Harris Scarfe TAS | K35: 4045 | L35: Ulverstone | M35: verbal abuse | N35: A customer came into the store to return a online purchase and only had the confirmation email, so I asked for the itemized one to see what the purchase price was for coffee machine to proceed with return, she couldn't find and was going to go to car for a better look because she didn't have her glasses on, came back into the store and said she hadn't received it and demanded that I ring to see why she hadn't been sent, she showed me her zip pay and I explained I couldn't give out her personal details on the phone and asked nicely if she could ring them, she got louder and demanded that it was my store and said you will ring them, as she was very loud and I was being polite I said excuse me, she proceeded to call me a cunt and grab her item, I replied with sorry but she replied with fucken cunt | O35: Injury | Q35: No Assessment | R35: Closed | S35: 0 | T35: FALSE | U35: Not Applicable | V35: Reaction to stressors - other, multiple or not specified | W35: Head - unspecified locations | X35: Mental Stress | Y35: Other mental stress factors | Z35: Human agencies | AB35: 0 | AC35: Non Work Related Injury | AD35: #N/A | AF35: 44382 | AH35: =DATEDIF(AF35,H35,"Y") -> 2 | AI35: =IF(AG35=0,DATEDIF(AF35,TODAY(),"Y"),DATEDIF(AF35,AG35,"Y")) -> 5 | AJ35: =IF(AH35=0,"Under 1 Year",IF(AND(AH35>=1,AH35<=5),"1-5 Years",IF(AND(AH35>=6,AH35<=10),"6-10 Years",IF(AND(AH35>=11,AH35<=15),"11-15 Years",IF(AND(AH35>=16,AH35<=20),"16-20 Years",IF(AND(AH35>=21,AH35<=25),"21-25 Years",IF(AND(AH35>=26,AH35<=30),"26-30 Years","More Than 30 Years"))))))) -> 1-5 Years | AK35: PART TIME | AL35: 25.25 | AM35: 56 | AN35: =IF(AM35<20,"Less Than 20 Years",IF(AND(AM35>=20,AM35<=24),"20-24 Years",IF(AND(AM35>=25,AM35<=34),"25-34 Years",IF(AND(AM35>=35,AM35<=44),"35-44 Years",IF(AND(AM35>=45,AM35<=54),"45-54 Years","More Than 55 Years"))))) -> More Than 55 Years | AO35: DEC, FY24 | AP35: Q2, FY24 | AQ35: Incident | AT35: Mental Stress | AU35: Human agencies | AV35: Harris Scarfe | AW35: TAS | AX35: Store | AY35: Harris Scarfe | AZ35: SA/TAS | BA35: Harris Scarfe | BB35: Harris Scarfe - SA/TAS
