Workbook
Name ANSW: #REF!
Name HC: #REF!

Sheet Go1_LearningStatReport_JUN FY25
B2: Learning Status | D2: Completed | J2: % Complete | M2: In Progress | S2: % In Progress
D3: Completed FEED | E3: Completed FEED | F3: Completed FEED | G3: Completed FEED | H3: Completed FEED | M3: In Progress FEED | N3: In Progress FEED | O3: In Progress FEED | P3: In Progress FEED | Q3: In Progress FEED
D4: FY25 | F4: FY26 | J4: =F6&", "&F4 -> JUL, FY26 | M4: FY25 | O4: FY26 | S4: =O6&", "&O4 -> JUL, FY26
D5: =D6&", "&D4 -> JUL, FY25 | E5: =D6&", "&D4 -> JUL, FY25 | F5: =F6&", "&F4 -> JUL, FY26 | G5: =F6&", "&F4 -> JUL, FY26 | M5: =M6&", "&M4 -> JUL, FY25 | N5: =M6&", "&M4 -> JUL, FY25 | O5: =O6&", "&O4 -> JUL, FY26 | P5: =O6&", "&O4 -> JUL, FY26
B6: Brand/Function | D6: JUL | E6: YTD | F6: JUL | G6: YTD | H6: VAR | J6: Headcount | K6: % | M6: JUL | N6: YTD | O6: JUL | P6: YTD | Q6: VAR | S6: Headcount | T6: %
B7: eCommerce & Omni Channel | D7: {=_xlfn.XLOOKUP($B7,INDIRECT("'"&D$3&"'!"&"$A3:$A14"),_xlfn.XLOOKUP(D$5,INDIRECT("'"&D$3&"'!"&"$B2:$AZ2"),INDIRECT("'"&D$3&"'!"&"$B3:$AZ14")))} -> 1 | E7: {=_xlfn.XLOOKUP(E$6&" "&$B7,INDIRECT("'"&E$3&"'!"&"$A17:$A28"),_xlfn.XLOOKUP(E$5,INDIRECT("'"&E$3&"'!"&"$B2:$AZ2"),INDIRECT("'"&E$3&"'!"&"$B17:$AZ28")))} -> 1 | F7: {=_xlfn.XLOOKUP($B7,INDIRECT("'"&F$3&"'!"&"$A3:$A14"),_xlfn.XLOOKUP(F$5,INDIRECT("'"&F$3&"'!"&"$B2:$AZ2"),INDIRECT("'"&F$3&"'!"&"$B3:$AZ14")))} -> 0 | G7: {=_xlfn.XLOOKUP(G$6&" "&$B7,INDIRECT("'"&G$3&"'!"&"$A17:$A28"),_xlfn.XLOOKUP(G$5,INDIRECT("'"&G$3&"'!"&"$B2:$AZ2"),INDIRECT("'"&G$3&"'!"&"$B17:$AZ28")))} -> 0 | H7: =G7-E7 -> -1 | J7: =COUNTIF('Active Employees '!$R:$R,'Go1_LearningStatReport_JUN FY25'!$B7) -> 64 | K7: =F7/J7 -> 0 | M7: {=_xlfn.XLOOKUP($B7,INDIRECT("'"&M$3&"'!"&"$A3:$A14"),_xlfn.XLOOKUP(M$5,INDIRECT("'"&M$3&"'!"&"$B2:$AZ2"),INDIRECT("'"&M$3&"'!"&"$B3:$AZ14")))} -> 0 | N7: {=_xlfn.XLOOKUP(N$6&" "&$B7,INDIRECT("'"&N$3&"'!"&"$A17:$A28"),_xlfn.XLOOKUP(N$5,INDIRECT("'"&N$3&"'!"&"$B2:$AZ2"),INDIRECT("'"&N$3&"'!"&"$B17:$AZ28")))} -> 9 | O7: {=_xlfn.XLOOKUP($B7,INDIRECT("'"&O$3&"'!"&"$A3:$A14"),_xlfn.XLOOKUP(O$5,INDIRECT("'"&O$3&"'!"&"$B2:$AZ2"),INDIRECT("'"&O$3&"'!"&"$B3:$AZ14")))} -> 1 | P7: {=_xlfn.XLOOKUP(P$6&" "&$B7,INDIRECT("'"&P$3&"'!"&"$A17:$A28"),_xlfn.XLOOKUP(P$5,INDIRECT("'"&P$3&"'!"&"$B2:$AZ2"),INDIRECT("'"&P$3&"'!"&"$B17:$AZ28")))} -> 1 | Q7: =P7-N7 -> -8 | S7: =COUNTIF('Active Employees '!$R:$R,'Go1_LearningStatReport_JUN FY25'!$B7) -> 64 | T7: =O7/S7 -> 0.015625
B8: FFM | D8: {=_xlfn.XLOOKUP($B8,INDIRECT("'"&D$3&"'!"&"$A3:$A14"),_xlfn.XLOOKUP(D$5,INDIRECT("'"&D$3&"'!"&"$B2:$AZ2"),INDIRECT("'"&D$3&"'!"&"$B3:$AZ14")))} -> 0 | E8: {=_xlfn.XLOOKUP(E$6&" "&$B8,INDIRECT("'"&E$3&"'!"&"$A17:$A28"),_xlfn.XLOOKUP(E$5,INDIRECT("'"&E$3&"'!"&"$B2:$AZ2"),INDIRECT("'"&E$3&"'!"&"$B17:$AZ28")))} -> 0 | F8: {=_xlfn.XLOOKUP($B8,INDIRECT("'"&F$3&"'!"&"$A3:$A14"),_xlfn.XLOOKUP(F$5,INDIRECT("'"&F$3&"'!"&"$B2:$AZ2"),INDIRECT("'"&F$3&"'!"&"$B3:$AZ14")))} -> 0 | G8: {=_xlfn.XLOOKUP(G$6&" "&$B8,INDIRECT("'"&G$3&"'!"&"$A17:$A28"),_xlfn.XLOOKUP(G$5,INDIRECT("'"&G$3&"'!"&"$B2:$AZ2"),INDIRECT("'"&G$3&"'!"&"$B17:$AZ28")))} -> 0 | H8: =G8-E8 -> 0 | J8: =COUNTIF('Active Employees '!$R:$R,'Go1_LearningStatReport_JUN FY25'!$B8) -> 29 | K8: =F8/J8 -> 0 | M8: {=_xlfn.XLOOKUP($B8,INDIRECT("'"&M$3&"'!"&"$A3:$A14"),_xlfn.XLOOKUP(M$5,INDIRECT("'"&M$3&"'!"&"$B2:$AZ2"),INDIRECT("'"&M$3&"'!"&"$B3:$AZ14")))} -> 0 | N8: {=_xlfn.XLOOKUP(N$6&" "&$B8,INDIRECT("'"&N$3&"'!"&"$A17:$A28"),_xlfn.XLOOKUP(N$5,INDIRECT("'"&N$3&"'!"&"$B2:$AZ2"),INDIRECT("'"&N$3&"'!"&"$B17:$AZ28")))} -> 2 | O8: {=_xlfn.XLOOKUP($B8,INDIRECT("'"&O$3&"'!"&"$A3:$A14"),_xlfn.XLOOKUP(O$5,INDIRECT("'"&O$3&"'!"&"$B2:$AZ2"),INDIRECT("'"&O$3&"'!"&"$B3:$AZ14")))} -> 0 | P8: {=_xlfn.XLOOKUP(P$6&" "&$B8,INDIRECT("'"&P$3&"'!"&"$A17:$A28"),_xlfn.XLOOKUP(P$5,INDIRECT("'"&P$3&"'!"&"$B2:$AZ2"),INDIRECT("'"&P$3&"'!"&"$B17:$AZ28")))} -> 0 | Q8: =P8-N8 -> -2 | S8: =COUNTIF('Active Employees '!$R:$R,'Go1_LearningStatReport_JUN FY25'!$B8) -> 29 | T8: =O8/S8 -> 0
B9: Finance | D9: {=_xlfn.XLOOKUP($B9,INDIRECT("'"&D$3&"'!"&"$A3:$A14"),_xlfn.XLOOKUP(D$5,INDIRECT("'"&D$3&"'!"&"$B2:$AZ2"),INDIRECT("'"&D$3&"'!"&"$B3:$AZ14")))} -> 0 | E9: {=_xlfn.XLOOKUP(E$6&" "&$B9,INDIRECT("'"&E$3&"'!"&"$A17:$A28"),_xlfn.XLOOKUP(E$5,INDIRECT("'"&E$3&"'!"&"$B2:$AZ2"),INDIRECT("'"&E$3&"'!"&"$B17:$AZ28")))} -> 0 | F9: {=_xlfn.XLOOKUP($B9,INDIRECT("'"&F$3&"'!"&"$A3:$A14"),_xlfn.XLOOKUP(F$5,INDIRECT("'"&F$3&"'!"&"$B2:$AZ2"),INDIRECT("'"&F$3&"'!"&"$B3:$AZ14")))} -> 0 | G9: {=_xlfn.XLOOKUP(G$6&" "&$B9,INDIRECT("'"&G$3&"'!"&"$A17:$A28"),_xlfn.XLOOKUP(G$5,INDIRECT("'"&G$3&"'!"&"$B2:$AZ2"),INDIRECT("'"&G$3&"'!"&"$B17:$AZ28")))} -> 0 | H9: =G9-E9 -> 0 | J9: =COUNTIF('Active Employees '!$R:$R,'Go1_LearningStatReport_JUN FY25'!$B9) -> 34 | K9: =F9/J9 -> 0 | M9: {=_xlfn.XLOOKUP($B9,INDIRECT("'"&M$3&"'!"&"$A3:$A14"),_xlfn.XLOOKUP(M$5,INDIRECT("'"&M$3&"'!"&"$B2:$AZ2"),INDIRECT("'"&M$3&"'!"&"$B3:$AZ14")))} -> 0 | N9: {=_xlfn.XLOOKUP(N$6&" "&$B9,INDIRECT("'"&N$3&"'!"&"$A17:$A28"),_xlfn.XLOOKUP(N$5,INDIRECT("'"&N$3&"'!"&"$B2:$AZ2"),INDIRECT("'"&N$3&"'!"&"$B17:$AZ28")))} -> 1 | O9: {=_xlfn.XLOOKUP($B9,INDIRECT("'"&O$3&"'!"&"$A3:$A14"),_xlfn.XLOOKUP(O$5,INDIRECT("'"&O$3&"'!"&"$B2:$AZ2"),INDIRECT("'"&O$3&"'!"&"$B3:$AZ14")))} -> 0 | P9: {=_xlfn.XLOOKUP(P$6&" "&$B9,INDIRECT("'"&P$3&"'!"&"$A17:$A28"),_xlfn.XLOOKUP(P$5,INDIRECT("'"&P$3&"'!"&"$B2:$AZ2"),INDIRECT("'"&P$3&"'!"&"$B17:$AZ28")))} -> 0 | Q9: =P9-N9 -> -1 | S9: =COUNTIF('Active Employees '!$R:$R,'Go1_LearningStatReport_JUN FY25'!$B9) -> 34 | T9: =O9/S9 -> 0
B10: Human Resources | D10: {=_xlfn.XLOOKUP($B10,INDIRECT("'"&D$3&"'!"&"$A3:$A14"),_xlfn.XLOOKUP(D$5,INDIRECT("'"&D$3&"'!"&"$B2:$AZ2"),INDIRECT("'"&D$3&"'!"&"$B3:$AZ14")))} -> 42 | E10: {=_xlfn.XLOOKUP(E$6&" "&$B10,INDIRECT("'"&E$3&"'!"&"$A17:$A28"),_xlfn.XLOOKUP(E$5,INDIRECT("'"&E$3&"'!"&"$B2:$AZ2"),INDIRECT("'"&E$3&"'!"&"$B17:$AZ28")))} -> 42 | F10: {=_xlfn.XLOOKUP($B10,INDIRECT("'"&F$3&"'!"&"$A3:$A14"),_xlfn.XLOOKUP(F$5,INDIRECT("'"&F$3&"'!"&"$B2:$AZ2"),INDIRECT("'"&F$3&"'!"&"$B3:$AZ14")))} -> 0 | G10: {=_xlfn.XLOOKUP(G$6&" "&$B10,INDIRECT("'"&G$3&"'!"&"$A17:$A28"),_xlfn.XLOOKUP(G$5,INDIRECT("'"&G$3&"'!"&"$B2:$AZ2"),INDIRECT("'"&G$3&"'!"&"$B17:$AZ28")))} -> 0 | H10: =G10-E10 -> -42 | J10: =COUNTIF('Active Employees '!$R:$R,'Go1_LearningStatReport_JUN FY25'!$B10) -> 46 | K10: =F10/J10 -> 0 | M10: {=_xlfn.XLOOKUP($B10,INDIRECT("'"&M$3&"'!"&"$A3:$A14"),_xlfn.XLOOKUP(M$5,INDIRECT("'"&M$3&"'!"&"$B2:$AZ2"),INDIRECT("'"&M$3&"'!"&"$B3:$AZ14")))} -> 11 | N10: {=_xlfn.XLOOKUP(N$6&" "&$B10,INDIRECT("'"&N$3&"'!"&"$A17:$A28"),_xlfn.XLOOKUP(N$5,INDIRECT("'"&N$3&"'!"&"$B2:$AZ2"),INDIRECT("'"&N$3&"'!"&"$B17:$AZ28")))} -> 22 | O10: {=_xlfn.XLOOKUP($B10,INDIRECT("'"&O$3&"'!"&"$A3:$A14"),_xlfn.XLOOKUP(O$5,INDIRECT("'"&O$3&"'!"&"$B2:$AZ2"),INDIRECT("'"&O$3&"'!"&"$B3:$AZ14")))} -> 0 | P10: {=_xlfn.XLOOKUP(P$6&" "&$B10,INDIRECT("'"&P$3&"'!"&"$A17:$A28"),_xlfn.XLOOKUP(P$5,INDIRECT("'"&P$3&"'!"&"$B2:$AZ2"),INDIRECT("'"&P$3&"'!"&"$B17:$AZ28")))} -> 0 | Q10: =P10-N10 -> -22 | S10: =COUNTIF('Active Employees '!$R:$R,'Go1_LearningStatReport_JUN FY25'!$B10) -> 46 | T10: =O10/S10 -> 0
B11: Insights & Analytics | D11: {=_xlfn.XLOOKUP($B11,INDIRECT("'"&D$3&"'!"&"$A3:$A14"),_xlfn.XLOOKUP(D$5,INDIRECT("'"&D$3&"'!"&"$B2:$AZ2"),INDIRECT("'"&D$3&"'!"&"$B3:$AZ14")))} -> 0 | E11: {=_xlfn.XLOOKUP(E$6&" "&$B11,INDIRECT("'"&E$3&"'!"&"$A17:$A28"),_xlfn.XLOOKUP(E$5,INDIRECT("'"&E$3&"'!"&"$B2:$AZ2"),INDIRECT("'"&E$3&"'!"&"$B17:$AZ28")))} -> 0 | F11: {=_xlfn.XLOOKUP($B11,INDIRECT("'"&F$3&"'!"&"$A3:$A14"),_xlfn.XLOOKUP(F$5,INDIRECT("'"&F$3&"'!"&"$B2:$AZ2"),INDIRECT("'"&F$3&"'!"&"$B3:$AZ14")))} -> 0 | G11: {=_xlfn.XLOOKUP(G$6&" "&$B11,INDIRECT("'"&G$3&"'!"&"$A17:$A28"),_xlfn.XLOOKUP(G$5,INDIRECT("'"&G$3&"'!"&"$B2:$AZ2"),INDIRECT("'"&G$3&"'!"&"$B17:$AZ28")))} -> 0 | H11: =G11-E11 -> 0 | J11: =COUNTIF('Active Employees '!$R:$R,'Go1_LearningStatReport_JUN FY25'!$B11) -> 6 | K11: =F11/J11 -> 0 | M11: {=_xlfn.XLOOKUP($B11,INDIRECT("'"&M$3&"'!"&"$A3:$A14"),_xlfn.XLOOKUP(M$5,INDIRECT("'"&M$3&"'!"&"$B2:$AZ2"),INDIRECT("'"&M$3&"'!"&"$B3:$AZ14")))} -> 0 | N11: {=_xlfn.XLOOKUP(N$6&" "&$B11,INDIRECT("'"&N$3&"'!"&"$A17:$A28"),_xlfn.XLOOKUP(N$5,INDIRECT("'"&N$3&"'!"&"$B2:$AZ2"),INDIRECT("'"&N$3&"'!"&"$B17:$AZ28")))} -> 0 | O11: {=_xlfn.XLOOKUP($B11,INDIRECT("'"&O$3&"'!"&"$A3:$A14"),_xlfn.XLOOKUP(O$5,INDIRECT("'"&O$3&"'!"&"$B2:$AZ2"),INDIRECT("'"&O$3&"'!"&"$B3:$AZ14")))} -> 0 | P11: {=_xlfn.XLOOKUP(P$6&" "&$B11,INDIRECT("'"&P$3&"'!"&"$A17:$A28"),_xlfn.XLOOKUP(P$5,INDIRECT("'"&P$3&"'!"&"$B2:$AZ2"),INDIRECT("'"&P$3&"'!"&"$B17:$AZ28")))} -> 0 | Q11: =P11-N11 -> 0 | S11: =COUNTIF('Active Employees '!$R:$R,'Go1_LearningStatReport_JUN FY25'!$B11) -> 6 | T11: =O11/S11 -> 0
B12: IT | D12: {=_xlfn.XLOOKUP($B12,INDIRECT("'"&D$3&"'!"&"$A3:$A14"),_xlfn.XLOOKUP(D$5,INDIRECT("'"&D$3&"'!"&"$B2:$AZ2"),INDIRECT("'"&D$3&"'!"&"$B3:$AZ14")))} -> 0 | E12: {=_xlfn.XLOOKUP(E$6&" "&$B12,INDIRECT("'"&E$3&"'!"&"$A17:$A28"),_xlfn.XLOOKUP(E$5,INDIRECT("'"&E$3&"'!"&"$B2:$AZ2"),INDIRECT("'"&E$3&"'!"&"$B17:$AZ28")))} -> 0 | F12: {=_xlfn.XLOOKUP($B12,INDIRECT("'"&F$3&"'!"&"$A3:$A14"),_xlfn.XLOOKUP(F$5,INDIRECT("'"&F$3&"'!"&"$B2:$AZ2"),INDIRECT("'"&F$3&"'!"&"$B3:$AZ14")))} -> 0 | G12: {=_xlfn.XLOOKUP(G$6&" "&$B12,INDIRECT("'"&G$3&"'!"&"$A17:$A28"),_xlfn.XLOOKUP(G$5,INDIRECT("'"&G$3&"'!"&"$B2:$AZ2"),INDIRECT("'"&G$3&"'!"&"$B17:$AZ28")))} -> 0 | H12: =G12-E12 -> 0 | J12: =COUNTIF('Active Employees '!$R:$R,'Go1_LearningStatReport_JUN FY25'!$B12) -> 70 | K12: =F12/J12 -> 0 | M12: {=_xlfn.XLOOKUP($B12,INDIRECT("'"&M$3&"'!"&"$A3:$A14"),_xlfn.XLOOKUP(M$5,INDIRECT("'"&M$3&"'!"&"$B2:$AZ2"),INDIRECT("'"&M$3&"'!"&"$B3:$AZ14")))} -> 5 | N12: {=_xlfn.XLOOKUP(N$6&" "&$B12,INDIRECT("'"&N$3&"'!"&"$A17:$A28"),_xlfn.XLOOKUP(N$5,INDIRECT("'"&N$3&"'!"&"$B2:$AZ2"),INDIRECT("'"&N$3&"'!"&"$B17:$AZ28")))} -> 22 | O12: {=_xlfn.XLOOKUP($B12,INDIRECT("'"&O$3&"'!"&"$A3:$A14"),_xlfn.XLOOKUP(O$5,INDIRECT("'"&O$3&"'!"&"$B2:$AZ2"),INDIRECT("'"&O$3&"'!"&"$B3:$AZ14")))} -> 0 | P12: {=_xlfn.XLOOKUP(P$6&" "&$B12,INDIRECT("'"&P$3&"'!"&"$A17:$A28"),_xlfn.XLOOKUP(P$5,INDIRECT("'"&P$3&"'!"&"$B2:$AZ2"),INDIRECT("'"&P$3&"'!"&"$B17:$AZ28")))} -> 0 | Q12: =P12-N12 -> -22 | S12: =COUNTIF('Active Employees '!$R:$R,'Go1_LearningStatReport_JUN FY25'!$B12) -> 70 | T12: =O12/S12 -> 0
B13: Marketing | D13: {=_xlfn.XLOOKUP($B13,INDIRECT("'"&D$3&"'!"&"$A3:$A14"),_xlfn.XLOOKUP(D$5,INDIRECT("'"&D$3&"'!"&"$B2:$AZ2"),INDIRECT("'"&D$3&"'!"&"$B3:$AZ14")))} -> 0 | E13: {=_xlfn.XLOOKUP(E$6&" "&$B13,INDIRECT("'"&E$3&"'!"&"$A17:$A28"),_xlfn.XLOOKUP(E$5,INDIRECT("'"&E$3&"'!"&"$B2:$AZ2"),INDIRECT("'"&E$3&"'!"&"$B17:$AZ28")))} -> 0 | F13: {=_xlfn.XLOOKUP($B13,INDIRECT("'"&F$3&"'!"&"$A3:$A14"),_xlfn.XLOOKUP(F$5,INDIRECT("'"&F$3&"'!"&"$B2:$AZ2"),INDIRECT("'"&F$3&"'!"&"$B3:$AZ14")))} -> 0 | G13: {=_xlfn.XLOOKUP(G$6&" "&$B13,INDIRECT("'"&G$3&"'!"&"$A17:$A28"),_xlfn.XLOOKUP(G$5,INDIRECT("'"&G$3&"'!"&"$B2:$AZ2"),INDIRECT("'"&G$3&"'!"&"$B17:$AZ28")))} -> 0 | H13: =G13-E13 -> 0 | J13: =COUNTIF('Active Employees '!$R:$R,'Go1_LearningStatReport_JUN FY25'!$B13) -> 67 | K13: =F13/J13 -> 0 | M13: {=_xlfn.XLOOKUP($B13,INDIRECT("'"&M$3&"'!"&"$A3:$A14"),_xlfn.XLOOKUP(M$5,INDIRECT("'"&M$3&"'!"&"$B2:$AZ2"),INDIRECT("'"&M$3&"'!"&"$B3:$AZ14")))} -> 1 | N13: {=_xlfn.XLOOKUP(N$6&" "&$B13,INDIRECT("'"&N$3&"'!"&"$A17:$A28"),_xlfn.XLOOKUP(N$5,INDIRECT("'"&N$3&"'!"&"$B2:$AZ2"),INDIRECT("'"&N$3&"'!"&"$B17:$AZ28")))} -> 12 | O13: {=_xlfn.XLOOKUP($B13,INDIRECT("'"&O$3&"'!"&"$A3:$A14"),_xlfn.XLOOKUP(O$5,INDIRECT("'"&O$3&"'!"&"$B2:$AZ2"),INDIRECT("'"&O$3&"'!"&"$B3:$AZ14")))} -> 0 | P13: {=_xlfn.XLOOKUP(P$6&" "&$B13,INDIRECT("'"&P$3&"'!"&"$A17:$A28"),_xlfn.XLOOKUP(P$5,INDIRECT("'"&P$3&"'!"&"$B2:$AZ2"),INDIRECT("'"&P$3&"'!"&"$B17:$AZ28")))} -> 0 | Q13: =P13-N13 -> -12 | S13: =COUNTIF('Active Employees '!$R:$R,'Go1_LearningStatReport_JUN FY25'!$B13) -> 67 | T13: =O13/S13 -> 0
B14: Property and Store Development | D14: {=_xlfn.XLOOKUP($B14,INDIRECT("'"&D$3&"'!"&"$A3:$A14"),_xlfn.XLOOKUP(D$5,INDIRECT("'"&D$3&"'!"&"$B2:$AZ2"),INDIRECT("'"&D$3&"'!"&"$B3:$AZ14")))} -> 7 | E14: {=_xlfn.XLOOKUP(E$6&" "&$B14,INDIRECT("'"&E$3&"'!"&"$A17:$A28"),_xlfn.XLOOKUP(E$5,INDIRECT("'"&E$3&"'!"&"$B2:$AZ2"),INDIRECT("'"&E$3&"'!"&"$B17:$AZ28")))} -> 7 | F14: {=_xlfn.XLOOKUP($B14,INDIRECT("'"&F$3&"'!"&"$A3:$A14"),_xlfn.XLOOKUP(F$5,INDIRECT("'"&F$3&"'!"&"$B2:$AZ2"),INDIRECT("'"&F$3&"'!"&"$B3:$AZ14")))} -> 0 | G14: {=_xlfn.XLOOKUP(G$6&" "&$B14,INDIRECT("'"&G$3&"'!"&"$A17:$A28"),_xlfn.XLOOKUP(G$5,INDIRECT("'"&G$3&"'!"&"$B2:$AZ2"),INDIRECT("'"&G$3&"'!"&"$B17:$AZ28")))} -> 0 | H14: =G14-E14 -> -7 | J14: =COUNTIF('Active Employees '!$R:$R,'Go1_LearningStatReport_JUN FY25'!$B14) -> 26 | K14: =F14/J14 -> 0 | M14: {=_xlfn.XLOOKUP($B14,INDIRECT("'"&M$3&"'!"&"$A3:$A14"),_xlfn.XLOOKUP(M$5,INDIRECT("'"&M$3&"'!"&"$B2:$AZ2"),INDIRECT("'"&M$3&"'!"&"$B3:$AZ14")))} -> 2 | N14: {=_xlfn.XLOOKUP(N$6&" "&$B14,INDIRECT("'"&N$3&"'!"&"$A17:$A28"),_xlfn.XLOOKUP(N$5,INDIRECT("'"&N$3&"'!"&"$B2:$AZ2"),INDIRECT("'"&N$3&"'!"&"$B17:$AZ28")))} -> 7 | O14: {=_xlfn.XLOOKUP($B14,INDIRECT("'"&O$3&"'!"&"$A3:$A14"),_xlfn.XLOOKUP(O$5,INDIRECT("'"&O$3&"'!"&"$B2:$AZ2"),INDIRECT("'"&O$3&"'!"&"$B3:$AZ14")))} -> 0 | P14: {=_xlfn.XLOOKUP(P$6&" "&$B14,INDIRECT("'"&P$3&"'!"&"$A17:$A28"),_xlfn.XLOOKUP(P$5,INDIRECT("'"&P$3&"'!"&"$B2:$AZ2"),INDIRECT("'"&P$3&"'!"&"$B17:$AZ28")))} -> 0 | Q14: =P14-N14 -> -7 | S14: =COUNTIF('Active Employees '!$R:$R,'Go1_LearningStatReport_JUN FY25'!$B14) -> 26 | T14: =O14/S14 -> 0
B15: SPG Development | D15: {=_xlfn.XLOOKUP($B15,INDIRECT("'"&D$3&"'!"&"$A3:$A14"),_xlfn.XLOOKUP(D$5,INDIRECT("'"&D$3&"'!"&"$B2:$AZ2"),INDIRECT("'"&D$3&"'!"&"$B3:$AZ14")))} -> 0 | E15: {=_xlfn.XLOOKUP(E$6&" "&$B15,INDIRECT("'"&E$3&"'!"&"$A17:$A28"),_xlfn.XLOOKUP(E$5,INDIRECT("'"&E$3&"'!"&"$B2:$AZ2"),INDIRECT("'"&E$3&"'!"&"$B17:$AZ28")))} -> 0 | F15: {=_xlfn.XLOOKUP($B15,INDIRECT("'"&F$3&"'!"&"$A3:$A14"),_xlfn.XLOOKUP(F$5,INDIRECT("'"&F$3&"'!"&"$B2:$AZ2"),INDIRECT("'"&F$3&"'!"&"$B3:$AZ14")))} -> 0 | G15: {=_xlfn.XLOOKUP(G$6&" "&$B15,INDIRECT("'"&G$3&"'!"&"$A17:$A28"),_xlfn.XLOOKUP(G$5,INDIRECT("'"&G$3&"'!"&"$B2:$AZ2"),INDIRECT("'"&G$3&"'!"&"$B17:$AZ28")))} -> 0 | H15: =G15-E15 -> 0 | J15: =COUNTIF('Active Employees '!$R:$R,'Go1_LearningStatReport_JUN FY25'!$B15) -> 14 | K15: =F15/J15 -> 0 | M15: {=_xlfn.XLOOKUP($B15,INDIRECT("'"&M$3&"'!"&"$A3:$A14"),_xlfn.XLOOKUP(M$5,INDIRECT("'"&M$3&"'!"&"$B2:$AZ2"),INDIRECT("'"&M$3&"'!"&"$B3:$AZ14")))} -> 0 | N15: {=_xlfn.XLOOKUP(N$6&" "&$B15,INDIRECT("'"&N$3&"'!"&"$A17:$A28"),_xlfn.XLOOKUP(N$5,INDIRECT("'"&N$3&"'!"&"$B2:$AZ2"),INDIRECT("'"&N$3&"'!"&"$B17:$AZ28")))} -> 1 | O15: {=_xlfn.XLOOKUP($B15,INDIRECT("'"&O$3&"'!"&"$A3:$A14"),_xlfn.XLOOKUP(O$5,INDIRECT("'"&O$3&"'!"&"$B2:$AZ2"),INDIRECT("'"&O$3&"'!"&"$B3:$AZ14")))} -> 0 | P15: {=_xlfn.XLOOKUP(P$6&" "&$B15,INDIRECT("'"&P$3&"'!"&"$A17:$A28"),_xlfn.XLOOKUP(P$5,INDIRECT("'"&P$3&"'!"&"$B2:$AZ2"),INDIRECT("'"&P$3&"'!"&"$B17:$AZ28")))} -> 0 | Q15: =P15-N15 -> -1 | S15: =COUNTIF('Active Employees '!$R:$R,'Go1_LearningStatReport_JUN FY25'!$B15) -> 14 | T15: =O15/S15 -> 0
B16: Spot Merch | D16: {=_xlfn.XLOOKUP($B16,INDIRECT("'"&D$3&"'!"&"$A3:$A14"),_xlfn.XLOOKUP(D$5,INDIRECT("'"&D$3&"'!"&"$B2:$AZ2"),INDIRECT("'"&D$3&"'!"&"$B3:$AZ14")))} -> 0 | E16: {=_xlfn.XLOOKUP(E$6&" "&$B16,INDIRECT("'"&E$3&"'!"&"$A17:$A28"),_xlfn.XLOOKUP(E$5,INDIRECT("'"&E$3&"'!"&"$B2:$AZ2"),INDIRECT("'"&E$3&"'!"&"$B17:$AZ28")))} -> 0 | F16: {=_xlfn.XLOOKUP($B16,INDIRECT("'"&F$3&"'!"&"$A3:$A14"),_xlfn.XLOOKUP(F$5,INDIRECT("'"&F$3&"'!"&"$B2:$AZ2"),INDIRECT("'"&F$3&"'!"&"$B3:$AZ14")))} -> 0 | G16: {=_xlfn.XLOOKUP(G$6&" "&$B16,INDIRECT("'"&G$3&"'!"&"$A17:$A28"),_xlfn.XLOOKUP(G$5,INDIRECT("'"&G$3&"'!"&"$B2:$AZ2"),INDIRECT("'"&G$3&"'!"&"$B17:$AZ28")))} -> 0 | H16: =G16-E16 -> 0 | J16: =COUNTIF('Active Employees '!$R:$R,'Go1_LearningStatReport_JUN FY25'!$B16) -> 97 | K16: =F16/J16 -> 0 | M16: {=_xlfn.XLOOKUP($B16,INDIRECT("'"&M$3&"'!"&"$A3:$A14"),_xlfn.XLOOKUP(M$5,INDIRECT("'"&M$3&"'!"&"$B2:$AZ2"),INDIRECT("'"&M$3&"'!"&"$B3:$AZ14")))} -> 0 | N16: {=_xlfn.XLOOKUP(N$6&" "&$B16,INDIRECT("'"&N$3&"'!"&"$A17:$A28"),_xlfn.XLOOKUP(N$5,INDIRECT("'"&N$3&"'!"&"$B2:$AZ2"),INDIRECT("'"&N$3&"'!"&"$B17:$AZ28")))} -> 0 | O16: {=_xlfn.XLOOKUP($B16,INDIRECT("'"&O$3&"'!"&"$A3:$A14"),_xlfn.XLOOKUP(O$5,INDIRECT("'"&O$3&"'!"&"$B2:$AZ2"),INDIRECT("'"&O$3&"'!"&"$B3:$AZ14")))} -> 0 | P16: {=_xlfn.XLOOKUP(P$6&" "&$B16,INDIRECT("'"&P$3&"'!"&"$A17:$A28"),_xlfn.XLOOKUP(P$5,INDIRECT("'"&P$3&"'!"&"$B2:$AZ2"),INDIRECT("'"&P$3&"'!"&"$B17:$AZ28")))} -> 0 | Q16: =P16-N16 -> 0 | S16: =COUNTIF('Active Employees '!$R:$R,'Go1_LearningStatReport_JUN FY25'!$B16) -> 97 | T16: =O16/S16 -> 0
B17: Spotlight Group Aviation | D17: {=_xlfn.XLOOKUP($B17,INDIRECT("'"&D$3&"'!"&"$A3:$A14"),_xlfn.XLOOKUP(D$5,INDIRECT("'"&D$3&"'!"&"$B2:$AZ2"),INDIRECT("'"&D$3&"'!"&"$B3:$AZ14")))} -> 0 | E17: {=_xlfn.XLOOKUP(E$6&" "&$B17,INDIRECT("'"&E$3&"'!"&"$A17:$A28"),_xlfn.XLOOKUP(E$5,INDIRECT("'"&E$3&"'!"&"$B2:$AZ2"),INDIRECT("'"&E$3&"'!"&"$B17:$AZ28")))} -> 0 | F17: {=_xlfn.XLOOKUP($B17,INDIRECT("'"&F$3&"'!"&"$A3:$A14"),_xlfn.XLOOKUP(F$5,INDIRECT("'"&F$3&"'!"&"$B2:$AZ2"),INDIRECT("'"&F$3&"'!"&"$B3:$AZ14")))} -> 0 | G17: {=_xlfn.XLOOKUP(G$6&" "&$B17,INDIRECT("'"&G$3&"'!"&"$A17:$A28"),_xlfn.XLOOKUP(G$5,INDIRECT("'"&G$3&"'!"&"$B2:$AZ2"),INDIRECT("'"&G$3&"'!"&"$B17:$AZ28")))} -> 0 | H17: =G17-E17 -> 0 | J17: =COUNTIF('Active Employees '!$R:$R,'Go1_LearningStatReport_JUN FY25'!$B17) -> 6 | K17: =F17/J17 -> 0 | M17: {=_xlfn.XLOOKUP($B17,INDIRECT("'"&M$3&"'!"&"$A3:$A14"),_xlfn.XLOOKUP(M$5,INDIRECT("'"&M$3&"'!"&"$B2:$AZ2"),INDIRECT("'"&M$3&"'!"&"$B3:$AZ14")))} -> 0 | N17: {=_xlfn.XLOOKUP(N$6&" "&$B17,INDIRECT("'"&N$3&"'!"&"$A17:$A28"),_xlfn.XLOOKUP(N$5,INDIRECT("'"&N$3&"'!"&"$B2:$AZ2"),INDIRECT("'"&N$3&"'!"&"$B17:$AZ28")))} -> 0 | O17: {=_xlfn.XLOOKUP($B17,INDIRECT("'"&O$3&"'!"&"$A3:$A14"),_xlfn.XLOOKUP(O$5,INDIRECT("'"&O$3&"'!"&"$B2:$AZ2"),INDIRECT("'"&O$3&"'!"&"$B3:$AZ14")))} -> 0 | P17: {=_xlfn.XLOOKUP(P$6&" "&$B17,INDIRECT("'"&P$3&"'!"&"$A17:$A28"),_xlfn.XLOOKUP(P$5,INDIRECT("'"&P$3&"'!"&"$B2:$AZ2"),INDIRECT("'"&P$3&"'!"&"$B17:$AZ28")))} -> 0 | Q17: =P17-N17 -> 0 | S17: =COUNTIF('Active Employees '!$R:$R,'Go1_LearningStatReport_JUN FY25'!$B17) -> 6 | T17: =O17/S17 -> 0
B18: Supply Chain | D18: {=_xlfn.XLOOKUP($B18,INDIRECT("'"&D$3&"'!"&"$A3:$A14"),_xlfn.XLOOKUP(D$5,INDIRECT("'"&D$3&"'!"&"$B2:$AZ2"),INDIRECT("'"&D$3&"'!"&"$B3:$AZ14")))} -> 5 | E18: {=_xlfn.XLOOKUP(E$6&" "&$B18,INDIRECT("'"&E$3&"'!"&"$A17:$A28"),_xlfn.XLOOKUP(E$5,INDIRECT("'"&E$3&"'!"&"$B2:$AZ2"),INDIRECT("'"&E$3&"'!"&"$B17:$AZ28")))} -> 5 | F18: {=_xlfn.XLOOKUP($B18,INDIRECT("'"&F$3&"'!"&"$A3:$A14"),_xlfn.XLOOKUP(F$5,INDIRECT("'"&F$3&"'!"&"$B2:$AZ2"),INDIRECT("'"&F$3&"'!"&"$B3:$AZ14")))} -> 0 | G18: {=_xlfn.XLOOKUP(G$6&" "&$B18,INDIRECT("'"&G$3&"'!"&"$A17:$A28"),_xlfn.XLOOKUP(G$5,INDIRECT("'"&G$3&"'!"&"$B2:$AZ2"),INDIRECT("'"&G$3&"'!"&"$B17:$AZ28")))} -> 0 | H18: =G18-E18 -> -5 | J18: =COUNTIF('Active Employees '!$R:$R,'Go1_LearningStatReport_JUN FY25'!$B18) -> 168 | K18: =F18/J18 -> 0 | M18: {=_xlfn.XLOOKUP($B18,INDIRECT("'"&M$3&"'!"&"$A3:$A14"),_xlfn.XLOOKUP(M$5,INDIRECT("'"&M$3&"'!"&"$B2:$AZ2"),INDIRECT("'"&M$3&"'!"&"$B3:$AZ14")))} -> 0 | N18: {=_xlfn.XLOOKUP(N$6&" "&$B18,INDIRECT("'"&N$3&"'!"&"$A17:$A28"),_xlfn.XLOOKUP(N$5,INDIRECT("'"&N$3&"'!"&"$B2:$AZ2"),INDIRECT("'"&N$3&"'!"&"$B17:$AZ28")))} -> 8 | O18: {=_xlfn.XLOOKUP($B18,INDIRECT("'"&O$3&"'!"&"$A3:$A14"),_xlfn.XLOOKUP(O$5,INDIRECT("'"&O$3&"'!"&"$B2:$AZ2"),INDIRECT("'"&O$3&"'!"&"$B3:$AZ14")))} -> 0 | P18: {=_xlfn.XLOOKUP(P$6&" "&$B18,INDIRECT("'"&P$3&"'!"&"$A17:$A28"),_xlfn.XLOOKUP(P$5,INDIRECT("'"&P$3&"'!"&"$B2:$AZ2"),INDIRECT("'"&P$3&"'!"&"$B17:$AZ28")))} -> 0 | Q18: =P18-N18 -> -8 | S18: =COUNTIF('Active Employees '!$R:$R,'Go1_LearningStatReport_JUN FY25'!$B18) -> 168 | T18: =O18/S18 -> 0
B19: Grand Total | D19: =SUM(D7:D18) -> 55 | E19: =SUM(E7:E18) -> 55 | F19: =SUM(F7:F18) -> 0 | G19: =SUM(G7:G18) -> 0 | H19: =SUM(H7:H18) -> -55 | J19: =SUM(J7:J18) -> 627 | K19: =F19/J19 -> 0 | M19: =SUM(M7:M18) -> 19 | N19: =SUM(N7:N18) -> 84 | O19: =SUM(O7:O18) -> 1 | P19: =SUM(P7:P18) -> 1 | Q19: =SUM(Q7:Q18) -> -83 | S19: =SUM(S7:S18) -> 627 | T19: =O19/S19 -> 0.0015948963
B20: *Var denotes the Variance in YTD Columns

Sheet Currently Assigned
A3: Count of Status | B3: Column Labels
A4: Row Labels | B4: Assigned | C4: Grand Total
A5: Finance | B5: 121 | C5: 121
A6: Human Resources | B6: 83 | C6: 83
A7: IT | B7: 371 | C7: 371
A8: Marketing | B8: 212 | C8: 212
A9: SPG Development | B9: 70 | C9: 70
A10: Supply Chain | B10: 141 | C10: 141
A11: Grand Total | B11: 998 | C11: 998
A23: Status | B23: Completed
A25: Count of Status | B25: Column Labels
A26: Row Labels | B26: JUL, FY25 | C26: AUG, FY25 | D26: SEP, FY25 | E26: OCT, FY25 | F26: NOV, FY25 | G26: DEC, FY25 | H26: JAN, FY25 | I26: FEB, FY25 | J26: MAR, FY25 | K26: APR, FY25 | L26: MAY, FY25 | M26: JUN, FY25 | N26: Grand Total
A27: Finance | L27: 3 | M27: 4 | N27: 7
A28: Human Resources | B28: 42 | C28: 4 | D28: 10 | E28: 3 | F28: 1 | G28: 2 | H28: 1 | I28: 4 | J28: 3 | N28: 70
A29: IT | C29: 1 | D29: 2 | F29: 1 | I29: 2 | N29: 6
A30: Marketing | C30: 6 | J30: 2 | L30: 4 | N30: 12
A31: Supply Chain | B31: 5 | J31: 5 | K31: 5 | L31: 1 | M31: 2 | N31: 18
A32: Grand Total | B32: 47 | C32: 11 | D32: 12 | E32: 3 | F32: 2 | G32: 2 | H32: 1 | I32: 6 | J32: 10 | K32: 5 | L32: 8 | M32: 6 | N32: 113
A38: Status | B38: In Progress
A40: Count of Status | B40: Column Labels
A41: Row Labels | B41: JUL, FY25 | C41: AUG, FY25 | D41: SEP, FY25 | E41: OCT, FY25 | F41: NOV, FY25 | G41: DEC, FY25 | H41: FEB, FY25 | I41: MAR, FY25 | J41: MAY, FY25 | K41: JUN, FY25 | L41: Grand Total
A42: Finance | J42: 1 | K42: 2 | L42: 3
A43: Human Resources | B43: 11 | D43: 2 | E43: 1 | F43: 2 | I43: 1 | J43: 3 | L43: 20
A44: IT | B44: 5 | C44: 1 | H44: 2 | L44: 8
A45: Marketing | B45: 1 | G45: 1 | I45: 1 | L45: 3
A46: SPG Development | F46: 3 | L46: 3
A47: Supply Chain | G47: 1 | I47: 2 | L47: 3
A48: Grand Total | B48: 17 | C48: 1 | D48: 2 | E48: 1 | F48: 5 | G48: 2 | H48: 2 | I48: 4 | J48: 4 | K48: 2 | L48: 40

Sheet Completed FEED
A1: Completed | B1: FY24 | S1: FY25 | AJ1: FY26
A2: Shared Services | B2: ="JUL, "&B1 -> JUL, FY24 | C2: ="AUG, "&B1 -> AUG, FY24 | D2: ="SEP, "&B1 -> SEP, FY24 | E2: ="Q1, "&B1 -> Q1, FY24 | F2: ="OCT, "&B1 -> OCT, FY24 | G2: ="NOV, "&B1 -> NOV, FY24 | H2: ="DEC, "&B1 -> DEC, FY24 | I2: ="Q2, "&B1 -> Q2, FY24 | J2: ="JAN, "&B1 -> JAN, FY24 | K2: ="FEB, "&B1 -> FEB, FY24 | L2: ="MAR, "&B1 -> MAR, FY24 | M2: ="Q3, "&B1 -> Q3, FY24 | N2: ="APR, "&B1 -> APR, FY24 | O2: ="MAY, "&B1 -> MAY, FY24 | P2: ="JUN, "&B1 -> JUN, FY24 | Q2: ="Q4, "&B1 -> Q4, FY24 | R2: ="Full Year, "&B1 -> Full Year, FY24 | S2: ="JUL, "&S1 -> JUL, FY25 | T2: ="AUG, "&S1 -> AUG, FY25 | U2: ="SEP, "&S1 -> SEP, FY25 | V2: ="Q1, "&S1 -> Q1, FY25 | W2: ="OCT, "&S1 -> OCT, FY25 | X2: ="NOV, "&S1 -> NOV, FY25 | Y2: ="DEC, "&S1 -> DEC, FY25 | Z2: ="Q2, "&S1 -> Q2, FY25 | AA2: ="JAN, "&S1 -> JAN, FY25 | AB2: ="FEB, "&S1 -> FEB, FY25 | AC2: ="MAR, "&S1 -> MAR, FY25 | AD2: ="Q3, "&S1 -> Q3, FY25 | AE2: ="APR, "&S1 -> APR, FY25 | AF2: ="MAY, "&S1 -> MAY, FY25 | AG2: ="JUN, "&S1 -> JUN, FY25 | AH2: ="Q4, "&S1 -> Q4, FY25 | AI2: ="Full Year, "&S1 -> Full Year, FY25 | AJ2: ="JUL, "&AJ1 -> JUL, FY26 | AK2: ="AUG, "&AJ1 -> AUG, FY26 | AL2: ="SEP, "&AJ1 -> SEP, FY26 | AM2: ="Q1, "&AJ1 -> Q1, FY26 | AN2: ="OCT, "&AJ1 -> OCT, FY26 | AO2: ="NOV, "&AJ1 -> NOV, FY26 | AP2: ="DEC, "&AJ1 -> DEC, FY26 | AQ2: ="Q2, "&AJ1 -> Q2, FY26 | AR2: ="JAN, "&AJ1 -> JAN, FY26 | AS2: ="FEB, "&AJ1 -> FEB, FY26 | AT2: ="MAR, "&AJ1 -> MAR, FY26 | AU2: ="Q3, "&AJ1 -> Q3, FY26 | AV2: ="APR, "&AJ1 -> APR, FY26 | AW2: ="MAY, "&AJ1 -> MAY, FY26 | AX2: ="JUN, "&AJ1 -> JUN, FY26 | AY2: ="Q4, "&AJ1 -> Q4, FY26 | AZ2: ="Full Year, "&AJ1 -> Full Year, FY26
A3: eCommerce & Omni Channel | B3: =COUNTIFS('Assigned Learning Data Dump'!$W:$W,'Completed FEED'!$A3,'Assigned Learning Data Dump'!$F:$F,$A$1,'Assigned Learning Data Dump'!$U:$U,'Completed FEED'!B$2) -> 8 | C3: =COUNTIFS('Assigned Learning Data Dump'!$W:$W,'Completed FEED'!$A3,'Assigned Learning Data Dump'!$F:$F,$A$1,'Assigned Learning Data Dump'!$U:$U,'Completed FEED'!C$2) -> 0 | D3: =COUNTIFS('Assigned Learning Data Dump'!$W:$W,'Completed FEED'!$A3,'Assigned Learning Data Dump'!$F:$F,$A$1,'Assigned Learning Data Dump'!$U:$U,'Completed FEED'!D$2) -> 1 | E3: =SUBTOTAL(9,B3:D3) -> 9 | F3: =COUNTIFS('Assigned Learning Data Dump'!$W:$W,'Completed FEED'!$A3,'Assigned Learning Data Dump'!$F:$F,$A$1,'Assigned Learning Data Dump'!$U:$U,'Completed FEED'!F$2) -> 0 | G3: =COUNTIFS('Assigned Learning Data Dump'!$W:$W,'Completed FEED'!$A3,'Assigned Learning Data Dump'!$F:$F,$A$1,'Assigned Learning Data Dump'!$U:$U,'Completed FEED'!G$2) -> 0 | H3: =COUNTIFS('Assigned Learning Data Dump'!$W:$W,'Completed FEED'!$A3,'Assigned Learning Data Dump'!$F:$F,$A$1,'Assigned Learning Data Dump'!$U:$U,'Completed FEED'!H$2) -> 0 | I3: =SUBTOTAL(9,F3:H3) -> 0 | J3: =COUNTIFS('Assigned Learning Data Dump'!$W:$W,'Completed FEED'!$A3,'Assigned Learning Data Dump'!$F:$F,$A$1,'Assigned Learning Data Dump'!$U:$U,'Completed FEED'!J$2) -> 2 | K3: =COUNTIFS('Assigned Learning Data Dump'!$W:$W,'Completed FEED'!$A3,'Assigned Learning Data Dump'!$F:$F,$A$1,'Assigned Learning Data Dump'!$U:$U,'Completed FEED'!K$2) -> 2 | L3: =COUNTIFS('Assigned Learning Data Dump'!$W:$W,'Completed FEED'!$A3,'Assigned Learning Data Dump'!$F:$F,$A$1,'Assigned Learning Data Dump'!$U:$U,'Completed FEED'!L$2) -> 4 | M3: =SUBTOTAL(9,J3:L3) -> 8 | N3: =COUNTIFS('Assigned Learning Data Dump'!$W:$W,'Completed FEED'!$A3,'Assigned Learning Data Dump'!$F:$F,$A$1,'Assigned Learning Data Dump'!$U:$U,'Completed FEED'!N$2) -> 0 | O3: =COUNTIFS('Assigned Learning Data Dump'!$W:$W,'Completed FEED'!$A3,'Assigned Learning Data Dump'!$F:$F,$A$1,'Assigned Learning Data Dump'!$U:$U,'Completed FEED'!O$2) -> 1 | P3: =COUNTIFS('Assigned Learning Data Dump'!$W:$W,'Completed FEED'!$A3,'Assigned Learning Data Dump'!$F:$F,$A$1,'Assigned Learning Data Dump'!$U:$U,'Completed FEED'!P$2) -> 13 | Q3: =SUBTOTAL(9,N3:P3) -> 14 | R3: =SUBTOTAL(9,B3:Q3) -> 31 | S3: =COUNTIFS('Assigned Learning Data Dump'!$W:$W,'Completed FEED'!$A3,'Assigned Learning Data Dump'!$F:$F,$A$1,'Assigned Learning Data Dump'!$U:$U,'Completed FEED'!S$2) -> 1 | T3: =COUNTIFS('Assigned Learning Data Dump'!$W:$W,'Completed FEED'!$A3,'Assigned Learning Data Dump'!$F:$F,$A$1,'Assigned Learning Data Dump'!$U:$U,'Completed FEED'!T$2) -> 0 | U3: =COUNTIFS('Assigned Learning Data Dump'!$W:$W,'Completed FEED'!$A3,'Assigned Learning Data Dump'!$F:$F,$A$1,'Assigned Learning Data Dump'!$U:$U,'Completed FEED'!U$2) -> 0 | V3: =SUBTOTAL(9,S3:U3) -> 1 | W3: =COUNTIFS('Assigned Learning Data Dump'!$W:$W,'Completed FEED'!$A3,'Assigned Learning Data Dump'!$F:$F,$A$1,'Assigned Learning Data Dump'!$U:$U,'Completed FEED'!W$2) -> 2 | X3: =COUNTIFS('Assigned Learning Data Dump'!$W:$W,'Completed FEED'!$A3,'Assigned Learning Data Dump'!$F:$F,$A$1,'Assigned Learning Data Dump'!$U:$U,'Completed FEED'!X$2) -> 0 | Y3: =COUNTIFS('Assigned Learning Data Dump'!$W:$W,'Completed FEED'!$A3,'Assigned Learning Data Dump'!$F:$F,$A$1,'Assigned Learning Data Dump'!$U:$U,'Completed FEED'!Y$2) -> 6 | Z3: =SUBTOTAL(9,W3:Y3) -> 8 | AA3: =COUNTIFS('Assigned Learning Data Dump'!$W:$W,'Completed FEED'!$A3,'Assigned Learning Data Dump'!$F:$F,$A$1,'Assigned Learning Data Dump'!$U:$U,'Completed FEED'!AA$2) -> 0 | AB3: =COUNTIFS('Assigned Learning Data Dump'!$W:$W,'Completed FEED'!$A3,'Assigned Learning Data Dump'!$F:$F,$A$1,'Assigned Learning Data Dump'!$U:$U,'Completed FEED'!AB$2) -> 5 | AC3: =COUNTIFS('Assigned Learning Data Dump'!$W:$W,'Completed FEED'!$A3,'Assigned Learning Data Dump'!$F:$F,$A$1,'Assigned Learning Data Dump'!$U:$U,'Completed FEED'!AC$2) -> 0 | AD3: =SUBTOTAL(9,AA3:AC3) -> 5 | AE3: =COUNTIFS('Assigned Learning Data Dump'!$W:$W,'Completed FEED'!$A3,'Assigned Learning Data Dump'!$F:$F,$A$1,'Assigned Learning Data Dump'!$U:$U,'Completed FEED'!AE$2) -> 0 | AF3: =COUNTIFS('Assigned Learning Data Dump'!$W:$W,'Completed FEED'!$A3,'Assigned Learning Data Dump'!$F:$F,$A$1,'Assigned Learning Data Dump'!$U:$U,'Completed FEED'!AF$2) -> 1 | AG3: =COUNTIFS('Assigned Learning Data Dump'!$W:$W,'Completed FEED'!$A3,'Assigned Learning Data Dump'!$F:$F,$A$1,'Assigned Learning Data Dump'!$U:$U,'Completed FEED'!AG$2) -> 0 | AH3: =SUBTOTAL(9,AE3:AG3) -> 1 | AI3: =SUBTOTAL(9,S3:AH3) -> 15 | AJ3: =COUNTIFS('Assigned Learning Data Dump'!$W:$W,'Completed FEED'!$A3,'Assigned Learning Data Dump'!$F:$F,$A$1,'Assigned Learning Data Dump'!$U:$U,'Completed FEED'!AJ$2) -> 0 | AK3: =COUNTIFS('Assigned Learning Data Dump'!$W:$W,'Completed FEED'!$A3,'Assigned Learning Data Dump'!$F:$F,$A$1,'Assigned Learning Data Dump'!$U:$U,'Completed FEED'!AK$2) -> 0 | AL3: =COUNTIFS('Assigned Learning Data Dump'!$W:$W,'Completed FEED'!$A3,'Assigned Learning Data Dump'!$F:$F,$A$1,'Assigned Learning Data Dump'!$U:$U,'Completed FEED'!AL$2) -> 0 | AM3: =SUBTOTAL(9,AJ3:AL3) -> 0 | AN3: =COUNTIFS('Assigned Learning Data Dump'!$W:$W,'Completed FEED'!$A3,'Assigned Learning Data Dump'!$F:$F,$A$1,'Assigned Learning Data Dump'!$U:$U,'Completed FEED'!AN$2) -> 0 | AO3: =COUNTIFS('Assigned Learning Data Dump'!$W:$W,'Completed FEED'!$A3,'Assigned Learning Data Dump'!$F:$F,$A$1,'Assigned Learning Data Dump'!$U:$U,'Completed FEED'!AO$2) -> 0 | AP3: =COUNTIFS('Assigned Learning Data Dump'!$W:$W,'Completed FEED'!$A3,'Assigned Learning Data Dump'!$F:$F,$A$1,'Assigned Learning Data Dump'!$U:$U,'Completed FEED'!AP$2) -> 0 | AQ3: =SUBTOTAL(9,AN3:AP3) -> 0 | AR3: =COUNTIFS('Assigned Learning Data Dump'!$W:$W,'Completed FEED'!$A3,'Assigned Learning Data Dump'!$F:$F,$A$1,'Assigned Learning Data Dump'!$U:$U,'Completed FEED'!AR$2) -> 0 | AS3: =COUNTIFS('Assigned Learning Data Dump'!$W:$W,'Completed FEED'!$A3,'Assigned Learning Data Dump'!$F:$F,$A$1,'Assigned Learning Data Dump'!$U:$U,'Completed FEED'!AS$2) -> 0 | AT3: =COUNTIFS('Assigned Learning Data Dump'!$W:$W,'Completed FEED'!$A3,'Assigned Learning Data Dump'!$F:$F,$A$1,'Assigned Learning Data Dump'!$U:$U,'Completed FEED'!AT$2) -> 0 | AU3: =SUBTOTAL(9,AR3:AT3) -> 0 | AV3: =COUNTIFS('Assigned Learning Data Dump'!$W:$W,'Completed FEED'!$A3,'Assigned Learning Data Dump'!$F:$F,$A$1,'Assigned Learning Data Dump'!$U:$U,'Completed FEED'!AV$2) -> 0 | AW3: =COUNTIFS('Assigned Learning Data Dump'!$W:$W,'Completed FEED'!$A3,'Assigned Learning Data Dump'!$F:$F,$A$1,'Assigned Learning Data Dump'!$U:$U,'Completed FEED'!AW$2) -> 0 | AX3: =COUNTIFS('Assigned Learning Data Dump'!$W:$W,'Completed FEED'!$A3,'Assigned Learning Data Dump'!$F:$F,$A$1,'Assigned Learning Data Dump'!$U:$U,'Completed FEED'!AX$2) -> 0 | AY3: =SUBTOTAL(9,AV3:AX3) -> 0 | AZ3: =SUBTOTAL(9,AJ3:AY3) -> 0
A4: FFM | B4: =COUNTIFS('Assigned Learning Data Dump'!$W:$W,'Completed FEED'!$A4,'Assigned Learning Data Dump'!$F:$F,$A$1,'Assigned Learning Data Dump'!$U:$U,'Completed FEED'!B$2) -> 2 | C4: =COUNTIFS('Assigned Learning Data Dump'!$W:$W,'Completed FEED'!$A4,'Assigned Learning Data Dump'!$F:$F,$A$1,'Assigned Learning Data Dump'!$U:$U,'Completed FEED'!C$2) -> 0 | D4: =COUNTIFS('Assigned Learning Data Dump'!$W:$W,'Completed FEED'!$A4,'Assigned Learning Data Dump'!$F:$F,$A$1,'Assigned Learning Data Dump'!$U:$U,'Completed FEED'!D$2) -> 0 | E4: =SUBTOTAL(9,B4:D4) -> 2 | F4: =COUNTIFS('Assigned Learning Data Dump'!$W:$W,'Completed FEED'!$A4,'Assigned Learning Data Dump'!$F:$F,$A$1,'Assigned Learning Data Dump'!$U:$U,'Completed FEED'!F$2) -> 0 | G4: =COUNTIFS('Assigned Learning Data Dump'!$W:$W,'Completed FEED'!$A4,'Assigned Learning Data Dump'!$F:$F,$A$1,'Assigned Learning Data Dump'!$U:$U,'Completed FEED'!G$2) -> 0 | H4: =COUNTIFS('Assigned Learning Data Dump'!$W:$W,'Completed FEED'!$A4,'Assigned Learning Data Dump'!$F:$F,$A$1,'Assigned Learning Data Dump'!$U:$U,'Completed FEED'!H$2) -> 0 | I4: =SUBTOTAL(9,F4:H4) -> 0 | J4: =COUNTIFS('Assigned Learning Data Dump'!$W:$W,'Completed FEED'!$A4,'Assigned Learning Data Dump'!$F:$F,$A$1,'Assigned Learning Data Dump'!$U:$U,'Completed FEED'!J$2) -> 0 | K4: =COUNTIFS('Assigned Learning Data Dump'!$W:$W,'Completed FEED'!$A4,'Assigned Learning Data Dump'!$F:$F,$A$1,'Assigned Learning Data Dump'!$U:$U,'Completed FEED'!K$2) -> 0 | L4: =COUNTIFS('Assigned Learning Data Dump'!$W:$W,'Completed FEED'!$A4,'Assigned Learning Data Dump'!$F:$F,$A$1,'Assigned Learning Data Dump'!$U:$U,'Completed FEED'!L$2) -> 0 | M4: =SUBTOTAL(9,J4:L4) -> 0 | N4: =COUNTIFS('Assigned Learning Data Dump'!$W:$W,'Completed FEED'!$A4,'Assigned Learning Data Dump'!$F:$F,$A$1,'Assigned Learning Data Dump'!$U:$U,'Completed FEED'!N$2) -> 1 | O4: =COUNTIFS('Assigned Learning Data Dump'!$W:$W,'Completed FEED'!$A4,'Assigned Learning Data Dump'!$F:$F,$A$1,'Assigned Learning Data Dump'!$U:$U,'Completed FEED'!O$2) -> 0 | P4: =COUNTIFS('Assigned Learning Data Dump'!$W:$W,'Completed FEED'!$A4,'Assigned Learning Data Dump'!$F:$F,$A$1,'Assigned Learning Data Dump'!$U:$U,'Completed FEED'!P$2) -> 0 | Q4: =SUBTOTAL(9,N4:P4) -> 1 | R4: =SUBTOTAL(9,B4:Q4) -> 3 | S4: =COUNTIFS('Assigned Learning Data Dump'!$W:$W,'Completed FEED'!$A4,'Assigned Learning Data Dump'!$F:$F,$A$1,'Assigned Learning Data Dump'!$U:$U,'Completed FEED'!S$2) -> 0 | T4: =COUNTIFS('Assigned Learning Data Dump'!$W:$W,'Completed FEED'!$A4,'Assigned Learning Data Dump'!$F:$F,$A$1,'Assigned Learning Data Dump'!$U:$U,'Completed FEED'!T$2) -> 0 | U4: =COUNTIFS('Assigned Learning Data Dump'!$W:$W,'Completed FEED'!$A4,'Assigned Learning Data Dump'!$F:$F,$A$1,'Assigned Learning Data Dump'!$U:$U,'Completed FEED'!U$2) -> 0 | V4: =SUBTOTAL(9,S4:U4) -> 0 | W4: =COUNTIFS('Assigned Learning Data Dump'!$W:$W,'Completed FEED'!$A4,'Assigned Learning Data Dump'!$F:$F,$A$1,'Assigned Learning Data Dump'!$U:$U,'Completed FEED'!W$2) -> 0 | X4: =COUNTIFS('Assigned Learning Data Dump'!$W:$W,'Completed FEED'!$A4,'Assigned Learning Data Dump'!$F:$F,$A$1,'Assigned Learning Data Dump'!$U:$U,'Completed FEED'!X$2) -> 0 | Y4: =COUNTIFS('Assigned Learning Data Dump'!$W:$W,'Completed FEED'!$A4,'Assigned Learning Data Dump'!$F:$F,$A$1,'Assigned Learning Data Dump'!$U:$U,'Completed FEED'!Y$2) -> 0 | Z4: =SUBTOTAL(9,W4:Y4) -> 0 | AA4: =COUNTIFS('Assigned Learning Data Dump'!$W:$W,'Completed FEED'!$A4,'Assigned Learning Data Dump'!$F:$F,$A$1,'Assigned Learning Data Dump'!$U:$U,'Completed FEED'!AA$2) -> 0 | AB4: =COUNTIFS('Assigned Learning Data Dump'!$W:$W,'Completed FEED'!$A4,'Assigned Learning Data Dump'!$F:$F,$A$1,'Assigned Learning Data Dump'!$U:$U,'Completed FEED'!AB$2) -> 0 | AC4: =COUNTIFS('Assigned Learning Data Dump'!$W:$W,'Completed FEED'!$A4,'Assigned Learning Data Dump'!$F:$F,$A$1,'Assigned Learning Data Dump'!$U:$U,'Completed FEED'!AC$2) -> 0 | AD4: =SUBTOTAL(9,AA4:AC4) -> 0 | AE4: =COUNTIFS('Assigned Learning Data Dump'!$W:$W,'Completed FEED'!$A4,'Assigned Learning Data Dump'!$F:$F,$A$1,'Assigned Learning Data Dump'!$U:$U,'Completed FEED'!AE$2) -> 0 | AF4: =COUNTIFS('Assigned Learning Data Dump'!$W:$W,'Completed FEED'!$A4,'Assigned Learning Data Dump'!$F:$F,$A$1,'Assigned Learning Data Dump'!$U:$U,'Completed FEED'!AF$2) -> 0 | AG4: =COUNTIFS('Assigned Learning Data Dump'!$W:$W,'Completed FEED'!$A4,'Assigned Learning Data Dump'!$F:$F,$A$1,'Assigned Learning Data Dump'!$U:$U,'Completed FEED'!AG$2) -> 0 | AH4: =SUBTOTAL(9,AE4:AG4) -> 0 | AI4: =SUBTOTAL(9,S4:AH4) -> 0 | AJ4: =COUNTIFS('Assigned Learning Data Dump'!$W:$W,'Completed FEED'!$A4,'Assigned Learning Data Dump'!$F:$F,$A$1,'Assigned Learning Data Dump'!$U:$U,'Completed FEED'!AJ$2) -> 0 | AK4: =COUNTIFS('Assigned Learning Data Dump'!$W:$W,'Completed FEED'!$A4,'Assigned Learning Data Dump'!$F:$F,$A$1,'Assigned Learning Data Dump'!$U:$U,'Completed FEED'!AK$2) -> 0 | AL4: =COUNTIFS('Assigned Learning Data Dump'!$W:$W,'Completed FEED'!$A4,'Assigned Learning Data Dump'!$F:$F,$A$1,'Assigned Learning Data Dump'!$U:$U,'Completed FEED'!AL$2) -> 0 | AM4: =SUBTOTAL(9,AJ4:AL4) -> 0 | AN4: =COUNTIFS('Assigned Learning Data Dump'!$W:$W,'Completed FEED'!$A4,'Assigned Learning Data Dump'!$F:$F,$A$1,'Assigned Learning Data Dump'!$U:$U,'Completed FEED'!AN$2) -> 0 | AO4: =COUNTIFS('Assigned Learning Data Dump'!$W:$W,'Completed FEED'!$A4,'Assigned Learning Data Dump'!$F:$F,$A$1,'Assigned Learning Data Dump'!$U:$U,'Completed FEED'!AO$2) -> 0 | AP4: =COUNTIFS('Assigned Learning Data Dump'!$W:$W,'Completed FEED'!$A4,'Assigned Learning Data Dump'!$F:$F,$A$1,'Assigned Learning Data Dump'!$U:$U,'Completed FEED'!AP$2) -> 0 | AQ4: =SUBTOTAL(9,AN4:AP4) -> 0 | AR4: =COUNTIFS('Assigned Learning Data Dump'!$W:$W,'Completed FEED'!$A4,'Assigned Learning Data Dump'!$F:$F,$A$1,'Assigned Learning Data Dump'!$U:$U,'Completed FEED'!AR$2) -> 0 | AS4: =COUNTIFS('Assigned Learning Data Dump'!$W:$W,'Completed FEED'!$A4,'Assigned Learning Data Dump'!$F:$F,$A$1,'Assigned Learning Data Dump'!$U:$U,'Completed FEED'!AS$2) -> 0 | AT4: =COUNTIFS('Assigned Learning Data Dump'!$W:$W,'Completed FEED'!$A4,'Assigned Learning Data Dump'!$F:$F,$A$1,'Assigned Learning Data Dump'!$U:$U,'Completed FEED'!AT$2) -> 0 | AU4: =SUBTOTAL(9,AR4:AT4) -> 0 | AV4: =COUNTIFS('Assigned Learning Data Dump'!$W:$W,'Completed FEED'!$A4,'Assigned Learning Data Dump'!$F:$F,$A$1,'Assigned Learning Data Dump'!$U:$U,'Completed FEED'!AV$2) -> 0 | AW4: =COUNTIFS('Assigned Learning Data Dump'!$W:$W,'Completed FEED'!$A4,'Assigned Learning Data Dump'!$F:$F,$A$1,'Assigned Learning Data Dump'!$U:$U,'Completed FEED'!AW$2) -> 0 | AX4: =COUNTIFS('Assigned Learning Data Dump'!$W:$W,'Completed FEED'!$A4,'Assigned Learning Data Dump'!$F:$F,$A$1,'Assigned Learning Data Dump'!$U:$U,'Completed FEED'!AX$2) -> 0 | AY4: =SUBTOTAL(9,AV4:AX4) -> 0 | AZ4: =SUBTOTAL(9,AJ4:AY4) -> 0
A5: Finance | B5: =COUNTIFS('Assigned Learning Data Dump'!$W:$W,'Completed FEED'!$A5,'Assigned Learning Data Dump'!$F:$F,$A$1,'Assigned Learning Data Dump'!$U:$U,'Completed FEED'!B$2) -> 2 | C5: =COUNTIFS('Assigned Learning Data Dump'!$W:$W,'Completed FEED'!$A5,'Assigned Learning Data Dump'!$F:$F,$A$1,'Assigned Learning Data Dump'!$U:$U,'Completed FEED'!C$2) -> 0 | D5: =COUNTIFS('Assigned Learning Data Dump'!$W:$W,'Completed FEED'!$A5,'Assigned Learning Data Dump'!$F:$F,$A$1,'Assigned Learning Data Dump'!$U:$U,'Completed FEED'!D$2) -> 0 | E5: =SUBTOTAL(9,B5:D5) -> 2 | F5: =COUNTIFS('Assigned Learning Data Dump'!$W:$W,'Completed FEED'!$A5,'Assigned Learning Data Dump'!$F:$F,$A$1,'Assigned Learning Data Dump'!$U:$U,'Completed FEED'!F$2) -> 0 | G5: =COUNTIFS('Assigned Learning Data Dump'!$W:$W,'Completed FEED'!$A5,'Assigned Learning Data Dump'!$F:$F,$A$1,'Assigned Learning Data Dump'!$U:$U,'Completed FEED'!G$2) -> 0 | H5: =COUNTIFS('Assigned Learning Data Dump'!$W:$W,'Completed FEED'!$A5,'Assigned Learning Data Dump'!$F:$F,$A$1,'Assigned Learning Data Dump'!$U:$U,'Completed FEED'!H$2) -> 0 | I5: =SUBTOTAL(9,F5:H5) -> 0 | J5: =COUNTIFS('Assigned Learning Data Dump'!$W:$W,'Completed FEED'!$A5,'Assigned Learning Data Dump'!$F:$F,$A$1,'Assigned Learning Data Dump'!$U:$U,'Completed FEED'!J$2) -> 0 | K5: =COUNTIFS('Assigned Learning Data Dump'!$W:$W,'Completed FEED'!$A5,'Assigned Learning Data Dump'!$F:$F,$A$1,'Assigned Learning Data Dump'!$U:$U,'Completed FEED'!K$2) -> 0 | L5: =COUNTIFS('Assigned Learning Data Dump'!$W:$W,'Completed FEED'!$A5,'Assigned Learning Data Dump'!$F:$F,$A$1,'Assigned Learning Data Dump'!$U:$U,'Completed FEED'!L$2) -> 0 | M5: =SUBTOTAL(9,J5:L5) -> 0 | N5: =COUNTIFS('Assigned Learning Data Dump'!$W:$W,'Completed FEED'!$A5,'Assigned Learning Data Dump'!$F:$F,$A$1,'Assigned Learning Data Dump'!$U:$U,'Completed FEED'!N$2) -> 0 | O5: =COUNTIFS('Assigned Learning Data Dump'!$W:$W,'Completed FEED'!$A5,'Assigned Learning Data Dump'!$F:$F,$A$1,'Assigned Learning Data Dump'!$U:$U,'Completed FEED'!O$2) -> 0 | P5: =COUNTIFS('Assigned Learning Data Dump'!$W:$W,'Completed FEED'!$A5,'Assigned Learning Data Dump'!$F:$F,$A$1,'Assigned Learning Data Dump'!$U:$U,'Completed FEED'!P$2) -> 0 | Q5: =SUBTOTAL(9,N5:P5) -> 0 | R5: =SUBTOTAL(9,B5:Q5) -> 2 | S5: =COUNTIFS('Assigned Learning Data Dump'!$W:$W,'Completed FEED'!$A5,'Assigned Learning Data Dump'!$F:$F,$A$1,'Assigned Learning Data Dump'!$U:$U,'Completed FEED'!S$2) -> 0 | T5: =COUNTIFS('Assigned Learning Data Dump'!$W:$W,'Completed FEED'!$A5,'Assigned Learning Data Dump'!$F:$F,$A$1,'Assigned Learning Data Dump'!$U:$U,'Completed FEED'!T$2) -> 0 | U5: =COUNTIFS('Assigned Learning Data Dump'!$W:$W,'Completed FEED'!$A5,'Assigned Learning Data Dump'!$F:$F,$A$1,'Assigned Learning Data Dump'!$U:$U,'Completed FEED'!U$2) -> 0 | V5: =SUBTOTAL(9,S5:U5) -> 0 | W5: =COUNTIFS('Assigned Learning Data Dump'!$W:$W,'Completed FEED'!$A5,'Assigned Learning Data Dump'!$F:$F,$A$1,'Assigned Learning Data Dump'!$U:$U,'Completed FEED'!W$2) -> 0 | X5: =COUNTIFS('Assigned Learning Data Dump'!$W:$W,'Completed FEED'!$A5,'Assigned Learning Data Dump'!$F:$F,$A$1,'Assigned Learning Data Dump'!$U:$U,'Completed FEED'!X$2) -> 0 | Y5: =COUNTIFS('Assigned Learning Data Dump'!$W:$W,'Completed FEED'!$A5,'Assigned Learning Data Dump'!$F:$F,$A$1,'Assigned Learning Data Dump'!$U:$U,'Completed FEED'!Y$2) -> 0 | Z5: =SUBTOTAL(9,W5:Y5) -> 0 | AA5: =COUNTIFS('Assigned Learning Data Dump'!$W:$W,'Completed FEED'!$A5,'Assigned Learning Data Dump'!$F:$F,$A$1,'Assigned Learning Data Dump'!$U:$U,'Completed FEED'!AA$2) -> 0 | AB5: =COUNTIFS('Assigned Learning Data Dump'!$W:$W,'Completed FEED'!$A5,'Assigned Learning Data Dump'!$F:$F,$A$1,'Assigned Learning Data Dump'!$U:$U,'Completed FEED'!AB$2) -> 0 | AC5: =COUNTIFS('Assigned Learning Data Dump'!$W:$W,'Completed FEED'!$A5,'Assigned Learning Data Dump'!$F:$F,$A$1,'Assigned Learning Data Dump'!$U:$U,'Completed FEED'!AC$2) -> 0 | AD5: =SUBTOTAL(9,AA5:AC5) -> 0 | AE5: =COUNTIFS('Assigned Learning Data Dump'!$W:$W,'Completed FEED'!$A5,'Assigned Learning Data Dump'!$F:$F,$A$1,'Assigned Learning Data Dump'!$U:$U,'Completed FEED'!AE$2) -> 0 | AF5: =COUNTIFS('Assigned Learning Data Dump'!$W:$W,'Completed FEED'!$A5,'Assigned Learning Data Dump'!$F:$F,$A$1,'Assigned Learning Data Dump'!$U:$U,'Completed FEED'!AF$2) -> 3 | AG5: =COUNTIFS('Assigned Learning Data Dump'!$W:$W,'Completed FEED'!$A5,'Assigned Learning Data Dump'!$F:$F,$A$1,'Assigned Learning Data Dump'!$U:$U,'Completed FEED'!AG$2) -> 4 | AH5: =SUBTOTAL(9,AE5:AG5) -> 7 | AI5: =SUBTOTAL(9,S5:AH5) -> 7 | AJ5: =COUNTIFS('Assigned Learning Data Dump'!$W:$W,'Completed FEED'!$A5,'Assigned Learning Data Dump'!$F:$F,$A$1,'Assigned Learning Data Dump'!$U:$U,'Completed FEED'!AJ$2) -> 0 | AK5: =COUNTIFS('Assigned Learning Data Dump'!$W:$W,'Completed FEED'!$A5,'Assigned Learning Data Dump'!$F:$F,$A$1,'Assigned Learning Data Dump'!$U:$U,'Completed FEED'!AK$2) -> 0 | AL5: =COUNTIFS('Assigned Learning Data Dump'!$W:$W,'Completed FEED'!$A5,'Assigned Learning Data Dump'!$F:$F,$A$1,'Assigned Learning Data Dump'!$U:$U,'Completed FEED'!AL$2) -> 0 | AM5: =SUBTOTAL(9,AJ5:AL5) -> 0 | AN5: =COUNTIFS('Assigned Learning Data Dump'!$W:$W,'Completed FEED'!$A5,'Assigned Learning Data Dump'!$F:$F,$A$1,'Assigned Learning Data Dump'!$U:$U,'Completed FEED'!AN$2) -> 0 | AO5: =COUNTIFS('Assigned Learning Data Dump'!$W:$W,'Completed FEED'!$A5,'Assigned Learning Data Dump'!$F:$F,$A$1,'Assigned Learning Data Dump'!$U:$U,'Completed FEED'!AO$2) -> 0 | AP5: =COUNTIFS('Assigned Learning Data Dump'!$W:$W,'Completed FEED'!$A5,'Assigned Learning Data Dump'!$F:$F,$A$1,'Assigned Learning Data Dump'!$U:$U,'Completed FEED'!AP$2) -> 0 | AQ5: =SUBTOTAL(9,AN5:AP5) -> 0 | AR5: =COUNTIFS('Assigned Learning Data Dump'!$W:$W,'Completed FEED'!$A5,'Assigned Learning Data Dump'!$F:$F,$A$1,'Assigned Learning Data Dump'!$U:$U,'Completed FEED'!AR$2) -> 0 | AS5: =COUNTIFS('Assigned Learning Data Dump'!$W:$W,'Completed FEED'!$A5,'Assigned Learning Data Dump'!$F:$F,$A$1,'Assigned Learning Data Dump'!$U:$U,'Completed FEED'!AS$2) -> 0 | AT5: =COUNTIFS('Assigned Learning Data Dump'!$W:$W,'Completed FEED'!$A5,'Assigned Learning Data Dump'!$F:$F,$A$1,'Assigned Learning Data Dump'!$U:$U,'Completed FEED'!AT$2) -> 0 | AU5: =SUBTOTAL(9,AR5:AT5) -> 0 | AV5: =COUNTIFS('Assigned Learning Data Dump'!$W:$W,'Completed FEED'!$A5,'Assigned Learning Data Dump'!$F:$F,$A$1,'Assigned Learning Data Dump'!$U:$U,'Completed FEED'!AV$2) -> 0 | AW5: =COUNTIFS('Assigned Learning Data Dump'!$W:$W,'Completed FEED'!$A5,'Assigned Learning Data Dump'!$F:$F,$A$1,'Assigned Learning Data Dump'!$U:$U,'Completed FEED'!AW$2) -> 0 | AX5: =COUNTIFS('Assigned Learning Data Dump'!$W:$W,'Completed FEED'!$A5,'Assigned Learning Data Dump'!$F:$F,$A$1,'Assigned Learning Data Dump'!$U:$U,'Completed FEED'!AX$2) -> 0 | AY5: =SUBTOTAL(9,AV5:AX5) -> 0 | AZ5: =SUBTOTAL(9,AJ5:AY5) -> 0
A6: Human Resources | B6: =COUNTIFS('Assigned Learning Data Dump'!$W:$W,'Completed FEED'!$A6,'Assigned Learning Data Dump'!$F:$F,$A$1,'Assigned Learning Data Dump'!$U:$U,'Completed FEED'!B$2) -> 12 | C6: =COUNTIFS('Assigned Learning Data Dump'!$W:$W,'Completed FEED'!$A6,'Assigned Learning Data Dump'!$F:$F,$A$1,'Assigned Learning Data Dump'!$U:$U,'Completed FEED'!C$2) -> 0 | D6: =COUNTIFS('Assigned Learning Data Dump'!$W:$W,'Completed FEED'!$A6,'Assigned Learning Data Dump'!$F:$F,$A$1,'Assigned Learning Data Dump'!$U:$U,'Completed FEED'!D$2) -> 61 | E6: =SUBTOTAL(9,B6:D6) -> 73 | F6: =COUNTIFS('Assigned Learning Data Dump'!$W:$W,'Completed FEED'!$A6,'Assigned Learning Data Dump'!$F:$F,$A$1,'Assigned Learning Data Dump'!$U:$U,'Completed FEED'!F$2) -> 0 | G6: =COUNTIFS('Assigned Learning Data Dump'!$W:$W,'Completed FEED'!$A6,'Assigned Learning Data Dump'!$F:$F,$A$1,'Assigned Learning Data Dump'!$U:$U,'Completed FEED'!G$2) -> 0 | H6: =COUNTIFS('Assigned Learning Data Dump'!$W:$W,'Completed FEED'!$A6,'Assigned Learning Data Dump'!$F:$F,$A$1,'Assigned Learning Data Dump'!$U:$U,'Completed FEED'!H$2) -> 8 | I6: =SUBTOTAL(9,F6:H6) -> 8 | J6: =COUNTIFS('Assigned Learning Data Dump'!$W:$W,'Completed FEED'!$A6,'Assigned Learning Data Dump'!$F:$F,$A$1,'Assigned Learning Data Dump'!$U:$U,'Completed FEED'!J$2) -> 1 | K6: =COUNTIFS('Assigned Learning Data Dump'!$W:$W,'Completed FEED'!$A6,'Assigned Learning Data Dump'!$F:$F,$A$1,'Assigned Learning Data Dump'!$U:$U,'Completed FEED'!K$2) -> 8 | L6: =COUNTIFS('Assigned Learning Data Dump'!$W:$W,'Completed FEED'!$A6,'Assigned Learning Data Dump'!$F:$F,$A$1,'Assigned Learning Data Dump'!$U:$U,'Completed FEED'!L$2) -> 1 | M6: =SUBTOTAL(9,J6:L6) -> 10 | N6: =COUNTIFS('Assigned Learning Data Dump'!$W:$W,'Completed FEED'!$A6,'Assigned Learning Data Dump'!$F:$F,$A$1,'Assigned Learning Data Dump'!$U:$U,'Completed FEED'!N$2) -> 1 | O6: =COUNTIFS('Assigned Learning Data Dump'!$W:$W,'Completed FEED'!$A6,'Assigned Learning Data Dump'!$F:$F,$A$1,'Assigned Learning Data Dump'!$U:$U,'Completed FEED'!O$2) -> 4 | P6: =COUNTIFS('Assigned Learning Data Dump'!$W:$W,'Completed FEED'!$A6,'Assigned Learning Data Dump'!$F:$F,$A$1,'Assigned Learning Data Dump'!$U:$U,'Completed FEED'!P$2) -> 9 | Q6: =SUBTOTAL(9,N6:P6) -> 14 | R6: =SUBTOTAL(9,B6:Q6) -> 105 | S6: =COUNTIFS('Assigned Learning Data Dump'!$W:$W,'Completed FEED'!$A6,'Assigned Learning Data Dump'!$F:$F,$A$1,'Assigned Learning Data Dump'!$U:$U,'Completed FEED'!S$2) -> 42 | T6: =COUNTIFS('Assigned Learning Data Dump'!$W:$W,'Completed FEED'!$A6,'Assigned Learning Data Dump'!$F:$F,$A$1,'Assigned Learning Data Dump'!$U:$U,'Completed FEED'!T$2) -> 4 | U6: =COUNTIFS('Assigned Learning Data Dump'!$W:$W,'Completed FEED'!$A6,'Assigned Learning Data Dump'!$F:$F,$A$1,'Assigned Learning Data Dump'!$U:$U,'Completed FEED'!U$2) -> 10 | V6: =SUBTOTAL(9,S6:U6) -> 56 | W6: =COUNTIFS('Assigned Learning Data Dump'!$W:$W,'Completed FEED'!$A6,'Assigned Learning Data Dump'!$F:$F,$A$1,'Assigned Learning Data Dump'!$U:$U,'Completed FEED'!W$2) -> 3 | X6: =COUNTIFS('Assigned Learning Data Dump'!$W:$W,'Completed FEED'!$A6,'Assigned Learning Data Dump'!$F:$F,$A$1,'Assigned Learning Data Dump'!$U:$U,'Completed FEED'!X$2) -> 1 | Y6: =COUNTIFS('Assigned Learning Data Dump'!$W:$W,'Completed FEED'!$A6,'Assigned Learning Data Dump'!$F:$F,$A$1,'Assigned Learning Data Dump'!$U:$U,'Completed FEED'!Y$2) -> 2 | Z6: =SUBTOTAL(9,W6:Y6) -> 6 | AA6: =COUNTIFS('Assigned Learning Data Dump'!$W:$W,'Completed FEED'!$A6,'Assigned Learning Data Dump'!$F:$F,$A$1,'Assigned Learning Data Dump'!$U:$U,'Completed FEED'!AA$2) -> 1 | AB6: =COUNTIFS('Assigned Learning Data Dump'!$W:$W,'Completed FEED'!$A6,'Assigned Learning Data Dump'!$F:$F,$A$1,'Assigned Learning Data Dump'!$U:$U,'Completed FEED'!AB$2) -> 4 | AC6: =COUNTIFS('Assigned Learning Data Dump'!$W:$W,'Completed FEED'!$A6,'Assigned Learning Data Dump'!$F:$F,$A$1,'Assigned Learning Data Dump'!$U:$U,'Completed FEED'!AC$2) -> 3 | AD6: =SUBTOTAL(9,AA6:AC6) -> 8 | AE6: =COUNTIFS('Assigned Learning Data Dump'!$W:$W,'Completed FEED'!$A6,'Assigned Learning Data Dump'!$F:$F,$A$1,'Assigned Learning Data Dump'!$U:$U,'Completed FEED'!AE$2) -> 0 | AF6: =COUNTIFS('Assigned Learning Data Dump'!$W:$W,'Completed FEED'!$A6,'Assigned Learning Data Dump'!$F:$F,$A$1,'Assigned Learning Data Dump'!$U:$U,'Completed FEED'!AF$2) -> 0 | AG6: =COUNTIFS('Assigned Learning Data Dump'!$W:$W,'Completed FEED'!$A6,'Assigned Learning Data Dump'!$F:$F,$A$1,'Assigned Learning Data Dump'!$U:$U,'Completed FEED'!AG$2) -> 0 | AH6: =SUBTOTAL(9,AE6:AG6) -> 0 | AI6: =SUBTOTAL(9,S6:AH6) -> 70 | AJ6: =COUNTIFS('Assigned Learning Data Dump'!$W:$W,'Completed FEED'!$A6,'Assigned Learning Data Dump'!$F:$F,$A$1,'Assigned Learning Data Dump'!$U:$U,'Completed FEED'!AJ$2) -> 0 | AK6: =COUNTIFS('Assigned Learning Data Dump'!$W:$W,'Completed FEED'!$A6,'Assigned Learning Data Dump'!$F:$F,$A$1,'Assigned Learning Data Dump'!$U:$U,'Completed FEED'!AK$2) -> 0 | AL6: =COUNTIFS('Assigned Learning Data Dump'!$W:$W,'Completed FEED'!$A6,'Assigned Learning Data Dump'!$F:$F,$A$1,'Assigned Learning Data Dump'!$U:$U,'Completed FEED'!AL$2) -> 0 | AM6: =SUBTOTAL(9,AJ6:AL6) -> 0 | AN6: =COUNTIFS('Assigned Learning Data Dump'!$W:$W,'Completed FEED'!$A6,'Assigned Learning Data Dump'!$F:$F,$A$1,'Assigned Learning Data Dump'!$U:$U,'Completed FEED'!AN$2) -> 0 | AO6: =COUNTIFS('Assigned Learning Data Dump'!$W:$W,'Completed FEED'!$A6,'Assigned Learning Data Dump'!$F:$F,$A$1,'Assigned Learning Data Dump'!$U:$U,'Completed FEED'!AO$2) -> 0 | AP6: =COUNTIFS('Assigned Learning Data Dump'!$W:$W,'Completed FEED'!$A6,'Assigned Learning Data Dump'!$F:$F,$A$1,'Assigned Learning Data Dump'!$U:$U,'Completed FEED'!AP$2) -> 0 | AQ6: =SUBTOTAL(9,AN6:AP6) -> 0 | AR6: =COUNTIFS('Assigned Learning Data Dump'!$W:$W,'Completed FEED'!$A6,'Assigned Learning Data Dump'!$F:$F,$A$1,'Assigned Learning Data Dump'!$U:$U,'Completed FEED'!AR$2) -> 0 | AS6: =COUNTIFS('Assigned Learning Data Dump'!$W:$W,'Completed FEED'!$A6,'Assigned Learning Data Dump'!$F:$F,$A$1,'Assigned Learning Data Dump'!$U:$U,'Completed FEED'!AS$2) -> 0 | AT6: =COUNTIFS('Assigned Learning Data Dump'!$W:$W,'Completed FEED'!$A6,'Assigned Learning Data Dump'!$F:$F,$A$1,'Assigned Learning Data Dump'!$U:$U,'Completed FEED'!AT$2) -> 0 | AU6: =SUBTOTAL(9,AR6:AT6) -> 0 | AV6: =COUNTIFS('Assigned Learning Data Dump'!$W:$W,'Completed FEED'!$A6,'Assigned Learning Data Dump'!$F:$F,$A$1,'Assigned Learning Data Dump'!$U:$U,'Completed FEED'!AV$2) -> 0 | AW6: =COUNTIFS('Assigned Learning Data Dump'!$W:$W,'Completed FEED'!$A6,'Assigned Learning Data Dump'!$F:$F,$A$1,'Assigned Learning Data Dump'!$U:$U,'Completed FEED'!AW$2) -> 0 | AX6: =COUNTIFS('Assigned Learning Data Dump'!$W:$W,'Completed FEED'!$A6,'Assigned Learning Data Dump'!$F:$F,$A$1,'Assigned Learning Data Dump'!$U:$U,'Completed FEED'!AX$2) -> 0 | AY6: =SUBTOTAL(9,AV6:AX6) -> 0 | AZ6: =SUBTOTAL(9,AJ6:AY6) -> 0
A7: Insights & Analytics | B7: =COUNTIFS('Assigned Learning Data Dump'!$W:$W,'Completed FEED'!$A7,'Assigned Learning Data Dump'!$F:$F,$A$1,'Assigned Learning Data Dump'!$U:$U,'Completed FEED'!B$2) -> 0 | C7: =COUNTIFS('Assigned Learning Data Dump'!$W:$W,'Completed FEED'!$A7,'Assigned Learning Data Dump'!$F:$F,$A$1,'Assigned Learning Data Dump'!$U:$U,'Completed FEED'!C$2) -> 0 | D7: =COUNTIFS('Assigned Learning Data Dump'!$W:$W,'Completed FEED'!$A7,'Assigned Learning Data Dump'!$F:$F,$A$1,'Assigned Learning Data Dump'!$U:$U,'Completed FEED'!D$2) -> 0 | E7: =SUBTOTAL(9,B7:D7) -> 0 | F7: =COUNTIFS('Assigned Learning Data Dump'!$W:$W,'Completed FEED'!$A7,'Assigned Learning Data Dump'!$F:$F,$A$1,'Assigned Learning Data Dump'!$U:$U,'Completed FEED'!F$2) -> 0 | G7: =COUNTIFS('Assigned Learning Data Dump'!$W:$W,'Completed FEED'!$A7,'Assigned Learning Data Dump'!$F:$F,$A$1,'Assigned Learning Data Dump'!$U:$U,'Completed FEED'!G$2) -> 0 | H7: =COUNTIFS('Assigned Learning Data Dump'!$W:$W,'Completed FEED'!$A7,'Assigned Learning Data Dump'!$F:$F,$A$1,'Assigned Learning Data Dump'!$U:$U,'Completed FEED'!H$2) -> 0 | I7: =SUBTOTAL(9,F7:H7) -> 0 | J7: =COUNTIFS('Assigned Learning Data Dump'!$W:$W,'Completed FEED'!$A7,'Assigned Learning Data Dump'!$F:$F,$A$1,'Assigned Learning Data Dump'!$U:$U,'Completed FEED'!J$2) -> 0 | K7: =COUNTIFS('Assigned Learning Data Dump'!$W:$W,'Completed FEED'!$A7,'Assigned Learning Data Dump'!$F:$F,$A$1,'Assigned Learning Data Dump'!$U:$U,'Completed FEED'!K$2) -> 0 | L7: =COUNTIFS('Assigned Learning Data Dump'!$W:$W,'Completed FEED'!$A7,'Assigned Learning Data Dump'!$F:$F,$A$1,'Assigned Learning Data Dump'!$U:$U,'Completed FEED'!L$2) -> 0 | M7: =SUBTOTAL(9,J7:L7) -> 0 | N7: =COUNTIFS('Assigned Learning Data Dump'!$W:$W,'Completed FEED'!$A7,'Assigned Learning Data Dump'!$F:$F,$A$1,'Assigned Learning Data Dump'!$U:$U,'Completed FEED'!N$2) -> 0 | O7: =COUNTIFS('Assigned Learning Data Dump'!$W:$W,'Completed FEED'!$A7,'Assigned Learning Data Dump'!$F:$F,$A$1,'Assigned Learning Data Dump'!$U:$U,'Completed FEED'!O$2) -> 0 | P7: =COUNTIFS('Assigned Learning Data Dump'!$W:$W,'Completed FEED'!$A7,'Assigned Learning Data Dump'!$F:$F,$A$1,'Assigned Learning Data Dump'!$U:$U,'Completed FEED'!P$2) -> 0 | Q7: =SUBTOTAL(9,N7:P7) -> 0 | R7: =SUBTOTAL(9,B7:Q7) -> 0 | S7: =COUNTIFS('Assigned Learning Data Dump'!$W:$W,'Completed FEED'!$A7,'Assigned Learning Data Dump'!$F:$F,$A$1,'Assigned Learning Data Dump'!$U:$U,'Completed FEED'!S$2) -> 0 | T7: =COUNTIFS('Assigned Learning Data Dump'!$W:$W,'Completed FEED'!$A7,'Assigned Learning Data Dump'!$F:$F,$A$1,'Assigned Learning Data Dump'!$U:$U,'Completed FEED'!T$2) -> 0 | U7: =COUNTIFS('Assigned Learning Data Dump'!$W:$W,'Completed FEED'!$A7,'Assigned Learning Data Dump'!$F:$F,$A$1,'Assigned Learning Data Dump'!$U:$U,'Completed FEED'!U$2) -> 0 | V7: =SUBTOTAL(9,S7:U7) -> 0 | W7: =COUNTIFS('Assigned Learning Data Dump'!$W:$W,'Completed FEED'!$A7,'Assigned Learning Data Dump'!$F:$F,$A$1,'Assigned Learning Data Dump'!$U:$U,'Completed FEED'!W$2) -> 0 | X7: =COUNTIFS('Assigned Learning Data Dump'!$W:$W,'Completed FEED'!$A7,'Assigned Learning Data Dump'!$F:$F,$A$1,'Assigned Learning Data Dump'!$U:$U,'Completed FEED'!X$2) -> 0 | Y7: =COUNTIFS('Assigned Learning Data Dump'!$W:$W,'Completed FEED'!$A7,'Assigned Learning Data Dump'!$F:$F,$A$1,'Assigned Learning Data Dump'!$U:$U,'Completed FEED'!Y$2) -> 0 | Z7: =SUBTOTAL(9,W7:Y7) -> 0 | AA7: =COUNTIFS('Assigned Learning Data Dump'!$W:$W,'Completed FEED'!$A7,'Assigned Learning Data Dump'!$F:$F,$A$1,'Assigned Learning Data Dump'!$U:$U,'Completed FEED'!AA$2) -> 0 | AB7: =COUNTIFS('Assigned Learning Data Dump'!$W:$W,'Completed FEED'!$A7,'Assigned Learning Data Dump'!$F:$F,$A$1,'Assigned Learning Data Dump'!$U:$U,'Completed FEED'!AB$2) -> 1 | AC7: =COUNTIFS('Assigned Learning Data Dump'!$W:$W,'Completed FEED'!$A7,'Assigned Learning Data Dump'!$F:$F,$A$1,'Assigned Learning Data Dump'!$U:$U,'Completed FEED'!AC$2) -> 0 | AD7: =SUBTOTAL(9,AA7:AC7) -> 1 | AE7: =COUNTIFS('Assigned Learning Data Dump'!$W:$W,'Completed FEED'!$A7,'Assigned Learning Data Dump'!$F:$F,$A$1,'Assigned Learning Data Dump'!$U:$U,'Completed FEED'!AE$2) -> 0 | AF7: =COUNTIFS('Assigned Learning Data Dump'!$W:$W,'Completed FEED'!$A7,'Assigned Learning Data Dump'!$F:$F,$A$1,'Assigned Learning Data Dump'!$U:$U,'Completed FEED'!AF$2) -> 2 | AG7: =COUNTIFS('Assigned Learning Data Dump'!$W:$W,'Completed FEED'!$A7,'Assigned Learning Data Dump'!$F:$F,$A$1,'Assigned Learning Data Dump'!$U:$U,'Completed FEED'!AG$2) -> 0 | AH7: =SUBTOTAL(9,AE7:AG7) -> 2 | AI7: =SUBTOTAL(9,S7:AH7) -> 3 | AJ7: =COUNTIFS('Assigned Learning Data Dump'!$W:$W,'Completed FEED'!$A7,'Assigned Learning Data Dump'!$F:$F,$A$1,'Assigned Learning Data Dump'!$U:$U,'Completed FEED'!AJ$2) -> 0 | AK7: =COUNTIFS('Assigned Learning Data Dump'!$W:$W,'Completed FEED'!$A7,'Assigned Learning Data Dump'!$F:$F,$A$1,'Assigned Learning Data Dump'!$U:$U,'Completed FEED'!AK$2) -> 0 | AL7: =COUNTIFS('Assigned Learning Data Dump'!$W:$W,'Completed FEED'!$A7,'Assigned Learning Data Dump'!$F:$F,$A$1,'Assigned Learning Data Dump'!$U:$U,'Completed FEED'!AL$2) -> 0 | AM7: =SUBTOTAL(9,AJ7:AL7) -> 0 | AN7: =COUNTIFS('Assigned Learning Data Dump'!$W:$W,'Completed FEED'!$A7,'Assigned Learning Data Dump'!$F:$F,$A$1,'Assigned Learning Data Dump'!$U:$U,'Completed FEED'!AN$2) -> 0 | AO7: =COUNTIFS('Assigned Learning Data Dump'!$W:$W,'Completed FEED'!$A7,'Assigned Learning Data Dump'!$F:$F,$A$1,'Assigned Learning Data Dump'!$U:$U,'Completed FEED'!AO$2) -> 0 | AP7: =COUNTIFS('Assigned Learning Data Dump'!$W:$W,'Completed FEED'!$A7,'Assigned Learning Data Dump'!$F:$F,$A$1,'Assigned Learning Data Dump'!$U:$U,'Completed FEED'!AP$2) -> 0 | AQ7: =SUBTOTAL(9,AN7:AP7) -> 0 | AR7: =COUNTIFS('Assigned Learning Data Dump'!$W:$W,'Completed FEED'!$A7,'Assigned Learning Data Dump'!$F:$F,$A$1,'Assigned Learning Data Dump'!$U:$U,'Completed FEED'!AR$2) -> 0 | AS7: =COUNTIFS('Assigned Learning Data Dump'!$W:$W,'Completed FEED'!$A7,'Assigned Learning Data Dump'!$F:$F,$A$1,'Assigned Learning Data Dump'!$U:$U,'Completed FEED'!AS$2) -> 0 | AT7: =COUNTIFS('Assigned Learning Data Dump'!$W:$W,'Completed FEED'!$A7,'Assigned Learning Data Dump'!$F:$F,$A$1,'Assigned Learning Data Dump'!$U:$U,'Completed FEED'!AT$2) -> 0 | AU7: =SUBTOTAL(9,AR7:AT7) -> 0 | AV7: =COUNTIFS('Assigned Learning Data Dump'!$W:$W,'Completed FEED'!$A7,'Assigned Learning Data Dump'!$F:$F,$A$1,'Assigned Learning Data Dump'!$U:$U,'Completed FEED'!AV$2) -> 0 | AW7: =COUNTIFS('Assigned Learning Data Dump'!$W:$W,'Completed FEED'!$A7,'Assigned Learning Data Dump'!$F:$F,$A$1,'Assigned Learning Data Dump'!$U:$U,'Completed FEED'!AW$2) -> 0 | AX7: =COUNTIFS('Assigned Learning Data Dump'!$W:$W,'Completed FEED'!$A7,'Assigned Learning Data Dump'!$F:$F,$A$1,'Assigned Learning Data Dump'!$U:$U,'Completed FEED'!AX$2) -> 0 | AY7: =SUBTOTAL(9,AV7:AX7) -> 0 | AZ7: =SUBTOTAL(9,AJ7:AY7) -> 0
A8: IT | B8: =COUNTIFS('Assigned Learning Data Dump'!$W:$W,'Completed FEED'!$A8,'Assigned Learning Data Dump'!$F:$F,$A$1,'Assigned Learning Data Dump'!$U:$U,'Completed FEED'!B$2) -> 7 | C8: =COUNTIFS('Assigned Learning Data Dump'!$W:$W,'Completed FEED'!$A8,'Assigned Learning Data Dump'!$F:$F,$A$1,'Assigned Learning Data Dump'!$U:$U,'Completed FEED'!C$2) -> 11 | D8: =COUNTIFS('Assigned Learning Data Dump'!$W:$W,'Completed FEED'!$A8,'Assigned Learning Data Dump'!$F:$F,$A$1,'Assigned Learning Data Dump'!$U:$U,'Completed FEED'!D$2) -> 4 | E8: =SUBTOTAL(9,B8:D8) -> 22 | F8: =COUNTIFS('Assigned Learning Data Dump'!$W:$W,'Completed FEED'!$A8,'Assigned Learning Data Dump'!$F:$F,$A$1,'Assigned Learning Data Dump'!$U:$U,'Completed FEED'!F$2) -> 7 | G8: =COUNTIFS('Assigned Learning Data Dump'!$W:$W,'Completed FEED'!$A8,'Assigned Learning Data Dump'!$F:$F,$A$1,'Assigned Learning Data Dump'!$U:$U,'Completed FEED'!G$2) -> 2 | H8: =COUNTIFS('Assigned Learning Data Dump'!$W:$W,'Completed FEED'!$A8,'Assigned Learning Data Dump'!$F:$F,$A$1,'Assigned Learning Data Dump'!$U:$U,'Completed FEED'!H$2) -> 0 | I8: =SUBTOTAL(9,F8:H8) -> 9 | J8: =COUNTIFS('Assigned Learning Data Dump'!$W:$W,'Completed FEED'!$A8,'Assigned Learning Data Dump'!$F:$F,$A$1,'Assigned Learning Data Dump'!$U:$U,'Completed FEED'!J$2) -> 1 | K8: =COUNTIFS('Assigned Learning Data Dump'!$W:$W,'Completed FEED'!$A8,'Assigned Learning Data Dump'!$F:$F,$A$1,'Assigned Learning Data Dump'!$U:$U,'Completed FEED'!K$2) -> 2 | L8: =COUNTIFS('Assigned Learning Data Dump'!$W:$W,'Completed FEED'!$A8,'Assigned Learning Data Dump'!$F:$F,$A$1,'Assigned Learning Data Dump'!$U:$U,'Completed FEED'!L$2) -> 0 | M8: =SUBTOTAL(9,J8:L8) -> 3 | N8: =COUNTIFS('Assigned Learning Data Dump'!$W:$W,'Completed FEED'!$A8,'Assigned Learning Data Dump'!$F:$F,$A$1,'Assigned Learning Data Dump'!$U:$U,'Completed FEED'!N$2) -> 4 | O8: =COUNTIFS('Assigned Learning Data Dump'!$W:$W,'Completed FEED'!$A8,'Assigned Learning Data Dump'!$F:$F,$A$1,'Assigned Learning Data Dump'!$U:$U,'Completed FEED'!O$2) -> 4 | P8: =COUNTIFS('Assigned Learning Data Dump'!$W:$W,'Completed FEED'!$A8,'Assigned Learning Data Dump'!$F:$F,$A$1,'Assigned Learning Data Dump'!$U:$U,'Completed FEED'!P$2) -> 15 | Q8: =SUBTOTAL(9,N8:P8) -> 23 | R8: =SUBTOTAL(9,B8:Q8) -> 57 | S8: =COUNTIFS('Assigned Learning Data Dump'!$W:$W,'Completed FEED'!$A8,'Assigned Learning Data Dump'!$F:$F,$A$1,'Assigned Learning Data Dump'!$U:$U,'Completed FEED'!S$2) -> 0 | T8: =COUNTIFS('Assigned Learning Data Dump'!$W:$W,'Completed FEED'!$A8,'Assigned Learning Data Dump'!$F:$F,$A$1,'Assigned Learning Data Dump'!$U:$U,'Completed FEED'!T$2) -> 1 | U8: =COUNTIFS('Assigned Learning Data Dump'!$W:$W,'Completed FEED'!$A8,'Assigned Learning Data Dump'!$F:$F,$A$1,'Assigned Learning Data Dump'!$U:$U,'Completed FEED'!U$2) -> 2 | V8: =SUBTOTAL(9,S8:U8) -> 3 | W8: =COUNTIFS('Assigned Learning Data Dump'!$W:$W,'Completed FEED'!$A8,'Assigned Learning Data Dump'!$F:$F,$A$1,'Assigned Learning Data Dump'!$U:$U,'Completed FEED'!W$2) -> 0 | X8: =COUNTIFS('Assigned Learning Data Dump'!$W:$W,'Completed FEED'!$A8,'Assigned Learning Data Dump'!$F:$F,$A$1,'Assigned Learning Data Dump'!$U:$U,'Completed FEED'!X$2) -> 1 | Y8: =COUNTIFS('Assigned Learning Data Dump'!$W:$W,'Completed FEED'!$A8,'Assigned Learning Data Dump'!$F:$F,$A$1,'Assigned Learning Data Dump'!$U:$U,'Completed FEED'!Y$2) -> 0 | Z8: =SUBTOTAL(9,W8:Y8) -> 1 | AA8: =COUNTIFS('Assigned Learning Data Dump'!$W:$W,'Completed FEED'!$A8,'Assigned Learning Data Dump'!$F:$F,$A$1,'Assigned Learning Data Dump'!$U:$U,'Completed FEED'!AA$2) -> 0 | AB8: =COUNTIFS('Assigned Learning Data Dump'!$W:$W,'Completed FEED'!$A8,'Assigned Learning Data Dump'!$F:$F,$A$1,'Assigned Learning Data Dump'!$U:$U,'Completed FEED'!AB$2) -> 2 | AC8: =COUNTIFS('Assigned Learning Data Dump'!$W:$W,'Completed FEED'!$A8,'Assigned Learning Data Dump'!$F:$F,$A$1,'Assigned Learning Data Dump'!$U:$U,'Completed FEED'!AC$2) -> 0 | AD8: =SUBTOTAL(9,AA8:AC8) -> 2 | AE8: =COUNTIFS('Assigned Learning Data Dump'!$W:$W,'Completed FEED'!$A8,'Assigned Learning Data Dump'!$F:$F,$A$1,'Assigned Learning Data Dump'!$U:$U,'Completed FEED'!AE$2) -> 0 | AF8: =COUNTIFS('Assigned Learning Data Dump'!$W:$W,'Completed FEED'!$A8,'Assigned Learning Data Dump'!$F:$F,$A$1,'Assigned Learning Data Dump'!$U:$U,'Completed FEED'!AF$2) -> 0 | AG8: =COUNTIFS('Assigned Learning Data Dump'!$W:$W,'Completed FEED'!$A8,'Assigned Learning Data Dump'!$F:$F,$A$1,'Assigned Learning Data Dump'!$U:$U,'Completed FEED'!AG$2) -> 0 | AH8: =SUBTOTAL(9,AE8:AG8) -> 0 | AI8: =SUBTOTAL(9,S8:AH8) -> 6 | AJ8: =COUNTIFS('Assigned Learning Data Dump'!$W:$W,'Completed FEED'!$A8,'Assigned Learning Data Dump'!$F:$F,$A$1,'Assigned Learning Data Dump'!$U:$U,'Completed FEED'!AJ$2) -> 0 | AK8: =COUNTIFS('Assigned Learning Data Dump'!$W:$W,'Completed FEED'!$A8,'Assigned Learning Data Dump'!$F:$F,$A$1,'Assigned Learning Data Dump'!$U:$U,'Completed FEED'!AK$2) -> 0 | AL8: =COUNTIFS('Assigned Learning Data Dump'!$W:$W,'Completed FEED'!$A8,'Assigned Learning Data Dump'!$F:$F,$A$1,'Assigned Learning Data Dump'!$U:$U,'Completed FEED'!AL$2) -> 0 | AM8: =SUBTOTAL(9,AJ8:AL8) -> 0 | AN8: =COUNTIFS('Assigned Learning Data Dump'!$W:$W,'Completed FEED'!$A8,'Assigned Learning Data Dump'!$F:$F,$A$1,'Assigned Learning Data Dump'!$U:$U,'Completed FEED'!AN$2) -> 0 | AO8: =COUNTIFS('Assigned Learning Data Dump'!$W:$W,'Completed FEED'!$A8,'Assigned Learning Data Dump'!$F:$F,$A$1,'Assigned Learning Data Dump'!$U:$U,'Completed FEED'!AO$2) -> 0 | AP8: =COUNTIFS('Assigned Learning Data Dump'!$W:$W,'Completed FEED'!$A8,'Assigned Learning Data Dump'!$F:$F,$A$1,'Assigned Learning Data Dump'!$U:$U,'Completed FEED'!AP$2) -> 0 | AQ8: =SUBTOTAL(9,AN8:AP8) -> 0 | AR8: =COUNTIFS('Assigned Learning Data Dump'!$W:$W,'Completed FEED'!$A8,'Assigned Learning Data Dump'!$F:$F,$A$1,'Assigned Learning Data Dump'!$U:$U,'Completed FEED'!AR$2) -> 0 | AS8: =COUNTIFS('Assigned Learning Data Dump'!$W:$W,'Completed FEED'!$A8,'Assigned Learning Data Dump'!$F:$F,$A$1,'Assigned Learning Data Dump'!$U:$U,'Completed FEED'!AS$2) -> 0 | AT8: =COUNTIFS('Assigned Learning Data Dump'!$W:$W,'Completed FEED'!$A8,'Assigned Learning Data Dump'!$F:$F,$A$1,'Assigned Learning Data Dump'!$U:$U,'Completed FEED'!AT$2) -> 0 | AU8: =SUBTOTAL(9,AR8:AT8) -> 0 | AV8: =COUNTIFS('Assigned Learning Data Dump'!$W:$W,'Completed FEED'!$A8,'Assigned Learning Data Dump'!$F:$F,$A$1,'Assigned Learning Data Dump'!$U:$U,'Completed FEED'!AV$2) -> 0 | AW8: =COUNTIFS('Assigned Learning Data Dump'!$W:$W,'Completed FEED'!$A8,'Assigned Learning Data Dump'!$F:$F,$A$1,'Assigned Learning Data Dump'!$U:$U,'Completed FEED'!AW$2) -> 0 | AX8: =COUNTIFS('Assigned Learning Data Dump'!$W:$W,'Completed FEED'!$A8,'Assigned Learning Data Dump'!$F:$F,$A$1,'Assigned Learning Data Dump'!$U:$U,'Completed FEED'!AX$2) -> 0 | AY8: =SUBTOTAL(9,AV8:AX8) -> 0 | AZ8: =SUBTOTAL(9,AJ8:AY8) -> 0
A9: Marketing | B9: =COUNTIFS('Assigned Learning Data Dump'!$W:$W,'Completed FEED'!$A9,'Assigned Learning Data Dump'!$F:$F,$A$1,'Assigned Learning Data Dump'!$U:$U,'Completed FEED'!B$2) -> 3 | C9: =COUNTIFS('Assigned Learning Data Dump'!$W:$W,'Completed FEED'!$A9,'Assigned Learning Data Dump'!$F:$F,$A$1,'Assigned Learning Data Dump'!$U:$U,'Completed FEED'!C$2) -> 0 | D9: =COUNTIFS('Assigned Learning Data Dump'!$W:$W,'Completed FEED'!$A9,'Assigned Learning Data Dump'!$F:$F,$A$1,'Assigned Learning Data Dump'!$U:$U,'Completed FEED'!D$2) -> 0 | E9: =SUBTOTAL(9,B9:D9) -> 3 | F9: =COUNTIFS('Assigned Learning Data Dump'!$W:$W,'Completed FEED'!$A9,'Assigned Learning Data Dump'!$F:$F,$A$1,'Assigned Learning Data Dump'!$U:$U,'Completed FEED'!F$2) -> 2 | G9: =COUNTIFS('Assigned Learning Data Dump'!$W:$W,'Completed FEED'!$A9,'Assigned Learning Data Dump'!$F:$F,$A$1,'Assigned Learning Data Dump'!$U:$U,'Completed FEED'!G$2) -> 0 | H9: =COUNTIFS('Assigned Learning Data Dump'!$W:$W,'Completed FEED'!$A9,'Assigned Learning Data Dump'!$F:$F,$A$1,'Assigned Learning Data Dump'!$U:$U,'Completed FEED'!H$2) -> 0 | I9: =SUBTOTAL(9,F9:H9) -> 2 | J9: =COUNTIFS('Assigned Learning Data Dump'!$W:$W,'Completed FEED'!$A9,'Assigned Learning Data Dump'!$F:$F,$A$1,'Assigned Learning Data Dump'!$U:$U,'Completed FEED'!J$2) -> 0 | K9: =COUNTIFS('Assigned Learning Data Dump'!$W:$W,'Completed FEED'!$A9,'Assigned Learning Data Dump'!$F:$F,$A$1,'Assigned Learning Data Dump'!$U:$U,'Completed FEED'!K$2) -> 0 | L9: =COUNTIFS('Assigned Learning Data Dump'!$W:$W,'Completed FEED'!$A9,'Assigned Learning Data Dump'!$F:$F,$A$1,'Assigned Learning Data Dump'!$U:$U,'Completed FEED'!L$2) -> 0 | M9: =SUBTOTAL(9,J9:L9) -> 0 | N9: =COUNTIFS('Assigned Learning Data Dump'!$W:$W,'Completed FEED'!$A9,'Assigned Learning Data Dump'!$F:$F,$A$1,'Assigned Learning Data Dump'!$U:$U,'Completed FEED'!N$2) -> 0 | O9: =COUNTIFS('Assigned Learning Data Dump'!$W:$W,'Completed FEED'!$A9,'Assigned Learning Data Dump'!$F:$F,$A$1,'Assigned Learning Data Dump'!$U:$U,'Completed FEED'!O$2) -> 7 | P9: =COUNTIFS('Assigned Learning Data Dump'!$W:$W,'Completed FEED'!$A9,'Assigned Learning Data Dump'!$F:$F,$A$1,'Assigned Learning Data Dump'!$U:$U,'Completed FEED'!P$2) -> 4 | Q9: =SUBTOTAL(9,N9:P9) -> 11 | R9: =SUBTOTAL(9,B9:Q9) -> 16 | S9: =COUNTIFS('Assigned Learning Data Dump'!$W:$W,'Completed FEED'!$A9,'Assigned Learning Data Dump'!$F:$F,$A$1,'Assigned Learning Data Dump'!$U:$U,'Completed FEED'!S$2) -> 0 | T9: =COUNTIFS('Assigned Learning Data Dump'!$W:$W,'Completed FEED'!$A9,'Assigned Learning Data Dump'!$F:$F,$A$1,'Assigned Learning Data Dump'!$U:$U,'Completed FEED'!T$2) -> 6 | U9: =COUNTIFS('Assigned Learning Data Dump'!$W:$W,'Completed FEED'!$A9,'Assigned Learning Data Dump'!$F:$F,$A$1,'Assigned Learning Data Dump'!$U:$U,'Completed FEED'!U$2) -> 0 | V9: =SUBTOTAL(9,S9:U9) -> 6 | W9: =COUNTIFS('Assigned Learning Data Dump'!$W:$W,'Completed FEED'!$A9,'Assigned Learning Data Dump'!$F:$F,$A$1,'Assigned Learning Data Dump'!$U:$U,'Completed FEED'!W$2) -> 0 | X9: =COUNTIFS('Assigned Learning Data Dump'!$W:$W,'Completed FEED'!$A9,'Assigned Learning Data Dump'!$F:$F,$A$1,'Assigned Learning Data Dump'!$U:$U,'Completed FEED'!X$2) -> 0 | Y9: =COUNTIFS('Assigned Learning Data Dump'!$W:$W,'Completed FEED'!$A9,'Assigned Learning Data Dump'!$F:$F,$A$1,'Assigned Learning Data Dump'!$U:$U,'Completed FEED'!Y$2) -> 0 | Z9: =SUBTOTAL(9,W9:Y9) -> 0 | AA9: =COUNTIFS('Assigned Learning Data Dump'!$W:$W,'Completed FEED'!$A9,'Assigned Learning Data Dump'!$F:$F,$A$1,'Assigned Learning Data Dump'!$U:$U,'Completed FEED'!AA$2) -> 0 | AB9: =COUNTIFS('Assigned Learning Data Dump'!$W:$W,'Completed FEED'!$A9,'Assigned Learning Data Dump'!$F:$F,$A$1,'Assigned Learning Data Dump'!$U:$U,'Completed FEED'!AB$2) -> 0 | AC9: =COUNTIFS('Assigned Learning Data Dump'!$W:$W,'Completed FEED'!$A9,'Assigned Learning Data Dump'!$F:$F,$A$1,'Assigned Learning Data Dump'!$U:$U,'Completed FEED'!AC$2) -> 2 | AD9: =SUBTOTAL(9,AA9:AC9) -> 2 | AE9: =COUNTIFS('Assigned Learning Data Dump'!$W:$W,'Completed FEED'!$A9,'Assigned Learning Data Dump'!$F:$F,$A$1,'Assigned Learning Data Dump'!$U:$U,'Completed FEED'!AE$2) -> 0 | AF9: =COUNTIFS('Assigned Learning Data Dump'!$W:$W,'Completed FEED'!$A9,'Assigned Learning Data Dump'!$F:$F,$A$1,'Assigned Learning Data Dump'!$U:$U,'Completed FEED'!AF$2) -> 4 | AG9: =COUNTIFS('Assigned Learning Data Dump'!$W:$W,'Completed FEED'!$A9,'Assigned Learning Data Dump'!$F:$F,$A$1,'Assigned Learning Data Dump'!$U:$U,'Completed FEED'!AG$2) -> 0 | AH9: =SUBTOTAL(9,AE9:AG9) -> 4 | AI9: =SUBTOTAL(9,S9:AH9) -> 12 | AJ9: =COUNTIFS('Assigned Learning Data Dump'!$W:$W,'Completed FEED'!$A9,'Assigned Learning Data Dump'!$F:$F,$A$1,'Assigned Learning Data Dump'!$U:$U,'Completed FEED'!AJ$2) -> 0 | AK9: =COUNTIFS('Assigned Learning Data Dump'!$W:$W,'Completed FEED'!$A9,'Assigned Learning Data Dump'!$F:$F,$A$1,'Assigned Learning Data Dump'!$U:$U,'Completed FEED'!AK$2) -> 0 | AL9: =COUNTIFS('Assigned Learning Data Dump'!$W:$W,'Completed FEED'!$A9,'Assigned Learning Data Dump'!$F:$F,$A$1,'Assigned Learning Data Dump'!$U:$U,'Completed FEED'!AL$2) -> 0 | AM9: =SUBTOTAL(9,AJ9:AL9) -> 0 | AN9: =COUNTIFS('Assigned Learning Data Dump'!$W:$W,'Completed FEED'!$A9,'Assigned Learning Data Dump'!$F:$F,$A$1,'Assigned Learning Data Dump'!$U:$U,'Completed FEED'!AN$2) -> 0 | AO9: =COUNTIFS('Assigned Learning Data Dump'!$W:$W,'Completed FEED'!$A9,'Assigned Learning Data Dump'!$F:$F,$A$1,'Assigned Learning Data Dump'!$U:$U,'Completed FEED'!AO$2) -> 0 | AP9: =COUNTIFS('Assigned Learning Data Dump'!$W:$W,'Completed FEED'!$A9,'Assigned Learning Data Dump'!$F:$F,$A$1,'Assigned Learning Data Dump'!$U:$U,'Completed FEED'!AP$2) -> 0 | AQ9: =SUBTOTAL(9,AN9:AP9) -> 0 | AR9: =COUNTIFS('Assigned Learning Data Dump'!$W:$W,'Completed FEED'!$A9,'Assigned Learning Data Dump'!$F:$F,$A$1,'Assigned Learning Data Dump'!$U:$U,'Completed FEED'!AR$2) -> 0 | AS9: =COUNTIFS('Assigned Learning Data Dump'!$W:$W,'Completed FEED'!$A9,'Assigned Learning Data Dump'!$F:$F,$A$1,'Assigned Learning Data Dump'!$U:$U,'Completed FEED'!AS$2) -> 0 | AT9: =COUNTIFS('Assigned Learning Data Dump'!$W:$W,'Completed FEED'!$A9,'Assigned Learning Data Dump'!$F:$F,$A$1,'Assigned Learning Data Dump'!$U:$U,'Completed FEED'!AT$2) -> 0 | AU9: =SUBTOTAL(9,AR9:AT9) -> 0 | AV9: =COUNTIFS('Assigned Learning Data Dump'!$W:$W,'Completed FEED'!$A9,'Assigned Learning Data Dump'!$F:$F,$A$1,'Assigned Learning Data Dump'!$U:$U,'Completed FEED'!AV$2) -> 0 | AW9: =COUNTIFS('Assigned Learning Data Dump'!$W:$W,'Completed FEED'!$A9,'Assigned Learning Data Dump'!$F:$F,$A$1,'Assigned Learning Data Dump'!$U:$U,'Completed FEED'!AW$2) -> 0 | AX9: =COUNTIFS('Assigned Learning Data Dump'!$W:$W,'Completed FEED'!$A9,'Assigned Learning Data Dump'!$F:$F,$A$1,'Assigned Learning Data Dump'!$U:$U,'Completed FEED'!AX$2) -> 0 | AY9: =SUBTOTAL(9,AV9:AX9) -> 0 | AZ9: =SUBTOTAL(9,AJ9:AY9) -> 0
A10: Property and Store Development | B10: =COUNTIFS('Assigned Learning Data Dump'!$W:$W,'Completed FEED'!$A10,'Assigned Learning Data Dump'!$F:$F,$A$1,'Assigned Learning Data Dump'!$U:$U,'Completed FEED'!B$2) -> 2 | C10: =COUNTIFS('Assigned Learning Data Dump'!$W:$W,'Completed FEED'!$A10,'Assigned Learning Data Dump'!$F:$F,$A$1,'Assigned Learning Data Dump'!$U:$U,'Completed FEED'!C$2) -> 1 | D10: =COUNTIFS('Assigned Learning Data Dump'!$W:$W,'Completed FEED'!$A10,'Assigned Learning Data Dump'!$F:$F,$A$1,'Assigned Learning Data Dump'!$U:$U,'Completed FEED'!D$2) -> 0 | E10: =SUBTOTAL(9,B10:D10) -> 3 | F10: =COUNTIFS('Assigned Learning Data Dump'!$W:$W,'Completed FEED'!$A10,'Assigned Learning Data Dump'!$F:$F,$A$1,'Assigned Learning Data Dump'!$U:$U,'Completed FEED'!F$2) -> 0 | G10: =COUNTIFS('Assigned Learning Data Dump'!$W:$W,'Completed FEED'!$A10,'Assigned Learning Data Dump'!$F:$F,$A$1,'Assigned Learning Data Dump'!$U:$U,'Completed FEED'!G$2) -> 0 | H10: =COUNTIFS('Assigned Learning Data Dump'!$W:$W,'Completed FEED'!$A10,'Assigned Learning Data Dump'!$F:$F,$A$1,'Assigned Learning Data Dump'!$U:$U,'Completed FEED'!H$2) -> 1 | I10: =SUBTOTAL(9,F10:H10) -> 1 | J10: =COUNTIFS('Assigned Learning Data Dump'!$W:$W,'Completed FEED'!$A10,'Assigned Learning Data Dump'!$F:$F,$A$1,'Assigned Learning Data Dump'!$U:$U,'Completed FEED'!J$2) -> 1 | K10: =COUNTIFS('Assigned Learning Data Dump'!$W:$W,'Completed FEED'!$A10,'Assigned Learning Data Dump'!$F:$F,$A$1,'Assigned Learning Data Dump'!$U:$U,'Completed FEED'!K$2) -> 1 | L10: =COUNTIFS('Assigned Learning Data Dump'!$W:$W,'Completed FEED'!$A10,'Assigned Learning Data Dump'!$F:$F,$A$1,'Assigned Learning Data Dump'!$U:$U,'Completed FEED'!L$2) -> 0 | M10: =SUBTOTAL(9,J10:L10) -> 2 | N10: =COUNTIFS('Assigned Learning Data Dump'!$W:$W,'Completed FEED'!$A10,'Assigned Learning Data Dump'!$F:$F,$A$1,'Assigned Learning Data Dump'!$U:$U,'Completed FEED'!N$2) -> 2 | O10: =COUNTIFS('Assigned Learning Data Dump'!$W:$W,'Completed FEED'!$A10,'Assigned Learning Data Dump'!$F:$F,$A$1,'Assigned Learning Data Dump'!$U:$U,'Completed FEED'!O$2) -> 0 | P10: =COUNTIFS('Assigned Learning Data Dump'!$W:$W,'Completed FEED'!$A10,'Assigned Learning Data Dump'!$F:$F,$A$1,'Assigned Learning Data Dump'!$U:$U,'Completed FEED'!P$2) -> 2 | Q10: =SUBTOTAL(9,N10:P10) -> 4 | R10: =SUBTOTAL(9,B10:Q10) -> 10 | S10: =COUNTIFS('Assigned Learning Data Dump'!$W:$W,'Completed FEED'!$A10,'Assigned Learning Data Dump'!$F:$F,$A$1,'Assigned Learning Data Dump'!$U:$U,'Completed FEED'!S$2) -> 7 | T10: =COUNTIFS('Assigned Learning Data Dump'!$W:$W,'Completed FEED'!$A10,'Assigned Learning Data Dump'!$F:$F,$A$1,'Assigned Learning Data Dump'!$U:$U,'Completed FEED'!T$2) -> 1 | U10: =COUNTIFS('Assigned Learning Data Dump'!$W:$W,'Completed FEED'!$A10,'Assigned Learning Data Dump'!$F:$F,$A$1,'Assigned Learning Data Dump'!$U:$U,'Completed FEED'!U$2) -> 0 | V10: =SUBTOTAL(9,S10:U10) -> 8 | W10: =COUNTIFS('Assigned Learning Data Dump'!$W:$W,'Completed FEED'!$A10,'Assigned Learning Data Dump'!$F:$F,$A$1,'Assigned Learning Data Dump'!$U:$U,'Completed FEED'!W$2) -> 0 | X10: =COUNTIFS('Assigned Learning Data Dump'!$W:$W,'Completed FEED'!$A10,'Assigned Learning Data Dump'!$F:$F,$A$1,'Assigned Learning Data Dump'!$U:$U,'Completed FEED'!X$2) -> 0 | Y10: =COUNTIFS('Assigned Learning Data Dump'!$W:$W,'Completed FEED'!$A10,'Assigned Learning Data Dump'!$F:$F,$A$1,'Assigned Learning Data Dump'!$U:$U,'Completed FEED'!Y$2) -> 0 | Z10: =SUBTOTAL(9,W10:Y10) -> 0 | AA10: =COUNTIFS('Assigned Learning Data Dump'!$W:$W,'Completed FEED'!$A10,'Assigned Learning Data Dump'!$F:$F,$A$1,'Assigned Learning Data Dump'!$U:$U,'Completed FEED'!AA$2) -> 2 | AB10: =COUNTIFS('Assigned Learning Data Dump'!$W:$W,'Completed FEED'!$A10,'Assigned Learning Data Dump'!$F:$F,$A$1,'Assigned Learning Data Dump'!$U:$U,'Completed FEED'!AB$2) -> 0 | AC10: =COUNTIFS('Assigned Learning Data Dump'!$W:$W,'Completed FEED'!$A10,'Assigned Learning Data Dump'!$F:$F,$A$1,'Assigned Learning Data Dump'!$U:$U,'Completed FEED'!AC$2) -> 0 | AD10: =SUBTOTAL(9,AA10:AC10) -> 2 | AE10: =COUNTIFS('Assigned Learning Data Dump'!$W:$W,'Completed FEED'!$A10,'Assigned Learning Data Dump'!$F:$F,$A$1,'Assigned Learning Data Dump'!$U:$U,'Completed FEED'!AE$2) -> 1 | AF10: =COUNTIFS('Assigned Learning Data Dump'!$W:$W,'Completed FEED'!$A10,'Assigned Learning Data Dump'!$F:$F,$A$1,'Assigned Learning Data Dump'!$U:$U,'Completed FEED'!AF$2) -> 1 | AG10: =COUNTIFS('Assigned Learning Data Dump'!$W:$W,'Completed FEED'!$A10,'Assigned Learning Data Dump'!$F:$F,$A$1,'Assigned Learning Data Dump'!$U:$U,'Completed FEED'!AG$2) -> 0 | AH10: =SUBTOTAL(9,AE10:AG10) -> 2 | AI10: =SUBTOTAL(9,S10:AH10) -> 12 | AJ10: =COUNTIFS('Assigned Learning Data Dump'!$W:$W,'Completed FEED'!$A10,'Assigned Learning Data Dump'!$F:$F,$A$1,'Assigned Learning Data Dump'!$U:$U,'Completed FEED'!AJ$2) -> 0 | AK10: =COUNTIFS('Assigned Learning Data Dump'!$W:$W,'Completed FEED'!$A10,'Assigned Learning Data Dump'!$F:$F,$A$1,'Assigned Learning Data Dump'!$U:$U,'Completed FEED'!AK$2) -> 0 | AL10: =COUNTIFS('Assigned Learning Data Dump'!$W:$W,'Completed FEED'!$A10,'Assigned Learning Data Dump'!$F:$F,$A$1,'Assigned Learning Data Dump'!$U:$U,'Completed FEED'!AL$2) -> 0 | AM10: =SUBTOTAL(9,AJ10:AL10) -> 0 | AN10: =COUNTIFS('Assigned Learning Data Dump'!$W:$W,'Completed FEED'!$A10,'Assigned Learning Data Dump'!$F:$F,$A$1,'Assigned Learning Data Dump'!$U:$U,'Completed FEED'!AN$2) -> 0 | AO10: =COUNTIFS('Assigned Learning Data Dump'!$W:$W,'Completed FEED'!$A10,'Assigned Learning Data Dump'!$F:$F,$A$1,'Assigned Learning Data Dump'!$U:$U,'Completed FEED'!AO$2) -> 0 | AP10: =COUNTIFS('Assigned Learning Data Dump'!$W:$W,'Completed FEED'!$A10,'Assigned Learning Data Dump'!$F:$F,$A$1,'Assigned Learning Data Dump'!$U:$U,'Completed FEED'!AP$2) -> 0 | AQ10: =SUBTOTAL(9,AN10:AP10) -> 0 | AR10: =COUNTIFS('Assigned Learning Data Dump'!$W:$W,'Completed FEED'!$A10,'Assigned Learning Data Dump'!$F:$F,$A$1,'Assigned Learning Data Dump'!$U:$U,'Completed FEED'!AR$2) -> 0 | AS10: =COUNTIFS('Assigned Learning Data Dump'!$W:$W,'Completed FEED'!$A10,'Assigned Learning Data Dump'!$F:$F,$A$1,'Assigned Learning Data Dump'!$U:$U,'Completed FEED'!AS$2) -> 0 | AT10: =COUNTIFS('Assigned Learning Data Dump'!$W:$W,'Completed FEED'!$A10,'Assigned Learning Data Dump'!$F:$F,$A$1,'Assigned Learning Data Dump'!$U:$U,'Completed FEED'!AT$2) -> 0 | AU10: =SUBTOTAL(9,AR10:AT10) -> 0 | AV10: =COUNTIFS('Assigned Learning Data Dump'!$W:$W,'Completed FEED'!$A10,'Assigned Learning Data Dump'!$F:$F,$A$1,'Assigned Learning Data Dump'!$U:$U,'Completed FEED'!AV$2) -> 0 | AW10: =COUNTIFS('Assigned Learning Data Dump'!$W:$W,'Completed FEED'!$A10,'Assigned Learning Data Dump'!$F:$F,$A$1,'Assigned Learning Data Dump'!$U:$U,'Completed FEED'!AW$2) -> 0 | AX10: =COUNTIFS('Assigned Learning Data Dump'!$W:$W,'Completed FEED'!$A10,'Assigned Learning Data Dump'!$F:$F,$A$1,'Assigned Learning Data Dump'!$U:$U,'Completed FEED'!AX$2) -> 0 | AY10: =SUBTOTAL(9,AV10:AX10) -> 0 | AZ10: =SUBTOTAL(9,AJ10:AY10) -> 0
A11: SPG Development | B11: =COUNTIFS('Assigned Learning Data Dump'!$W:$W,'Completed FEED'!$A11,'Assigned Learning Data Dump'!$F:$F,$A$1,'Assigned Learning Data Dump'!$U:$U,'Completed FEED'!B$2) -> 3 | C11: =COUNTIFS('Assigned Learning Data Dump'!$W:$W,'Completed FEED'!$A11,'Assigned Learning Data Dump'!$F:$F,$A$1,'Assigned Learning Data Dump'!$U:$U,'Completed FEED'!C$2) -> 0 | D11: =COUNTIFS('Assigned Learning Data Dump'!$W:$W,'Completed FEED'!$A11,'Assigned Learning Data Dump'!$F:$F,$A$1,'Assigned Learning Data Dump'!$U:$U,'Completed FEED'!D$2) -> 0 | E11: =SUBTOTAL(9,B11:D11) -> 3 | F11: =COUNTIFS('Assigned Learning Data Dump'!$W:$W,'Completed FEED'!$A11,'Assigned Learning Data Dump'!$F:$F,$A$1,'Assigned Learning Data Dump'!$U:$U,'Completed FEED'!F$2) -> 0 | G11: =COUNTIFS('Assigned Learning Data Dump'!$W:$W,'Completed FEED'!$A11,'Assigned Learning Data Dump'!$F:$F,$A$1,'Assigned Learning Data Dump'!$U:$U,'Completed FEED'!G$2) -> 0 | H11: =COUNTIFS('Assigned Learning Data Dump'!$W:$W,'Completed FEED'!$A11,'Assigned Learning Data Dump'!$F:$F,$A$1,'Assigned Learning Data Dump'!$U:$U,'Completed FEED'!H$2) -> 0 | I11: =SUBTOTAL(9,F11:H11) -> 0 | J11: =COUNTIFS('Assigned Learning Data Dump'!$W:$W,'Completed FEED'!$A11,'Assigned Learning Data Dump'!$F:$F,$A$1,'Assigned Learning Data Dump'!$U:$U,'Completed FEED'!J$2) -> 0 | K11: =COUNTIFS('Assigned Learning Data Dump'!$W:$W,'Completed FEED'!$A11,'Assigned Learning Data Dump'!$F:$F,$A$1,'Assigned Learning Data Dump'!$U:$U,'Completed FEED'!K$2) -> 1 | L11: =COUNTIFS('Assigned Learning Data Dump'!$W:$W,'Completed FEED'!$A11,'Assigned Learning Data Dump'!$F:$F,$A$1,'Assigned Learning Data Dump'!$U:$U,'Completed FEED'!L$2) -> 0 | M11: =SUBTOTAL(9,J11:L11) -> 1 | N11: =COUNTIFS('Assigned Learning Data Dump'!$W:$W,'Completed FEED'!$A11,'Assigned Learning Data Dump'!$F:$F,$A$1,'Assigned Learning Data Dump'!$U:$U,'Completed FEED'!N$2) -> 0 | O11: =COUNTIFS('Assigned Learning Data Dump'!$W:$W,'Completed FEED'!$A11,'Assigned Learning Data Dump'!$F:$F,$A$1,'Assigned Learning Data Dump'!$U:$U,'Completed FEED'!O$2) -> 0 | P11: =COUNTIFS('Assigned Learning Data Dump'!$W:$W,'Completed FEED'!$A11,'Assigned Learning Data Dump'!$F:$F,$A$1,'Assigned Learning Data Dump'!$U:$U,'Completed FEED'!P$2) -> 0 | Q11: =SUBTOTAL(9,N11:P11) -> 0 | R11: =SUBTOTAL(9,B11:Q11) -> 4 | S11: =COUNTIFS('Assigned Learning Data Dump'!$W:$W,'Completed FEED'!$A11,'Assigned Learning Data Dump'!$F:$F,$A$1,'Assigned Learning Data Dump'!$U:$U,'Completed FEED'!S$2) -> 0 | T11: =COUNTIFS('Assigned Learning Data Dump'!$W:$W,'Completed FEED'!$A11,'Assigned Learning Data Dump'!$F:$F,$A$1,'Assigned Learning Data Dump'!$U:$U,'Completed FEED'!T$2) -> 0 | U11: =COUNTIFS('Assigned Learning Data Dump'!$W:$W,'Completed FEED'!$A11,'Assigned Learning Data Dump'!$F:$F,$A$1,'Assigned Learning Data Dump'!$U:$U,'Completed FEED'!U$2) -> 0 | V11: =SUBTOTAL(9,S11:U11) -> 0 | W11: =COUNTIFS('Assigned Learning Data Dump'!$W:$W,'Completed FEED'!$A11,'Assigned Learning Data Dump'!$F:$F,$A$1,'Assigned Learning Data Dump'!$U:$U,'Completed FEED'!W$2) -> 0 | X11: =COUNTIFS('Assigned Learning Data Dump'!$W:$W,'Completed FEED'!$A11,'Assigned Learning Data Dump'!$F:$F,$A$1,'Assigned Learning Data Dump'!$U:$U,'Completed FEED'!X$2) -> 0 | Y11: =COUNTIFS('Assigned Learning Data Dump'!$W:$W,'Completed FEED'!$A11,'Assigned Learning Data Dump'!$F:$F,$A$1,'Assigned Learning Data Dump'!$U:$U,'Completed FEED'!Y$2) -> 0 | Z11: =SUBTOTAL(9,W11:Y11) -> 0 | AA11: =COUNTIFS('Assigned Learning Data Dump'!$W:$W,'Completed FEED'!$A11,'Assigned Learning Data Dump'!$F:$F,$A$1,'Assigned Learning Data Dump'!$U:$U,'Completed FEED'!AA$2) -> 0 | AB11: =COUNTIFS('Assigned Learning Data Dump'!$W:$W,'Completed FEED'!$A11,'Assigned Learning Data Dump'!$F:$F,$A$1,'Assigned Learning Data Dump'!$U:$U,'Completed FEED'!AB$2) -> 0 | AC11: =COUNTIFS('Assigned Learning Data Dump'!$W:$W,'Completed FEED'!$A11,'Assigned Learning Data Dump'!$F:$F,$A$1,'Assigned Learning Data Dump'!$U:$U,'Completed FEED'!AC$2) -> 0 | AD11: =SUBTOTAL(9,AA11:AC11) -> 0 | AE11: =COUNTIFS('Assigned Learning Data Dump'!$W:$W,'Completed FEED'!$A11,'Assigned Learning Data Dump'!$F:$F,$A$1,'Assigned Learning Data Dump'!$U:$U,'Completed FEED'!AE$2) -> 0 | AF11: =COUNTIFS('Assigned Learning Data Dump'!$W:$W,'Completed FEED'!$A11,'Assigned Learning Data Dump'!$F:$F,$A$1,'Assigned Learning Data Dump'!$U:$U,'Completed FEED'!AF$2) -> 0 | AG11: =COUNTIFS('Assigned Learning Data Dump'!$W:$W,'Completed FEED'!$A11,'Assigned Learning Data Dump'!$F:$F,$A$1,'Assigned Learning Data Dump'!$U:$U,'Completed FEED'!AG$2) -> 0 | AH11: =SUBTOTAL(9,AE11:AG11) -> 0 | AI11: =SUBTOTAL(9,S11:AH11) -> 0 | AJ11: =COUNTIFS('Assigned Learning Data Dump'!$W:$W,'Completed FEED'!$A11,'Assigned Learning Data Dump'!$F:$F,$A$1,'Assigned Learning Data Dump'!$U:$U,'Completed FEED'!AJ$2) -> 0 | AK11: =COUNTIFS('Assigned Learning Data Dump'!$W:$W,'Completed FEED'!$A11,'Assigned Learning Data Dump'!$F:$F,$A$1,'Assigned Learning Data Dump'!$U:$U,'Completed FEED'!AK$2) -> 0 | AL11: =COUNTIFS('Assigned Learning Data Dump'!$W:$W,'Completed FEED'!$A11,'Assigned Learning Data Dump'!$F:$F,$A$1,'Assigned Learning Data Dump'!$U:$U,'Completed FEED'!AL$2) -> 0 | AM11: =SUBTOTAL(9,AJ11:AL11) -> 0 | AN11: =COUNTIFS('Assigned Learning Data Dump'!$W:$W,'Completed FEED'!$A11,'Assigned Learning Data Dump'!$F:$F,$A$1,'Assigned Learning Data Dump'!$U:$U,'Completed FEED'!AN$2) -> 0 | AO11: =COUNTIFS('Assigned Learning Data Dump'!$W:$W,'Completed FEED'!$A11,'Assigned Learning Data Dump'!$F:$F,$A$1,'Assigned Learning Data Dump'!$U:$U,'Completed FEED'!AO$2) -> 0 | AP11: =COUNTIFS('Assigned Learning Data Dump'!$W:$W,'Completed FEED'!$A11,'Assigned Learning Data Dump'!$F:$F,$A$1,'Assigned Learning Data Dump'!$U:$U,'Completed FEED'!AP$2) -> 0 | AQ11: =SUBTOTAL(9,AN11:AP11) -> 0 | AR11: =COUNTIFS('Assigned Learning Data Dump'!$W:$W,'Completed FEED'!$A11,'Assigned Learning Data Dump'!$F:$F,$A$1,'Assigned Learning Data Dump'!$U:$U,'Completed FEED'!AR$2) -> 0 | AS11: =COUNTIFS('Assigned Learning Data Dump'!$W:$W,'Completed FEED'!$A11,'Assigned Learning Data Dump'!$F:$F,$A$1,'Assigned Learning Data Dump'!$U:$U,'Completed FEED'!AS$2) -> 0 | AT11: =COUNTIFS('Assigned Learning Data Dump'!$W:$W,'Completed FEED'!$A11,'Assigned Learning Data Dump'!$F:$F,$A$1,'Assigned Learning Data Dump'!$U:$U,'Completed FEED'!AT$2) -> 0 | AU11: =SUBTOTAL(9,AR11:AT11) -> 0 | AV11: =COUNTIFS('Assigned Learning Data Dump'!$W:$W,'Completed FEED'!$A11,'Assigned Learning Data Dump'!$F:$F,$A$1,'Assigned Learning Data Dump'!$U:$U,'Completed FEED'!AV$2) -> 0 | AW11: =COUNTIFS('Assigned Learning Data Dump'!$W:$W,'Completed FEED'!$A11,'Assigned Learning Data Dump'!$F:$F,$A$1,'Assigned Learning Data Dump'!$U:$U,'Completed FEED'!AW$2) -> 0 | AX11: =COUNTIFS('Assigned Learning Data Dump'!$W:$W,'Completed FEED'!$A11,'Assigned Learning Data Dump'!$F:$F,$A$1,'Assigned Learning Data Dump'!$U:$U,'Completed FEED'!AX$2) -> 0 | AY11: =SUBTOTAL(9,AV11:AX11) -> 0 | AZ11: =SUBTOTAL(9,AJ11:AY11) -> 0
A12: Spot Merch | B12: =COUNTIFS('Assigned Learning Data Dump'!$W:$W,'Completed FEED'!$A12,'Assigned Learning Data Dump'!$F:$F,$A$1,'Assigned Learning Data Dump'!$U:$U,'Completed FEED'!B$2) -> 0 | C12: =COUNTIFS('Assigned Learning Data Dump'!$W:$W,'Completed FEED'!$A12,'Assigned Learning Data Dump'!$F:$F,$A$1,'Assigned Learning Data Dump'!$U:$U,'Completed FEED'!C$2) -> 0 | D12: =COUNTIFS('Assigned Learning Data Dump'!$W:$W,'Completed FEED'!$A12,'Assigned Learning Data Dump'!$F:$F,$A$1,'Assigned Learning Data Dump'!$U:$U,'Completed FEED'!D$2) -> 0 | E12: =SUBTOTAL(9,B12:D12) -> 0 | F12: =COUNTIFS('Assigned Learning Data Dump'!$W:$W,'Completed FEED'!$A12,'Assigned Learning Data Dump'!$F:$F,$A$1,'Assigned Learning Data Dump'!$U:$U,'Completed FEED'!F$2) -> 0 | G12: =COUNTIFS('Assigned Learning Data Dump'!$W:$W,'Completed FEED'!$A12,'Assigned Learning Data Dump'!$F:$F,$A$1,'Assigned Learning Data Dump'!$U:$U,'Completed FEED'!G$2) -> 0 | H12: =COUNTIFS('Assigned Learning Data Dump'!$W:$W,'Completed FEED'!$A12,'Assigned Learning Data Dump'!$F:$F,$A$1,'Assigned Learning Data Dump'!$U:$U,'Completed FEED'!H$2) -> 0 | I12: =SUBTOTAL(9,F12:H12) -> 0 | J12: =COUNTIFS('Assigned Learning Data Dump'!$W:$W,'Completed FEED'!$A12,'Assigned Learning Data Dump'!$F:$F,$A$1,'Assigned Learning Data Dump'!$U:$U,'Completed FEED'!J$2) -> 0 | K12: =COUNTIFS('Assigned Learning Data Dump'!$W:$W,'Completed FEED'!$A12,'Assigned Learning Data Dump'!$F:$F,$A$1,'Assigned Learning Data Dump'!$U:$U,'Completed FEED'!K$2) -> 0 | L12: =COUNTIFS('Assigned Learning Data Dump'!$W:$W,'Completed FEED'!$A12,'Assigned Learning Data Dump'!$F:$F,$A$1,'Assigned Learning Data Dump'!$U:$U,'Completed FEED'!L$2) -> 0 | M12: =SUBTOTAL(9,J12:L12) -> 0 | N12: =COUNTIFS('Assigned Learning Data Dump'!$W:$W,'Completed FEED'!$A12,'Assigned Learning Data Dump'!$F:$F,$A$1,'Assigned Learning Data Dump'!$U:$U,'Completed FEED'!N$2) -> 0 | O12: =COUNTIFS('Assigned Learning Data Dump'!$W:$W,'Completed FEED'!$A12,'Assigned Learning Data Dump'!$F:$F,$A$1,'Assigned Learning Data Dump'!$U:$U,'Completed FEED'!O$2) -> 0 | P12: =COUNTIFS('Assigned Learning Data Dump'!$W:$W,'Completed FEED'!$A12,'Assigned Learning Data Dump'!$F:$F,$A$1,'Assigned Learning Data Dump'!$U:$U,'Completed FEED'!P$2) -> 0 | Q12: =SUBTOTAL(9,N12:P12) -> 0 | R12: =SUBTOTAL(9,B12:Q12) -> 0 | S12: =COUNTIFS('Assigned Learning Data Dump'!$W:$W,'Completed FEED'!$A12,'Assigned Learning Data Dump'!$F:$F,$A$1,'Assigned Learning Data Dump'!$U:$U,'Completed FEED'!S$2) -> 0 | T12: =COUNTIFS('Assigned Learning Data Dump'!$W:$W,'Completed FEED'!$A12,'Assigned Learning Data Dump'!$F:$F,$A$1,'Assigned Learning Data Dump'!$U:$U,'Completed FEED'!T$2) -> 0 | U12: =COUNTIFS('Assigned Learning Data Dump'!$W:$W,'Completed FEED'!$A12,'Assigned Learning Data Dump'!$F:$F,$A$1,'Assigned Learning Data Dump'!$U:$U,'Completed FEED'!U$2) -> 0 | V12: =SUBTOTAL(9,S12:U12) -> 0 | W12: =COUNTIFS('Assigned Learning Data Dump'!$W:$W,'Completed FEED'!$A12,'Assigned Learning Data Dump'!$F:$F,$A$1,'Assigned Learning Data Dump'!$U:$U,'Completed FEED'!W$2) -> 0 | X12: =COUNTIFS('Assigned Learning Data Dump'!$W:$W,'Completed FEED'!$A12,'Assigned Learning Data Dump'!$F:$F,$A$1,'Assigned Learning Data Dump'!$U:$U,'Completed FEED'!X$2) -> 0 | Y12: =COUNTIFS('Assigned Learning Data Dump'!$W:$W,'Completed FEED'!$A12,'Assigned Learning Data Dump'!$F:$F,$A$1,'Assigned Learning Data Dump'!$U:$U,'Completed FEED'!Y$2) -> 0 | Z12: =SUBTOTAL(9,W12:Y12) -> 0 | AA12: =COUNTIFS('Assigned Learning Data Dump'!$W:$W,'Completed FEED'!$A12,'Assigned Learning Data Dump'!$F:$F,$A$1,'Assigned Learning Data Dump'!$U:$U,'Completed FEED'!AA$2) -> 0 | AB12: =COUNTIFS('Assigned Learning Data Dump'!$W:$W,'Completed FEED'!$A12,'Assigned Learning Data Dump'!$F:$F,$A$1,'Assigned Learning Data Dump'!$U:$U,'Completed FEED'!AB$2) -> 0 | AC12: =COUNTIFS('Assigned Learning Data Dump'!$W:$W,'Completed FEED'!$A12,'Assigned Learning Data Dump'!$F:$F,$A$1,'Assigned Learning Data Dump'!$U:$U,'Completed FEED'!AC$2) -> 0 | AD12: =SUBTOTAL(9,AA12:AC12) -> 0 | AE12: =COUNTIFS('Assigned Learning Data Dump'!$W:$W,'Completed FEED'!$A12,'Assigned Learning Data Dump'!$F:$F,$A$1,'Assigned Learning Data Dump'!$U:$U,'Completed FEED'!AE$2) -> 0 | AF12: =COUNTIFS('Assigned Learning Data Dump'!$W:$W,'Completed FEED'!$A12,'Assigned Learning Data Dump'!$F:$F,$A$1,'Assigned Learning Data Dump'!$U:$U,'Completed FEED'!AF$2) -> 0 | AG12: =COUNTIFS('Assigned Learning Data Dump'!$W:$W,'Completed FEED'!$A12,'Assigned Learning Data Dump'!$F:$F,$A$1,'Assigned Learning Data Dump'!$U:$U,'Completed FEED'!AG$2) -> 0 | AH12: =SUBTOTAL(9,AE12:AG12) -> 0 | AI12: =SUBTOTAL(9,S12:AH12) -> 0 | AJ12: =COUNTIFS('Assigned Learning Data Dump'!$W:$W,'Completed FEED'!$A12,'Assigned Learning Data Dump'!$F:$F,$A$1,'Assigned Learning Data Dump'!$U:$U,'Completed FEED'!AJ$2) -> 0 | AK12: =COUNTIFS('Assigned Learning Data Dump'!$W:$W,'Completed FEED'!$A12,'Assigned Learning Data Dump'!$F:$F,$A$1,'Assigned Learning Data Dump'!$U:$U,'Completed FEED'!AK$2) -> 0 | AL12: =COUNTIFS('Assigned Learning Data Dump'!$W:$W,'Completed FEED'!$A12,'Assigned Learning Data Dump'!$F:$F,$A$1,'Assigned Learning Data Dump'!$U:$U,'Completed FEED'!AL$2) -> 0 | AM12: =SUBTOTAL(9,AJ12:AL12) -> 0 | AN12: =COUNTIFS('Assigned Learning Data Dump'!$W:$W,'Completed FEED'!$A12,'Assigned Learning Data Dump'!$F:$F,$A$1,'Assigned Learning Data Dump'!$U:$U,'Completed FEED'!AN$2) -> 0 | AO12: =COUNTIFS('Assigned Learning Data Dump'!$W:$W,'Completed FEED'!$A12,'Assigned Learning Data Dump'!$F:$F,$A$1,'Assigned Learning Data Dump'!$U:$U,'Completed FEED'!AO$2) -> 0 | AP12: =COUNTIFS('Assigned Learning Data Dump'!$W:$W,'Completed FEED'!$A12,'Assigned Learning Data Dump'!$F:$F,$A$1,'Assigned Learning Data Dump'!$U:$U,'Completed FEED'!AP$2) -> 0 | AQ12: =SUBTOTAL(9,AN12:AP12) -> 0 | AR12: =COUNTIFS('Assigned Learning Data Dump'!$W:$W,'Completed FEED'!$A12,'Assigned Learning Data Dump'!$F:$F,$A$1,'Assigned Learning Data Dump'!$U:$U,'Completed FEED'!AR$2) -> 0 | AS12: =COUNTIFS('Assigned Learning Data Dump'!$W:$W,'Completed FEED'!$A12,'Assigned Learning Data Dump'!$F:$F,$A$1,'Assigned Learning Data Dump'!$U:$U,'Completed FEED'!AS$2) -> 0 | AT12: =COUNTIFS('Assigned Learning Data Dump'!$W:$W,'Completed FEED'!$A12,'Assigned Learning Data Dump'!$F:$F,$A$1,'Assigned Learning Data Dump'!$U:$U,'Completed FEED'!AT$2) -> 0 | AU12: =SUBTOTAL(9,AR12:AT12) -> 0 | AV12: =COUNTIFS('Assigned Learning Data Dump'!$W:$W,'Completed FEED'!$A12,'Assigned Learning Data Dump'!$F:$F,$A$1,'Assigned Learning Data Dump'!$U:$U,'Completed FEED'!AV$2) -> 0 | AW12: =COUNTIFS('Assigned Learning Data Dump'!$W:$W,'Completed FEED'!$A12,'Assigned Learning Data Dump'!$F:$F,$A$1,'Assigned Learning Data Dump'!$U:$U,'Completed FEED'!AW$2) -> 0 | AX12: =COUNTIFS('Assigned Learning Data Dump'!$W:$W,'Completed FEED'!$A12,'Assigned Learning Data Dump'!$F:$F,$A$1,'Assigned Learning Data Dump'!$U:$U,'Completed FEED'!AX$2) -> 0 | AY12: =SUBTOTAL(9,AV12:AX12) -> 0 | AZ12: =SUBTOTAL(9,AJ12:AY12) -> 0
A13: Spotlight Group Aviation | B13: =COUNTIFS('Assigned Learning Data Dump'!$W:$W,'Completed FEED'!$A13,'Assigned Learning Data Dump'!$F:$F,$A$1,'Assigned Learning Data Dump'!$U:$U,'Completed FEED'!B$2) -> 0 | C13: =COUNTIFS('Assigned Learning Data Dump'!$W:$W,'Completed FEED'!$A13,'Assigned Learning Data Dump'!$F:$F,$A$1,'Assigned Learning Data Dump'!$U:$U,'Completed FEED'!C$2) -> 0 | D13: =COUNTIFS('Assigned Learning Data Dump'!$W:$W,'Completed FEED'!$A13,'Assigned Learning Data Dump'!$F:$F,$A$1,'Assigned Learning Data Dump'!$U:$U,'Completed FEED'!D$2) -> 0 | E13: =SUBTOTAL(9,B13:D13) -> 0 | F13: =COUNTIFS('Assigned Learning Data Dump'!$W:$W,'Completed FEED'!$A13,'Assigned Learning Data Dump'!$F:$F,$A$1,'Assigned Learning Data Dump'!$U:$U,'Completed FEED'!F$2) -> 0 | G13: =COUNTIFS('Assigned Learning Data Dump'!$W:$W,'Completed FEED'!$A13,'Assigned Learning Data Dump'!$F:$F,$A$1,'Assigned Learning Data Dump'!$U:$U,'Completed FEED'!G$2) -> 0 | H13: =COUNTIFS('Assigned Learning Data Dump'!$W:$W,'Completed FEED'!$A13,'Assigned Learning Data Dump'!$F:$F,$A$1,'Assigned Learning Data Dump'!$U:$U,'Completed FEED'!H$2) -> 0 | I13: =SUBTOTAL(9,F13:H13) -> 0 | J13: =COUNTIFS('Assigned Learning Data Dump'!$W:$W,'Completed FEED'!$A13,'Assigned Learning Data Dump'!$F:$F,$A$1,'Assigned Learning Data Dump'!$U:$U,'Completed FEED'!J$2) -> 0 | K13: =COUNTIFS('Assigned Learning Data Dump'!$W:$W,'Completed FEED'!$A13,'Assigned Learning Data Dump'!$F:$F,$A$1,'Assigned Learning Data Dump'!$U:$U,'Completed FEED'!K$2) -> 0 | L13: =COUNTIFS('Assigned Learning Data Dump'!$W:$W,'Completed FEED'!$A13,'Assigned Learning Data Dump'!$F:$F,$A$1,'Assigned Learning Data Dump'!$U:$U,'Completed FEED'!L$2) -> 0 | M13: =SUBTOTAL(9,J13:L13) -> 0 | N13: =COUNTIFS('Assigned Learning Data Dump'!$W:$W,'Completed FEED'!$A13,'Assigned Learning Data Dump'!$F:$F,$A$1,'Assigned Learning Data Dump'!$U:$U,'Completed FEED'!N$2) -> 0 | O13: =COUNTIFS('Assigned Learning Data Dump'!$W:$W,'Completed FEED'!$A13,'Assigned Learning Data Dump'!$F:$F,$A$1,'Assigned Learning Data Dump'!$U:$U,'Completed FEED'!O$2) -> 0 | P13: =COUNTIFS('Assigned Learning Data Dump'!$W:$W,'Completed FEED'!$A13,'Assigned Learning Data Dump'!$F:$F,$A$1,'Assigned Learning Data Dump'!$U:$U,'Completed FEED'!P$2) -> 0 | Q13: =SUBTOTAL(9,N13:P13) -> 0 | R13: =SUBTOTAL(9,B13:Q13) -> 0 | S13: =COUNTIFS('Assigned Learning Data Dump'!$W:$W,'Completed FEED'!$A13,'Assigned Learning Data Dump'!$F:$F,$A$1,'Assigned Learning Data Dump'!$U:$U,'Completed FEED'!S$2) -> 0 | T13: =COUNTIFS('Assigned Learning Data Dump'!$W:$W,'Completed FEED'!$A13,'Assigned Learning Data Dump'!$F:$F,$A$1,'Assigned Learning Data Dump'!$U:$U,'Completed FEED'!T$2) -> 0 | U13: =COUNTIFS('Assigned Learning Data Dump'!$W:$W,'Completed FEED'!$A13,'Assigned Learning Data Dump'!$F:$F,$A$1,'Assigned Learning Data Dump'!$U:$U,'Completed FEED'!U$2) -> 0 | V13: =SUBTOTAL(9,S13:U13) -> 0 | W13: =COUNTIFS('Assigned Learning Data Dump'!$W:$W,'Completed FEED'!$A13,'Assigned Learning Data Dump'!$F:$F,$A$1,'Assigned Learning Data Dump'!$U:$U,'Completed FEED'!W$2) -> 0 | X13: =COUNTIFS('Assigned Learning Data Dump'!$W:$W,'Completed FEED'!$A13,'Assigned Learning Data Dump'!$F:$F,$A$1,'Assigned Learning Data Dump'!$U:$U,'Completed FEED'!X$2) -> 0 | Y13: =COUNTIFS('Assigned Learning Data Dump'!$W:$W,'Completed FEED'!$A13,'Assigned Learning Data Dump'!$F:$F,$A$1,'Assigned Learning Data Dump'!$U:$U,'Completed FEED'!Y$2) -> 0 | Z13: =SUBTOTAL(9,W13:Y13) -> 0 | AA13: =COUNTIFS('Assigned Learning Data Dump'!$W:$W,'Completed FEED'!$A13,'Assigned Learning Data Dump'!$F:$F,$A$1,'Assigned Learning Data Dump'!$U:$U,'Completed FEED'!AA$2) -> 0 | AB13: =COUNTIFS('Assigned Learning Data Dump'!$W:$W,'Completed FEED'!$A13,'Assigned Learning Data Dump'!$F:$F,$A$1,'Assigned Learning Data Dump'!$U:$U,'Completed FEED'!AB$2) -> 0 | AC13: =COUNTIFS('Assigned Learning Data Dump'!$W:$W,'Completed FEED'!$A13,'Assigned Learning Data Dump'!$F:$F,$A$1,'Assigned Learning Data Dump'!$U:$U,'Completed FEED'!AC$2) -> 1 | AD13: =SUBTOTAL(9,AA13:AC13) -> 1 | AE13: =COUNTIFS('Assigned Learning Data Dump'!$W:$W,'Completed FEED'!$A13,'Assigned Learning Data Dump'!$F:$F,$A$1,'Assigned Learning Data Dump'!$U:$U,'Completed FEED'!AE$2) -> 0 | AF13: =COUNTIFS('Assigned Learning Data Dump'!$W:$W,'Completed FEED'!$A13,'Assigned Learning Data Dump'!$F:$F,$A$1,'Assigned Learning Data Dump'!$U:$U,'Completed FEED'!AF$2) -> 0 | AG13: =COUNTIFS('Assigned Learning Data Dump'!$W:$W,'Completed FEED'!$A13,'Assigned Learning Data Dump'!$F:$F,$A$1,'Assigned Learning Data Dump'!$U:$U,'Completed FEED'!AG$2) -> 0 | AH13: =SUBTOTAL(9,AE13:AG13) -> 0 | AI13: =SUBTOTAL(9,S13:AH13) -> 1 | AJ13: =COUNTIFS('Assigned Learning Data Dump'!$W:$W,'Completed FEED'!$A13,'Assigned Learning Data Dump'!$F:$F,$A$1,'Assigned Learning Data Dump'!$U:$U,'Completed FEED'!AJ$2) -> 0 | AK13: =COUNTIFS('Assigned Learning Data Dump'!$W:$W,'Completed FEED'!$A13,'Assigned Learning Data Dump'!$F:$F,$A$1,'Assigned Learning Data Dump'!$U:$U,'Completed FEED'!AK$2) -> 0 | AL13: =COUNTIFS('Assigned Learning Data Dump'!$W:$W,'Completed FEED'!$A13,'Assigned Learning Data Dump'!$F:$F,$A$1,'Assigned Learning Data Dump'!$U:$U,'Completed FEED'!AL$2) -> 0 | AM13: =SUBTOTAL(9,AJ13:AL13) -> 0 | AN13: =COUNTIFS('Assigned Learning Data Dump'!$W:$W,'Completed FEED'!$A13,'Assigned Learning Data Dump'!$F:$F,$A$1,'Assigned Learning Data Dump'!$U:$U,'Completed FEED'!AN$2) -> 0 | AO13: =COUNTIFS('Assigned Learning Data Dump'!$W:$W,'Completed FEED'!$A13,'Assigned Learning Data Dump'!$F:$F,$A$1,'Assigned Learning Data Dump'!$U:$U,'Completed FEED'!AO$2) -> 0 | AP13: =COUNTIFS('Assigned Learning Data Dump'!$W:$W,'Completed FEED'!$A13,'Assigned Learning Data Dump'!$F:$F,$A$1,'Assigned Learning Data Dump'!$U:$U,'Completed FEED'!AP$2) -> 0 | AQ13: =SUBTOTAL(9,AN13:AP13) -> 0 | AR13: =COUNTIFS('Assigned Learning Data Dump'!$W:$W,'Completed FEED'!$A13,'Assigned Learning Data Dump'!$F:$F,$A$1,'Assigned Learning Data Dump'!$U:$U,'Completed FEED'!AR$2) -> 0 | AS13: =COUNTIFS('Assigned Learning Data Dump'!$W:$W,'Completed FEED'!$A13,'Assigned Learning Data Dump'!$F:$F,$A$1,'Assigned Learning Data Dump'!$U:$U,'Completed FEED'!AS$2) -> 0 | AT13: =COUNTIFS('Assigned Learning Data Dump'!$W:$W,'Completed FEED'!$A13,'Assigned Learning Data Dump'!$F:$F,$A$1,'Assigned Learning Data Dump'!$U:$U,'Completed FEED'!AT$2) -> 0 | AU13: =SUBTOTAL(9,AR13:AT13) -> 0 | AV13: =COUNTIFS('Assigned Learning Data Dump'!$W:$W,'Completed FEED'!$A13,'Assigned Learning Data Dump'!$F:$F,$A$1,'Assigned Learning Data Dump'!$U:$U,'Completed FEED'!AV$2) -> 0 | AW13: =COUNTIFS('Assigned Learning Data Dump'!$W:$W,'Completed FEED'!$A13,'Assigned Learning Data Dump'!$F:$F,$A$1,'Assigned Learning Data Dump'!$U:$U,'Completed FEED'!AW$2) -> 0 | AX13: =COUNTIFS('Assigned Learning Data Dump'!$W:$W,'Completed FEED'!$A13,'Assigned Learning Data Dump'!$F:$F,$A$1,'Assigned Learning Data Dump'!$U:$U,'Completed FEED'!AX$2) -> 0 | AY13: =SUBTOTAL(9,AV13:AX13) -> 0 | AZ13: =SUBTOTAL(9,AJ13:AY13) -> 0
A14: Supply Chain | B14: =COUNTIFS('Assigned Learning Data Dump'!$W:$W,'Completed FEED'!$A14,'Assigned Learning Data Dump'!$F:$F,$A$1,'Assigned Learning Data Dump'!$U:$U,'Completed FEED'!B$2) -> 0 | C14: =COUNTIFS('Assigned Learning Data Dump'!$W:$W,'Completed FEED'!$A14,'Assigned Learning Data Dump'!$F:$F,$A$1,'Assigned Learning Data Dump'!$U:$U,'Completed FEED'!C$2) -> 2 | D14: =COUNTIFS('Assigned Learning Data Dump'!$W:$W,'Completed FEED'!$A14,'Assigned Learning Data Dump'!$F:$F,$A$1,'Assigned Learning Data Dump'!$U:$U,'Completed FEED'!D$2) -> 1 | E14: =SUBTOTAL(9,B14:D14) -> 3 | F14: =COUNTIFS('Assigned Learning Data Dump'!$W:$W,'Completed FEED'!$A14,'Assigned Learning Data Dump'!$F:$F,$A$1,'Assigned Learning Data Dump'!$U:$U,'Completed FEED'!F$2) -> 0 | G14: =COUNTIFS('Assigned Learning Data Dump'!$W:$W,'Completed FEED'!$A14,'Assigned Learning Data Dump'!$F:$F,$A$1,'Assigned Learning Data Dump'!$U:$U,'Completed FEED'!G$2) -> 0 | H14: =COUNTIFS('Assigned Learning Data Dump'!$W:$W,'Completed FEED'!$A14,'Assigned Learning Data Dump'!$F:$F,$A$1,'Assigned Learning Data Dump'!$U:$U,'Completed FEED'!H$2) -> 0 | I14: =SUBTOTAL(9,F14:H14) -> 0 | J14: =COUNTIFS('Assigned Learning Data Dump'!$W:$W,'Completed FEED'!$A14,'Assigned Learning Data Dump'!$F:$F,$A$1,'Assigned Learning Data Dump'!$U:$U,'Completed FEED'!J$2) -> 0 | K14: =COUNTIFS('Assigned Learning Data Dump'!$W:$W,'Completed FEED'!$A14,'Assigned Learning Data Dump'!$F:$F,$A$1,'Assigned Learning Data Dump'!$U:$U,'Completed FEED'!K$2) -> 0 | L14: =COUNTIFS('Assigned Learning Data Dump'!$W:$W,'Completed FEED'!$A14,'Assigned Learning Data Dump'!$F:$F,$A$1,'Assigned Learning Data Dump'!$U:$U,'Completed FEED'!L$2) -> 0 | M14: =SUBTOTAL(9,J14:L14) -> 0 | N14: =COUNTIFS('Assigned Learning Data Dump'!$W:$W,'Completed FEED'!$A14,'Assigned Learning Data Dump'!$F:$F,$A$1,'Assigned Learning Data Dump'!$U:$U,'Completed FEED'!N$2) -> 0 | O14: =COUNTIFS('Assigned Learning Data Dump'!$W:$W,'Completed FEED'!$A14,'Assigned Learning Data Dump'!$F:$F,$A$1,'Assigned Learning Data Dump'!$U:$U,'Completed FEED'!O$2) -> 3 | P14: =COUNTIFS('Assigned Learning Data Dump'!$W:$W,'Completed FEED'!$A14,'Assigned Learning Data Dump'!$F:$F,$A$1,'Assigned Learning Data Dump'!$U:$U,'Completed FEED'!P$2) -> 1 | Q14: =SUBTOTAL(9,N14:P14) -> 4 | R14: =SUBTOTAL(9,B14:Q14) -> 7 | S14: =COUNTIFS('Assigned Learning Data Dump'!$W:$W,'Completed FEED'!$A14,'Assigned Learning Data Dump'!$F:$F,$A$1,'Assigned Learning Data Dump'!$U:$U,'Completed FEED'!S$2) -> 5 | T14: =COUNTIFS('Assigned Learning Data Dump'!$W:$W,'Completed FEED'!$A14,'Assigned Learning Data Dump'!$F:$F,$A$1,'Assigned Learning Data Dump'!$U:$U,'Completed FEED'!T$2) -> 0 | U14: =COUNTIFS('Assigned Learning Data Dump'!$W:$W,'Completed FEED'!$A14,'Assigned Learning Data Dump'!$F:$F,$A$1,'Assigned Learning Data Dump'!$U:$U,'Completed FEED'!U$2) -> 0 | V14: =SUBTOTAL(9,S14:U14) -> 5 | W14: =COUNTIFS('Assigned Learning Data Dump'!$W:$W,'Completed FEED'!$A14,'Assigned Learning Data Dump'!$F:$F,$A$1,'Assigned Learning Data Dump'!$U:$U,'Completed FEED'!W$2) -> 0 | X14: =COUNTIFS('Assigned Learning Data Dump'!$W:$W,'Completed FEED'!$A14,'Assigned Learning Data Dump'!$F:$F,$A$1,'Assigned Learning Data Dump'!$U:$U,'Completed FEED'!X$2) -> 0 | Y14: =COUNTIFS('Assigned Learning Data Dump'!$W:$W,'Completed FEED'!$A14,'Assigned Learning Data Dump'!$F:$F,$A$1,'Assigned Learning Data Dump'!$U:$U,'Completed FEED'!Y$2) -> 0 | Z14: =SUBTOTAL(9,W14:Y14) -> 0 | AA14: =COUNTIFS('Assigned Learning Data Dump'!$W:$W,'Completed FEED'!$A14,'Assigned Learning Data Dump'!$F:$F,$A$1,'Assigned Learning Data Dump'!$U:$U,'Completed FEED'!AA$2) -> 0 | AB14: =COUNTIFS('Assigned Learning Data Dump'!$W:$W,'Completed FEED'!$A14,'Assigned Learning Data Dump'!$F:$F,$A$1,'Assigned Learning Data Dump'!$U:$U,'Completed FEED'!AB$2) -> 0 | AC14: =COUNTIFS('Assigned Learning Data Dump'!$W:$W,'Completed FEED'!$A14,'Assigned Learning Data Dump'!$F:$F,$A$1,'Assigned Learning Data Dump'!$U:$U,'Completed FEED'!AC$2) -> 5 | AD14: =SUBTOTAL(9,AA14:AC14) -> 5 | AE14: =COUNTIFS('Assigned Learning Data Dump'!$W:$W,'Completed FEED'!$A14,'Assigned Learning Data Dump'!$F:$F,$A$1,'Assigned Learning Data Dump'!$U:$U,'Completed FEED'!AE$2) -> 5 | AF14: =COUNTIFS('Assigned Learning Data Dump'!$W:$W,'Completed FEED'!$A14,'Assigned Learning Data Dump'!$F:$F,$A$1,'Assigned Learning Data Dump'!$U:$U,'Completed FEED'!AF$2) -> 1 | AG14: =COUNTIFS('Assigned Learning Data Dump'!$W:$W,'Completed FEED'!$A14,'Assigned Learning Data Dump'!$F:$F,$A$1,'Assigned Learning Data Dump'!$U:$U,'Completed FEED'!AG$2) -> 2 | AH14: =SUBTOTAL(9,AE14:AG14) -> 8 | AI14: =SUBTOTAL(9,S14:AH14) -> 18 | AJ14: =COUNTIFS('Assigned Learning Data Dump'!$W:$W,'Completed FEED'!$A14,'Assigned Learning Data Dump'!$F:$F,$A$1,'Assigned Learning Data Dump'!$U:$U,'Completed FEED'!AJ$2) -> 0 | AK14: =COUNTIFS('Assigned Learning Data Dump'!$W:$W,'Completed FEED'!$A14,'Assigned Learning Data Dump'!$F:$F,$A$1,'Assigned Learning Data Dump'!$U:$U,'Completed FEED'!AK$2) -> 0 | AL14: =COUNTIFS('Assigned Learning Data Dump'!$W:$W,'Completed FEED'!$A14,'Assigned Learning Data Dump'!$F:$F,$A$1,'Assigned Learning Data Dump'!$U:$U,'Completed FEED'!AL$2) -> 0 | AM14: =SUBTOTAL(9,AJ14:AL14) -> 0 | AN14: =COUNTIFS('Assigned Learning Data Dump'!$W:$W,'Completed FEED'!$A14,'Assigned Learning Data Dump'!$F:$F,$A$1,'Assigned Learning Data Dump'!$U:$U,'Completed FEED'!AN$2) -> 0 | AO14: =COUNTIFS('Assigned Learning Data Dump'!$W:$W,'Completed FEED'!$A14,'Assigned Learning Data Dump'!$F:$F,$A$1,'Assigned Learning Data Dump'!$U:$U,'Completed FEED'!AO$2) -> 0 | AP14: =COUNTIFS('Assigned Learning Data Dump'!$W:$W,'Completed FEED'!$A14,'Assigned Learning Data Dump'!$F:$F,$A$1,'Assigned Learning Data Dump'!$U:$U,'Completed FEED'!AP$2) -> 0 | AQ14: =SUBTOTAL(9,AN14:AP14) -> 0 | AR14: =COUNTIFS('Assigned Learning Data Dump'!$W:$W,'Completed FEED'!$A14,'Assigned Learning Data Dump'!$F:$F,$A$1,'Assigned Learning Data Dump'!$U:$U,'Completed FEED'!AR$2) -> 0 | AS14: =COUNTIFS('Assigned Learning Data Dump'!$W:$W,'Completed FEED'!$A14,'Assigned Learning Data Dump'!$F:$F,$A$1,'Assigned Learning Data Dump'!$U:$U,'Completed FEED'!AS$2) -> 0 | AT14: =COUNTIFS('Assigned Learning Data Dump'!$W:$W,'Completed FEED'!$A14,'Assigned Learning Data Dump'!$F:$F,$A$1,'Assigned Learning Data Dump'!$U:$U,'Completed FEED'!AT$2) -> 0 | AU14: =SUBTOTAL(9,AR14:AT14) -> 0 | AV14: =COUNTIFS('Assigned Learning Data Dump'!$W:$W,'Completed FEED'!$A14,'Assigned Learning Data Dump'!$F:$F,$A$1,'Assigned Learning Data Dump'!$U:$U,'Completed FEED'!AV$2) -> 0 | AW14: =COUNTIFS('Assigned Learning Data Dump'!$W:$W,'Completed FEED'!$A14,'Assigned Learning Data Dump'!$F:$F,$A$1,'Assigned Learning Data Dump'!$U:$U,'Completed FEED'!AW$2) -> 0 | AX14: =COUNTIFS('Assigned Learning Data Dump'!$W:$W,'Completed FEED'!$A14,'Assigned Learning Data Dump'!$F:$F,$A$1,'Assigned Learning Data Dump'!$U:$U,'Completed FEED'!AX$2) -> 0 | AY14: =SUBTOTAL(9,AV14:AX14) -> 0 | AZ14: =SUBTOTAL(9,AJ14:AY14) -> 0
A15: Grand Total | B15: =SUM(B3:B14) -> 39 | C15: =SUM(C3:C14) -> 14 | D15: =SUM(D3:D14) -> 67 | E15: =SUBTOTAL(9,B15:D15) -> 120 | F15: =SUM(F3:F14) -> 9 | G15: =SUM(G3:G14) -> 2 | H15: =SUM(H3:H14) -> 9 | I15: =SUBTOTAL(9,F15:H15) -> 20 | J15: =SUM(J3:J14) -> 5 | K15: =SUM(K3:K14) -> 14 | L15: =SUM(L3:L14) -> 5 | M15: =SUBTOTAL(9,J15:L15) -> 24 | N15: =SUM(N3:N14) -> 8 | O15: =SUM(O3:O14) -> 19 | P15: =SUM(P3:P14) -> 44 | Q15: =SUBTOTAL(9,N15:P15) -> 71 | R15: =SUBTOTAL(9,B15:Q15) -> 235 | S15: =SUM(S3:S14) -> 55 | T15: =SUM(T3:T14) -> 12 | U15: =SUM(U3:U14) -> 12 | V15: =SUBTOTAL(9,S15:U15) -> 79 | W15: =SUM(W3:W14) -> 5 | X15: =SUM(X3:X14) -> 2 | Y15: =SUM(Y3:Y14) -> 8 | Z15: =SUBTOTAL(9,W15:Y15) -> 15 | AA15: =SUM(AA3:AA14) -> 3 | AB15: =SUM(AB3:AB14) -> 12 | AC15: =SUM(AC3:AC14) -> 11 | AD15: =SUBTOTAL(9,AA15:AC15) -> 26 | AE15: =SUM(AE3:AE14) -> 6 | AF15: =SUM(AF3:AF14) -> 12 | AG15: =SUM(AG3:AG14) -> 6 | AH15: =SUBTOTAL(9,AE15:AG15) -> 24 | AI15: =SUBTOTAL(9,S15:AH15) -> 144 | AJ15: =SUM(AJ3:AJ14) -> 0 | AK15: =SUM(AK3:AK14) -> 0 | AL15: =SUM(AL3:AL14) -> 0 | AM15: =SUBTOTAL(9,AJ15:AL15) -> 0 | AN15: =SUM(AN3:AN14) -> 0 | AO15: =SUM(AO3:AO14) -> 0 | AP15: =SUM(AP3:AP14) -> 0 | AQ15: =SUBTOTAL(9,AN15:AP15) -> 0 | AR15: =SUM(AR3:AR14) -> 0 | AS15: =SUM(AS3:AS14) -> 0 | AT15: =SUM(AT3:AT14) -> 0 | AU15: =SUBTOTAL(9,AR15:AT15) -> 0 | AV15: =SUM(AV3:AV14) -> 0 | AW15: =SUM(AW3:AW14) -> 0 | AX15: =SUM(AX3:AX14) -> 0 | AY15: =SUBTOTAL(9,AV15:AX15) -> 0 | AZ15: =SUBTOTAL(9,AJ15:AY15) -> 0
A17: ="YTD "&A3 -> YTD eCommerce & Omni Channel | B17: =SUBTOTAL(9,$B3:B3) -> 8 | C17: =SUBTOTAL(9,$B3:C3) -> 8 | D17: =SUBTOTAL(9,$B3:D3) -> 9 | E17: =SUBTOTAL(9,$B3:E3) -> 9 | F17: =SUBTOTAL(9,$B3:F3) -> 9 | G17: =SUBTOTAL(9,$B3:G3) -> 9 | H17: =SUBTOTAL(9,$B3:H3) -> 9 | I17: =SUBTOTAL(9,$B3:I3) -> 9 | ... R17: =SUBTOTAL(9,$B3:R3) -> 31 | S17: =SUBTOTAL(9,$S3:S3) -> 1 | T17: =SUBTOTAL(9,$S3:T3) -> 1 | U17: =SUBTOTAL(9,$S3:U3) -> 1 | V17: =SUBTOTAL(9,$S3:V3) -> 1 | W17: =SUBTOTAL(9,$S3:W3) -> 3 | X17: =SUBTOTAL(9,$S3:X3) -> 3 | Y17: =SUBTOTAL(9,$S3:Y3) -> 9 | Z17: =SUBTOTAL(9,$S3:Z3) -> 9 | ... AI17: =SUBTOTAL(9,$S3:AI3) -> 15 | AJ17: =SUBTOTAL(9,$AJ3:AJ3) -> 0 | AK17: =SUBTOTAL(9,$AJ3:AK3) -> 0 | AL17: =SUBTOTAL(9,$AJ3:AL3) -> 0 | AM17: =SUBTOTAL(9,$AJ3:AM3) -> 0 | AN17: =SUBTOTAL(9,$AJ3:AN3) -> 0 | AO17: =SUBTOTAL(9,$AJ3:AO3) -> 0 | AP17: =SUBTOTAL(9,$AJ3:AP3) -> 0 | AQ17: =SUBTOTAL(9,$AJ3:AQ3) -> 0 | ... AZ17: =SUBTOTAL(9,$AJ3:AZ3) -> 0
A18: ="YTD "&A4 -> YTD FFM | B18: =SUBTOTAL(9,$B4:B4) -> 2 | C18: =SUBTOTAL(9,$B4:C4) -> 2 | D18: =SUBTOTAL(9,$B4:D4) -> 2 | E18: =SUBTOTAL(9,$B4:E4) -> 2 | F18: =SUBTOTAL(9,$B4:F4) -> 2 | G18: =SUBTOTAL(9,$B4:G4) -> 2 | H18: =SUBTOTAL(9,$B4:H4) -> 2 | I18: =SUBTOTAL(9,$B4:I4) -> 2 | ... R18: =SUBTOTAL(9,$B4:R4) -> 3 | S18: =SUBTOTAL(9,$S4:S4) -> 0 | T18: =SUBTOTAL(9,$S4:T4) -> 0 | U18: =SUBTOTAL(9,$S4:U4) -> 0 | V18: =SUBTOTAL(9,$S4:V4) -> 0 | W18: =SUBTOTAL(9,$S4:W4) -> 0 | X18: =SUBTOTAL(9,$S4:X4) -> 0 | Y18: =SUBTOTAL(9,$S4:Y4) -> 0 | Z18: =SUBTOTAL(9,$S4:Z4) -> 0 | ... AI18: =SUBTOTAL(9,$S4:AI4) -> 0 | AJ18: =SUBTOTAL(9,$AJ4:AJ4) -> 0 | AK18: =SUBTOTAL(9,$AJ4:AK4) -> 0 | AL18: =SUBTOTAL(9,$AJ4:AL4) -> 0 | AM18: =SUBTOTAL(9,$AJ4:AM4) -> 0 | AN18: =SUBTOTAL(9,$AJ4:AN4) -> 0 | AO18: =SUBTOTAL(9,$AJ4:AO4) -> 0 | AP18: =SUBTOTAL(9,$AJ4:AP4) -> 0 | AQ18: =SUBTOTAL(9,$AJ4:AQ4) -> 0 | ... AZ18: =SUBTOTAL(9,$AJ4:AZ4) -> 0
A19: ="YTD "&A5 -> YTD Finance | B19: =SUBTOTAL(9,$B5:B5) -> 2 | C19: =SUBTOTAL(9,$B5:C5) -> 2 | D19: =SUBTOTAL(9,$B5:D5) -> 2 | E19: =SUBTOTAL(9,$B5:E5) -> 2 | F19: =SUBTOTAL(9,$B5:F5) -> 2 | G19: =SUBTOTAL(9,$B5:G5) -> 2 | H19: =SUBTOTAL(9,$B5:H5) -> 2 | I19: =SUBTOTAL(9,$B5:I5) -> 2 | ... R19: =SUBTOTAL(9,$B5:R5) -> 2 | S19: =SUBTOTAL(9,$S5:S5) -> 0 | T19: =SUBTOTAL(9,$S5:T5) -> 0 | U19: =SUBTOTAL(9,$S5:U5) -> 0 | V19: =SUBTOTAL(9,$S5:V5) -> 0 | W19: =SUBTOTAL(9,$S5:W5) -> 0 | X19: =SUBTOTAL(9,$S5:X5) -> 0 | Y19: =SUBTOTAL(9,$S5:Y5) -> 0 | Z19: =SUBTOTAL(9,$S5:Z5) -> 0 | ... AI19: =SUBTOTAL(9,$S5:AI5) -> 7 | AJ19: =SUBTOTAL(9,$AJ5:AJ5) -> 0 | AK19: =SUBTOTAL(9,$AJ5:AK5) -> 0 | AL19: =SUBTOTAL(9,$AJ5:AL5) -> 0 | AM19: =SUBTOTAL(9,$AJ5:AM5) -> 0 | AN19: =SUBTOTAL(9,$AJ5:AN5) -> 0 | AO19: =SUBTOTAL(9,$AJ5:AO5) -> 0 | AP19: =SUBTOTAL(9,$AJ5:AP5) -> 0 | AQ19: =SUBTOTAL(9,$AJ5:AQ5) -> 0 | ... AZ19: =SUBTOTAL(9,$AJ5:AZ5) -> 0
A20: ="YTD "&A6 -> YTD Human Resources | B20: =SUBTOTAL(9,$B6:B6) -> 12 | C20: =SUBTOTAL(9,$B6:C6) -> 12 | D20: =SUBTOTAL(9,$B6:D6) -> 73 | E20: =SUBTOTAL(9,$B6:E6) -> 73 | F20: =SUBTOTAL(9,$B6:F6) -> 73 | G20: =SUBTOTAL(9,$B6:G6) -> 73 | H20: =SUBTOTAL(9,$B6:H6) -> 81 | I20: =SUBTOTAL(9,$B6:I6) -> 81 | ... R20: =SUBTOTAL(9,$B6:R6) -> 105 | S20: =SUBTOTAL(9,$S6:S6) -> 42 | T20: =SUBTOTAL(9,$S6:T6) -> 46 | U20: =SUBTOTAL(9,$S6:U6) -> 56 | V20: =SUBTOTAL(9,$S6:V6) -> 56 | W20: =SUBTOTAL(9,$S6:W6) -> 59 | X20: =SUBTOTAL(9,$S6:X6) -> 60 | Y20: =SUBTOTAL(9,$S6:Y6) -> 62 | Z20: =SUBTOTAL(9,$S6:Z6) -> 62 | ... AI20: =SUBTOTAL(9,$S6:AI6) -> 70 | AJ20: =SUBTOTAL(9,$AJ6:AJ6) -> 0 | AK20: =SUBTOTAL(9,$AJ6:AK6) -> 0 | AL20: =SUBTOTAL(9,$AJ6:AL6) -> 0 | AM20: =SUBTOTAL(9,$AJ6:AM6) -> 0 | AN20: =SUBTOTAL(9,$AJ6:AN6) -> 0 | AO20: =SUBTOTAL(9,$AJ6:AO6) -> 0 | AP20: =SUBTOTAL(9,$AJ6:AP6) -> 0 | AQ20: =SUBTOTAL(9,$AJ6:AQ6) -> 0 | ... AZ20: =SUBTOTAL(9,$AJ6:AZ6) -> 0
A21: ="YTD "&A7 -> YTD Insights & Analytics | B21: =SUBTOTAL(9,$B7:B7) -> 0 | C21: =SUBTOTAL(9,$B7:C7) -> 0 | D21: =SUBTOTAL(9,$B7:D7) -> 0 | E21: =SUBTOTAL(9,$B7:E7) -> 0 | F21: =SUBTOTAL(9,$B7:F7) -> 0 | G21: =SUBTOTAL(9,$B7:G7) -> 0 | H21: =SUBTOTAL(9,$B7:H7) -> 0 | I21: =SUBTOTAL(9,$B7:I7) -> 0 | ... R21: =SUBTOTAL(9,$B7:R7) -> 0 | S21: =SUBTOTAL(9,$S7:S7) -> 0 | T21: =SUBTOTAL(9,$S7:T7) -> 0 | U21: =SUBTOTAL(9,$S7:U7) -> 0 | V21: =SUBTOTAL(9,$S7:V7) -> 0 | W21: =SUBTOTAL(9,$S7:W7) -> 0 | X21: =SUBTOTAL(9,$S7:X7) -> 0 | Y21: =SUBTOTAL(9,$S7:Y7) -> 0 | Z21: =SUBTOTAL(9,$S7:Z7) -> 0 | ... AI21: =SUBTOTAL(9,$S7:AI7) -> 3 | AJ21: =SUBTOTAL(9,$AJ7:AJ7) -> 0 | AK21: =SUBTOTAL(9,$AJ7:AK7) -> 0 | AL21: =SUBTOTAL(9,$AJ7:AL7) -> 0 | AM21: =SUBTOTAL(9,$AJ7:AM7) -> 0 | AN21: =SUBTOTAL(9,$AJ7:AN7) -> 0 | AO21: =SUBTOTAL(9,$AJ7:AO7) -> 0 | AP21: =SUBTOTAL(9,$AJ7:AP7) -> 0 | AQ21: =SUBTOTAL(9,$AJ7:AQ7) -> 0 | ... AZ21: =SUBTOTAL(9,$AJ7:AZ7) -> 0
A22: ="YTD "&A8 -> YTD IT | B22: =SUBTOTAL(9,$B8:B8) -> 7 | C22: =SUBTOTAL(9,$B8:C8) -> 18 | D22: =SUBTOTAL(9,$B8:D8) -> 22 | E22: =SUBTOTAL(9,$B8:E8) -> 22 | F22: =SUBTOTAL(9,$B8:F8) -> 29 | G22: =SUBTOTAL(9,$B8:G8) -> 31 | H22: =SUBTOTAL(9,$B8:H8) -> 31 | I22: =SUBTOTAL(9,$B8:I8) -> 31 | ... R22: =SUBTOTAL(9,$B8:R8) -> 57 | S22: =SUBTOTAL(9,$S8:S8) -> 0 | T22: =SUBTOTAL(9,$S8:T8) -> 1 | U22: =SUBTOTAL(9,$S8:U8) -> 3 | V22: =SUBTOTAL(9,$S8:V8) -> 3 | W22: =SUBTOTAL(9,$S8:W8) -> 3 | X22: =SUBTOTAL(9,$S8:X8) -> 4 | Y22: =SUBTOTAL(9,$S8:Y8) -> 4 | Z22: =SUBTOTAL(9,$S8:Z8) -> 4 | ... AI22: =SUBTOTAL(9,$S8:AI8) -> 6 | AJ22: =SUBTOTAL(9,$AJ8:AJ8) -> 0 | AK22: =SUBTOTAL(9,$AJ8:AK8) -> 0 | AL22: =SUBTOTAL(9,$AJ8:AL8) -> 0 | AM22: =SUBTOTAL(9,$AJ8:AM8) -> 0 | AN22: =SUBTOTAL(9,$AJ8:AN8) -> 0 | AO22: =SUBTOTAL(9,$AJ8:AO8) -> 0 | AP22: =SUBTOTAL(9,$AJ8:AP8) -> 0 | AQ22: =SUBTOTAL(9,$AJ8:AQ8) -> 0 | ... AZ22: =SUBTOTAL(9,$AJ8:AZ8) -> 0
A23: ="YTD "&A9 -> YTD Marketing | B23: =SUBTOTAL(9,$B9:B9) -> 3 | C23: =SUBTOTAL(9,$B9:C9) -> 3 | D23: =SUBTOTAL(9,$B9:D9) -> 3 | E23: =SUBTOTAL(9,$B9:E9) -> 3 | F23: =SUBTOTAL(9,$B9:F9) -> 5 | G23: =SUBTOTAL(9,$B9:G9) -> 5 | H23: =SUBTOTAL(9,$B9:H9) -> 5 | I23: =SUBTOTAL(9,$B9:I9) -> 5 | ... R23: =SUBTOTAL(9,$B9:R9) -> 16 | S23: =SUBTOTAL(9,$S9:S9) -> 0 | T23: =SUBTOTAL(9,$S9:T9) -> 6 | U23: =SUBTOTAL(9,$S9:U9) -> 6 | V23: =SUBTOTAL(9,$S9:V9) -> 6 | W23: =SUBTOTAL(9,$S9:W9) -> 6 | X23: =SUBTOTAL(9,$S9:X9) -> 6 | Y23: =SUBTOTAL(9,$S9:Y9) -> 6 | Z23: =SUBTOTAL(9,$S9:Z9) -> 6 | ... AI23: =SUBTOTAL(9,$S9:AI9) -> 12 | AJ23: =SUBTOTAL(9,$AJ9:AJ9) -> 0 | AK23: =SUBTOTAL(9,$AJ9:AK9) -> 0 | AL23: =SUBTOTAL(9,$AJ9:AL9) -> 0 | AM23: =SUBTOTAL(9,$AJ9:AM9) -> 0 | AN23: =SUBTOTAL(9,$AJ9:AN9) -> 0 | AO23: =SUBTOTAL(9,$AJ9:AO9) -> 0 | AP23: =SUBTOTAL(9,$AJ9:AP9) -> 0 | AQ23: =SUBTOTAL(9,$AJ9:AQ9) -> 0 | ... AZ23: =SUBTOTAL(9,$AJ9:AZ9) -> 0
A24: ="YTD "&A10 -> YTD Property and Store Development | B24: =SUBTOTAL(9,$B10:B10) -> 2 | C24: =SUBTOTAL(9,$B10:C10) -> 3 | D24: =SUBTOTAL(9,$B10:D10) -> 3 | E24: =SUBTOTAL(9,$B10:E10) -> 3 | F24: =SUBTOTAL(9,$B10:F10) -> 3 | G24: =SUBTOTAL(9,$B10:G10) -> 3 | H24: =SUBTOTAL(9,$B10:H10) -> 4 | I24: =SUBTOTAL(9,$B10:I10) -> 4 | ... R24: =SUBTOTAL(9,$B10:R10) -> 10 | S24: =SUBTOTAL(9,$S10:S10) -> 7 | T24: =SUBTOTAL(9,$S10:T10) -> 8 | U24: =SUBTOTAL(9,$S10:U10) -> 8 | V24: =SUBTOTAL(9,$S10:V10) -> 8 | W24: =SUBTOTAL(9,$S10:W10) -> 8 | X24: =SUBTOTAL(9,$S10:X10) -> 8 | Y24: =SUBTOTAL(9,$S10:Y10) -> 8 | Z24: =SUBTOTAL(9,$S10:Z10) -> 8 | ... AI24: =SUBTOTAL(9,$S10:AI10) -> 12 | AJ24: =SUBTOTAL(9,$AJ10:AJ10) -> 0 | AK24: =SUBTOTAL(9,$AJ10:AK10) -> 0 | AL24: =SUBTOTAL(9,$AJ10:AL10) -> 0 | AM24: =SUBTOTAL(9,$AJ10:AM10) -> 0 | AN24: =SUBTOTAL(9,$AJ10:AN10) -> 0 | AO24: =SUBTOTAL(9,$AJ10:AO10) -> 0 | AP24: =SUBTOTAL(9,$AJ10:AP10) -> 0 | AQ24: =SUBTOTAL(9,$AJ10:AQ10) -> 0 | ... AZ24: =SUBTOTAL(9,$AJ10:AZ10) -> 0
A25: ="YTD "&A11 -> YTD SPG Development | B25: =SUBTOTAL(9,$B11:B11) -> 3 | C25: =SUBTOTAL(9,$B11:C11) -> 3 | D25: =SUBTOTAL(9,$B11:D11) -> 3 | E25: =SUBTOTAL(9,$B11:E11) -> 3 | F25: =SUBTOTAL(9,$B11:F11) -> 3 | G25: =SUBTOTAL(9,$B11:G11) -> 3 | H25: =SUBTOTAL(9,$B11:H11) -> 3 | I25: =SUBTOTAL(9,$B11:I11) -> 3 | ... R25: =SUBTOTAL(9,$B11:R11) -> 4 | S25: =SUBTOTAL(9,$S11:S11) -> 0 | T25: =SUBTOTAL(9,$S11:T11) -> 0 | U25: =SUBTOTAL(9,$S11:U11) -> 0 | V25: =SUBTOTAL(9,$S11:V11) -> 0 | W25: =SUBTOTAL(9,$S11:W11) -> 0 | X25: =SUBTOTAL(9,$S11:X11) -> 0 | Y25: =SUBTOTAL(9,$S11:Y11) -> 0 | Z25: =SUBTOTAL(9,$S11:Z11) -> 0 | ... AI25: =SUBTOTAL(9,$S11:AI11) -> 0 | AJ25: =SUBTOTAL(9,$AJ11:AJ11) -> 0 | AK25: =SUBTOTAL(9,$AJ11:AK11) -> 0 | AL25: =SUBTOTAL(9,$AJ11:AL11) -> 0 | AM25: =SUBTOTAL(9,$AJ11:AM11) -> 0 | AN25: =SUBTOTAL(9,$AJ11:AN11) -> 0 | AO25: =SUBTOTAL(9,$AJ11:AO11) -> 0 | AP25: =SUBTOTAL(9,$AJ11:AP11) -> 0 | AQ25: =SUBTOTAL(9,$AJ11:AQ11) -> 0 | ... AZ25: =SUBTOTAL(9,$AJ11:AZ11) -> 0
A26: ="YTD "&A12 -> YTD Spot Merch | B26: =SUBTOTAL(9,$B12:B12) -> 0 | C26: =SUBTOTAL(9,$B12:C12) -> 0 | D26: =SUBTOTAL(9,$B12:D12) -> 0 | E26: =SUBTOTAL(9,$B12:E12) -> 0 | F26: =SUBTOTAL(9,$B12:F12) -> 0 | G26: =SUBTOTAL(9,$B12:G12) -> 0 | H26: =SUBTOTAL(9,$B12:H12) -> 0 | I26: =SUBTOTAL(9,$B12:I12) -> 0 | ... R26: =SUBTOTAL(9,$B12:R12) -> 0 | S26: =SUBTOTAL(9,$S12:S12) -> 0 | T26: =SUBTOTAL(9,$S12:T12) -> 0 | U26: =SUBTOTAL(9,$S12:U12) -> 0 | V26: =SUBTOTAL(9,$S12:V12) -> 0 | W26: =SUBTOTAL(9,$S12:W12) -> 0 | X26: =SUBTOTAL(9,$S12:X12) -> 0 | Y26: =SUBTOTAL(9,$S12:Y12) -> 0 | Z26: =SUBTOTAL(9,$S12:Z12) -> 0 | ... AI26: =SUBTOTAL(9,$S12:AI12) -> 0 | AJ26: =SUBTOTAL(9,$AJ12:AJ12) -> 0 | AK26: =SUBTOTAL(9,$AJ12:AK12) -> 0 | AL26: =SUBTOTAL(9,$AJ12:AL12) -> 0 | AM26: =SUBTOTAL(9,$AJ12:AM12) -> 0 | AN26: =SUBTOTAL(9,$AJ12:AN12) -> 0 | AO26: =SUBTOTAL(9,$AJ12:AO12) -> 0 | AP26: =SUBTOTAL(9,$AJ12:AP12) -> 0 | AQ26: =SUBTOTAL(9,$AJ12:AQ12) -> 0 | ... AZ26: =SUBTOTAL(9,$AJ12:AZ12) -> 0
A27: ="YTD "&A13 -> YTD Spotlight Group Aviation | B27: =SUBTOTAL(9,$B13:B13) -> 0 | C27: =SUBTOTAL(9,$B13:C13) -> 0 | D27: =SUBTOTAL(9,$B13:D13) -> 0 | E27: =SUBTOTAL(9,$B13:E13) -> 0 | F27: =SUBTOTAL(9,$B13:F13) -> 0 | G27: =SUBTOTAL(9,$B13:G13) -> 0 | H27: =SUBTOTAL(9,$B13:H13) -> 0 | I27: =SUBTOTAL(9,$B13:I13) -> 0 | ... R27: =SUBTOTAL(9,$B13:R13) -> 0 | S27: =SUBTOTAL(9,$S13:S13) -> 0 | T27: =SUBTOTAL(9,$S13:T13) -> 0 | U27: =SUBTOTAL(9,$S13:U13) -> 0 | V27: =SUBTOTAL(9,$S13:V13) -> 0 | W27: =SUBTOTAL(9,$S13:W13) -> 0 | X27: =SUBTOTAL(9,$S13:X13) -> 0 | Y27: =SUBTOTAL(9,$S13:Y13) -> 0 | Z27: =SUBTOTAL(9,$S13:Z13) -> 0 | ... AI27: =SUBTOTAL(9,$S13:AI13) -> 1 | AJ27: =SUBTOTAL(9,$AJ13:AJ13) -> 0 | AK27: =SUBTOTAL(9,$AJ13:AK13) -> 0 | AL27: =SUBTOTAL(9,$AJ13:AL13) -> 0 | AM27: =SUBTOTAL(9,$AJ13:AM13) -> 0 | AN27: =SUBTOTAL(9,$AJ13:AN13) -> 0 | AO27: =SUBTOTAL(9,$AJ13:AO13) -> 0 | AP27: =SUBTOTAL(9,$AJ13:AP13) -> 0 | AQ27: =SUBTOTAL(9,$AJ13:AQ13) -> 0 | ... AZ27: =SUBTOTAL(9,$AJ13:AZ13) -> 0
A28: ="YTD "&A14 -> YTD Supply Chain | B28: =SUBTOTAL(9,$B14:B14) -> 0 | C28: =SUBTOTAL(9,$B14:C14) -> 2 | D28: =SUBTOTAL(9,$B14:D14) -> 3 | E28: =SUBTOTAL(9,$B14:E14) -> 3 | F28: =SUBTOTAL(9,$B14:F14) -> 3 | G28: =SUBTOTAL(9,$B14:G14) -> 3 | H28: =SUBTOTAL(9,$B14:H14) -> 3 | I28: =SUBTOTAL(9,$B14:I14) -> 3 | ... R28: =SUBTOTAL(9,$B14:R14) -> 7 | S28: =SUBTOTAL(9,$S14:S14) -> 5 | T28: =SUBTOTAL(9,$S14:T14) -> 5 | U28: =SUBTOTAL(9,$S14:U14) -> 5 | V28: =SUBTOTAL(9,$S14:V14) -> 5 | W28: =SUBTOTAL(9,$S14:W14) -> 5 | X28: =SUBTOTAL(9,$S14:X14) -> 5 | Y28: =SUBTOTAL(9,$S14:Y14) -> 5 | Z28: =SUBTOTAL(9,$S14:Z14) -> 5 | ... AI28: =SUBTOTAL(9,$S14:AI14) -> 18 | AJ28: =SUBTOTAL(9,$AJ14:AJ14) -> 0 | AK28: =SUBTOTAL(9,$AJ14:AK14) -> 0 | AL28: =SUBTOTAL(9,$AJ14:AL14) -> 0 | AM28: =SUBTOTAL(9,$AJ14:AM14) -> 0 | AN28: =SUBTOTAL(9,$AJ14:AN14) -> 0 | AO28: =SUBTOTAL(9,$AJ14:AO14) -> 0 | AP28: =SUBTOTAL(9,$AJ14:AP14) -> 0 | AQ28: =SUBTOTAL(9,$AJ14:AQ14) -> 0 | ... AZ28: =SUBTOTAL(9,$AJ14:AZ14) -> 0

Sheet In Progress FEED
A1: In Progress | B1: FY24 | S1: FY25 | AJ1: FY26
A2: Shared Services | B2: ="JUL, "&B1 -> JUL, FY24 | C2: ="AUG, "&B1 -> AUG, FY24 | D2: ="SEP, "&B1 -> SEP, FY24 | E2: ="Q1, "&B1 -> Q1, FY24 | F2: ="OCT, "&B1 -> OCT, FY24 | G2: ="NOV, "&B1 -> NOV, FY24 | H2: ="DEC, "&B1 -> DEC, FY24 | I2: ="Q2, "&B1 -> Q2, FY24 | J2: ="JAN, "&B1 -> JAN, FY24 | K2: ="FEB, "&B1 -> FEB, FY24 | L2: ="MAR, "&B1 -> MAR, FY24 | M2: ="Q3, "&B1 -> Q3, FY24 | N2: ="APR, "&B1 -> APR, FY24 | O2: ="MAY, "&B1 -> MAY, FY24 | P2: ="JUN, "&B1 -> JUN, FY24 | Q2: ="Q4, "&B1 -> Q4, FY24 | R2: ="Full Year, "&B1 -> Full Year, FY24 | S2: ="JUL, "&S1 -> JUL, FY25 | T2: ="AUG, "&S1 -> AUG, FY25 | U2: ="SEP, "&S1 -> SEP, FY25 | V2: ="Q1, "&S1 -> Q1, FY25 | W2: ="OCT, "&S1 -> OCT, FY25 | X2: ="NOV, "&S1 -> NOV, FY25 | Y2: ="DEC, "&S1 -> DEC, FY25 | Z2: ="Q2, "&S1 -> Q2, FY25 | AA2: ="JAN, "&S1 -> JAN, FY25 | AB2: ="FEB, "&S1 -> FEB, FY25 | AC2: ="MAR, "&S1 -> MAR, FY25 | AD2: ="Q3, "&S1 -> Q3, FY25 | AE2: ="APR, "&S1 -> APR, FY25 | AF2: ="MAY, "&S1 -> MAY, FY25 | AG2: ="JUN, "&S1 -> JUN, FY25 | AH2: ="Q4, "&S1 -> Q4, FY25 | AI2: ="Full Year, "&S1 -> Full Year, FY25 | AJ2: ="JUL, "&AJ1 -> JUL, FY26 | AK2: ="AUG, "&AJ1 -> AUG, FY26 | AL2: ="SEP, "&AJ1 -> SEP, FY26 | AM2: ="Q1, "&AJ1 -> Q1, FY26 | AN2: ="OCT, "&AJ1 -> OCT, FY26 | AO2: ="NOV, "&AJ1 -> NOV, FY26 | AP2: ="DEC, "&AJ1 -> DEC, FY26 | AQ2: ="Q2, "&AJ1 -> Q2, FY26 | AR2: ="JAN, "&AJ1 -> JAN, FY26 | AS2: ="FEB, "&AJ1 -> FEB, FY26 | AT2: ="MAR, "&AJ1 -> MAR, FY26 | AU2: ="Q3, "&AJ1 -> Q3, FY26 | AV2: ="APR, "&AJ1 -> APR, FY26 | AW2: ="MAY, "&AJ1 -> MAY, FY26 | AX2: ="JUN, "&AJ1 -> JUN, FY26 | AY2: ="Q4, "&AJ1 -> Q4, FY26 | AZ2: ="Full Year, "&AJ1 -> Full Year, FY26
A3: eCommerce & Omni Channel | B3: =COUNTIFS('Assigned Learning Data Dump'!$W:$W,'In Progress FEED'!$A3,'Assigned Learning Data Dump'!$F:$F,$A$1,'Assigned Learning Data Dump'!$U:$U,'In Progress FEED'!B$2) -> 1 | C3: =COUNTIFS('Assigned Learning Data Dump'!$W:$W,'In Progress FEED'!$A3,'Assigned Learning Data Dump'!$F:$F,$A$1,'Assigned Learning Data Dump'!$U:$U,'In Progress FEED'!C$2) -> 0 | D3: =COUNTIFS('Assigned Learning Data Dump'!$W:$W,'In Progress FEED'!$A3,'Assigned Learning Data Dump'!$F:$F,$A$1,'Assigned Learning Data Dump'!$U:$U,'In Progress FEED'!D$2) -> 1 | E3: =SUBTOTAL(9,B3:D3) -> 2 | F3: =COUNTIFS('Assigned Learning Data Dump'!$W:$W,'In Progress FEED'!$A3,'Assigned Learning Data Dump'!$F:$F,$A$1,'Assigned Learning Data Dump'!$U:$U,'In Progress FEED'!F$2) -> 0 | G3: =COUNTIFS('Assigned Learning Data Dump'!$W:$W,'In Progress FEED'!$A3,'Assigned Learning Data Dump'!$F:$F,$A$1,'Assigned Learning Data Dump'!$U:$U,'In Progress FEED'!G$2) -> 0 | H3: =COUNTIFS('Assigned Learning Data Dump'!$W:$W,'In Progress FEED'!$A3,'Assigned Learning Data Dump'!$F:$F,$A$1,'Assigned Learning Data Dump'!$U:$U,'In Progress FEED'!H$2) -> 0 | I3: =SUBTOTAL(9,F3:H3) -> 0 | J3: =COUNTIFS('Assigned Learning Data Dump'!$W:$W,'In Progress FEED'!$A3,'Assigned Learning Data Dump'!$F:$F,$A$1,'Assigned Learning Data Dump'!$U:$U,'In Progress FEED'!J$2) -> 0 | K3: =COUNTIFS('Assigned Learning Data Dump'!$W:$W,'In Progress FEED'!$A3,'Assigned Learning Data Dump'!$F:$F,$A$1,'Assigned Learning Data Dump'!$U:$U,'In Progress FEED'!K$2) -> 0 | L3: =COUNTIFS('Assigned Learning Data Dump'!$W:$W,'In Progress FEED'!$A3,'Assigned Learning Data Dump'!$F:$F,$A$1,'Assigned Learning Data Dump'!$U:$U,'In Progress FEED'!L$2) -> 3 | M3: =SUBTOTAL(9,J3:L3) -> 3 | N3: =COUNTIFS('Assigned Learning Data Dump'!$W:$W,'In Progress FEED'!$A3,'Assigned Learning Data Dump'!$F:$F,$A$1,'Assigned Learning Data Dump'!$U:$U,'In Progress FEED'!N$2) -> 0 | O3: =COUNTIFS('Assigned Learning Data Dump'!$W:$W,'In Progress FEED'!$A3,'Assigned Learning Data Dump'!$F:$F,$A$1,'Assigned Learning Data Dump'!$U:$U,'In Progress FEED'!O$2) -> 0 | P3: =COUNTIFS('Assigned Learning Data Dump'!$W:$W,'In Progress FEED'!$A3,'Assigned Learning Data Dump'!$F:$F,$A$1,'Assigned Learning Data Dump'!$U:$U,'In Progress FEED'!P$2) -> 4 | Q3: =SUBTOTAL(9,N3:P3) -> 4 | R3: =SUBTOTAL(9,B3:Q3) -> 9 | S3: =COUNTIFS('Assigned Learning Data Dump'!$W:$W,'In Progress FEED'!$A3,'Assigned Learning Data Dump'!$F:$F,$A$1,'Assigned Learning Data Dump'!$U:$U,'In Progress FEED'!S$2) -> 0 | T3: =COUNTIFS('Assigned Learning Data Dump'!$W:$W,'In Progress FEED'!$A3,'Assigned Learning Data Dump'!$F:$F,$A$1,'Assigned Learning Data Dump'!$U:$U,'In Progress FEED'!T$2) -> 0 | U3: =COUNTIFS('Assigned Learning Data Dump'!$W:$W,'In Progress FEED'!$A3,'Assigned Learning Data Dump'!$F:$F,$A$1,'Assigned Learning Data Dump'!$U:$U,'In Progress FEED'!U$2) -> 0 | V3: =SUBTOTAL(9,S3:U3) -> 0 | W3: =COUNTIFS('Assigned Learning Data Dump'!$W:$W,'In Progress FEED'!$A3,'Assigned Learning Data Dump'!$F:$F,$A$1,'Assigned Learning Data Dump'!$U:$U,'In Progress FEED'!W$2) -> 0 | X3: =COUNTIFS('Assigned Learning Data Dump'!$W:$W,'In Progress FEED'!$A3,'Assigned Learning Data Dump'!$F:$F,$A$1,'Assigned Learning Data Dump'!$U:$U,'In Progress FEED'!X$2) -> 0 | Y3: =COUNTIFS('Assigned Learning Data Dump'!$W:$W,'In Progress FEED'!$A3,'Assigned Learning Data Dump'!$F:$F,$A$1,'Assigned Learning Data Dump'!$U:$U,'In Progress FEED'!Y$2) -> 3 | Z3: =SUBTOTAL(9,W3:Y3) -> 3 | AA3: =COUNTIFS('Assigned Learning Data Dump'!$W:$W,'In Progress FEED'!$A3,'Assigned Learning Data Dump'!$F:$F,$A$1,'Assigned Learning Data Dump'!$U:$U,'In Progress FEED'!AA$2) -> 0 | AB3: =COUNTIFS('Assigned Learning Data Dump'!$W:$W,'In Progress FEED'!$A3,'Assigned Learning Data Dump'!$F:$F,$A$1,'Assigned Learning Data Dump'!$U:$U,'In Progress FEED'!AB$2) -> 0 | AC3: =COUNTIFS('Assigned Learning Data Dump'!$W:$W,'In Progress FEED'!$A3,'Assigned Learning Data Dump'!$F:$F,$A$1,'Assigned Learning Data Dump'!$U:$U,'In Progress FEED'!AC$2) -> 0 | AD3: =SUBTOTAL(9,AA3:AC3) -> 0 | AE3: =COUNTIFS('Assigned Learning Data Dump'!$W:$W,'In Progress FEED'!$A3,'Assigned Learning Data Dump'!$F:$F,$A$1,'Assigned Learning Data Dump'!$U:$U,'In Progress FEED'!AE$2) -> 0 | AF3: =COUNTIFS('Assigned Learning Data Dump'!$W:$W,'In Progress FEED'!$A3,'Assigned Learning Data Dump'!$F:$F,$A$1,'Assigned Learning Data Dump'!$U:$U,'In Progress FEED'!AF$2) -> 1 | AG3: =COUNTIFS('Assigned Learning Data Dump'!$W:$W,'In Progress FEED'!$A3,'Assigned Learning Data Dump'!$F:$F,$A$1,'Assigned Learning Data Dump'!$U:$U,'In Progress FEED'!AG$2) -> 2 | AH3: =SUBTOTAL(9,AE3:AG3) -> 3 | AI3: =SUBTOTAL(9,S3:AH3) -> 6 | AJ3: =COUNTIFS('Assigned Learning Data Dump'!$W:$W,'In Progress FEED'!$A3,'Assigned Learning Data Dump'!$F:$F,$A$1,'Assigned Learning Data Dump'!$U:$U,'In Progress FEED'!AJ$2) -> 1 | AK3: =COUNTIFS('Assigned Learning Data Dump'!$W:$W,'In Progress FEED'!$A3,'Assigned Learning Data Dump'!$F:$F,$A$1,'Assigned Learning Data Dump'!$U:$U,'In Progress FEED'!AK$2) -> 0 | AL3: =COUNTIFS('Assigned Learning Data Dump'!$W:$W,'In Progress FEED'!$A3,'Assigned Learning Data Dump'!$F:$F,$A$1,'Assigned Learning Data Dump'!$U:$U,'In Progress FEED'!AL$2) -> 0 | AM3: =SUBTOTAL(9,AJ3:AL3) -> 1 | AN3: =COUNTIFS('Assigned Learning Data Dump'!$W:$W,'In Progress FEED'!$A3,'Assigned Learning Data Dump'!$F:$F,$A$1,'Assigned Learning Data Dump'!$U:$U,'In Progress FEED'!AN$2) -> 0 | AO3: =COUNTIFS('Assigned Learning Data Dump'!$W:$W,'In Progress FEED'!$A3,'Assigned Learning Data Dump'!$F:$F,$A$1,'Assigned Learning Data Dump'!$U:$U,'In Progress FEED'!AO$2) -> 0 | AP3: =COUNTIFS('Assigned Learning Data Dump'!$W:$W,'In Progress FEED'!$A3,'Assigned Learning Data Dump'!$F:$F,$A$1,'Assigned Learning Data Dump'!$U:$U,'In Progress FEED'!AP$2) -> 0 | AQ3: =SUBTOTAL(9,AN3:AP3) -> 0 | AR3: =COUNTIFS('Assigned Learning Data Dump'!$W:$W,'In Progress FEED'!$A3,'Assigned Learning Data Dump'!$F:$F,$A$1,'Assigned Learning Data Dump'!$U:$U,'In Progress FEED'!AR$2) -> 0 | AS3: =COUNTIFS('Assigned Learning Data Dump'!$W:$W,'In Progress FEED'!$A3,'Assigned Learning Data Dump'!$F:$F,$A$1,'Assigned Learning Data Dump'!$U:$U,'In Progress FEED'!AS$2) -> 0 | AT3: =COUNTIFS('Assigned Learning Data Dump'!$W:$W,'In Progress FEED'!$A3,'Assigned Learning Data Dump'!$F:$F,$A$1,'Assigned Learning Data Dump'!$U:$U,'In Progress FEED'!AT$2) -> 0 | AU3: =SUBTOTAL(9,AR3:AT3) -> 0 | AV3: =COUNTIFS('Assigned Learning Data Dump'!$W:$W,'In Progress FEED'!$A3,'Assigned Learning Data Dump'!$F:$F,$A$1,'Assigned Learning Data Dump'!$U:$U,'In Progress FEED'!AV$2) -> 0 | AW3: =COUNTIFS('Assigned Learning Data Dump'!$W:$W,'In Progress FEED'!$A3,'Assigned Learning Data Dump'!$F:$F,$A$1,'Assigned Learning Data Dump'!$U:$U,'In Progress FEED'!AW$2) -> 0 | AX3: =COUNTIFS('Assigned Learning Data Dump'!$W:$W,'In Progress FEED'!$A3,'Assigned Learning Data Dump'!$F:$F,$A$1,'Assigned Learning Data Dump'!$U:$U,'In Progress FEED'!AX$2) -> 0 | AY3: =SUBTOTAL(9,AV3:AX3) -> 0 | AZ3: =SUBTOTAL(9,AJ3:AY3) -> 1
A4: FFM | B4: =COUNTIFS('Assigned Learning Data Dump'!$W:$W,'In Progress FEED'!$A4,'Assigned Learning Data Dump'!$F:$F,$A$1,'Assigned Learning Data Dump'!$U:$U,'In Progress FEED'!B$2) -> 0 | C4: =COUNTIFS('Assigned Learning Data Dump'!$W:$W,'In Progress FEED'!$A4,'Assigned Learning Data Dump'!$F:$F,$A$1,'Assigned Learning Data Dump'!$U:$U,'In Progress FEED'!C$2) -> 0 | D4: =COUNTIFS('Assigned Learning Data Dump'!$W:$W,'In Progress FEED'!$A4,'Assigned Learning Data Dump'!$F:$F,$A$1,'Assigned Learning Data Dump'!$U:$U,'In Progress FEED'!D$2) -> 0 | E4: =SUBTOTAL(9,B4:D4) -> 0 | F4: =COUNTIFS('Assigned Learning Data Dump'!$W:$W,'In Progress FEED'!$A4,'Assigned Learning Data Dump'!$F:$F,$A$1,'Assigned Learning Data Dump'!$U:$U,'In Progress FEED'!F$2) -> 0 | G4: =COUNTIFS('Assigned Learning Data Dump'!$W:$W,'In Progress FEED'!$A4,'Assigned Learning Data Dump'!$F:$F,$A$1,'Assigned Learning Data Dump'!$U:$U,'In Progress FEED'!G$2) -> 0 | H4: =COUNTIFS('Assigned Learning Data Dump'!$W:$W,'In Progress FEED'!$A4,'Assigned Learning Data Dump'!$F:$F,$A$1,'Assigned Learning Data Dump'!$U:$U,'In Progress FEED'!H$2) -> 0 | I4: =SUBTOTAL(9,F4:H4) -> 0 | J4: =COUNTIFS('Assigned Learning Data Dump'!$W:$W,'In Progress FEED'!$A4,'Assigned Learning Data Dump'!$F:$F,$A$1,'Assigned Learning Data Dump'!$U:$U,'In Progress FEED'!J$2) -> 2 | K4: =COUNTIFS('Assigned Learning Data Dump'!$W:$W,'In Progress FEED'!$A4,'Assigned Learning Data Dump'!$F:$F,$A$1,'Assigned Learning Data Dump'!$U:$U,'In Progress FEED'!K$2) -> 0 | L4: =COUNTIFS('Assigned Learning Data Dump'!$W:$W,'In Progress FEED'!$A4,'Assigned Learning Data Dump'!$F:$F,$A$1,'Assigned Learning Data Dump'!$U:$U,'In Progress FEED'!L$2) -> 0 | M4: =SUBTOTAL(9,J4:L4) -> 2 | N4: =COUNTIFS('Assigned Learning Data Dump'!$W:$W,'In Progress FEED'!$A4,'Assigned Learning Data Dump'!$F:$F,$A$1,'Assigned Learning Data Dump'!$U:$U,'In Progress FEED'!N$2) -> 0 | O4: =COUNTIFS('Assigned Learning Data Dump'!$W:$W,'In Progress FEED'!$A4,'Assigned Learning Data Dump'!$F:$F,$A$1,'Assigned Learning Data Dump'!$U:$U,'In Progress FEED'!O$2) -> 0 | P4: =COUNTIFS('Assigned Learning Data Dump'!$W:$W,'In Progress FEED'!$A4,'Assigned Learning Data Dump'!$F:$F,$A$1,'Assigned Learning Data Dump'!$U:$U,'In Progress FEED'!P$2) -> 0 | Q4: =SUBTOTAL(9,N4:P4) -> 0 | R4: =SUBTOTAL(9,B4:Q4) -> 2 | S4: =COUNTIFS('Assigned Learning Data Dump'!$W:$W,'In Progress FEED'!$A4,'Assigned Learning Data Dump'!$F:$F,$A$1,'Assigned Learning Data Dump'!$U:$U,'In Progress FEED'!S$2) -> 0 | T4: =COUNTIFS('Assigned Learning Data Dump'!$W:$W,'In Progress FEED'!$A4,'Assigned Learning Data Dump'!$F:$F,$A$1,'Assigned Learning Data Dump'!$U:$U,'In Progress FEED'!T$2) -> 1 | U4: =COUNTIFS('Assigned Learning Data Dump'!$W:$W,'In Progress FEED'!$A4,'Assigned Learning Data Dump'!$F:$F,$A$1,'Assigned Learning Data Dump'!$U:$U,'In Progress FEED'!U$2) -> 0 | V4: =SUBTOTAL(9,S4:U4) -> 1 | W4: =COUNTIFS('Assigned Learning Data Dump'!$W:$W,'In Progress FEED'!$A4,'Assigned Learning Data Dump'!$F:$F,$A$1,'Assigned Learning Data Dump'!$U:$U,'In Progress FEED'!W$2) -> 0 | X4: =COUNTIFS('Assigned Learning Data Dump'!$W:$W,'In Progress FEED'!$A4,'Assigned Learning Data Dump'!$F:$F,$A$1,'Assigned Learning Data Dump'!$U:$U,'In Progress FEED'!X$2) -> 0 | Y4: =COUNTIFS('Assigned Learning Data Dump'!$W:$W,'In Progress FEED'!$A4,'Assigned Learning Data Dump'!$F:$F,$A$1,'Assigned Learning Data Dump'!$U:$U,'In Progress FEED'!Y$2) -> 0 | Z4: =SUBTOTAL(9,W4:Y4) -> 0 | AA4: =COUNTIFS('Assigned Learning Data Dump'!$W:$W,'In Progress FEED'!$A4,'Assigned Learning Data Dump'!$F:$F,$A$1,'Assigned Learning Data Dump'!$U:$U,'In Progress FEED'!AA$2) -> 0 | AB4: =COUNTIFS('Assigned Learning Data Dump'!$W:$W,'In Progress FEED'!$A4,'Assigned Learning Data Dump'!$F:$F,$A$1,'Assigned Learning Data Dump'!$U:$U,'In Progress FEED'!AB$2) -> 0 | AC4: =COUNTIFS('Assigned Learning Data Dump'!$W:$W,'In Progress FEED'!$A4,'Assigned Learning Data Dump'!$F:$F,$A$1,'Assigned Learning Data Dump'!$U:$U,'In Progress FEED'!AC$2) -> 0 | AD4: =SUBTOTAL(9,AA4:AC4) -> 0 | AE4: =COUNTIFS('Assigned Learning Data Dump'!$W:$W,'In Progress FEED'!$A4,'Assigned Learning Data Dump'!$F:$F,$A$1,'Assigned Learning Data Dump'!$U:$U,'In Progress FEED'!AE$2) -> 0 | AF4: =COUNTIFS('Assigned Learning Data Dump'!$W:$W,'In Progress FEED'!$A4,'Assigned Learning Data Dump'!$F:$F,$A$1,'Assigned Learning Data Dump'!$U:$U,'In Progress FEED'!AF$2) -> 0 | AG4: =COUNTIFS('Assigned Learning Data Dump'!$W:$W,'In Progress FEED'!$A4,'Assigned Learning Data Dump'!$F:$F,$A$1,'Assigned Learning Data Dump'!$U:$U,'In Progress FEED'!AG$2) -> 0 | AH4: =SUBTOTAL(9,AE4:AG4) -> 0 | AI4: =SUBTOTAL(9,S4:AH4) -> 1 | AJ4: =COUNTIFS('Assigned Learning Data Dump'!$W:$W,'In Progress FEED'!$A4,'Assigned Learning Data Dump'!$F:$F,$A$1,'Assigned Learning Data Dump'!$U:$U,'In Progress FEED'!AJ$2) -> 0 | AK4: =COUNTIFS('Assigned Learning Data Dump'!$W:$W,'In Progress FEED'!$A4,'Assigned Learning Data Dump'!$F:$F,$A$1,'Assigned Learning Data Dump'!$U:$U,'In Progress FEED'!AK$2) -> 0 | AL4: =COUNTIFS('Assigned Learning Data Dump'!$W:$W,'In Progress FEED'!$A4,'Assigned Learning Data Dump'!$F:$F,$A$1,'Assigned Learning Data Dump'!$U:$U,'In Progress FEED'!AL$2) -> 0 | AM4: =SUBTOTAL(9,AJ4:AL4) -> 0 | AN4: =COUNTIFS('Assigned Learning Data Dump'!$W:$W,'In Progress FEED'!$A4,'Assigned Learning Data Dump'!$F:$F,$A$1,'Assigned Learning Data Dump'!$U:$U,'In Progress FEED'!AN$2) -> 0 | AO4: =COUNTIFS('Assigned Learning Data Dump'!$W:$W,'In Progress FEED'!$A4,'Assigned Learning Data Dump'!$F:$F,$A$1,'Assigned Learning Data Dump'!$U:$U,'In Progress FEED'!AO$2) -> 0 | AP4: =COUNTIFS('Assigned Learning Data Dump'!$W:$W,'In Progress FEED'!$A4,'Assigned Learning Data Dump'!$F:$F,$A$1,'Assigned Learning Data Dump'!$U:$U,'In Progress FEED'!AP$2) -> 0 | AQ4: =SUBTOTAL(9,AN4:AP4) -> 0 | AR4: =COUNTIFS('Assigned Learning Data Dump'!$W:$W,'In Progress FEED'!$A4,'Assigned Learning Data Dump'!$F:$F,$A$1,'Assigned Learning Data Dump'!$U:$U,'In Progress FEED'!AR$2) -> 0 | AS4: =COUNTIFS('Assigned Learning Data Dump'!$W:$W,'In Progress FEED'!$A4,'Assigned Learning Data Dump'!$F:$F,$A$1,'Assigned Learning Data Dump'!$U:$U,'In Progress FEED'!AS$2) -> 0 | AT4: =COUNTIFS('Assigned Learning Data Dump'!$W:$W,'In Progress FEED'!$A4,'Assigned Learning Data Dump'!$F:$F,$A$1,'Assigned Learning Data Dump'!$U:$U,'In Progress FEED'!AT$2) -> 0 | AU4: =SUBTOTAL(9,AR4:AT4) -> 0 | AV4: =COUNTIFS('Assigned Learning Data Dump'!$W:$W,'In Progress FEED'!$A4,'Assigned Learning Data Dump'!$F:$F,$A$1,'Assigned Learning Data Dump'!$U:$U,'In Progress FEED'!AV$2) -> 0 | AW4: =COUNTIFS('Assigned Learning Data Dump'!$W:$W,'In Progress FEED'!$A4,'Assigned Learning Data Dump'!$F:$F,$A$1,'Assigned Learning Data Dump'!$U:$U,'In Progress FEED'!AW$2) -> 0 | AX4: =COUNTIFS('Assigned Learning Data Dump'!$W:$W,'In Progress FEED'!$A4,'Assigned Learning Data Dump'!$F:$F,$A$1,'Assigned Learning Data Dump'!$U:$U,'In Progress FEED'!AX$2) -> 0 | AY4: =SUBTOTAL(9,AV4:AX4) -> 0 | AZ4: =SUBTOTAL(9,AJ4:AY4) -> 0
A5: Finance | B5: =COUNTIFS('Assigned Learning Data Dump'!$W:$W,'In Progress FEED'!$A5,'Assigned Learning Data Dump'!$F:$F,$A$1,'Assigned Learning Data Dump'!$U:$U,'In Progress FEED'!B$2) -> 0 | C5: =COUNTIFS('Assigned Learning Data Dump'!$W:$W,'In Progress FEED'!$A5,'Assigned Learning Data Dump'!$F:$F,$A$1,'Assigned Learning Data Dump'!$U:$U,'In Progress FEED'!C$2) -> 0 | D5: =COUNTIFS('Assigned Learning Data Dump'!$W:$W,'In Progress FEED'!$A5,'Assigned Learning Data Dump'!$F:$F,$A$1,'Assigned Learning Data Dump'!$U:$U,'In Progress FEED'!D$2) -> 0 | E5: =SUBTOTAL(9,B5:D5) -> 0 | F5: =COUNTIFS('Assigned Learning Data Dump'!$W:$W,'In Progress FEED'!$A5,'Assigned Learning Data Dump'!$F:$F,$A$1,'Assigned Learning Data Dump'!$U:$U,'In Progress FEED'!F$2) -> 0 | G5: =COUNTIFS('Assigned Learning Data Dump'!$W:$W,'In Progress FEED'!$A5,'Assigned Learning Data Dump'!$F:$F,$A$1,'Assigned Learning Data Dump'!$U:$U,'In Progress FEED'!G$2) -> 0 | H5: =COUNTIFS('Assigned Learning Data Dump'!$W:$W,'In Progress FEED'!$A5,'Assigned Learning Data Dump'!$F:$F,$A$1,'Assigned Learning Data Dump'!$U:$U,'In Progress FEED'!H$2) -> 0 | I5: =SUBTOTAL(9,F5:H5) -> 0 | J5: =COUNTIFS('Assigned Learning Data Dump'!$W:$W,'In Progress FEED'!$A5,'Assigned Learning Data Dump'!$F:$F,$A$1,'Assigned Learning Data Dump'!$U:$U,'In Progress FEED'!J$2) -> 0 | K5: =COUNTIFS('Assigned Learning Data Dump'!$W:$W,'In Progress FEED'!$A5,'Assigned Learning Data Dump'!$F:$F,$A$1,'Assigned Learning Data Dump'!$U:$U,'In Progress FEED'!K$2) -> 0 | L5: =COUNTIFS('Assigned Learning Data Dump'!$W:$W,'In Progress FEED'!$A5,'Assigned Learning Data Dump'!$F:$F,$A$1,'Assigned Learning Data Dump'!$U:$U,'In Progress FEED'!L$2) -> 0 | M5: =SUBTOTAL(9,J5:L5) -> 0 | N5: =COUNTIFS('Assigned Learning Data Dump'!$W:$W,'In Progress FEED'!$A5,'Assigned Learning Data Dump'!$F:$F,$A$1,'Assigned Learning Data Dump'!$U:$U,'In Progress FEED'!N$2) -> 0 | O5: =COUNTIFS('Assigned Learning Data Dump'!$W:$W,'In Progress FEED'!$A5,'Assigned Learning Data Dump'!$F:$F,$A$1,'Assigned Learning Data Dump'!$U:$U,'In Progress FEED'!O$2) -> 0 | P5: =COUNTIFS('Assigned Learning Data Dump'!$W:$W,'In Progress FEED'!$A5,'Assigned Learning Data Dump'!$F:$F,$A$1,'Assigned Learning Data Dump'!$U:$U,'In Progress FEED'!P$2) -> 1 | Q5: =SUBTOTAL(9,N5:P5) -> 1 | R5: =SUBTOTAL(9,B5:Q5) -> 1 | S5: =COUNTIFS('Assigned Learning Data Dump'!$W:$W,'In Progress FEED'!$A5,'Assigned Learning Data Dump'!$F:$F,$A$1,'Assigned Learning Data Dump'!$U:$U,'In Progress FEED'!S$2) -> 0 | T5: =COUNTIFS('Assigned Learning Data Dump'!$W:$W,'In Progress FEED'!$A5,'Assigned Learning Data Dump'!$F:$F,$A$1,'Assigned Learning Data Dump'!$U:$U,'In Progress FEED'!T$2) -> 0 | U5: =COUNTIFS('Assigned Learning Data Dump'!$W:$W,'In Progress FEED'!$A5,'Assigned Learning Data Dump'!$F:$F,$A$1,'Assigned Learning Data Dump'!$U:$U,'In Progress FEED'!U$2) -> 0 | V5: =SUBTOTAL(9,S5:U5) -> 0 | W5: =COUNTIFS('Assigned Learning Data Dump'!$W:$W,'In Progress FEED'!$A5,'Assigned Learning Data Dump'!$F:$F,$A$1,'Assigned Learning Data Dump'!$U:$U,'In Progress FEED'!W$2) -> 0 | X5: =COUNTIFS('Assigned Learning Data Dump'!$W:$W,'In Progress FEED'!$A5,'Assigned Learning Data Dump'!$F:$F,$A$1,'Assigned Learning Data Dump'!$U:$U,'In Progress FEED'!X$2) -> 0 | Y5: =COUNTIFS('Assigned Learning Data Dump'!$W:$W,'In Progress FEED'!$A5,'Assigned Learning Data Dump'!$F:$F,$A$1,'Assigned Learning Data Dump'!$U:$U,'In Progress FEED'!Y$2) -> 0 | Z5: =SUBTOTAL(9,W5:Y5) -> 0 | AA5: =COUNTIFS('Assigned Learning Data Dump'!$W:$W,'In Progress FEED'!$A5,'Assigned Learning Data Dump'!$F:$F,$A$1,'Assigned Learning Data Dump'!$U:$U,'In Progress FEED'!AA$2) -> 0 | AB5: =COUNTIFS('Assigned Learning Data Dump'!$W:$W,'In Progress FEED'!$A5,'Assigned Learning Data Dump'!$F:$F,$A$1,'Assigned Learning Data Dump'!$U:$U,'In Progress FEED'!AB$2) -> 0 | AC5: =COUNTIFS('Assigned Learning Data Dump'!$W:$W,'In Progress FEED'!$A5,'Assigned Learning Data Dump'!$F:$F,$A$1,'Assigned Learning Data Dump'!$U:$U,'In Progress FEED'!AC$2) -> 0 | AD5: =SUBTOTAL(9,AA5:AC5) -> 0 | AE5: =COUNTIFS('Assigned Learning Data Dump'!$W:$W,'In Progress FEED'!$A5,'Assigned Learning Data Dump'!$F:$F,$A$1,'Assigned Learning Data Dump'!$U:$U,'In Progress FEED'!AE$2) -> 0 | AF5: =COUNTIFS('Assigned Learning Data Dump'!$W:$W,'In Progress FEED'!$A5,'Assigned Learning Data Dump'!$F:$F,$A$1,'Assigned Learning Data Dump'!$U:$U,'In Progress FEED'!AF$2) -> 1 | AG5: =COUNTIFS('Assigned Learning Data Dump'!$W:$W,'In Progress FEED'!$A5,'Assigned Learning Data Dump'!$F:$F,$A$1,'Assigned Learning Data Dump'!$U:$U,'In Progress FEED'!AG$2) -> 2 | AH5: =SUBTOTAL(9,AE5:AG5) -> 3 | AI5: =SUBTOTAL(9,S5:AH5) -> 3 | AJ5: =COUNTIFS('Assigned Learning Data Dump'!$W:$W,'In Progress FEED'!$A5,'Assigned Learning Data Dump'!$F:$F,$A$1,'Assigned Learning Data Dump'!$U:$U,'In Progress FEED'!AJ$2) -> 0 | AK5: =COUNTIFS('Assigned Learning Data Dump'!$W:$W,'In Progress FEED'!$A5,'Assigned Learning Data Dump'!$F:$F,$A$1,'Assigned Learning Data Dump'!$U:$U,'In Progress FEED'!AK$2) -> 0 | AL5: =COUNTIFS('Assigned Learning Data Dump'!$W:$W,'In Progress FEED'!$A5,'Assigned Learning Data Dump'!$F:$F,$A$1,'Assigned Learning Data Dump'!$U:$U,'In Progress FEED'!AL$2) -> 0 | AM5: =SUBTOTAL(9,AJ5:AL5) -> 0 | AN5: =COUNTIFS('Assigned Learning Data Dump'!$W:$W,'In Progress FEED'!$A5,'Assigned Learning Data Dump'!$F:$F,$A$1,'Assigned Learning Data Dump'!$U:$U,'In Progress FEED'!AN$2) -> 0 | AO5: =COUNTIFS('Assigned Learning Data Dump'!$W:$W,'In Progress FEED'!$A5,'Assigned Learning Data Dump'!$F:$F,$A$1,'Assigned Learning Data Dump'!$U:$U,'In Progress FEED'!AO$2) -> 0 | AP5: =COUNTIFS('Assigned Learning Data Dump'!$W:$W,'In Progress FEED'!$A5,'Assigned Learning Data Dump'!$F:$F,$A$1,'Assigned Learning Data Dump'!$U:$U,'In Progress FEED'!AP$2) -> 0 | AQ5: =SUBTOTAL(9,AN5:AP5) -> 0 | AR5: =COUNTIFS('Assigned Learning Data Dump'!$W:$W,'In Progress FEED'!$A5,'Assigned Learning Data Dump'!$F:$F,$A$1,'Assigned Learning Data Dump'!$U:$U,'In Progress FEED'!AR$2) -> 0 | AS5: =COUNTIFS('Assigned Learning Data Dump'!$W:$W,'In Progress FEED'!$A5,'Assigned Learning Data Dump'!$F:$F,$A$1,'Assigned Learning Data Dump'!$U:$U,'In Progress FEED'!AS$2) -> 0 | AT5: =COUNTIFS('Assigned Learning Data Dump'!$W:$W,'In Progress FEED'!$A5,'Assigned Learning Data Dump'!$F:$F,$A$1,'Assigned Learning Data Dump'!$U:$U,'In Progress FEED'!AT$2) -> 0 | AU5: =SUBTOTAL(9,AR5:AT5) -> 0 | AV5: =COUNTIFS('Assigned Learning Data Dump'!$W:$W,'In Progress FEED'!$A5,'Assigned Learning Data Dump'!$F:$F,$A$1,'Assigned Learning Data Dump'!$U:$U,'In Progress FEED'!AV$2) -> 0 | AW5: =COUNTIFS('Assigned Learning Data Dump'!$W:$W,'In Progress FEED'!$A5,'Assigned Learning Data Dump'!$F:$F,$A$1,'Assigned Learning Data Dump'!$U:$U,'In Progress FEED'!AW$2) -> 0 | AX5: =COUNTIFS('Assigned Learning Data Dump'!$W:$W,'In Progress FEED'!$A5,'Assigned Learning Data Dump'!$F:$F,$A$1,'Assigned Learning Data Dump'!$U:$U,'In Progress FEED'!AX$2) -> 0 | AY5: =SUBTOTAL(9,AV5:AX5) -> 0 | AZ5: =SUBTOTAL(9,AJ5:AY5) -> 0
A6: Human Resources | B6: =COUNTIFS('Assigned Learning Data Dump'!$W:$W,'In Progress FEED'!$A6,'Assigned Learning Data Dump'!$F:$F,$A$1,'Assigned Learning Data Dump'!$U:$U,'In Progress FEED'!B$2) -> 3 | C6: =COUNTIFS('Assigned Learning Data Dump'!$W:$W,'In Progress FEED'!$A6,'Assigned Learning Data Dump'!$F:$F,$A$1,'Assigned Learning Data Dump'!$U:$U,'In Progress FEED'!C$2) -> 0 | D6: =COUNTIFS('Assigned Learning Data Dump'!$W:$W,'In Progress FEED'!$A6,'Assigned Learning Data Dump'!$F:$F,$A$1,'Assigned Learning Data Dump'!$U:$U,'In Progress FEED'!D$2) -> 1 | E6: =SUBTOTAL(9,B6:D6) -> 4 | F6: =COUNTIFS('Assigned Learning Data Dump'!$W:$W,'In Progress FEED'!$A6,'Assigned Learning Data Dump'!$F:$F,$A$1,'Assigned Learning Data Dump'!$U:$U,'In Progress FEED'!F$2) -> 0 | G6: =COUNTIFS('Assigned Learning Data Dump'!$W:$W,'In Progress FEED'!$A6,'Assigned Learning Data Dump'!$F:$F,$A$1,'Assigned Learning Data Dump'!$U:$U,'In Progress FEED'!G$2) -> 0 | H6: =COUNTIFS('Assigned Learning Data Dump'!$W:$W,'In Progress FEED'!$A6,'Assigned Learning Data Dump'!$F:$F,$A$1,'Assigned Learning Data Dump'!$U:$U,'In Progress FEED'!H$2) -> 0 | I6: =SUBTOTAL(9,F6:H6) -> 0 | J6: =COUNTIFS('Assigned Learning Data Dump'!$W:$W,'In Progress FEED'!$A6,'Assigned Learning Data Dump'!$F:$F,$A$1,'Assigned Learning Data Dump'!$U:$U,'In Progress FEED'!J$2) -> 1 | K6: =COUNTIFS('Assigned Learning Data Dump'!$W:$W,'In Progress FEED'!$A6,'Assigned Learning Data Dump'!$F:$F,$A$1,'Assigned Learning Data Dump'!$U:$U,'In Progress FEED'!K$2) -> 1 | L6: =COUNTIFS('Assigned Learning Data Dump'!$W:$W,'In Progress FEED'!$A6,'Assigned Learning Data Dump'!$F:$F,$A$1,'Assigned Learning Data Dump'!$U:$U,'In Progress FEED'!L$2) -> 0 | M6: =SUBTOTAL(9,J6:L6) -> 2 | N6: =COUNTIFS('Assigned Learning Data Dump'!$W:$W,'In Progress FEED'!$A6,'Assigned Learning Data Dump'!$F:$F,$A$1,'Assigned Learning Data Dump'!$U:$U,'In Progress FEED'!N$2) -> 0 | O6: =COUNTIFS('Assigned Learning Data Dump'!$W:$W,'In Progress FEED'!$A6,'Assigned Learning Data Dump'!$F:$F,$A$1,'Assigned Learning Data Dump'!$U:$U,'In Progress FEED'!O$2) -> 3 | P6: =COUNTIFS('Assigned Learning Data Dump'!$W:$W,'In Progress FEED'!$A6,'Assigned Learning Data Dump'!$F:$F,$A$1,'Assigned Learning Data Dump'!$U:$U,'In Progress FEED'!P$2) -> 2 | Q6: =SUBTOTAL(9,N6:P6) -> 5 | R6: =SUBTOTAL(9,B6:Q6) -> 11 | S6: =COUNTIFS('Assigned Learning Data Dump'!$W:$W,'In Progress FEED'!$A6,'Assigned Learning Data Dump'!$F:$F,$A$1,'Assigned Learning Data Dump'!$U:$U,'In Progress FEED'!S$2) -> 11 | T6: =COUNTIFS('Assigned Learning Data Dump'!$W:$W,'In Progress FEED'!$A6,'Assigned Learning Data Dump'!$F:$F,$A$1,'Assigned Learning Data Dump'!$U:$U,'In Progress FEED'!T$2) -> 0 | U6: =COUNTIFS('Assigned Learning Data Dump'!$W:$W,'In Progress FEED'!$A6,'Assigned Learning Data Dump'!$F:$F,$A$1,'Assigned Learning Data Dump'!$U:$U,'In Progress FEED'!U$2) -> 2 | V6: =SUBTOTAL(9,S6:U6) -> 13 | W6: =COUNTIFS('Assigned Learning Data Dump'!$W:$W,'In Progress FEED'!$A6,'Assigned Learning Data Dump'!$F:$F,$A$1,'Assigned Learning Data Dump'!$U:$U,'In Progress FEED'!W$2) -> 1 | X6: =COUNTIFS('Assigned Learning Data Dump'!$W:$W,'In Progress FEED'!$A6,'Assigned Learning Data Dump'!$F:$F,$A$1,'Assigned Learning Data Dump'!$U:$U,'In Progress FEED'!X$2) -> 2 | Y6: =COUNTIFS('Assigned Learning Data Dump'!$W:$W,'In Progress FEED'!$A6,'Assigned Learning Data Dump'!$F:$F,$A$1,'Assigned Learning Data Dump'!$U:$U,'In Progress FEED'!Y$2) -> 0 | Z6: =SUBTOTAL(9,W6:Y6) -> 3 | AA6: =COUNTIFS('Assigned Learning Data Dump'!$W:$W,'In Progress FEED'!$A6,'Assigned Learning Data Dump'!$F:$F,$A$1,'Assigned Learning Data Dump'!$U:$U,'In Progress FEED'!AA$2) -> 0 | AB6: =COUNTIFS('Assigned Learning Data Dump'!$W:$W,'In Progress FEED'!$A6,'Assigned Learning Data Dump'!$F:$F,$A$1,'Assigned Learning Data Dump'!$U:$U,'In Progress FEED'!AB$2) -> 0 | AC6: =COUNTIFS('Assigned Learning Data Dump'!$W:$W,'In Progress FEED'!$A6,'Assigned Learning Data Dump'!$F:$F,$A$1,'Assigned Learning Data Dump'!$U:$U,'In Progress FEED'!AC$2) -> 1 | AD6: =SUBTOTAL(9,AA6:AC6) -> 1 | AE6: =COUNTIFS('Assigned Learning Data Dump'!$W:$W,'In Progress FEED'!$A6,'Assigned Learning Data Dump'!$F:$F,$A$1,'Assigned Learning Data Dump'!$U:$U,'In Progress FEED'!AE$2) -> 0 | AF6: =COUNTIFS('Assigned Learning Data Dump'!$W:$W,'In Progress FEED'!$A6,'Assigned Learning Data Dump'!$F:$F,$A$1,'Assigned Learning Data Dump'!$U:$U,'In Progress FEED'!AF$2) -> 3 | AG6: =COUNTIFS('Assigned Learning Data Dump'!$W:$W,'In Progress FEED'!$A6,'Assigned Learning Data Dump'!$F:$F,$A$1,'Assigned Learning Data Dump'!$U:$U,'In Progress FEED'!AG$2) -> 0 | AH6: =SUBTOTAL(9,AE6:AG6) -> 3 | AI6: =SUBTOTAL(9,S6:AH6) -> 20 | AJ6: =COUNTIFS('Assigned Learning Data Dump'!$W:$W,'In Progress FEED'!$A6,'Assigned Learning Data Dump'!$F:$F,$A$1,'Assigned Learning Data Dump'!$U:$U,'In Progress FEED'!AJ$2) -> 0 | AK6: =COUNTIFS('Assigned Learning Data Dump'!$W:$W,'In Progress FEED'!$A6,'Assigned Learning Data Dump'!$F:$F,$A$1,'Assigned Learning Data Dump'!$U:$U,'In Progress FEED'!AK$2) -> 0 | AL6: =COUNTIFS('Assigned Learning Data Dump'!$W:$W,'In Progress FEED'!$A6,'Assigned Learning Data Dump'!$F:$F,$A$1,'Assigned Learning Data Dump'!$U:$U,'In Progress FEED'!AL$2) -> 0 | AM6: =SUBTOTAL(9,AJ6:AL6) -> 0 | AN6: =COUNTIFS('Assigned Learning Data Dump'!$W:$W,'In Progress FEED'!$A6,'Assigned Learning Data Dump'!$F:$F,$A$1,'Assigned Learning Data Dump'!$U:$U,'In Progress FEED'!AN$2) -> 0 | AO6: =COUNTIFS('Assigned Learning Data Dump'!$W:$W,'In Progress FEED'!$A6,'Assigned Learning Data Dump'!$F:$F,$A$1,'Assigned Learning Data Dump'!$U:$U,'In Progress FEED'!AO$2) -> 0 | AP6: =COUNTIFS('Assigned Learning Data Dump'!$W:$W,'In Progress FEED'!$A6,'Assigned Learning Data Dump'!$F:$F,$A$1,'Assigned Learning Data Dump'!$U:$U,'In Progress FEED'!AP$2) -> 0 | AQ6: =SUBTOTAL(9,AN6:AP6) -> 0 | AR6: =COUNTIFS('Assigned Learning Data Dump'!$W:$W,'In Progress FEED'!$A6,'Assigned Learning Data Dump'!$F:$F,$A$1,'Assigned Learning Data Dump'!$U:$U,'In Progress FEED'!AR$2) -> 0 | AS6: =COUNTIFS('Assigned Learning Data Dump'!$W:$W,'In Progress FEED'!$A6,'Assigned Learning Data Dump'!$F:$F,$A$1,'Assigned Learning Data Dump'!$U:$U,'In Progress FEED'!AS$2) -> 0 | AT6: =COUNTIFS('Assigned Learning Data Dump'!$W:$W,'In Progress FEED'!$A6,'Assigned Learning Data Dump'!$F:$F,$A$1,'Assigned Learning Data Dump'!$U:$U,'In Progress FEED'!AT$2) -> 0 | AU6: =SUBTOTAL(9,AR6:AT6) -> 0 | AV6: =COUNTIFS('Assigned Learning Data Dump'!$W:$W,'In Progress FEED'!$A6,'Assigned Learning Data Dump'!$F:$F,$A$1,'Assigned Learning Data Dump'!$U:$U,'In Progress FEED'!AV$2) -> 0 | AW6: =COUNTIFS('Assigned Learning Data Dump'!$W:$W,'In Progress FEED'!$A6,'Assigned Learning Data Dump'!$F:$F,$A$1,'Assigned Learning Data Dump'!$U:$U,'In Progress FEED'!AW$2) -> 0 | AX6: =COUNTIFS('Assigned Learning Data Dump'!$W:$W,'In Progress FEED'!$A6,'Assigned Learning Data Dump'!$F:$F,$A$1,'Assigned Learning Data Dump'!$U:$U,'In Progress FEED'!AX$2) -> 0 | AY6: =SUBTOTAL(9,AV6:AX6) -> 0 | AZ6: =SUBTOTAL(9,AJ6:AY6) -> 0
A7: Insights & Analytics | B7: =COUNTIFS('Assigned Learning Data Dump'!$W:$W,'In Progress FEED'!$A7,'Assigned Learning Data Dump'!$F:$F,$A$1,'Assigned Learning Data Dump'!$U:$U,'In Progress FEED'!B$2) -> 0 | C7: =COUNTIFS('Assigned Learning Data Dump'!$W:$W,'In Progress FEED'!$A7,'Assigned Learning Data Dump'!$F:$F,$A$1,'Assigned Learning Data Dump'!$U:$U,'In Progress FEED'!C$2) -> 0 | D7: =COUNTIFS('Assigned Learning Data Dump'!$W:$W,'In Progress FEED'!$A7,'Assigned Learning Data Dump'!$F:$F,$A$1,'Assigned Learning Data Dump'!$U:$U,'In Progress FEED'!D$2) -> 0 | E7: =SUBTOTAL(9,B7:D7) -> 0 | F7: =COUNTIFS('Assigned Learning Data Dump'!$W:$W,'In Progress FEED'!$A7,'Assigned Learning Data Dump'!$F:$F,$A$1,'Assigned Learning Data Dump'!$U:$U,'In Progress FEED'!F$2) -> 0 | G7: =COUNTIFS('Assigned Learning Data Dump'!$W:$W,'In Progress FEED'!$A7,'Assigned Learning Data Dump'!$F:$F,$A$1,'Assigned Learning Data Dump'!$U:$U,'In Progress FEED'!G$2) -> 0 | H7: =COUNTIFS('Assigned Learning Data Dump'!$W:$W,'In Progress FEED'!$A7,'Assigned Learning Data Dump'!$F:$F,$A$1,'Assigned Learning Data Dump'!$U:$U,'In Progress FEED'!H$2) -> 0 | I7: =SUBTOTAL(9,F7:H7) -> 0 | J7: =COUNTIFS('Assigned Learning Data Dump'!$W:$W,'In Progress FEED'!$A7,'Assigned Learning Data Dump'!$F:$F,$A$1,'Assigned Learning Data Dump'!$U:$U,'In Progress FEED'!J$2) -> 0 | K7: =COUNTIFS('Assigned Learning Data Dump'!$W:$W,'In Progress FEED'!$A7,'Assigned Learning Data Dump'!$F:$F,$A$1,'Assigned Learning Data Dump'!$U:$U,'In Progress FEED'!K$2) -> 0 | L7: =COUNTIFS('Assigned Learning Data Dump'!$W:$W,'In Progress FEED'!$A7,'Assigned Learning Data Dump'!$F:$F,$A$1,'Assigned Learning Data Dump'!$U:$U,'In Progress FEED'!L$2) -> 0 | M7: =SUBTOTAL(9,J7:L7) -> 0 | N7: =COUNTIFS('Assigned Learning Data Dump'!$W:$W,'In Progress FEED'!$A7,'Assigned Learning Data Dump'!$F:$F,$A$1,'Assigned Learning Data Dump'!$U:$U,'In Progress FEED'!N$2) -> 0 | O7: =COUNTIFS('Assigned Learning Data Dump'!$W:$W,'In Progress FEED'!$A7,'Assigned Learning Data Dump'!$F:$F,$A$1,'Assigned Learning Data Dump'!$U:$U,'In Progress FEED'!O$2) -> 0 | P7: =COUNTIFS('Assigned Learning Data Dump'!$W:$W,'In Progress FEED'!$A7,'Assigned Learning Data Dump'!$F:$F,$A$1,'Assigned Learning Data Dump'!$U:$U,'In Progress FEED'!P$2) -> 0 | Q7: =SUBTOTAL(9,N7:P7) -> 0 | R7: =SUBTOTAL(9,B7:Q7) -> 0 | S7: =COUNTIFS('Assigned Learning Data Dump'!$W:$W,'In Progress FEED'!$A7,'Assigned Learning Data Dump'!$F:$F,$A$1,'Assigned Learning Data Dump'!$U:$U,'In Progress FEED'!S$2) -> 0 | T7: =COUNTIFS('Assigned Learning Data Dump'!$W:$W,'In Progress FEED'!$A7,'Assigned Learning Data Dump'!$F:$F,$A$1,'Assigned Learning Data Dump'!$U:$U,'In Progress FEED'!T$2) -> 0 | U7: =COUNTIFS('Assigned Learning Data Dump'!$W:$W,'In Progress FEED'!$A7,'Assigned Learning Data Dump'!$F:$F,$A$1,'Assigned Learning Data Dump'!$U:$U,'In Progress FEED'!U$2) -> 0 | V7: =SUBTOTAL(9,S7:U7) -> 0 | W7: =COUNTIFS('Assigned Learning Data Dump'!$W:$W,'In Progress FEED'!$A7,'Assigned Learning Data Dump'!$F:$F,$A$1,'Assigned Learning Data Dump'!$U:$U,'In Progress FEED'!W$2) -> 0 | X7: =COUNTIFS('Assigned Learning Data Dump'!$W:$W,'In Progress FEED'!$A7,'Assigned Learning Data Dump'!$F:$F,$A$1,'Assigned Learning Data Dump'!$U:$U,'In Progress FEED'!X$2) -> 0 | Y7: =COUNTIFS('Assigned Learning Data Dump'!$W:$W,'In Progress FEED'!$A7,'Assigned Learning Data Dump'!$F:$F,$A$1,'Assigned Learning Data Dump'!$U:$U,'In Progress FEED'!Y$2) -> 0 | Z7: =SUBTOTAL(9,W7:Y7) -> 0 | AA7: =COUNTIFS('Assigned Learning Data Dump'!$W:$W,'In Progress FEED'!$A7,'Assigned Learning Data Dump'!$F:$F,$A$1,'Assigned Learning Data Dump'!$U:$U,'In Progress FEED'!AA$2) -> 0 | AB7: =COUNTIFS('Assigned Learning Data Dump'!$W:$W,'In Progress FEED'!$A7,'Assigned Learning Data Dump'!$F:$F,$A$1,'Assigned Learning Data Dump'!$U:$U,'In Progress FEED'!AB$2) -> 0 | AC7: =COUNTIFS('Assigned Learning Data Dump'!$W:$W,'In Progress FEED'!$A7,'Assigned Learning Data Dump'!$F:$F,$A$1,'Assigned Learning Data Dump'!$U:$U,'In Progress FEED'!AC$2) -> 0 | AD7: =SUBTOTAL(9,AA7:AC7) -> 0 | AE7: =COUNTIFS('Assigned Learning Data Dump'!$W:$W,'In Progress FEED'!$A7,'Assigned Learning Data Dump'!$F:$F,$A$1,'Assigned Learning Data Dump'!$U:$U,'In Progress FEED'!AE$2) -> 0 | AF7: =COUNTIFS('Assigned Learning Data Dump'!$W:$W,'In Progress FEED'!$A7,'Assigned Learning Data Dump'!$F:$F,$A$1,'Assigned Learning Data Dump'!$U:$U,'In Progress FEED'!AF$2) -> 0 | AG7: =COUNTIFS('Assigned Learning Data Dump'!$W:$W,'In Progress FEED'!$A7,'Assigned Learning Data Dump'!$F:$F,$A$1,'Assigned Learning Data Dump'!$U:$U,'In Progress FEED'!AG$2) -> 2 | AH7: =SUBTOTAL(9,AE7:AG7) -> 2 | AI7: =SUBTOTAL(9,S7:AH7) -> 2 | AJ7: =COUNTIFS('Assigned Learning Data Dump'!$W:$W,'In Progress FEED'!$A7,'Assigned Learning Data Dump'!$F:$F,$A$1,'Assigned Learning Data Dump'!$U:$U,'In Progress FEED'!AJ$2) -> 0 | AK7: =COUNTIFS('Assigned Learning Data Dump'!$W:$W,'In Progress FEED'!$A7,'Assigned Learning Data Dump'!$F:$F,$A$1,'Assigned Learning Data Dump'!$U:$U,'In Progress FEED'!AK$2) -> 0 | AL7: =COUNTIFS('Assigned Learning Data Dump'!$W:$W,'In Progress FEED'!$A7,'Assigned Learning Data Dump'!$F:$F,$A$1,'Assigned Learning Data Dump'!$U:$U,'In Progress FEED'!AL$2) -> 0 | AM7: =SUBTOTAL(9,AJ7:AL7) -> 0 | AN7: =COUNTIFS('Assigned Learning Data Dump'!$W:$W,'In Progress FEED'!$A7,'Assigned Learning Data Dump'!$F:$F,$A$1,'Assigned Learning Data Dump'!$U:$U,'In Progress FEED'!AN$2) -> 0 | AO7: =COUNTIFS('Assigned Learning Data Dump'!$W:$W,'In Progress FEED'!$A7,'Assigned Learning Data Dump'!$F:$F,$A$1,'Assigned Learning Data Dump'!$U:$U,'In Progress FEED'!AO$2) -> 0 | AP7: =COUNTIFS('Assigned Learning Data Dump'!$W:$W,'In Progress FEED'!$A7,'Assigned Learning Data Dump'!$F:$F,$A$1,'Assigned Learning Data Dump'!$U:$U,'In Progress FEED'!AP$2) -> 0 | AQ7: =SUBTOTAL(9,AN7:AP7) -> 0 | AR7: =COUNTIFS('Assigned Learning Data Dump'!$W:$W,'In Progress FEED'!$A7,'Assigned Learning Data Dump'!$F:$F,$A$1,'Assigned Learning Data Dump'!$U:$U,'In Progress FEED'!AR$2) -> 0 | AS7: =COUNTIFS('Assigned Learning Data Dump'!$W:$W,'In Progress FEED'!$A7,'Assigned Learning Data Dump'!$F:$F,$A$1,'Assigned Learning Data Dump'!$U:$U,'In Progress FEED'!AS$2) -> 0 | AT7: =COUNTIFS('Assigned Learning Data Dump'!$W:$W,'In Progress FEED'!$A7,'Assigned Learning Data Dump'!$F:$F,$A$1,'Assigned Learning Data Dump'!$U:$U,'In Progress FEED'!AT$2) -> 0 | AU7: =SUBTOTAL(9,AR7:AT7) -> 0 | AV7: =COUNTIFS('Assigned Learning Data Dump'!$W:$W,'In Progress FEED'!$A7,'Assigned Learning Data Dump'!$F:$F,$A$1,'Assigned Learning Data Dump'!$U:$U,'In Progress FEED'!AV$2) -> 0 | AW7: =COUNTIFS('Assigned Learning Data Dump'!$W:$W,'In Progress FEED'!$A7,'Assigned Learning Data Dump'!$F:$F,$A$1,'Assigned Learning Data Dump'!$U:$U,'In Progress FEED'!AW$2) -> 0 | AX7: =COUNTIFS('Assigned Learning Data Dump'!$W:$W,'In Progress FEED'!$A7,'Assigned Learning Data Dump'!$F:$F,$A$1,'Assigned Learning Data Dump'!$U:$U,'In Progress FEED'!AX$2) -> 0 | AY7: =SUBTOTAL(9,AV7:AX7) -> 0 | AZ7: =SUBTOTAL(9,AJ7:AY7) -> 0
A8: IT | B8: =COUNTIFS('Assigned Learning Data Dump'!$W:$W,'In Progress FEED'!$A8,'Assigned Learning Data Dump'!$F:$F,$A$1,'Assigned Learning Data Dump'!$U:$U,'In Progress FEED'!B$2) -> 3 | C8: =COUNTIFS('Assigned Learning Data Dump'!$W:$W,'In Progress FEED'!$A8,'Assigned Learning Data Dump'!$F:$F,$A$1,'Assigned Learning Data Dump'!$U:$U,'In Progress FEED'!C$2) -> 0 | D8: =COUNTIFS('Assigned Learning Data Dump'!$W:$W,'In Progress FEED'!$A8,'Assigned Learning Data Dump'!$F:$F,$A$1,'Assigned Learning Data Dump'!$U:$U,'In Progress FEED'!D$2) -> 0 | E8: =SUBTOTAL(9,B8:D8) -> 3 | F8: =COUNTIFS('Assigned Learning Data Dump'!$W:$W,'In Progress FEED'!$A8,'Assigned Learning Data Dump'!$F:$F,$A$1,'Assigned Learning Data Dump'!$U:$U,'In Progress FEED'!F$2) -> 4 | G8: =COUNTIFS('Assigned Learning Data Dump'!$W:$W,'In Progress FEED'!$A8,'Assigned Learning Data Dump'!$F:$F,$A$1,'Assigned Learning Data Dump'!$U:$U,'In Progress FEED'!G$2) -> 1 | H8: =COUNTIFS('Assigned Learning Data Dump'!$W:$W,'In Progress FEED'!$A8,'Assigned Learning Data Dump'!$F:$F,$A$1,'Assigned Learning Data Dump'!$U:$U,'In Progress FEED'!H$2) -> 2 | I8: =SUBTOTAL(9,F8:H8) -> 7 | J8: =COUNTIFS('Assigned Learning Data Dump'!$W:$W,'In Progress FEED'!$A8,'Assigned Learning Data Dump'!$F:$F,$A$1,'Assigned Learning Data Dump'!$U:$U,'In Progress FEED'!J$2) -> 0 | K8: =COUNTIFS('Assigned Learning Data Dump'!$W:$W,'In Progress FEED'!$A8,'Assigned Learning Data Dump'!$F:$F,$A$1,'Assigned Learning Data Dump'!$U:$U,'In Progress FEED'!K$2) -> 0 | L8: =COUNTIFS('Assigned Learning Data Dump'!$W:$W,'In Progress FEED'!$A8,'Assigned Learning Data Dump'!$F:$F,$A$1,'Assigned Learning Data Dump'!$U:$U,'In Progress FEED'!L$2) -> 0 | M8: =SUBTOTAL(9,J8:L8) -> 0 | N8: =COUNTIFS('Assigned Learning Data Dump'!$W:$W,'In Progress FEED'!$A8,'Assigned Learning Data Dump'!$F:$F,$A$1,'Assigned Learning Data Dump'!$U:$U,'In Progress FEED'!N$2) -> 0 | O8: =COUNTIFS('Assigned Learning Data Dump'!$W:$W,'In Progress FEED'!$A8,'Assigned Learning Data Dump'!$F:$F,$A$1,'Assigned Learning Data Dump'!$U:$U,'In Progress FEED'!O$2) -> 3 | P8: =COUNTIFS('Assigned Learning Data Dump'!$W:$W,'In Progress FEED'!$A8,'Assigned Learning Data Dump'!$F:$F,$A$1,'Assigned Learning Data Dump'!$U:$U,'In Progress FEED'!P$2) -> 4 | Q8: =SUBTOTAL(9,N8:P8) -> 7 | R8: =SUBTOTAL(9,B8:Q8) -> 17 | S8: =COUNTIFS('Assigned Learning Data Dump'!$W:$W,'In Progress FEED'!$A8,'Assigned Learning Data Dump'!$F:$F,$A$1,'Assigned Learning Data Dump'!$U:$U,'In Progress FEED'!S$2) -> 5 | T8: =COUNTIFS('Assigned Learning Data Dump'!$W:$W,'In Progress FEED'!$A8,'Assigned Learning Data Dump'!$F:$F,$A$1,'Assigned Learning Data Dump'!$U:$U,'In Progress FEED'!T$2) -> 1 | U8: =COUNTIFS('Assigned Learning Data Dump'!$W:$W,'In Progress FEED'!$A8,'Assigned Learning Data Dump'!$F:$F,$A$1,'Assigned Learning Data Dump'!$U:$U,'In Progress FEED'!U$2) -> 0 | V8: =SUBTOTAL(9,S8:U8) -> 6 | W8: =COUNTIFS('Assigned Learning Data Dump'!$W:$W,'In Progress FEED'!$A8,'Assigned Learning Data Dump'!$F:$F,$A$1,'Assigned Learning Data Dump'!$U:$U,'In Progress FEED'!W$2) -> 0 | X8: =COUNTIFS('Assigned Learning Data Dump'!$W:$W,'In Progress FEED'!$A8,'Assigned Learning Data Dump'!$F:$F,$A$1,'Assigned Learning Data Dump'!$U:$U,'In Progress FEED'!X$2) -> 0 | Y8: =COUNTIFS('Assigned Learning Data Dump'!$W:$W,'In Progress FEED'!$A8,'Assigned Learning Data Dump'!$F:$F,$A$1,'Assigned Learning Data Dump'!$U:$U,'In Progress FEED'!Y$2) -> 0 | Z8: =SUBTOTAL(9,W8:Y8) -> 0 | AA8: =COUNTIFS('Assigned Learning Data Dump'!$W:$W,'In Progress FEED'!$A8,'Assigned Learning Data Dump'!$F:$F,$A$1,'Assigned Learning Data Dump'!$U:$U,'In Progress FEED'!AA$2) -> 0 | AB8: =COUNTIFS('Assigned Learning Data Dump'!$W:$W,'In Progress FEED'!$A8,'Assigned Learning Data Dump'!$F:$F,$A$1,'Assigned Learning Data Dump'!$U:$U,'In Progress FEED'!AB$2) -> 2 | AC8: =COUNTIFS('Assigned Learning Data Dump'!$W:$W,'In Progress FEED'!$A8,'Assigned Learning Data Dump'!$F:$F,$A$1,'Assigned Learning Data Dump'!$U:$U,'In Progress FEED'!AC$2) -> 0 | AD8: =SUBTOTAL(9,AA8:AC8) -> 2 | AE8: =COUNTIFS('Assigned Learning Data Dump'!$W:$W,'In Progress FEED'!$A8,'Assigned Learning Data Dump'!$F:$F,$A$1,'Assigned Learning Data Dump'!$U:$U,'In Progress FEED'!AE$2) -> 0 | AF8: =COUNTIFS('Assigned Learning Data Dump'!$W:$W,'In Progress FEED'!$A8,'Assigned Learning Data Dump'!$F:$F,$A$1,'Assigned Learning Data Dump'!$U:$U,'In Progress FEED'!AF$2) -> 0 | AG8: =COUNTIFS('Assigned Learning Data Dump'!$W:$W,'In Progress FEED'!$A8,'Assigned Learning Data Dump'!$F:$F,$A$1,'Assigned Learning Data Dump'!$U:$U,'In Progress FEED'!AG$2) -> 0 | AH8: =SUBTOTAL(9,AE8:AG8) -> 0 | AI8: =SUBTOTAL(9,S8:AH8) -> 8 | AJ8: =COUNTIFS('Assigned Learning Data Dump'!$W:$W,'In Progress FEED'!$A8,'Assigned Learning Data Dump'!$F:$F,$A$1,'Assigned Learning Data Dump'!$U:$U,'In Progress FEED'!AJ$2) -> 0 | AK8: =COUNTIFS('Assigned Learning Data Dump'!$W:$W,'In Progress FEED'!$A8,'Assigned Learning Data Dump'!$F:$F,$A$1,'Assigned Learning Data Dump'!$U:$U,'In Progress FEED'!AK$2) -> 0 | AL8: =COUNTIFS('Assigned Learning Data Dump'!$W:$W,'In Progress FEED'!$A8,'Assigned Learning Data Dump'!$F:$F,$A$1,'Assigned Learning Data Dump'!$U:$U,'In Progress FEED'!AL$2) -> 0 | AM8: =SUBTOTAL(9,AJ8:AL8) -> 0 | AN8: =COUNTIFS('Assigned Learning Data Dump'!$W:$W,'In Progress FEED'!$A8,'Assigned Learning Data Dump'!$F:$F,$A$1,'Assigned Learning Data Dump'!$U:$U,'In Progress FEED'!AN$2) -> 0 | AO8: =COUNTIFS('Assigned Learning Data Dump'!$W:$W,'In Progress FEED'!$A8,'Assigned Learning Data Dump'!$F:$F,$A$1,'Assigned Learning Data Dump'!$U:$U,'In Progress FEED'!AO$2) -> 0 | AP8: =COUNTIFS('Assigned Learning Data Dump'!$W:$W,'In Progress FEED'!$A8,'Assigned Learning Data Dump'!$F:$F,$A$1,'Assigned Learning Data Dump'!$U:$U,'In Progress FEED'!AP$2) -> 0 | AQ8: =SUBTOTAL(9,AN8:AP8) -> 0 | AR8: =COUNTIFS('Assigned Learning Data Dump'!$W:$W,'In Progress FEED'!$A8,'Assigned Learning Data Dump'!$F:$F,$A$1,'Assigned Learning Data Dump'!$U:$U,'In Progress FEED'!AR$2) -> 0 | AS8: =COUNTIFS('Assigned Learning Data Dump'!$W:$W,'In Progress FEED'!$A8,'Assigned Learning Data Dump'!$F:$F,$A$1,'Assigned Learning Data Dump'!$U:$U,'In Progress FEED'!AS$2) -> 0 | AT8: =COUNTIFS('Assigned Learning Data Dump'!$W:$W,'In Progress FEED'!$A8,'Assigned Learning Data Dump'!$F:$F,$A$1,'Assigned Learning Data Dump'!$U:$U,'In Progress FEED'!AT$2) -> 0 | AU8: =SUBTOTAL(9,AR8:AT8) -> 0 | AV8: =COUNTIFS('Assigned Learning Data Dump'!$W:$W,'In Progress FEED'!$A8,'Assigned Learning Data Dump'!$F:$F,$A$1,'Assigned Learning Data Dump'!$U:$U,'In Progress FEED'!AV$2) -> 0 | AW8: =COUNTIFS('Assigned Learning Data Dump'!$W:$W,'In Progress FEED'!$A8,'Assigned Learning Data Dump'!$F:$F,$A$1,'Assigned Learning Data Dump'!$U:$U,'In Progress FEED'!AW$2) -> 0 | AX8: =COUNTIFS('Assigned Learning Data Dump'!$W:$W,'In Progress FEED'!$A8,'Assigned Learning Data Dump'!$F:$F,$A$1,'Assigned Learning Data Dump'!$U:$U,'In Progress FEED'!AX$2) -> 0 | AY8: =SUBTOTAL(9,AV8:AX8) -> 0 | AZ8: =SUBTOTAL(9,AJ8:AY8) -> 0
A9: Marketing | B9: =COUNTIFS('Assigned Learning Data Dump'!$W:$W,'In Progress FEED'!$A9,'Assigned Learning Data Dump'!$F:$F,$A$1,'Assigned Learning Data Dump'!$U:$U,'In Progress FEED'!B$2) -> 2 | C9: =COUNTIFS('Assigned Learning Data Dump'!$W:$W,'In Progress FEED'!$A9,'Assigned Learning Data Dump'!$F:$F,$A$1,'Assigned Learning Data Dump'!$U:$U,'In Progress FEED'!C$2) -> 4 | D9: =COUNTIFS('Assigned Learning Data Dump'!$W:$W,'In Progress FEED'!$A9,'Assigned Learning Data Dump'!$F:$F,$A$1,'Assigned Learning Data Dump'!$U:$U,'In Progress FEED'!D$2) -> 0 | E9: =SUBTOTAL(9,B9:D9) -> 6 | F9: =COUNTIFS('Assigned Learning Data Dump'!$W:$W,'In Progress FEED'!$A9,'Assigned Learning Data Dump'!$F:$F,$A$1,'Assigned Learning Data Dump'!$U:$U,'In Progress FEED'!F$2) -> 0 | G9: =COUNTIFS('Assigned Learning Data Dump'!$W:$W,'In Progress FEED'!$A9,'Assigned Learning Data Dump'!$F:$F,$A$1,'Assigned Learning Data Dump'!$U:$U,'In Progress FEED'!G$2) -> 0 | H9: =COUNTIFS('Assigned Learning Data Dump'!$W:$W,'In Progress FEED'!$A9,'Assigned Learning Data Dump'!$F:$F,$A$1,'Assigned Learning Data Dump'!$U:$U,'In Progress FEED'!H$2) -> 0 | I9: =SUBTOTAL(9,F9:H9) -> 0 | J9: =COUNTIFS('Assigned Learning Data Dump'!$W:$W,'In Progress FEED'!$A9,'Assigned Learning Data Dump'!$F:$F,$A$1,'Assigned Learning Data Dump'!$U:$U,'In Progress FEED'!J$2) -> 0 | K9: =COUNTIFS('Assigned Learning Data Dump'!$W:$W,'In Progress FEED'!$A9,'Assigned Learning Data Dump'!$F:$F,$A$1,'Assigned Learning Data Dump'!$U:$U,'In Progress FEED'!K$2) -> 0 | L9: =COUNTIFS('Assigned Learning Data Dump'!$W:$W,'In Progress FEED'!$A9,'Assigned Learning Data Dump'!$F:$F,$A$1,'Assigned Learning Data Dump'!$U:$U,'In Progress FEED'!L$2) -> 0 | M9: =SUBTOTAL(9,J9:L9) -> 0 | N9: =COUNTIFS('Assigned Learning Data Dump'!$W:$W,'In Progress FEED'!$A9,'Assigned Learning Data Dump'!$F:$F,$A$1,'Assigned Learning Data Dump'!$U:$U,'In Progress FEED'!N$2) -> 0 | O9: =COUNTIFS('Assigned Learning Data Dump'!$W:$W,'In Progress FEED'!$A9,'Assigned Learning Data Dump'!$F:$F,$A$1,'Assigned Learning Data Dump'!$U:$U,'In Progress FEED'!O$2) -> 3 | P9: =COUNTIFS('Assigned Learning Data Dump'!$W:$W,'In Progress FEED'!$A9,'Assigned Learning Data Dump'!$F:$F,$A$1,'Assigned Learning Data Dump'!$U:$U,'In Progress FEED'!P$2) -> 2 | Q9: =SUBTOTAL(9,N9:P9) -> 5 | R9: =SUBTOTAL(9,B9:Q9) -> 11 | S9: =COUNTIFS('Assigned Learning Data Dump'!$W:$W,'In Progress FEED'!$A9,'Assigned Learning Data Dump'!$F:$F,$A$1,'Assigned Learning Data Dump'!$U:$U,'In Progress FEED'!S$2) -> 1 | T9: =COUNTIFS('Assigned Learning Data Dump'!$W:$W,'In Progress FEED'!$A9,'Assigned Learning Data Dump'!$F:$F,$A$1,'Assigned Learning Data Dump'!$U:$U,'In Progress FEED'!T$2) -> 0 | U9: =COUNTIFS('Assigned Learning Data Dump'!$W:$W,'In Progress FEED'!$A9,'Assigned Learning Data Dump'!$F:$F,$A$1,'Assigned Learning Data Dump'!$U:$U,'In Progress FEED'!U$2) -> 0 | V9: =SUBTOTAL(9,S9:U9) -> 1 | W9: =COUNTIFS('Assigned Learning Data Dump'!$W:$W,'In Progress FEED'!$A9,'Assigned Learning Data Dump'!$F:$F,$A$1,'Assigned Learning Data Dump'!$U:$U,'In Progress FEED'!W$2) -> 0 | X9: =COUNTIFS('Assigned Learning Data Dump'!$W:$W,'In Progress FEED'!$A9,'Assigned Learning Data Dump'!$F:$F,$A$1,'Assigned Learning Data Dump'!$U:$U,'In Progress FEED'!X$2) -> 0 | Y9: =COUNTIFS('Assigned Learning Data Dump'!$W:$W,'In Progress FEED'!$A9,'Assigned Learning Data Dump'!$F:$F,$A$1,'Assigned Learning Data Dump'!$U:$U,'In Progress FEED'!Y$2) -> 1 | Z9: =SUBTOTAL(9,W9:Y9) -> 1 | AA9: =COUNTIFS('Assigned Learning Data Dump'!$W:$W,'In Progress FEED'!$A9,'Assigned Learning Data Dump'!$F:$F,$A$1,'Assigned Learning Data Dump'!$U:$U,'In Progress FEED'!AA$2) -> 0 | AB9: =COUNTIFS('Assigned Learning Data Dump'!$W:$W,'In Progress FEED'!$A9,'Assigned Learning Data Dump'!$F:$F,$A$1,'Assigned Learning Data Dump'!$U:$U,'In Progress FEED'!AB$2) -> 0 | AC9: =COUNTIFS('Assigned Learning Data Dump'!$W:$W,'In Progress FEED'!$A9,'Assigned Learning Data Dump'!$F:$F,$A$1,'Assigned Learning Data Dump'!$U:$U,'In Progress FEED'!AC$2) -> 1 | AD9: =SUBTOTAL(9,AA9:AC9) -> 1 | AE9: =COUNTIFS('Assigned Learning Data Dump'!$W:$W,'In Progress FEED'!$A9,'Assigned Learning Data Dump'!$F:$F,$A$1,'Assigned Learning Data Dump'!$U:$U,'In Progress FEED'!AE$2) -> 0 | AF9: =COUNTIFS('Assigned Learning Data Dump'!$W:$W,'In Progress FEED'!$A9,'Assigned Learning Data Dump'!$F:$F,$A$1,'Assigned Learning Data Dump'!$U:$U,'In Progress FEED'!AF$2) -> 0 | AG9: =COUNTIFS('Assigned Learning Data Dump'!$W:$W,'In Progress FEED'!$A9,'Assigned Learning Data Dump'!$F:$F,$A$1,'Assigned Learning Data Dump'!$U:$U,'In Progress FEED'!AG$2) -> 0 | AH9: =SUBTOTAL(9,AE9:AG9) -> 0 | AI9: =SUBTOTAL(9,S9:AH9) -> 3 | AJ9: =COUNTIFS('Assigned Learning Data Dump'!$W:$W,'In Progress FEED'!$A9,'Assigned Learning Data Dump'!$F:$F,$A$1,'Assigned Learning Data Dump'!$U:$U,'In Progress FEED'!AJ$2) -> 0 | AK9: =COUNTIFS('Assigned Learning Data Dump'!$W:$W,'In Progress FEED'!$A9,'Assigned Learning Data Dump'!$F:$F,$A$1,'Assigned Learning Data Dump'!$U:$U,'In Progress FEED'!AK$2) -> 0 | AL9: =COUNTIFS('Assigned Learning Data Dump'!$W:$W,'In Progress FEED'!$A9,'Assigned Learning Data Dump'!$F:$F,$A$1,'Assigned Learning Data Dump'!$U:$U,'In Progress FEED'!AL$2) -> 0 | AM9: =SUBTOTAL(9,AJ9:AL9) -> 0 | AN9: =COUNTIFS('Assigned Learning Data Dump'!$W:$W,'In Progress FEED'!$A9,'Assigned Learning Data Dump'!$F:$F,$A$1,'Assigned Learning Data Dump'!$U:$U,'In Progress FEED'!AN$2) -> 0 | AO9: =COUNTIFS('Assigned Learning Data Dump'!$W:$W,'In Progress FEED'!$A9,'Assigned Learning Data Dump'!$F:$F,$A$1,'Assigned Learning Data Dump'!$U:$U,'In Progress FEED'!AO$2) -> 0 | AP9: =COUNTIFS('Assigned Learning Data Dump'!$W:$W,'In Progress FEED'!$A9,'Assigned Learning Data Dump'!$F:$F,$A$1,'Assigned Learning Data Dump'!$U:$U,'In Progress FEED'!AP$2) -> 0 | AQ9: =SUBTOTAL(9,AN9:AP9) -> 0 | AR9: =COUNTIFS('Assigned Learning Data Dump'!$W:$W,'In Progress FEED'!$A9,'Assigned Learning Data Dump'!$F:$F,$A$1,'Assigned Learning Data Dump'!$U:$U,'In Progress FEED'!AR$2) -> 0 | AS9: =COUNTIFS('Assigned Learning Data Dump'!$W:$W,'In Progress FEED'!$A9,'Assigned Learning Data Dump'!$F:$F,$A$1,'Assigned Learning Data Dump'!$U:$U,'In Progress FEED'!AS$2) -> 0 | AT9: =COUNTIFS('Assigned Learning Data Dump'!$W:$W,'In Progress FEED'!$A9,'Assigned Learning Data Dump'!$F:$F,$A$1,'Assigned Learning Data Dump'!$U:$U,'In Progress FEED'!AT$2) -> 0 | AU9: =SUBTOTAL(9,AR9:AT9) -> 0 | AV9: =COUNTIFS('Assigned Learning Data Dump'!$W:$W,'In Progress FEED'!$A9,'Assigned Learning Data Dump'!$F:$F,$A$1,'Assigned Learning Data Dump'!$U:$U,'In Progress FEED'!AV$2) -> 0 | AW9: =COUNTIFS('Assigned Learning Data Dump'!$W:$W,'In Progress FEED'!$A9,'Assigned Learning Data Dump'!$F:$F,$A$1,'Assigned Learning Data Dump'!$U:$U,'In Progress FEED'!AW$2) -> 0 | AX9: =COUNTIFS('Assigned Learning Data Dump'!$W:$W,'In Progress FEED'!$A9,'Assigned Learning Data Dump'!$F:$F,$A$1,'Assigned Learning Data Dump'!$U:$U,'In Progress FEED'!AX$2) -> 0 | AY9: =SUBTOTAL(9,AV9:AX9) -> 0 | AZ9: =SUBTOTAL(9,AJ9:AY9) -> 0
A10: Property and Store Development | B10: =COUNTIFS('Assigned Learning Data Dump'!$W:$W,'In Progress FEED'!$A10,'Assigned Learning Data Dump'!$F:$F,$A$1,'Assigned Learning Data Dump'!$U:$U,'In Progress FEED'!B$2) -> 0 | C10: =COUNTIFS('Assigned Learning Data Dump'!$W:$W,'In Progress FEED'!$A10,'Assigned Learning Data Dump'!$F:$F,$A$1,'Assigned Learning Data Dump'!$U:$U,'In Progress FEED'!C$2) -> 2 | D10: =COUNTIFS('Assigned Learning Data Dump'!$W:$W,'In Progress FEED'!$A10,'Assigned Learning Data Dump'!$F:$F,$A$1,'Assigned Learning Data Dump'!$U:$U,'In Progress FEED'!D$2) -> 0 | E10: =SUBTOTAL(9,B10:D10) -> 2 | F10: =COUNTIFS('Assigned Learning Data Dump'!$W:$W,'In Progress FEED'!$A10,'Assigned Learning Data Dump'!$F:$F,$A$1,'Assigned Learning Data Dump'!$U:$U,'In Progress FEED'!F$2) -> 0 | G10: =COUNTIFS('Assigned Learning Data Dump'!$W:$W,'In Progress FEED'!$A10,'Assigned Learning Data Dump'!$F:$F,$A$1,'Assigned Learning Data Dump'!$U:$U,'In Progress FEED'!G$2) -> 0 | H10: =COUNTIFS('Assigned Learning Data Dump'!$W:$W,'In Progress FEED'!$A10,'Assigned Learning Data Dump'!$F:$F,$A$1,'Assigned Learning Data Dump'!$U:$U,'In Progress FEED'!H$2) -> 0 | I10: =SUBTOTAL(9,F10:H10) -> 0 | J10: =COUNTIFS('Assigned Learning Data Dump'!$W:$W,'In Progress FEED'!$A10,'Assigned Learning Data Dump'!$F:$F,$A$1,'Assigned Learning Data Dump'!$U:$U,'In Progress FEED'!J$2) -> 1 | K10: =COUNTIFS('Assigned Learning Data Dump'!$W:$W,'In Progress FEED'!$A10,'Assigned Learning Data Dump'!$F:$F,$A$1,'Assigned Learning Data Dump'!$U:$U,'In Progress FEED'!K$2) -> 0 | L10: =COUNTIFS('Assigned Learning Data Dump'!$W:$W,'In Progress FEED'!$A10,'Assigned Learning Data Dump'!$F:$F,$A$1,'Assigned Learning Data Dump'!$U:$U,'In Progress FEED'!L$2) -> 0 | M10: =SUBTOTAL(9,J10:L10) -> 1 | N10: =COUNTIFS('Assigned Learning Data Dump'!$W:$W,'In Progress FEED'!$A10,'Assigned Learning Data Dump'!$F:$F,$A$1,'Assigned Learning Data Dump'!$U:$U,'In Progress FEED'!N$2) -> 0 | O10: =COUNTIFS('Assigned Learning Data Dump'!$W:$W,'In Progress FEED'!$A10,'Assigned Learning Data Dump'!$F:$F,$A$1,'Assigned Learning Data Dump'!$U:$U,'In Progress FEED'!O$2) -> 1 | P10: =COUNTIFS('Assigned Learning Data Dump'!$W:$W,'In Progress FEED'!$A10,'Assigned Learning Data Dump'!$F:$F,$A$1,'Assigned Learning Data Dump'!$U:$U,'In Progress FEED'!P$2) -> 1 | Q10: =SUBTOTAL(9,N10:P10) -> 2 | R10: =SUBTOTAL(9,B10:Q10) -> 5 | S10: =COUNTIFS('Assigned Learning Data Dump'!$W:$W,'In Progress FEED'!$A10,'Assigned Learning Data Dump'!$F:$F,$A$1,'Assigned Learning Data Dump'!$U:$U,'In Progress FEED'!S$2) -> 2 | T10: =COUNTIFS('Assigned Learning Data Dump'!$W:$W,'In Progress FEED'!$A10,'Assigned Learning Data Dump'!$F:$F,$A$1,'Assigned Learning Data Dump'!$U:$U,'In Progress FEED'!T$2) -> 1 | U10: =COUNTIFS('Assigned Learning Data Dump'!$W:$W,'In Progress FEED'!$A10,'Assigned Learning Data Dump'!$F:$F,$A$1,'Assigned Learning Data Dump'!$U:$U,'In Progress FEED'!U$2) -> 0 | V10: =SUBTOTAL(9,S10:U10) -> 3 | W10: =COUNTIFS('Assigned Learning Data Dump'!$W:$W,'In Progress FEED'!$A10,'Assigned Learning Data Dump'!$F:$F,$A$1,'Assigned Learning Data Dump'!$U:$U,'In Progress FEED'!W$2) -> 0 | X10: =COUNTIFS('Assigned Learning Data Dump'!$W:$W,'In Progress FEED'!$A10,'Assigned Learning Data Dump'!$F:$F,$A$1,'Assigned Learning Data Dump'!$U:$U,'In Progress FEED'!X$2) -> 0 | Y10: =COUNTIFS('Assigned Learning Data Dump'!$W:$W,'In Progress FEED'!$A10,'Assigned Learning Data Dump'!$F:$F,$A$1,'Assigned Learning Data Dump'!$U:$U,'In Progress FEED'!Y$2) -> 0 | Z10: =SUBTOTAL(9,W10:Y10) -> 0 | AA10: =COUNTIFS('Assigned Learning Data Dump'!$W:$W,'In Progress FEED'!$A10,'Assigned Learning Data Dump'!$F:$F,$A$1,'Assigned Learning Data Dump'!$U:$U,'In Progress FEED'!AA$2) -> 0 | AB10: =COUNTIFS('Assigned Learning Data Dump'!$W:$W,'In Progress FEED'!$A10,'Assigned Learning Data Dump'!$F:$F,$A$1,'Assigned Learning Data Dump'!$U:$U,'In Progress FEED'!AB$2) -> 0 | AC10: =COUNTIFS('Assigned Learning Data Dump'!$W:$W,'In Progress FEED'!$A10,'Assigned Learning Data Dump'!$F:$F,$A$1,'Assigned Learning Data Dump'!$U:$U,'In Progress FEED'!AC$2) -> 0 | AD10: =SUBTOTAL(9,AA10:AC10) -> 0 | AE10: =COUNTIFS('Assigned Learning Data Dump'!$W:$W,'In Progress FEED'!$A10,'Assigned Learning Data Dump'!$F:$F,$A$1,'Assigned Learning Data Dump'!$U:$U,'In Progress FEED'!AE$2) -> 0 | AF10: =COUNTIFS('Assigned Learning Data Dump'!$W:$W,'In Progress FEED'!$A10,'Assigned Learning Data Dump'!$F:$F,$A$1,'Assigned Learning Data Dump'!$U:$U,'In Progress FEED'!AF$2) -> 2 | AG10: =COUNTIFS('Assigned Learning Data Dump'!$W:$W,'In Progress FEED'!$A10,'Assigned Learning Data Dump'!$F:$F,$A$1,'Assigned Learning Data Dump'!$U:$U,'In Progress FEED'!AG$2) -> 0 | AH10: =SUBTOTAL(9,AE10:AG10) -> 2 | AI10: =SUBTOTAL(9,S10:AH10) -> 5 | AJ10: =COUNTIFS('Assigned Learning Data Dump'!$W:$W,'In Progress FEED'!$A10,'Assigned Learning Data Dump'!$F:$F,$A$1,'Assigned Learning Data Dump'!$U:$U,'In Progress FEED'!AJ$2) -> 0 | AK10: =COUNTIFS('Assigned Learning Data Dump'!$W:$W,'In Progress FEED'!$A10,'Assigned Learning Data Dump'!$F:$F,$A$1,'Assigned Learning Data Dump'!$U:$U,'In Progress FEED'!AK$2) -> 0 | AL10: =COUNTIFS('Assigned Learning Data Dump'!$W:$W,'In Progress FEED'!$A10,'Assigned Learning Data Dump'!$F:$F,$A$1,'Assigned Learning Data Dump'!$U:$U,'In Progress FEED'!AL$2) -> 0 | AM10: =SUBTOTAL(9,AJ10:AL10) -> 0 | AN10: =COUNTIFS('Assigned Learning Data Dump'!$W:$W,'In Progress FEED'!$A10,'Assigned Learning Data Dump'!$F:$F,$A$1,'Assigned Learning Data Dump'!$U:$U,'In Progress FEED'!AN$2) -> 0 | AO10: =COUNTIFS('Assigned Learning Data Dump'!$W:$W,'In Progress FEED'!$A10,'Assigned Learning Data Dump'!$F:$F,$A$1,'Assigned Learning Data Dump'!$U:$U,'In Progress FEED'!AO$2) -> 0 | AP10: =COUNTIFS('Assigned Learning Data Dump'!$W:$W,'In Progress FEED'!$A10,'Assigned Learning Data Dump'!$F:$F,$A$1,'Assigned Learning Data Dump'!$U:$U,'In Progress FEED'!AP$2) -> 0 | AQ10: =SUBTOTAL(9,AN10:AP10) -> 0 | AR10: =COUNTIFS('Assigned Learning Data Dump'!$W:$W,'In Progress FEED'!$A10,'Assigned Learning Data Dump'!$F:$F,$A$1,'Assigned Learning Data Dump'!$U:$U,'In Progress FEED'!AR$2) -> 0 | AS10: =COUNTIFS('Assigned Learning Data Dump'!$W:$W,'In Progress FEED'!$A10,'Assigned Learning Data Dump'!$F:$F,$A$1,'Assigned Learning Data Dump'!$U:$U,'In Progress FEED'!AS$2) -> 0 | AT10: =COUNTIFS('Assigned Learning Data Dump'!$W:$W,'In Progress FEED'!$A10,'Assigned Learning Data Dump'!$F:$F,$A$1,'Assigned Learning Data Dump'!$U:$U,'In Progress FEED'!AT$2) -> 0 | AU10: =SUBTOTAL(9,AR10:AT10) -> 0 | AV10: =COUNTIFS('Assigned Learning Data Dump'!$W:$W,'In Progress FEED'!$A10,'Assigned Learning Data Dump'!$F:$F,$A$1,'Assigned Learning Data Dump'!$U:$U,'In Progress FEED'!AV$2) -> 0 | AW10: =COUNTIFS('Assigned Learning Data Dump'!$W:$W,'In Progress FEED'!$A10,'Assigned Learning Data Dump'!$F:$F,$A$1,'Assigned Learning Data Dump'!$U:$U,'In Progress FEED'!AW$2) -> 0 | AX10: =COUNTIFS('Assigned Learning Data Dump'!$W:$W,'In Progress FEED'!$A10,'Assigned Learning Data Dump'!$F:$F,$A$1,'Assigned Learning Data Dump'!$U:$U,'In Progress FEED'!AX$2) -> 0 | AY10: =SUBTOTAL(9,AV10:AX10) -> 0 | AZ10: =SUBTOTAL(9,AJ10:AY10) -> 0
A11: SPG Development | B11: =COUNTIFS('Assigned Learning Data Dump'!$W:$W,'In Progress FEED'!$A11,'Assigned Learning Data Dump'!$F:$F,$A$1,'Assigned Learning Data Dump'!$U:$U,'In Progress FEED'!B$2) -> 0 | C11: =COUNTIFS('Assigned Learning Data Dump'!$W:$W,'In Progress FEED'!$A11,'Assigned Learning Data Dump'!$F:$F,$A$1,'Assigned Learning Data Dump'!$U:$U,'In Progress FEED'!C$2) -> 0 | D11: =COUNTIFS('Assigned Learning Data Dump'!$W:$W,'In Progress FEED'!$A11,'Assigned Learning Data Dump'!$F:$F,$A$1,'Assigned Learning Data Dump'!$U:$U,'In Progress FEED'!D$2) -> 0 | E11: =SUBTOTAL(9,B11:D11) -> 0 | F11: =COUNTIFS('Assigned Learning Data Dump'!$W:$W,'In Progress FEED'!$A11,'Assigned Learning Data Dump'!$F:$F,$A$1,'Assigned Learning Data Dump'!$U:$U,'In Progress FEED'!F$2) -> 0 | G11: =COUNTIFS('Assigned Learning Data Dump'!$W:$W,'In Progress FEED'!$A11,'Assigned Learning Data Dump'!$F:$F,$A$1,'Assigned Learning Data Dump'!$U:$U,'In Progress FEED'!G$2) -> 0 | H11: =COUNTIFS('Assigned Learning Data Dump'!$W:$W,'In Progress FEED'!$A11,'Assigned Learning Data Dump'!$F:$F,$A$1,'Assigned Learning Data Dump'!$U:$U,'In Progress FEED'!H$2) -> 0 | I11: =SUBTOTAL(9,F11:H11) -> 0 | J11: =COUNTIFS('Assigned Learning Data Dump'!$W:$W,'In Progress FEED'!$A11,'Assigned Learning Data Dump'!$F:$F,$A$1,'Assigned Learning Data Dump'!$U:$U,'In Progress FEED'!J$2) -> 0 | K11: =COUNTIFS('Assigned Learning Data Dump'!$W:$W,'In Progress FEED'!$A11,'Assigned Learning Data Dump'!$F:$F,$A$1,'Assigned Learning Data Dump'!$U:$U,'In Progress FEED'!K$2) -> 1 | L11: =COUNTIFS('Assigned Learning Data Dump'!$W:$W,'In Progress FEED'!$A11,'Assigned Learning Data Dump'!$F:$F,$A$1,'Assigned Learning Data Dump'!$U:$U,'In Progress FEED'!L$2) -> 0 | M11: =SUBTOTAL(9,J11:L11) -> 1 | N11: =COUNTIFS('Assigned Learning Data Dump'!$W:$W,'In Progress FEED'!$A11,'Assigned Learning Data Dump'!$F:$F,$A$1,'Assigned Learning Data Dump'!$U:$U,'In Progress FEED'!N$2) -> 0 | O11: =COUNTIFS('Assigned Learning Data Dump'!$W:$W,'In Progress FEED'!$A11,'Assigned Learning Data Dump'!$F:$F,$A$1,'Assigned Learning Data Dump'!$U:$U,'In Progress FEED'!O$2) -> 0 | P11: =COUNTIFS('Assigned Learning Data Dump'!$W:$W,'In Progress FEED'!$A11,'Assigned Learning Data Dump'!$F:$F,$A$1,'Assigned Learning Data Dump'!$U:$U,'In Progress FEED'!P$2) -> 0 | Q11: =SUBTOTAL(9,N11:P11) -> 0 | R11: =SUBTOTAL(9,B11:Q11) -> 1 | S11: =COUNTIFS('Assigned Learning Data Dump'!$W:$W,'In Progress FEED'!$A11,'Assigned Learning Data Dump'!$F:$F,$A$1,'Assigned Learning Data Dump'!$U:$U,'In Progress FEED'!S$2) -> 0 | T11: =COUNTIFS('Assigned Learning Data Dump'!$W:$W,'In Progress FEED'!$A11,'Assigned Learning Data Dump'!$F:$F,$A$1,'Assigned Learning Data Dump'!$U:$U,'In Progress FEED'!T$2) -> 0 | U11: =COUNTIFS('Assigned Learning Data Dump'!$W:$W,'In Progress FEED'!$A11,'Assigned Learning Data Dump'!$F:$F,$A$1,'Assigned Learning Data Dump'!$U:$U,'In Progress FEED'!U$2) -> 0 | V11: =SUBTOTAL(9,S11:U11) -> 0 | W11: =COUNTIFS('Assigned Learning Data Dump'!$W:$W,'In Progress FEED'!$A11,'Assigned Learning Data Dump'!$F:$F,$A$1,'Assigned Learning Data Dump'!$U:$U,'In Progress FEED'!W$2) -> 0 | X11: =COUNTIFS('Assigned Learning Data Dump'!$W:$W,'In Progress FEED'!$A11,'Assigned Learning Data Dump'!$F:$F,$A$1,'Assigned Learning Data Dump'!$U:$U,'In Progress FEED'!X$2) -> 3 | Y11: =COUNTIFS('Assigned Learning Data Dump'!$W:$W,'In Progress FEED'!$A11,'Assigned Learning Data Dump'!$F:$F,$A$1,'Assigned Learning Data Dump'!$U:$U,'In Progress FEED'!Y$2) -> 0 | Z11: =SUBTOTAL(9,W11:Y11) -> 3 | AA11: =COUNTIFS('Assigned Learning Data Dump'!$W:$W,'In Progress FEED'!$A11,'Assigned Learning Data Dump'!$F:$F,$A$1,'Assigned Learning Data Dump'!$U:$U,'In Progress FEED'!AA$2) -> 0 | AB11: =COUNTIFS('Assigned Learning Data Dump'!$W:$W,'In Progress FEED'!$A11,'Assigned Learning Data Dump'!$F:$F,$A$1,'Assigned Learning Data Dump'!$U:$U,'In Progress FEED'!AB$2) -> 0 | AC11: =COUNTIFS('Assigned Learning Data Dump'!$W:$W,'In Progress FEED'!$A11,'Assigned Learning Data Dump'!$F:$F,$A$1,'Assigned Learning Data Dump'!$U:$U,'In Progress FEED'!AC$2) -> 0 | AD11: =SUBTOTAL(9,AA11:AC11) -> 0 | AE11: =COUNTIFS('Assigned Learning Data Dump'!$W:$W,'In Progress FEED'!$A11,'Assigned Learning Data Dump'!$F:$F,$A$1,'Assigned Learning Data Dump'!$U:$U,'In Progress FEED'!AE$2) -> 0 | AF11: =COUNTIFS('Assigned Learning Data Dump'!$W:$W,'In Progress FEED'!$A11,'Assigned Learning Data Dump'!$F:$F,$A$1,'Assigned Learning Data Dump'!$U:$U,'In Progress FEED'!AF$2) -> 0 | AG11: =COUNTIFS('Assigned Learning Data Dump'!$W:$W,'In Progress FEED'!$A11,'Assigned Learning Data Dump'!$F:$F,$A$1,'Assigned Learning Data Dump'!$U:$U,'In Progress FEED'!AG$2) -> 0 | AH11: =SUBTOTAL(9,AE11:AG11) -> 0 | AI11: =SUBTOTAL(9,S11:AH11) -> 3 | AJ11: =COUNTIFS('Assigned Learning Data Dump'!$W:$W,'In Progress FEED'!$A11,'Assigned Learning Data Dump'!$F:$F,$A$1,'Assigned Learning Data Dump'!$U:$U,'In Progress FEED'!AJ$2) -> 0 | AK11: =COUNTIFS('Assigned Learning Data Dump'!$W:$W,'In Progress FEED'!$A11,'Assigned Learning Data Dump'!$F:$F,$A$1,'Assigned Learning Data Dump'!$U:$U,'In Progress FEED'!AK$2) -> 0 | AL11: =COUNTIFS('Assigned Learning Data Dump'!$W:$W,'In Progress FEED'!$A11,'Assigned Learning Data Dump'!$F:$F,$A$1,'Assigned Learning Data Dump'!$U:$U,'In Progress FEED'!AL$2) -> 0 | AM11: =SUBTOTAL(9,AJ11:AL11) -> 0 | AN11: =COUNTIFS('Assigned Learning Data Dump'!$W:$W,'In Progress FEED'!$A11,'Assigned Learning Data Dump'!$F:$F,$A$1,'Assigned Learning Data Dump'!$U:$U,'In Progress FEED'!AN$2) -> 0 | AO11: =COUNTIFS('Assigned Learning Data Dump'!$W:$W,'In Progress FEED'!$A11,'Assigned Learning Data Dump'!$F:$F,$A$1,'Assigned Learning Data Dump'!$U:$U,'In Progress FEED'!AO$2) -> 0 | AP11: =COUNTIFS('Assigned Learning Data Dump'!$W:$W,'In Progress FEED'!$A11,'Assigned Learning Data Dump'!$F:$F,$A$1,'Assigned Learning Data Dump'!$U:$U,'In Progress FEED'!AP$2) -> 0 | AQ11: =SUBTOTAL(9,AN11:AP11) -> 0 | AR11: =COUNTIFS('Assigned Learning Data Dump'!$W:$W,'In Progress FEED'!$A11,'Assigned Learning Data Dump'!$F:$F,$A$1,'Assigned Learning Data Dump'!$U:$U,'In Progress FEED'!AR$2) -> 0 | AS11: =COUNTIFS('Assigned Learning Data Dump'!$W:$W,'In Progress FEED'!$A11,'Assigned Learning Data Dump'!$F:$F,$A$1,'Assigned Learning Data Dump'!$U:$U,'In Progress FEED'!AS$2) -> 0 | AT11: =COUNTIFS('Assigned Learning Data Dump'!$W:$W,'In Progress FEED'!$A11,'Assigned Learning Data Dump'!$F:$F,$A$1,'Assigned Learning Data Dump'!$U:$U,'In Progress FEED'!AT$2) -> 0 | AU11: =SUBTOTAL(9,AR11:AT11) -> 0 | AV11: =COUNTIFS('Assigned Learning Data Dump'!$W:$W,'In Progress FEED'!$A11,'Assigned Learning Data Dump'!$F:$F,$A$1,'Assigned Learning Data Dump'!$U:$U,'In Progress FEED'!AV$2) -> 0 | AW11: =COUNTIFS('Assigned Learning Data Dump'!$W:$W,'In Progress FEED'!$A11,'Assigned Learning Data Dump'!$F:$F,$A$1,'Assigned Learning Data Dump'!$U:$U,'In Progress FEED'!AW$2) -> 0 | AX11: =COUNTIFS('Assigned Learning Data Dump'!$W:$W,'In Progress FEED'!$A11,'Assigned Learning Data Dump'!$F:$F,$A$1,'Assigned Learning Data Dump'!$U:$U,'In Progress FEED'!AX$2) -> 0 | AY11: =SUBTOTAL(9,AV11:AX11) -> 0 | AZ11: =SUBTOTAL(9,AJ11:AY11) -> 0
A12: Spot Merch | B12: =COUNTIFS('Assigned Learning Data Dump'!$W:$W,'In Progress FEED'!$A12,'Assigned Learning Data Dump'!$F:$F,$A$1,'Assigned Learning Data Dump'!$U:$U,'In Progress FEED'!B$2) -> 0 | C12: =COUNTIFS('Assigned Learning Data Dump'!$W:$W,'In Progress FEED'!$A12,'Assigned Learning Data Dump'!$F:$F,$A$1,'Assigned Learning Data Dump'!$U:$U,'In Progress FEED'!C$2) -> 0 | D12: =COUNTIFS('Assigned Learning Data Dump'!$W:$W,'In Progress FEED'!$A12,'Assigned Learning Data Dump'!$F:$F,$A$1,'Assigned Learning Data Dump'!$U:$U,'In Progress FEED'!D$2) -> 0 | E12: =SUBTOTAL(9,B12:D12) -> 0 | F12: =COUNTIFS('Assigned Learning Data Dump'!$W:$W,'In Progress FEED'!$A12,'Assigned Learning Data Dump'!$F:$F,$A$1,'Assigned Learning Data Dump'!$U:$U,'In Progress FEED'!F$2) -> 0 | G12: =COUNTIFS('Assigned Learning Data Dump'!$W:$W,'In Progress FEED'!$A12,'Assigned Learning Data Dump'!$F:$F,$A$1,'Assigned Learning Data Dump'!$U:$U,'In Progress FEED'!G$2) -> 0 | H12: =COUNTIFS('Assigned Learning Data Dump'!$W:$W,'In Progress FEED'!$A12,'Assigned Learning Data Dump'!$F:$F,$A$1,'Assigned Learning Data Dump'!$U:$U,'In Progress FEED'!H$2) -> 0 | I12: =SUBTOTAL(9,F12:H12) -> 0 | J12: =COUNTIFS('Assigned Learning Data Dump'!$W:$W,'In Progress FEED'!$A12,'Assigned Learning Data Dump'!$F:$F,$A$1,'Assigned Learning Data Dump'!$U:$U,'In Progress FEED'!J$2) -> 0 | K12: =COUNTIFS('Assigned Learning Data Dump'!$W:$W,'In Progress FEED'!$A12,'Assigned Learning Data Dump'!$F:$F,$A$1,'Assigned Learning Data Dump'!$U:$U,'In Progress FEED'!K$2) -> 0 | L12: =COUNTIFS('Assigned Learning Data Dump'!$W:$W,'In Progress FEED'!$A12,'Assigned Learning Data Dump'!$F:$F,$A$1,'Assigned Learning Data Dump'!$U:$U,'In Progress FEED'!L$2) -> 0 | M12: =SUBTOTAL(9,J12:L12) -> 0 | N12: =COUNTIFS('Assigned Learning Data Dump'!$W:$W,'In Progress FEED'!$A12,'Assigned Learning Data Dump'!$F:$F,$A$1,'Assigned Learning Data Dump'!$U:$U,'In Progress FEED'!N$2) -> 0 | O12: =COUNTIFS('Assigned Learning Data Dump'!$W:$W,'In Progress FEED'!$A12,'Assigned Learning Data Dump'!$F:$F,$A$1,'Assigned Learning Data Dump'!$U:$U,'In Progress FEED'!O$2) -> 0 | P12: =COUNTIFS('Assigned Learning Data Dump'!$W:$W,'In Progress FEED'!$A12,'Assigned Learning Data Dump'!$F:$F,$A$1,'Assigned Learning Data Dump'!$U:$U,'In Progress FEED'!P$2) -> 0 | Q12: =SUBTOTAL(9,N12:P12) -> 0 | R12: =SUBTOTAL(9,B12:Q12) -> 0 | S12: =COUNTIFS('Assigned Learning Data Dump'!$W:$W,'In Progress FEED'!$A12,'Assigned Learning Data Dump'!$F:$F,$A$1,'Assigned Learning Data Dump'!$U:$U,'In Progress FEED'!S$2) -> 0 | T12: =COUNTIFS('Assigned Learning Data Dump'!$W:$W,'In Progress FEED'!$A12,'Assigned Learning Data Dump'!$F:$F,$A$1,'Assigned Learning Data Dump'!$U:$U,'In Progress FEED'!T$2) -> 0 | U12: =COUNTIFS('Assigned Learning Data Dump'!$W:$W,'In Progress FEED'!$A12,'Assigned Learning Data Dump'!$F:$F,$A$1,'Assigned Learning Data Dump'!$U:$U,'In Progress FEED'!U$2) -> 1 | V12: =SUBTOTAL(9,S12:U12) -> 1 | W12: =COUNTIFS('Assigned Learning Data Dump'!$W:$W,'In Progress FEED'!$A12,'Assigned Learning Data Dump'!$F:$F,$A$1,'Assigned Learning Data Dump'!$U:$U,'In Progress FEED'!W$2) -> 0 | X12: =COUNTIFS('Assigned Learning Data Dump'!$W:$W,'In Progress FEED'!$A12,'Assigned Learning Data Dump'!$F:$F,$A$1,'Assigned Learning Data Dump'!$U:$U,'In Progress FEED'!X$2) -> 0 | Y12: =COUNTIFS('Assigned Learning Data Dump'!$W:$W,'In Progress FEED'!$A12,'Assigned Learning Data Dump'!$F:$F,$A$1,'Assigned Learning Data Dump'!$U:$U,'In Progress FEED'!Y$2) -> 0 | Z12: =SUBTOTAL(9,W12:Y12) -> 0 | AA12: =COUNTIFS('Assigned Learning Data Dump'!$W:$W,'In Progress FEED'!$A12,'Assigned Learning Data Dump'!$F:$F,$A$1,'Assigned Learning Data Dump'!$U:$U,'In Progress FEED'!AA$2) -> 0 | AB12: =COUNTIFS('Assigned Learning Data Dump'!$W:$W,'In Progress FEED'!$A12,'Assigned Learning Data Dump'!$F:$F,$A$1,'Assigned Learning Data Dump'!$U:$U,'In Progress FEED'!AB$2) -> 0 | AC12: =COUNTIFS('Assigned Learning Data Dump'!$W:$W,'In Progress FEED'!$A12,'Assigned Learning Data Dump'!$F:$F,$A$1,'Assigned Learning Data Dump'!$U:$U,'In Progress FEED'!AC$2) -> 0 | AD12: =SUBTOTAL(9,AA12:AC12) -> 0 | AE12: =COUNTIFS('Assigned Learning Data Dump'!$W:$W,'In Progress FEED'!$A12,'Assigned Learning Data Dump'!$F:$F,$A$1,'Assigned Learning Data Dump'!$U:$U,'In Progress FEED'!AE$2) -> 0 | AF12: =COUNTIFS('Assigned Learning Data Dump'!$W:$W,'In Progress FEED'!$A12,'Assigned Learning Data Dump'!$F:$F,$A$1,'Assigned Learning Data Dump'!$U:$U,'In Progress FEED'!AF$2) -> 0 | AG12: =COUNTIFS('Assigned Learning Data Dump'!$W:$W,'In Progress FEED'!$A12,'Assigned Learning Data Dump'!$F:$F,$A$1,'Assigned Learning Data Dump'!$U:$U,'In Progress FEED'!AG$2) -> 0 | AH12: =SUBTOTAL(9,AE12:AG12) -> 0 | AI12: =SUBTOTAL(9,S12:AH12) -> 1 | AJ12: =COUNTIFS('Assigned Learning Data Dump'!$W:$W,'In Progress FEED'!$A12,'Assigned Learning Data Dump'!$F:$F,$A$1,'Assigned Learning Data Dump'!$U:$U,'In Progress FEED'!AJ$2) -> 0 | AK12: =COUNTIFS('Assigned Learning Data Dump'!$W:$W,'In Progress FEED'!$A12,'Assigned Learning Data Dump'!$F:$F,$A$1,'Assigned Learning Data Dump'!$U:$U,'In Progress FEED'!AK$2) -> 0 | AL12: =COUNTIFS('Assigned Learning Data Dump'!$W:$W,'In Progress FEED'!$A12,'Assigned Learning Data Dump'!$F:$F,$A$1,'Assigned Learning Data Dump'!$U:$U,'In Progress FEED'!AL$2) -> 0 | AM12: =SUBTOTAL(9,AJ12:AL12) -> 0 | AN12: =COUNTIFS('Assigned Learning Data Dump'!$W:$W,'In Progress FEED'!$A12,'Assigned Learning Data Dump'!$F:$F,$A$1,'Assigned Learning Data Dump'!$U:$U,'In Progress FEED'!AN$2) -> 0 | AO12: =COUNTIFS('Assigned Learning Data Dump'!$W:$W,'In Progress FEED'!$A12,'Assigned Learning Data Dump'!$F:$F,$A$1,'Assigned Learning Data Dump'!$U:$U,'In Progress FEED'!AO$2) -> 0 | AP12: =COUNTIFS('Assigned Learning Data Dump'!$W:$W,'In Progress FEED'!$A12,'Assigned Learning Data Dump'!$F:$F,$A$1,'Assigned Learning Data Dump'!$U:$U,'In Progress FEED'!AP$2) -> 0 | AQ12: =SUBTOTAL(9,AN12:AP12) -> 0 | AR12: =COUNTIFS('Assigned Learning Data Dump'!$W:$W,'In Progress FEED'!$A12,'Assigned Learning Data Dump'!$F:$F,$A$1,'Assigned Learning Data Dump'!$U:$U,'In Progress FEED'!AR$2) -> 0 | AS12: =COUNTIFS('Assigned Learning Data Dump'!$W:$W,'In Progress FEED'!$A12,'Assigned Learning Data Dump'!$F:$F,$A$1,'Assigned Learning Data Dump'!$U:$U,'In Progress FEED'!AS$2) -> 0 | AT12: =COUNTIFS('Assigned Learning Data Dump'!$W:$W,'In Progress FEED'!$A12,'Assigned Learning Data Dump'!$F:$F,$A$1,'Assigned Learning Data Dump'!$U:$U,'In Progress FEED'!AT$2) -> 0 | AU12: =SUBTOTAL(9,AR12:AT12) -> 0 | AV12: =COUNTIFS('Assigned Learning Data Dump'!$W:$W,'In Progress FEED'!$A12,'Assigned Learning Data Dump'!$F:$F,$A$1,'Assigned Learning Data Dump'!$U:$U,'In Progress FEED'!AV$2) -> 0 | AW12: =COUNTIFS('Assigned Learning Data Dump'!$W:$W,'In Progress FEED'!$A12,'Assigned Learning Data Dump'!$F:$F,$A$1,'Assigned Learning Data Dump'!$U:$U,'In Progress FEED'!AW$2) -> 0 | AX12: =COUNTIFS('Assigned Learning Data Dump'!$W:$W,'In Progress FEED'!$A12,'Assigned Learning Data Dump'!$F:$F,$A$1,'Assigned Learning Data Dump'!$U:$U,'In Progress FEED'!AX$2) -> 0 | AY12: =SUBTOTAL(9,AV12:AX12) -> 0 | AZ12: =SUBTOTAL(9,AJ12:AY12) -> 0
